Workbook
Name APUb: #REF!
Name BDcodCU: ApuB!$A$5:$A$50005
Name BDcodINS: InsB!$A$16:$A$3015
Name BDcuA: ApuB!$A$5:$DJ$50005
Name BDcuB: ApuB!$B$5:$DJ$50005
Name BDins: InsB!$A$16:$M$3015
Name cellbimuser0EB30BF1602D56040B4019F3: 1714952548072
Name cellbimuser33120D4C9001780EE8508FEB: 1715181719314
Name CODc: #REF!&"C"
Name CODp: #REF!
Name CODr: #REF!&"P"
Name DcCU: Datos!$J$13
Name Dins: Datos!$J$15
Name DLS: Datos!$AJ$12:$AJ$18
Name DpCU: Datos!$J$12
Name DpP: Datos!$J$9
Name EQ: #REF!
Name Frto: Datos!$J$19
Name JL: Datos!$H$19
Name MA: #REF!
Name MO: #REF!
Name NO: Datos!$AJ$12:$AJ$18

Sheet Datos
AQ1: NO | AT1: Feriados
B2: PROYECTO | AQ2: SI | AT2: Comienzo | AU2: Fin | AV2: Descripcion
B3: UBICACIÓN | AQ3: SI
B4: CLIENTE | AQ4: SI
B5: FECHA | AI5: Soles | AJ5: S/ | AQ5: SI
F6: MONEDA | AI6: Dólares | AJ6: $
B7: LOGO | C7: RW7o | D7: =IF(J7=AI5,AJ5,AJ6) -> S/ | G7: Procesar el presupuesto utilizando la moneda en | J7: Soles
F8: NÚMERO DE DECIMALES PARA REDONDEO
B9: MODALIDAD DE E. | C9: CONTRATA | G9: Parciales de las partidas en la hoja de presupuesto | J9: 2 | AI9: CONTRATA | AQ9: NO
B10: IMPUESTO (IGV) | C10: 0.18 | G10: Total de los metrados en cada partida | J10: 2 | AI10: ADMINISTRACION DIRECTA | AO10: CALENDARIO | AR10: PIE DEL PRESUPUESTO
D11: =Pto!G142 -> 352697.08 | AH11: 0 | AI11: 0 | AK11: 0 | AO11: Lunes | AP11: Laborable | AR11: VALOR FIJO
B12: COLOR DE TEXTOS: | G12: Parcial de los insumos en los APUs | J12: 2 | AI12: 1 | AJ12: 6 | AK12: 1 | AO12: Martes | AP12: Laborable | AR12: % COSTO DIRECTO
B13: Subpresupuesto | G13: Cantidad de MO y EQ en los APUs | J13: 4 | AI13: 2 | AJ13: 5 | AK13: 2 | AO13: Miercoles | AP13: Laborable | AR13: SUBTOTAL 1
B14: Título | D14: =VLOOKUP(C14,AL$10:AM$23,2,FALSE) -> #N/A | AI14: 3 | AK14: 3 | AO14: Jueves | AP14: Laborable | AR14: % SUBTOTAL 1
B15: Sub título de orden 1 | D15: =VLOOKUP(C15,AL$10:AM$23,2,FALSE) -> #N/A | G15: Precio de los insumos | J15: 2 | AI15: 4 | AK15: 4 | AO15: Viernes | AP15: Laborable | AR15: SUBTOTAL 2
B16: Sub título de orden 2 | D16: =VLOOKUP(C16,AL$10:AM$23,2,FALSE) -> #N/A | AI16: 5 | AK16: 5 | AO16: Sábado | AP16: Laborable | AR16: % SUBTOTAL 2
B17: Sub título de orden 3 | D17: =VLOOKUP(C17,AL$10:AM$23,2,FALSE) -> #N/A | F17: OTRAS OPCIONES | AI17: SI | AJ17: Parcial | AK17: 6 | AO17: Domingo | AP17: No laborable | AR17: SUBTOTAL 3
B18: Sub título de orden 4 | D18: =VLOOKUP(C18,AL$10:AM$23,2,FALSE) -> #N/A | I18: Factor costo mano de obra | J18: 1 | AI18: NO | AJ18: Cantidad | AK18: 7 | AR18: % SUBTOTAL 3
B19: Sub título de orden 5 | D19: =VLOOKUP(C19,AL$10:AM$23,2,FALSE) -> #N/A | G19: Jornada laboral | H19: 8 | I19: Factor para rendimiento | J19: 1 | AK19: 8 | AO19: TEXTO EN PANEL DE APUS | AR19: SUBTOTAL 4
B20: Sub título de orden 6 | D20: =VLOOKUP(C20,AL$10:AM$23,2,FALSE) -> #N/A | AI20: MO1 y EQ1 | AK20: 9 | AO20: Tamaño ET | AP20: 10 | AR20: % SUBTOTAL 4
B21: Sub título de orden 7 | D21: =VLOOKUP(C21,AL$10:AM$23,2,FALSE) -> #N/A | G21: Igualar el monto total de relación de insumos al CD | J21: SI | AI21: TODOS | AJ21: 1 | AO21: Fuente ET | AP21: Arial | AR21: % FILA ANTERIOR
B22: Sub título de orden 8 | D22: =VLOOKUP(C22,AL$10:AM$23,2,FALSE) -> #N/A | AO22: Tamaño DG | AP22: 9
B23: Sub título de orden 9 | D23: =VLOOKUP(C23,AL$10:AM$23,2,FALSE) -> #N/A | G23: Generar el gráfico de utilización de recursos para | J23: MO1 y EQ1 | AO23: Fuente DG | AP23: Arial
B25: Pie de presupuesto | G25: Al generar E.T. en Word usar IDEM en partidas repetidas | J25: SI
A26: CONTROL CONCURRENTE
A27: GESTION DEL PROYECTO | G27: Al generar E. T. en Word procesar UNIDAD | J27: SI
A28: GASTOS GENERALES
A29: UTILIDAD | G29: Al generar E.T. en Word procesar FORMA DE PAGO | J29: SI
A30: SUBTOTAL
A31: IMPUESTO (IGV) | G31: Calend. Adq. insumos de MO1 en DH y EQ1 en DM | J31: NO
A32: VALOR REFERENCIAL
A33: SUPERVISIÓN | G33: Al consolidar los insumos de las partidas calcular en base a | J33: Parcial
A34: EXPEDIENTE TÉCNICO
A35: LIQUIDACIÓN
A36: PIE DE PRESUPUESTO
A37: DESCRIPCIÓN | B37: SIM. | C37: VALOR | E37: TIPO
A38: GASTOS GENERALES | B38: GG | C38: 15 | E38: % COSTO DIRECTO
A39: UTILIDAD | B39: UT | C39: 10 | E39: % COSTO DIRECTO
A40: SUBTOTAL | B40: ST | E40: SUBTOTAL 1
A41: IMPUESTO (IGV) | B41: IM | C41: 18 | E41: % SUBTOTAL 1
A42: VALOR REFERENCIAL | B42: VR | E42: SUBTOTAL 2
A43: SUPERVISIÓN | B43: SU | C43: 2.5 | E43: % SUBTOTAL 2

Sheet InsB
A2: DATOS NECESARIOS PARA EL CALCULO DE FLETES
A3: INSUMOS | D3: FLETE CON VEHICULO | G3: FLETE CON ACEMILA Y PEON
D4: ORIGEN - DESTINO | F4: Prec. U. | G4: ORIGEN - DESTINO | K4: Prec. U. | L4: p.u.Cemento
A5: MATERIALES | D5: HUARAZ- HUARI | F5: 0.15 | G5: HUARI - OBRA(YUPAN) | K5: 0.06 | L5: 2.5
A6: AGREGADOS | F6: 0 | G6: HUARI - OBRA(YUPAN) | K6: 1.2 | L6: L | M6: A | N6: H
A7: TUBERIAS | F7: 0 | K7: 0 | L7: 6 | M7: 2.2 | N7: 1.5
A8: {=MAX(IF(BDcodINS<90001,BDcodINS,80000))} -> 80012 | B8: {=MAX(IF(BDcodINS<57001,BDcodINS,53500))} -> 53500 | C8: {=MAX(IF(BDcodINS<22501,BDcodINS,20000))} -> 20000
A9: {=MAX(IF(BDcodINS<80001,BDcodINS,77500))} -> 77500 | B9: {=MAX(IF(BDcodINS<53501,BDcodINS,50000))} -> 50000 | C9: {=MAX(IF(BDcodINS<77501,BDcodINS,75000))} -> 75000
A10: {=MAX(IF(BDcodINS<70001,BDcodINS,60000))} -> 60019 | B10: {=MAX(IF(BDcodINS<30001,BDcodINS,27500))} -> 27500 | C10: {=MAX(IF(BDcodINS<75001,BDcodINS,72500))} -> 72500
A11: {=MAX(IF(BDcodINS<50001,BDcodINS,30000))} -> 30141 | B11: {=MAX(IF(BDcodINS<27501,BDcodINS,25000))} -> 25000 | C11: {=MAX(IF(BDcodINS<72501,BDcodINS,70000))} -> 70001
A12: {=MAX(IF(BDcodINS<20001,BDcodINS,10000))} -> 10005 | B12: {=MAX(IF(BDcodINS<25001,BDcodINS,22500))} -> 22500 | C12: {=MAX(IF(BDcodINS<60001,BDcodINS,57000))} -> 57000 | N12: MONEDAS
A13: 60002 | B13: =MATCH($A$13,BDcodINS,0)+15 -> 25 | C13: {=MAX(IF(BDcodINS<95001,BDcodINS,90000))} -> 90004 | N13: =Datos!AI5 -> Soles | P13: =Datos!AI6 -> Dólares
A14: =COUNT(BDcodINS)+16 -> 198 | C14: {=MAX(IF(BDcodINS<100000,BDcodINS,95000))} -> 90004 | H14: SOLO TUBERIA | N14: Factor | O14: =1+Datos!$C$10 -> 1.18 | P14: 3.75 | Q14: =O14 -> 1.18
A15: Cod. | B15: IU | C15: Tipo | D15: Insumo | E15: Und | F15: =Datos!J7 -> Soles | G15: Peso unitario (kg) | H15: Long. (m) | I15: Ø ext. (mm) | J15: espesor (mm) | K15: Específica de Gastos | L15: Codigo de APU de SP | M15: Codigo insumo referido | N15: Adm. Directa | O15: Contrata | P15: Adm. Directa | Q15: Contrata
A16: 10001 | B16: 47 | C16: MO1 | D16: PEON | E16: HH | F16: =IF(AND($F$15=Datos!$AI$5,Datos!$C$9=Datos!$AI$10),IF(A16>30000,N16,ROUND(N16*Datos!$J$18,Dins)),IF(AND($F$15=Datos!$AI$5,Datos!$C$9=Datos!$AI$9),IF(A16>30000,O16,ROUND(O16*Datos!$J$18,Dins)),IF(AND($F$15=Datos!$AI$6,Datos!$C$9=Datos!$AI$10),IF(A16>30000,P16,ROUND(P16*Datos!$J$18,Dins)),IF(AND($F$15=Datos!$AI$6,Datos!$C$9=Datos!$AI$9),IF(A16>30000,Q16,ROUND(Q16*Datos!$J$18,Dins)))))) -> 12.64 | N16: 12.64 | O16: =IF(A16>30000,ROUND(N16/$O$14,Dins),ROUND(N16,Dins)) -> 12.64 | P16: =ROUND(N16/$P$14,Dins) -> 3.37 | Q16: =IF(A16>30000,ROUND(P16/$Q$14,Dins),ROUND(P16,Dins)) -> 3.37
A17: 10002 | B17: 47 | C17: MO1 | D17: OPERARIO TOPOGRAFO | E17: HH | F17: =IF(AND($F$15=Datos!$AI$5,Datos!$C$9=Datos!$AI$10),IF(A17>30000,N17,ROUND(N17*Datos!$J$18,Dins)),IF(AND($F$15=Datos!$AI$5,Datos!$C$9=Datos!$AI$9),IF(A17>30000,O17,ROUND(O17*Datos!$J$18,Dins)),IF(AND($F$15=Datos!$AI$6,Datos!$C$9=Datos!$AI$10),IF(A17>30000,P17,ROUND(P17*Datos!$J$18,Dins)),IF(AND($F$15=Datos!$AI$6,Datos!$C$9=Datos!$AI$9),IF(A17>30000,Q17,ROUND(Q17*Datos!$J$18,Dins)))))) -> 17.59 | N17: 17.59 | O17: =IF(A17>30000,ROUND(N17/$O$14,Dins),ROUND(N17,Dins)) -> 17.59 | P17: =ROUND(N17/$P$14,Dins) -> 4.69 | Q17: =IF(A17>30000,ROUND(P17/$Q$14,Dins),ROUND(P17,Dins)) -> 4.69
A18: 30001 | B18: 21 | C18: MA | D18: CEMENTO PORTLAND TIPO I (42.5 kg) | E18: bol | F18: =IF(AND($F$15=Datos!$AI$5,Datos!$C$9=Datos!$AI$10),IF(A18>30000,N18,ROUND(N18*Datos!$J$18,Dins)),IF(AND($F$15=Datos!$AI$5,Datos!$C$9=Datos!$AI$9),IF(A18>30000,O18,ROUND(O18*Datos!$J$18,Dins)),IF(AND($F$15=Datos!$AI$6,Datos!$C$9=Datos!$AI$10),IF(A18>30000,P18,ROUND(P18*Datos!$J$18,Dins)),IF(AND($F$15=Datos!$AI$6,Datos!$C$9=Datos!$AI$9),IF(A18>30000,Q18,ROUND(Q18*Datos!$J$18,Dins)))))) -> 27 | N18: 31.86 | O18: =IF(A18>30000,ROUND(N18/$O$14,Dins),ROUND(N18,Dins)) -> 27 | P18: =ROUND(N18/$P$14,Dins) -> 8.5 | Q18: =IF(A18>30000,ROUND(P18/$Q$14,Dins),ROUND(P18,Dins)) -> 7.2
A19: 30002 | B19: 38 | C19: MA | D19: HORMIGON | E19: m3 | F19: =IF(AND($F$15=Datos!$AI$5,Datos!$C$9=Datos!$AI$10),IF(A19>30000,N19,ROUND(N19*Datos!$J$18,Dins)),IF(AND($F$15=Datos!$AI$5,Datos!$C$9=Datos!$AI$9),IF(A19>30000,O19,ROUND(O19*Datos!$J$18,Dins)),IF(AND($F$15=Datos!$AI$6,Datos!$C$9=Datos!$AI$10),IF(A19>30000,P19,ROUND(P19*Datos!$J$18,Dins)),IF(AND($F$15=Datos!$AI$6,Datos!$C$9=Datos!$AI$9),IF(A19>30000,Q19,ROUND(Q19*Datos!$J$18,Dins)))))) -> 41.3 | N19: 48.73 | O19: =IF(A19>30000,ROUND(N19/$O$14,Dins),ROUND(N19,Dins)) -> 41.3 | P19: =ROUND(N19/$P$14,Dins) -> 12.99 | Q19: =IF(A19>30000,ROUND(P19/$Q$14,Dins),ROUND(P19,Dins)) -> 11.01
A20: 30003 | B20: 39 | C20: MA | D20: TIZA BOLSA DE 40 kg | E20: und | F20: =IF(AND($F$15=Datos!$AI$5,Datos!$C$9=Datos!$AI$10),IF(A20>30000,N20,ROUND(N20*Datos!$J$18,Dins)),IF(AND($F$15=Datos!$AI$5,Datos!$C$9=Datos!$AI$9),IF(A20>30000,O20,ROUND(O20*Datos!$J$18,Dins)),IF(AND($F$15=Datos!$AI$6,Datos!$C$9=Datos!$AI$10),IF(A20>30000,P20,ROUND(P20*Datos!$J$18,Dins)),IF(AND($F$15=Datos!$AI$6,Datos!$C$9=Datos!$AI$9),IF(A20>30000,Q20,ROUND(Q20*Datos!$J$18,Dins)))))) -> 20 | N20: 23.6 | O20: =IF(A20>30000,ROUND(N20/$O$14,Dins),ROUND(N20,Dins)) -> 20 | P20: =ROUND(N20/$P$14,Dins) -> 6.29 | Q20: =IF(A20>30000,ROUND(P20/$Q$14,Dins),ROUND(P20,Dins)) -> 5.33
A21: 30004 | B21: 30 | C21: MA | D21: OCRE ROJO | E21: kg | F21: =IF(AND($F$15=Datos!$AI$5,Datos!$C$9=Datos!$AI$10),IF(A21>30000,N21,ROUND(N21*Datos!$J$18,Dins)),IF(AND($F$15=Datos!$AI$5,Datos!$C$9=Datos!$AI$9),IF(A21>30000,O21,ROUND(O21*Datos!$J$18,Dins)),IF(AND($F$15=Datos!$AI$6,Datos!$C$9=Datos!$AI$10),IF(A21>30000,P21,ROUND(P21*Datos!$J$18,Dins)),IF(AND($F$15=Datos!$AI$6,Datos!$C$9=Datos!$AI$9),IF(A21>30000,Q21,ROUND(Q21*Datos!$J$18,Dins)))))) -> 8 | N21: 9.44 | O21: =IF(A21>30000,ROUND(N21/$O$14,Dins),ROUND(N21,Dins)) -> 8 | P21: =ROUND(N21/$P$14,Dins) -> 2.52 | Q21: =IF(A21>30000,ROUND(P21/$Q$14,Dins),ROUND(P21,Dins)) -> 2.14
A22: 30005 | B22: 54 | C22: MA | D22: PINTURA ESMALTE | E22: gal | F22: =IF(AND($F$15=Datos!$AI$5,Datos!$C$9=Datos!$AI$10),IF(A22>30000,N22,ROUND(N22*Datos!$J$18,Dins)),IF(AND($F$15=Datos!$AI$5,Datos!$C$9=Datos!$AI$9),IF(A22>30000,O22,ROUND(O22*Datos!$J$18,Dins)),IF(AND($F$15=Datos!$AI$6,Datos!$C$9=Datos!$AI$10),IF(A22>30000,P22,ROUND(P22*Datos!$J$18,Dins)),IF(AND($F$15=Datos!$AI$6,Datos!$C$9=Datos!$AI$9),IF(A22>30000,Q22,ROUND(Q22*Datos!$J$18,Dins)))))) -> 28 | N22: 33.04 | O22: =IF(A22>30000,ROUND(N22/$O$14,Dins),ROUND(N22,Dins)) -> 28 | P22: =ROUND(N22/$P$14,Dins) -> 8.81 | Q22: =IF(A22>30000,ROUND(P22/$Q$14,Dins),ROUND(P22,Dins)) -> 7.47
A23: 30006 | B23: 39 | C23: MA | D23: CORDEL | E23: rll | F23: =IF(AND($F$15=Datos!$AI$5,Datos!$C$9=Datos!$AI$10),IF(A23>30000,N23,ROUND(N23*Datos!$J$18,Dins)),IF(AND($F$15=Datos!$AI$5,Datos!$C$9=Datos!$AI$9),IF(A23>30000,O23,ROUND(O23*Datos!$J$18,Dins)),IF(AND($F$15=Datos!$AI$6,Datos!$C$9=Datos!$AI$10),IF(A23>30000,P23,ROUND(P23*Datos!$J$18,Dins)),IF(AND($F$15=Datos!$AI$6,Datos!$C$9=Datos!$AI$9),IF(A23>30000,Q23,ROUND(Q23*Datos!$J$18,Dins)))))) -> 23.8 | N23: 28.08 | O23: =IF(A23>30000,ROUND(N23/$O$14,Dins),ROUND(N23,Dins)) -> 23.8 | P23: =ROUND(N23/$P$14,Dins) -> 7.49 | Q23: =IF(A23>30000,ROUND(P23/$Q$14,Dins),ROUND(P23,Dins)) -> 6.35
A24: 60001 | B24: 49 | C24: EQ1 | D24: NIVEL TOPOGRAFICO | E24: HM | F24: =IF(AND($F$15=Datos!$AI$5,Datos!$C$9=Datos!$AI$10),IF(A24>30000,N24,ROUND(N24*Datos!$J$18,Dins)),IF(AND($F$15=Datos!$AI$5,Datos!$C$9=Datos!$AI$9),IF(A24>30000,O24,ROUND(O24*Datos!$J$18,Dins)),IF(AND($F$15=Datos!$AI$6,Datos!$C$9=Datos!$AI$10),IF(A24>30000,P24,ROUND(P24*Datos!$J$18,Dins)),IF(AND($F$15=Datos!$AI$6,Datos!$C$9=Datos!$AI$9),IF(A24>30000,Q24,ROUND(Q24*Datos!$J$18,Dins)))))) -> 3.75 | N24: 4.42 | O24: =IF(A24>30000,ROUND(N24/$O$14,Dins),ROUND(N24,Dins)) -> 3.75 | P24: =ROUND(N24/$P$14,Dins) -> 1.18 | Q24: =IF(A24>30000,ROUND(P24/$Q$14,Dins),ROUND(P24,Dins)) -> 1
A25: 60002 | B25: 49 | C25: EQ1 | D25: TEODOLITO | E25: HM | F25: =IF(AND($F$15=Datos!$AI$5,Datos!$C$9=Datos!$AI$10),IF(A25>30000,N25,ROUND(N25*Datos!$J$18,Dins)),IF(AND($F$15=Datos!$AI$5,Datos!$C$9=Datos!$AI$9),IF(A25>30000,O25,ROUND(O25*Datos!$J$18,Dins)),IF(AND($F$15=Datos!$AI$6,Datos!$C$9=Datos!$AI$10),IF(A25>30000,P25,ROUND(P25*Datos!$J$18,Dins)),IF(AND($F$15=Datos!$AI$6,Datos!$C$9=Datos!$AI$9),IF(A25>30000,Q25,ROUND(Q25*Datos!$J$18,Dins)))))) -> 6.25 | N25: 7.38 | O25: =IF(A25>30000,ROUND(N25/$O$14,Dins),ROUND(N25,Dins)) -> 6.25 | P25: =ROUND(N25/$P$14,Dins) -> 1.97 | Q25: =IF(A25>30000,ROUND(P25/$Q$14,Dins),ROUND(P25,Dins)) -> 1.67
A26: 30007 | B26: 49 | C26: MA | D26: NIVEL TOPOGRAFICO | E26: día | F26: =IF(AND($F$15=Datos!$AI$5,Datos!$C$9=Datos!$AI$10),IF(A26>30000,N26,ROUND(N26*Datos!$J$18,Dins)),IF(AND($F$15=Datos!$AI$5,Datos!$C$9=Datos!$AI$9),IF(A26>30000,O26,ROUND(O26*Datos!$J$18,Dins)),IF(AND($F$15=Datos!$AI$6,Datos!$C$9=Datos!$AI$10),IF(A26>30000,P26,ROUND(P26*Datos!$J$18,Dins)),IF(AND($F$15=Datos!$AI$6,Datos!$C$9=Datos!$AI$9),IF(A26>30000,Q26,ROUND(Q26*Datos!$J$18,Dins)))))) -> 30 | N26: 35.4 | O26: =IF(A26>30000,ROUND(N26/$O$14,Dins),ROUND(N26,Dins)) -> 30 | P26: =ROUND(N26/$P$14,Dins) -> 9.44 | Q26: =IF(A26>30000,ROUND(P26/$Q$14,Dins),ROUND(P26,Dins)) -> 8
A27: 30008 | B27: 30 | C27: MA | D27: TEODOLITO | E27: día | F27: =IF(AND($F$15=Datos!$AI$5,Datos!$C$9=Datos!$AI$10),IF(A27>30000,N27,ROUND(N27*Datos!$J$18,Dins)),IF(AND($F$15=Datos!$AI$5,Datos!$C$9=Datos!$AI$9),IF(A27>30000,O27,ROUND(O27*Datos!$J$18,Dins)),IF(AND($F$15=Datos!$AI$6,Datos!$C$9=Datos!$AI$10),IF(A27>30000,P27,ROUND(P27*Datos!$J$18,Dins)),IF(AND($F$15=Datos!$AI$6,Datos!$C$9=Datos!$AI$9),IF(A27>30000,Q27,ROUND(Q27*Datos!$J$18,Dins)))))) -> 50 | N27: 59 | O27: =IF(A27>30000,ROUND(N27/$O$14,Dins),ROUND(N27,Dins)) -> 50 | P27: =ROUND(N27/$P$14,Dins) -> 15.73 | Q27: =IF(A27>30000,ROUND(P27/$Q$14,Dins),ROUND(P27,Dins)) -> 13.33
... A82: 30043 | B82: 37 | C82: MA | D82: REGLA DE ALUMINIO 1" X 4" X 8" | E82: und | F82: =IF(AND($F$15=Datos!$AI$5,Datos!$C$9=Datos!$AI$10),IF(A82>30000,N82,ROUND(N82*Datos!$J$18,Dins)),IF(AND($F$15=Datos!$AI$5,Datos!$C$9=Datos!$AI$9),IF(A82>30000,O82,ROUND(O82*Datos!$J$18,Dins)),IF(AND($F$15=Datos!$AI$6,Datos!$C$9=Datos!$AI$10),IF(A82>30000,P82,ROUND(P82*Datos!$J$18,Dins)),IF(AND($F$15=Datos!$AI$6,Datos!$C$9=Datos!$AI$9),IF(A82>30000,Q82,ROUND(Q82*Datos!$J$18,Dins)))))) -> 60 | N82: 70.8 | O82: =IF(A82>30000,ROUND(N82/$O$14,Dins),ROUND(N82,Dins)) -> 60 | P82: =ROUND(N82/$P$14,Dins) -> 18.88 | Q82: =IF(A82>30000,ROUND(P82/$Q$14,Dins),ROUND(P82,Dins)) -> 16
A83: 90001 | C83: SP | D83: =ApuB!B$225 -> MORTERO 1:4 (cemento - arena) | E83: =ApuB!D$225 -> m3 | F83: =ApuB!E$225 -> 290.2 | L83: =ApuB!A$225 -> 10045 | O83: =IF(A83>30000,ROUND(N83/$O$14,Dins),ROUND(N83,Dins)) -> 0 | P83: =ROUND(N83/$P$14,Dins) -> 0 | Q83: =IF(A83>30000,ROUND(P83/$Q$14,Dins),ROUND(P83,Dins)) -> 0
A84: 30044 | B84: 2 | C84: MA | D84: CLAVOS PARA MADERA CON CABEZA DE 1" | E84: kg | F84: =IF(AND($F$15=Datos!$AI$5,Datos!$C$9=Datos!$AI$10),IF(A84>30000,N84,ROUND(N84*Datos!$J$18,Dins)),IF(AND($F$15=Datos!$AI$5,Datos!$C$9=Datos!$AI$9),IF(A84>30000,O84,ROUND(O84*Datos!$J$18,Dins)),IF(AND($F$15=Datos!$AI$6,Datos!$C$9=Datos!$AI$10),IF(A84>30000,P84,ROUND(P84*Datos!$J$18,Dins)),IF(AND($F$15=Datos!$AI$6,Datos!$C$9=Datos!$AI$9),IF(A84>30000,Q84,ROUND(Q84*Datos!$J$18,Dins)))))) -> 4.5 | N84: 5.31 | O84: =IF(A84>30000,ROUND(N84/$O$14,Dins),ROUND(N84,Dins)) -> 4.5 | P84: =ROUND(N84/$P$14,Dins) -> 1.42 | Q84: =IF(A84>30000,ROUND(P84/$Q$14,Dins),ROUND(P84,Dins)) -> 1.2
A85: 30045 | B85: 39 | C85: MA | D85: AGUARRAS MINERAL | E85: gal | F85: =IF(AND($F$15=Datos!$AI$5,Datos!$C$9=Datos!$AI$10),IF(A85>30000,N85,ROUND(N85*Datos!$J$18,Dins)),IF(AND($F$15=Datos!$AI$5,Datos!$C$9=Datos!$AI$9),IF(A85>30000,O85,ROUND(O85*Datos!$J$18,Dins)),IF(AND($F$15=Datos!$AI$6,Datos!$C$9=Datos!$AI$10),IF(A85>30000,P85,ROUND(P85*Datos!$J$18,Dins)),IF(AND($F$15=Datos!$AI$6,Datos!$C$9=Datos!$AI$9),IF(A85>30000,Q85,ROUND(Q85*Datos!$J$18,Dins)))))) -> 28 | N85: 33.04 | O85: =IF(A85>30000,ROUND(N85/$O$14,Dins),ROUND(N85,Dins)) -> 28 | P85: =ROUND(N85/$P$14,Dins) -> 8.81 | Q85: =IF(A85>30000,ROUND(P85/$Q$14,Dins),ROUND(P85,Dins)) -> 7.47
A86: 30046 | B86: 54 | C86: MA | D86: BARNIZ MARINO | E86: gal | F86: =IF(AND($F$15=Datos!$AI$5,Datos!$C$9=Datos!$AI$10),IF(A86>30000,N86,ROUND(N86*Datos!$J$18,Dins)),IF(AND($F$15=Datos!$AI$5,Datos!$C$9=Datos!$AI$9),IF(A86>30000,O86,ROUND(O86*Datos!$J$18,Dins)),IF(AND($F$15=Datos!$AI$6,Datos!$C$9=Datos!$AI$10),IF(A86>30000,P86,ROUND(P86*Datos!$J$18,Dins)),IF(AND($F$15=Datos!$AI$6,Datos!$C$9=Datos!$AI$9),IF(A86>30000,Q86,ROUND(Q86*Datos!$J$18,Dins)))))) -> 60 | N86: 70.8 | O86: =IF(A86>30000,ROUND(N86/$O$14,Dins),ROUND(N86,Dins)) -> 60 | P86: =ROUND(N86/$P$14,Dins) -> 18.88 | Q86: =IF(A86>30000,ROUND(P86/$Q$14,Dins),ROUND(P86,Dins)) -> 16
A87: 30047 | B87: 37 | C87: MA | D87: REGLA DE ALUMINIO 1½" X 4" X 10" | E87: und | F87: =IF(AND($F$15=Datos!$AI$5,Datos!$C$9=Datos!$AI$10),IF(A87>30000,N87,ROUND(N87*Datos!$J$18,Dins)),IF(AND($F$15=Datos!$AI$5,Datos!$C$9=Datos!$AI$9),IF(A87>30000,O87,ROUND(O87*Datos!$J$18,Dins)),IF(AND($F$15=Datos!$AI$6,Datos!$C$9=Datos!$AI$10),IF(A87>30000,P87,ROUND(P87*Datos!$J$18,Dins)),IF(AND($F$15=Datos!$AI$6,Datos!$C$9=Datos!$AI$9),IF(A87>30000,Q87,ROUND(Q87*Datos!$J$18,Dins)))))) -> 72 | N87: 84.96 | O87: =IF(A87>30000,ROUND(N87/$O$14,Dins),ROUND(N87,Dins)) -> 72 | P87: =ROUND(N87/$P$14,Dins) -> 22.66 | Q87: =IF(A87>30000,ROUND(P87/$Q$14,Dins),ROUND(P87,Dins)) -> 19.2
A88: 30048 | B88: 30 | C88: MA | D88: PORCELANATO VULCANO DE ZANNON 30 X 30 cm | E88: m2 | F88: =IF(AND($F$15=Datos!$AI$5,Datos!$C$9=Datos!$AI$10),IF(A88>30000,N88,ROUND(N88*Datos!$J$18,Dins)),IF(AND($F$15=Datos!$AI$5,Datos!$C$9=Datos!$AI$9),IF(A88>30000,O88,ROUND(O88*Datos!$J$18,Dins)),IF(AND($F$15=Datos!$AI$6,Datos!$C$9=Datos!$AI$10),IF(A88>30000,P88,ROUND(P88*Datos!$J$18,Dins)),IF(AND($F$15=Datos!$AI$6,Datos!$C$9=Datos!$AI$9),IF(A88>30000,Q88,ROUND(Q88*Datos!$J$18,Dins)))))) -> 16.5 | N88: 19.47 | O88: =IF(A88>30000,ROUND(N88/$O$14,Dins),ROUND(N88,Dins)) -> 16.5 | P88: =ROUND(N88/$P$14,Dins) -> 5.19 | Q88: =IF(A88>30000,ROUND(P88/$Q$14,Dins),ROUND(P88,Dins)) -> 4.4
A89: 30049 | B89: 39 | C89: MA | D89: FRAGUA NOVACEL COLOR GRIS | E89: kg | F89: =IF(AND($F$15=Datos!$AI$5,Datos!$C$9=Datos!$AI$10),IF(A89>30000,N89,ROUND(N89*Datos!$J$18,Dins)),IF(AND($F$15=Datos!$AI$5,Datos!$C$9=Datos!$AI$9),IF(A89>30000,O89,ROUND(O89*Datos!$J$18,Dins)),IF(AND($F$15=Datos!$AI$6,Datos!$C$9=Datos!$AI$10),IF(A89>30000,P89,ROUND(P89*Datos!$J$18,Dins)),IF(AND($F$15=Datos!$AI$6,Datos!$C$9=Datos!$AI$9),IF(A89>30000,Q89,ROUND(Q89*Datos!$J$18,Dins)))))) -> 6 | N89: 7.08 | O89: =IF(A89>30000,ROUND(N89/$O$14,Dins),ROUND(N89,Dins)) -> 6 | P89: =ROUND(N89/$P$14,Dins) -> 1.89 | Q89: =IF(A89>30000,ROUND(P89/$Q$14,Dins),ROUND(P89,Dins)) -> 1.6
A90: 90002 | C90: SP | D90: =ApuB!B$255 -> FRAGUA CON POLVO NOVACEL | E90: =ApuB!D$255 -> m2 | F90: =ApuB!E$255 -> 9.85 | L90: =ApuB!A$255 -> 10051 | O90: =IF(A90>30000,ROUND(N90/$O$14,Dins),ROUND(N90,Dins)) -> 0 | P90: =ROUND(N90/$P$14,Dins) -> 0 | Q90: =IF(A90>30000,ROUND(P90/$Q$14,Dins),ROUND(P90,Dins)) -> 0
A91: 30050 | B91: 30 | C91: MA | D91: PEGAMENTO EN POLVO NOVACEL | E91: kg | F91: =IF(AND($F$15=Datos!$AI$5,Datos!$C$9=Datos!$AI$10),IF(A91>30000,N91,ROUND(N91*Datos!$J$18,Dins)),IF(AND($F$15=Datos!$AI$5,Datos!$C$9=Datos!$AI$9),IF(A91>30000,O91,ROUND(O91*Datos!$J$18,Dins)),IF(AND($F$15=Datos!$AI$6,Datos!$C$9=Datos!$AI$10),IF(A91>30000,P91,ROUND(P91*Datos!$J$18,Dins)),IF(AND($F$15=Datos!$AI$6,Datos!$C$9=Datos!$AI$9),IF(A91>30000,Q91,ROUND(Q91*Datos!$J$18,Dins)))))) -> 0.6 | N91: 0.71 | O91: =IF(A91>30000,ROUND(N91/$O$14,Dins),ROUND(N91,Dins)) -> 0.6 | P91: =ROUND(N91/$P$14,Dins) -> 0.19 | Q91: =IF(A91>30000,ROUND(P91/$Q$14,Dins),ROUND(P91,Dins)) -> 0.16
A92: 30051 | B92: 24 | C92: MA | D92: CERAMICA CELIMA SERIE ANTIDESLIZANTE MOSAICO PISO/PARED 0.30X0.30 | E92: m2 | F92: =IF(AND($F$15=Datos!$AI$5,Datos!$C$9=Datos!$AI$10),IF(A92>30000,N92,ROUND(N92*Datos!$J$18,Dins)),IF(AND($F$15=Datos!$AI$5,Datos!$C$9=Datos!$AI$9),IF(A92>30000,O92,ROUND(O92*Datos!$J$18,Dins)),IF(AND($F$15=Datos!$AI$6,Datos!$C$9=Datos!$AI$10),IF(A92>30000,P92,ROUND(P92*Datos!$J$18,Dins)),IF(AND($F$15=Datos!$AI$6,Datos!$C$9=Datos!$AI$9),IF(A92>30000,Q92,ROUND(Q92*Datos!$J$18,Dins)))))) -> 45 | N92: 53.1 | O92: =IF(A92>30000,ROUND(N92/$O$14,Dins),ROUND(N92,Dins)) -> 45 | P92: =ROUND(N92/$P$14,Dins) -> 14.16 | Q92: =IF(A92>30000,ROUND(P92/$Q$14,Dins),ROUND(P92,Dins)) -> 12
A93: 30052 | B93: 39 | C93: MA | D93: ESCOBAS DE PAJA | E93: und | F93: =IF(AND($F$15=Datos!$AI$5,Datos!$C$9=Datos!$AI$10),IF(A93>30000,N93,ROUND(N93*Datos!$J$18,Dins)),IF(AND($F$15=Datos!$AI$5,Datos!$C$9=Datos!$AI$9),IF(A93>30000,O93,ROUND(O93*Datos!$J$18,Dins)),IF(AND($F$15=Datos!$AI$6,Datos!$C$9=Datos!$AI$10),IF(A93>30000,P93,ROUND(P93*Datos!$J$18,Dins)),IF(AND($F$15=Datos!$AI$6,Datos!$C$9=Datos!$AI$9),IF(A93>30000,Q93,ROUND(Q93*Datos!$J$18,Dins)))))) -> 12 | N93: 14.16 | O93: =IF(A93>30000,ROUND(N93/$O$14,Dins),ROUND(N93,Dins)) -> 12 | P93: =ROUND(N93/$P$14,Dins) -> 3.78 | Q93: =IF(A93>30000,ROUND(P93/$Q$14,Dins),ROUND(P93,Dins)) -> 3.2
A94: 90003 | C94: SP | D94: =ApuB!B$270 -> BASE GRANULAR E=0.10 m.COMPACTADA CON EQUIPO LIVIANO | E94: =ApuB!D$270 -> m2 | F94: =ApuB!E$270 -> 13.64 | L94: =ApuB!A$270 -> 10054 | O94: =IF(A94>30000,ROUND(N94/$O$14,Dins),ROUND(N94,Dins)) -> 0 | P94: =ROUND(N94/$P$14,Dins) -> 0 | Q94: =IF(A94>30000,ROUND(P94/$Q$14,Dins),ROUND(P94,Dins)) -> 0
A95: 30053 | B95: 30 | C95: MA | D95: PORCELANA NOVACEL COLOR | E95: kg | F95: =IF(AND($F$15=Datos!$AI$5,Datos!$C$9=Datos!$AI$10),IF(A95>30000,N95,ROUND(N95*Datos!$J$18,Dins)),IF(AND($F$15=Datos!$AI$5,Datos!$C$9=Datos!$AI$9),IF(A95>30000,O95,ROUND(O95*Datos!$J$18,Dins)),IF(AND($F$15=Datos!$AI$6,Datos!$C$9=Datos!$AI$10),IF(A95>30000,P95,ROUND(P95*Datos!$J$18,Dins)),IF(AND($F$15=Datos!$AI$6,Datos!$C$9=Datos!$AI$9),IF(A95>30000,Q95,ROUND(Q95*Datos!$J$18,Dins)))))) -> 6 | N95: 7.08 | O95: =IF(A95>30000,ROUND(N95/$O$14,Dins),ROUND(N95,Dins)) -> 6 | P95: =ROUND(N95/$P$14,Dins) -> 1.89 | Q95: =IF(A95>30000,ROUND(P95/$Q$14,Dins),ROUND(P95,Dins)) -> 1.6
A96: 90004 | C96: SP | D96: =ApuB!B$280 -> FRAGUA CON PORCELANA DE COLOR | E96: =ApuB!D$280 -> m2 | F96: =ApuB!E$280 -> 7.15 | L96: =ApuB!A$280 -> 10056 | O96: =IF(A96>30000,ROUND(N96/$O$14,Dins),ROUND(N96,Dins)) -> 0 | P96: =ROUND(N96/$P$14,Dins) -> 0 | Q96: =IF(A96>30000,ROUND(P96/$Q$14,Dins),ROUND(P96,Dins)) -> 0
A97: 30054 | B97: 24 | C97: MA | D97: CERAMICA CELIMA 0.30X0.30 cm | E97: m2 | F97: =IF(AND($F$15=Datos!$AI$5,Datos!$C$9=Datos!$AI$10),IF(A97>30000,N97,ROUND(N97*Datos!$J$18,Dins)),IF(AND($F$15=Datos!$AI$5,Datos!$C$9=Datos!$AI$9),IF(A97>30000,O97,ROUND(O97*Datos!$J$18,Dins)),IF(AND($F$15=Datos!$AI$6,Datos!$C$9=Datos!$AI$10),IF(A97>30000,P97,ROUND(P97*Datos!$J$18,Dins)),IF(AND($F$15=Datos!$AI$6,Datos!$C$9=Datos!$AI$9),IF(A97>30000,Q97,ROUND(Q97*Datos!$J$18,Dins)))))) -> 75 | N97: 88.5 | O97: =IF(A97>30000,ROUND(N97/$O$14,Dins),ROUND(N97,Dins)) -> 75 | P97: =ROUND(N97/$P$14,Dins) -> 23.6 | Q97: =IF(A97>30000,ROUND(P97/$Q$14,Dins),ROUND(P97,Dins)) -> 20
A98: 30055 | B98: 30 | C98: MA | D98: PEGAMENTO CELIMA EN POLVO | E98: kg | F98: =IF(AND($F$15=Datos!$AI$5,Datos!$C$9=Datos!$AI$10),IF(A98>30000,N98,ROUND(N98*Datos!$J$18,Dins)),IF(AND($F$15=Datos!$AI$5,Datos!$C$9=Datos!$AI$9),IF(A98>30000,O98,ROUND(O98*Datos!$J$18,Dins)),IF(AND($F$15=Datos!$AI$6,Datos!$C$9=Datos!$AI$10),IF(A98>30000,P98,ROUND(P98*Datos!$J$18,Dins)),IF(AND($F$15=Datos!$AI$6,Datos!$C$9=Datos!$AI$9),IF(A98>30000,Q98,ROUND(Q98*Datos!$J$18,Dins)))))) -> 0.6 | N98: 0.71 | O98: =IF(A98>30000,ROUND(N98/$O$14,Dins),ROUND(N98,Dins)) -> 0.6 | P98: =ROUND(N98/$P$14,Dins) -> 0.19 | Q98: =IF(A98>30000,ROUND(P98/$Q$14,Dins),ROUND(P98,Dins)) -> 0.16
A99: 30056 | B99: 17 | C99: MA | D99: TEJA ANDINA (1.16x0.70 m.) | E99: pln | F99: =IF(AND($F$15=Datos!$AI$5,Datos!$C$9=Datos!$AI$10),IF(A99>30000,N99,ROUND(N99*Datos!$J$18,Dins)),IF(AND($F$15=Datos!$AI$5,Datos!$C$9=Datos!$AI$9),IF(A99>30000,O99,ROUND(O99*Datos!$J$18,Dins)),IF(AND($F$15=Datos!$AI$6,Datos!$C$9=Datos!$AI$10),IF(A99>30000,P99,ROUND(P99*Datos!$J$18,Dins)),IF(AND($F$15=Datos!$AI$6,Datos!$C$9=Datos!$AI$9),IF(A99>30000,Q99,ROUND(Q99*Datos!$J$18,Dins)))))) -> 38 | N99: 44.84 | O99: =IF(A99>30000,ROUND(N99/$O$14,Dins),ROUND(N99,Dins)) -> 38 | P99: =ROUND(N99/$P$14,Dins) -> 11.96 | Q99: =IF(A99>30000,ROUND(P99/$Q$14,Dins),ROUND(P99,Dins)) -> 10.14
A100: 30057 | B100: 2 | C100: MA | D100: PERNOS DE ANCLAJE DE FIERRO GALVANIZADO CON CAPUCHON PLASTICO | E100: und | F100: =IF(AND($F$15=Datos!$AI$5,Datos!$C$9=Datos!$AI$10),IF(A100>30000,N100,ROUND(N100*Datos!$J$18,Dins)),IF(AND($F$15=Datos!$AI$5,Datos!$C$9=Datos!$AI$9),IF(A100>30000,O100,ROUND(O100*Datos!$J$18,Dins)),IF(AND($F$15=Datos!$AI$6,Datos!$C$9=Datos!$AI$10),IF(A100>30000,P100,ROUND(P100*Datos!$J$18,Dins)),IF(AND($F$15=Datos!$AI$6,Datos!$C$9=Datos!$AI$9),IF(A100>30000,Q100,ROUND(Q100*Datos!$J$18,Dins)))))) -> 1 | N100: 1.18 | O100: =IF(A100>30000,ROUND(N100/$O$14,Dins),ROUND(N100,Dins)) -> 1 | P100: =ROUND(N100/$P$14,Dins) -> 0.31 | Q100: =IF(A100>30000,ROUND(P100/$Q$14,Dins),ROUND(P100,Dins)) -> 0.26
A101: 30058 | B101: 26 | C101: MA | D101: CERRADURA PARA PUERTA PRINCIPAL | E101: und | F101: =IF(AND($F$15=Datos!$AI$5,Datos!$C$9=Datos!$AI$10),IF(A101>30000,N101,ROUND(N101*Datos!$J$18,Dins)),IF(AND($F$15=Datos!$AI$5,Datos!$C$9=Datos!$AI$9),IF(A101>30000,O101,ROUND(O101*Datos!$J$18,Dins)),IF(AND($F$15=Datos!$AI$6,Datos!$C$9=Datos!$AI$10),IF(A101>30000,P101,ROUND(P101*Datos!$J$18,Dins)),IF(AND($F$15=Datos!$AI$6,Datos!$C$9=Datos!$AI$9),IF(A101>30000,Q101,ROUND(Q101*Datos!$J$18,Dins)))))) -> 169.9 | N101: 200.48 | O101: =IF(A101>30000,ROUND(N101/$O$14,Dins),ROUND(N101,Dins)) -> 169.9 | P101: =ROUND(N101/$P$14,Dins) -> 53.46 | Q101: =IF(A101>30000,ROUND(P101/$Q$14,Dins),ROUND(P101,Dins)) -> 45.31
A102: 30059 | B102: 30 | C102: MA | D102: BISAGRA CAPUCHINA DE BRONCE 3" x 3" | E102: par | F102: =IF(AND($F$15=Datos!$AI$5,Datos!$C$9=Datos!$AI$10),IF(A102>30000,N102,ROUND(N102*Datos!$J$18,Dins)),IF(AND($F$15=Datos!$AI$5,Datos!$C$9=Datos!$AI$9),IF(A102>30000,O102,ROUND(O102*Datos!$J$18,Dins)),IF(AND($F$15=Datos!$AI$6,Datos!$C$9=Datos!$AI$10),IF(A102>30000,P102,ROUND(P102*Datos!$J$18,Dins)),IF(AND($F$15=Datos!$AI$6,Datos!$C$9=Datos!$AI$9),IF(A102>30000,Q102,ROUND(Q102*Datos!$J$18,Dins)))))) -> 24 | N102: 28.32 | O102: =IF(A102>30000,ROUND(N102/$O$14,Dins),ROUND(N102,Dins)) -> 24 | P102: =ROUND(N102/$P$14,Dins) -> 7.55 | Q102: =IF(A102>30000,ROUND(P102/$Q$14,Dins),ROUND(P102,Dins)) -> 6.4
A103: 80003 | B103: 39 | C103: SERVICIO | D103: PUERTA APANELADA P-02 | E103: und | F103: =IF(AND($F$15=Datos!$AI$5,Datos!$C$9=Datos!$AI$10),IF(A103>30000,N103,ROUND(N103*Datos!$J$18,Dins)),IF(AND($F$15=Datos!$AI$5,Datos!$C$9=Datos!$AI$9),IF(A103>30000,O103,ROUND(O103*Datos!$J$18,Dins)),IF(AND($F$15=Datos!$AI$6,Datos!$C$9=Datos!$AI$10),IF(A103>30000,P103,ROUND(P103*Datos!$J$18,Dins)),IF(AND($F$15=Datos!$AI$6,Datos!$C$9=Datos!$AI$9),IF(A103>30000,Q103,ROUND(Q103*Datos!$J$18,Dins)))))) -> 1600 | N103: 1888 | O103: =IF(A103>30000,ROUND(N103/$O$14,Dins),ROUND(N103,Dins)) -> 1600 | P103: =ROUND(N103/$P$14,Dins) -> 503.47 | Q103: =IF(A103>30000,ROUND(P103/$Q$14,Dins),ROUND(P103,Dins)) -> 426.67
A104: 30060 | B104: 26 | C104: MA | D104: CERRADURA YALE PRINCIPAL | E104: und | F104: =IF(AND($F$15=Datos!$AI$5,Datos!$C$9=Datos!$AI$10),IF(A104>30000,N104,ROUND(N104*Datos!$J$18,Dins)),IF(AND($F$15=Datos!$AI$5,Datos!$C$9=Datos!$AI$9),IF(A104>30000,O104,ROUND(O104*Datos!$J$18,Dins)),IF(AND($F$15=Datos!$AI$6,Datos!$C$9=Datos!$AI$10),IF(A104>30000,P104,ROUND(P104*Datos!$J$18,Dins)),IF(AND($F$15=Datos!$AI$6,Datos!$C$9=Datos!$AI$9),IF(A104>30000,Q104,ROUND(Q104*Datos!$J$18,Dins)))))) -> 129.9 | N104: 153.28 | O104: =IF(A104>30000,ROUND(N104/$O$14,Dins),ROUND(N104,Dins)) -> 129.9 | P104: =ROUND(N104/$P$14,Dins) -> 40.87 | Q104: =IF(A104>30000,ROUND(P104/$Q$14,Dins),ROUND(P104,Dins)) -> 34.64
A105: 80004 | B105: 39 | C105: SERVICIO | D105: PUERTA APANELADA P-01 | E105: und | F105: =IF(AND($F$15=Datos!$AI$5,Datos!$C$9=Datos!$AI$10),IF(A105>30000,N105,ROUND(N105*Datos!$J$18,Dins)),IF(AND($F$15=Datos!$AI$5,Datos!$C$9=Datos!$AI$9),IF(A105>30000,O105,ROUND(O105*Datos!$J$18,Dins)),IF(AND($F$15=Datos!$AI$6,Datos!$C$9=Datos!$AI$10),IF(A105>30000,P105,ROUND(P105*Datos!$J$18,Dins)),IF(AND($F$15=Datos!$AI$6,Datos!$C$9=Datos!$AI$9),IF(A105>30000,Q105,ROUND(Q105*Datos!$J$18,Dins)))))) -> 1100 | N105: 1298 | O105: =IF(A105>30000,ROUND(N105/$O$14,Dins),ROUND(N105,Dins)) -> 1100 | P105: =ROUND(N105/$P$14,Dins) -> 346.13 | Q105: =IF(A105>30000,ROUND(P105/$Q$14,Dins),ROUND(P105,Dins)) -> 293.33
A106: 30061 | B106: 30 | C106: MA | D106: BISAGRA CAPUCHINA DE BRONCE | E106: par | F106: =IF(AND($F$15=Datos!$AI$5,Datos!$C$9=Datos!$AI$10),IF(A106>30000,N106,ROUND(N106*Datos!$J$18,Dins)),IF(AND($F$15=Datos!$AI$5,Datos!$C$9=Datos!$AI$9),IF(A106>30000,O106,ROUND(O106*Datos!$J$18,Dins)),IF(AND($F$15=Datos!$AI$6,Datos!$C$9=Datos!$AI$10),IF(A106>30000,P106,ROUND(P106*Datos!$J$18,Dins)),IF(AND($F$15=Datos!$AI$6,Datos!$C$9=Datos!$AI$9),IF(A106>30000,Q106,ROUND(Q106*Datos!$J$18,Dins)))))) -> 24 | N106: 28.32 | O106: =IF(A106>30000,ROUND(N106/$O$14,Dins),ROUND(N106,Dins)) -> 24 | P106: =ROUND(N106/$P$14,Dins) -> 7.55 | Q106: =IF(A106>30000,ROUND(P106/$Q$14,Dins),ROUND(P106,Dins)) -> 6.4
A107: 30062 | B107: 26 | C107: MA | D107: CERRADURA PARA PUERTA INTERIOR | E107: und | F107: =IF(AND($F$15=Datos!$AI$5,Datos!$C$9=Datos!$AI$10),IF(A107>30000,N107,ROUND(N107*Datos!$J$18,Dins)),IF(AND($F$15=Datos!$AI$5,Datos!$C$9=Datos!$AI$9),IF(A107>30000,O107,ROUND(O107*Datos!$J$18,Dins)),IF(AND($F$15=Datos!$AI$6,Datos!$C$9=Datos!$AI$10),IF(A107>30000,P107,ROUND(P107*Datos!$J$18,Dins)),IF(AND($F$15=Datos!$AI$6,Datos!$C$9=Datos!$AI$9),IF(A107>30000,Q107,ROUND(Q107*Datos!$J$18,Dins)))))) -> 34.9 | N107: 41.18 | O107: =IF(A107>30000,ROUND(N107/$O$14,Dins),ROUND(N107,Dins)) -> 34.9 | P107: =ROUND(N107/$P$14,Dins) -> 10.98 | Q107: =IF(A107>30000,ROUND(P107/$Q$14,Dins),ROUND(P107,Dins)) -> 9.31
A108: 80005 | B108: 39 | C108: SERVICIO | D108: PUERTA CONTRAPLACADA P-01 A TODO COSTO | E108: und | F108: =IF(AND($F$15=Datos!$AI$5,Datos!$C$9=Datos!$AI$10),IF(A108>30000,N108,ROUND(N108*Datos!$J$18,Dins)),IF(AND($F$15=Datos!$AI$5,Datos!$C$9=Datos!$AI$9),IF(A108>30000,O108,ROUND(O108*Datos!$J$18,Dins)),IF(AND($F$15=Datos!$AI$6,Datos!$C$9=Datos!$AI$10),IF(A108>30000,P108,ROUND(P108*Datos!$J$18,Dins)),IF(AND($F$15=Datos!$AI$6,Datos!$C$9=Datos!$AI$9),IF(A108>30000,Q108,ROUND(Q108*Datos!$J$18,Dins)))))) -> 500 | N108: 590 | O108: =IF(A108>30000,ROUND(N108/$O$14,Dins),ROUND(N108,Dins)) -> 500 | P108: =ROUND(N108/$P$14,Dins) -> 157.33 | Q108: =IF(A108>30000,ROUND(P108/$Q$14,Dins),ROUND(P108,Dins)) -> 133.33
... A197: 30141 | B197: 77 | C197: MA | D197: VALVULA COMPUERTA DE 1" | E197: und | F197: =IF(AND($F$15=Datos!$AI$5,Datos!$C$9=Datos!$AI$10),IF(A197>30000,N197,ROUND(N197*Datos!$J$18,Dins)),IF(AND($F$15=Datos!$AI$5,Datos!$C$9=Datos!$AI$9),IF(A197>30000,O197,ROUND(O197*Datos!$J$18,Dins)),IF(AND($F$15=Datos!$AI$6,Datos!$C$9=Datos!$AI$10),IF(A197>30000,P197,ROUND(P197*Datos!$J$18,Dins)),IF(AND($F$15=Datos!$AI$6,Datos!$C$9=Datos!$AI$9),IF(A197>30000,Q197,ROUND(Q197*Datos!$J$18,Dins)))))) -> 42.55 | N197: 50.21 | O197: =IF(A197>30000,ROUND(N197/$O$14,Dins),ROUND(N197,Dins)) -> 42.55 | P197: =ROUND(N197/$P$14,Dins) -> 13.39 | Q197: =IF(A197>30000,ROUND(P197/$Q$14,Dins),ROUND(P197,Dins)) -> 11.35

Sheet ApuB
A1: 0 | B1: =MATCH($A$1,$A$5:$A$50004,0)+4 -> #N/A | C1: =#REF! -> #REF!
A2: =COUNT(BDcodCU)*5+5 -> 490 | C2: =COUNT(BDcodCU) -> 97
A3: =MAX($A$5:$A$50004)+1 -> 10098 | B3: Cifra de redondeo decimal del parcial | C3: =Datos!J12 -> 2
A4: Cod | B4: Denominación | C4: RTOf | D4: UND | E4: PU | F4: MO | G4: MA | H4: EQ | I4: nINS | J4: RTOi | K4: P.EST. | M4: SP | N4: ET | O4: 1 | P4: 2 | Q4: 3 | R4: 4 | S4: 5 | T4: 6 | U4: 7 | V4: 8 | W4: 9 | X4: 10 | Y4: 11 | Z4: 12 | AA4: 13 | AB4: 14 | AC4: 15 | AD4: 16 | AE4: 17 | AF4: 18 | AG4: 19 | AH4: 20 | AI4: 21 | AJ4: 22 | AK4: 23 | AL4: 24 | AM4: 25 | AN4: 26 | AO4: 27 | AP4: 28 | AQ4: 29 | AR4: 30 | AS4: 31 | AT4: 32 | AU4: 33 | AV4: 34 | AW4: 35 | AX4: 36 | AY4: 37 | AZ4: 38 | BA4: 39 | BB4: 40 | BC4: 41 | BD4: 42 | BE4: 43 | BF4: 44 | BG4: 45 | BH4: 46 | BI4: 47 | BJ4: 48 | BK4: 49 | BL4: 50 | BM4: 51 | BN4: 52 | BO4: 53 | BP4: 54 | BQ4: 55 | BR4: 56 | BS4: 57 | BT4: 58 | BU4: 59 | BV4: 60 | BW4: 61 | BX4: 62 | BY4: 63 | BZ4: 64 | CA4: 65 | CB4: 66 | CC4: 67 | CD4: 68 | CE4: 69 | CF4: 70 | CG4: 71 | CH4: 72 | CI4: 73 | CJ4: 74 | CK4: 75 | CL4: 76 | CM4: 77 | CN4: 78 | CO4: 79 | CP4: 80 | CQ4: 81 | CR4: 82 | CS4: 83 | CT4: 84 | CU4: 85 | CV4: 86 | CW4: 87 | CX4: 88 | CY4: 89 | CZ4: 90 | DA4: 91 | DB4: 92 | DC4: 93 | DD4: 94 | DE4: 95 | DF4: 96 | DG4: 97 | DH4: 98 | DI4: 99 | DJ4: 100
A5: 10001 | B5: TRAZO Y REPLANTEO INICIAL | C5: =ROUND(J5*JL*Frto/8,4) -> 200 | D5: m2 | E5: =SUM($O8:$X8) -> 3.02 | F5: =SUMIF($O5:$X5,"<22501",$O8:$X8) -> 1.21 | G5: =SUMIFS($O8:$X8,$O5:$X5,">30000",$O5:$X5,"<50001") -> 1.41 | H5: =SUMIFS($O8:$X8,$O5:$X5,">60000",$O5:$X5,"<70001") -> 0.4 | I5: 10 | J5: 200 | O5: 10001 | P5: 10002 | Q5: 30001 | R5: 30002 | S5: 30003 | T5: 30004 | U5: 30005 | V5: 30006 | W5: 60001 | X5: 60002
B6: =A5&"C" -> 10001C | O6: 1 | P6: 1 | Q6: 0.018 | R6: 0.0062 | S6: 0.02 | T6: 0.01 | U6: 0.005 | V6: 0.0015 | W6: 1 | X6: 1
O7: =IF(O9>10000,HLOOKUP(O9,N5:$O8,4,FALSE),IF(OR(AND(22500<O5,O5<25001),AND(50000<O5,O5<53501),AND(70000<O5,O5<72501)),$F5,IF(OR(AND(25001<O5,O5<27501),AND(53500<O5,O5<57001),AND(72500<O5,O5<75001)),$G5,IF(OR(AND(27500<O5,O5<30001),AND(57000<O5,O5<60001),AND(75000<O5,O5<77500)),$H5,VLOOKUP(O5,BDins,6,FALSE))))) -> 12.64 | P7: =IF(P9>10000,HLOOKUP(P9,O5:$O8,4,FALSE),IF(OR(AND(22500<P5,P5<25001),AND(50000<P5,P5<53501),AND(70000<P5,P5<72501)),$F5,IF(OR(AND(25001<P5,P5<27501),AND(53500<P5,P5<57001),AND(72500<P5,P5<75001)),$G5,IF(OR(AND(27500<P5,P5<30001),AND(57000<P5,P5<60001),AND(75000<P5,P5<77500)),$H5,VLOOKUP(P5,BDins,6,FALSE))))) -> 17.59 | Q7: =IF(Q9>10000,HLOOKUP(Q9,$O5:P8,4,FALSE),IF(OR(AND(22500<Q5,Q5<25001),AND(50000<Q5,Q5<53501),AND(70000<Q5,Q5<72501)),$F5,IF(OR(AND(25001<Q5,Q5<27501),AND(53500<Q5,Q5<57001),AND(72500<Q5,Q5<75001)),$G5,IF(OR(AND(27500<Q5,Q5<30001),AND(57000<Q5,Q5<60001),AND(75000<Q5,Q5<77500)),$H5,VLOOKUP(Q5,BDins,6,FALSE))))) -> 27 | R7: =IF(R9>10000,HLOOKUP(R9,$O5:Q8,4,FALSE),IF(OR(AND(22500<R5,R5<25001),AND(50000<R5,R5<53501),AND(70000<R5,R5<72501)),$F5,IF(OR(AND(25001<R5,R5<27501),AND(53500<R5,R5<57001),AND(72500<R5,R5<75001)),$G5,IF(OR(AND(27500<R5,R5<30001),AND(57000<R5,R5<60001),AND(75000<R5,R5<77500)),$H5,VLOOKUP(R5,BDins,6,FALSE))))) -> 41.3 | S7: =IF(S9>10000,HLOOKUP(S9,$O5:R8,4,FALSE),IF(OR(AND(22500<S5,S5<25001),AND(50000<S5,S5<53501),AND(70000<S5,S5<72501)),$F5,IF(OR(AND(25001<S5,S5<27501),AND(53500<S5,S5<57001),AND(72500<S5,S5<75001)),$G5,IF(OR(AND(27500<S5,S5<30001),AND(57000<S5,S5<60001),AND(75000<S5,S5<77500)),$H5,VLOOKUP(S5,BDins,6,FALSE))))) -> 20 | T7: =IF(T9>10000,HLOOKUP(T9,$O5:S8,4,FALSE),IF(OR(AND(22500<T5,T5<25001),AND(50000<T5,T5<53501),AND(70000<T5,T5<72501)),$F5,IF(OR(AND(25001<T5,T5<27501),AND(53500<T5,T5<57001),AND(72500<T5,T5<75001)),$G5,IF(OR(AND(27500<T5,T5<30001),AND(57000<T5,T5<60001),AND(75000<T5,T5<77500)),$H5,VLOOKUP(T5,BDins,6,FALSE))))) -> 8 | U7: =IF(U9>10000,HLOOKUP(U9,$O5:T8,4,FALSE),IF(OR(AND(22500<U5,U5<25001),AND(50000<U5,U5<53501),AND(70000<U5,U5<72501)),$F5,IF(OR(AND(25001<U5,U5<27501),AND(53500<U5,U5<57001),AND(72500<U5,U5<75001)),$G5,IF(OR(AND(27500<U5,U5<30001),AND(57000<U5,U5<60001),AND(75000<U5,U5<77500)),$H5,VLOOKUP(U5,BDins,6,FALSE))))) -> 28 | V7: =IF(V9>10000,HLOOKUP(V9,$O5:U8,4,FALSE),IF(OR(AND(22500<V5,V5<25001),AND(50000<V5,V5<53501),AND(70000<V5,V5<72501)),$F5,IF(OR(AND(25001<V5,V5<27501),AND(53500<V5,V5<57001),AND(72500<V5,V5<75001)),$G5,IF(OR(AND(27500<V5,V5<30001),AND(57000<V5,V5<60001),AND(75000<V5,V5<77500)),$H5,VLOOKUP(V5,BDins,6,FALSE))))) -> 23.8 | W7: =IF(W9>10000,HLOOKUP(W9,$O5:V8,4,FALSE),IF(OR(AND(22500<W5,W5<25001),AND(50000<W5,W5<53501),AND(70000<W5,W5<72501)),$F5,IF(OR(AND(25001<W5,W5<27501),AND(53500<W5,W5<57001),AND(72500<W5,W5<75001)),$G5,IF(OR(AND(27500<W5,W5<30001),AND(57000<W5,W5<60001),AND(75000<W5,W5<77500)),$H5,VLOOKUP(W5,BDins,6,FALSE))))) -> 3.75 | X7: =IF(X9>10000,HLOOKUP(X9,$O5:W8,4,FALSE),IF(OR(AND(22500<X5,X5<25001),AND(50000<X5,X5<53501),AND(70000<X5,X5<72501)),$F5,IF(OR(AND(25001<X5,X5<27501),AND(53500<X5,X5<57001),AND(72500<X5,X5<75001)),$G5,IF(OR(AND(27500<X5,X5<30001),AND(57000<X5,X5<60001),AND(75000<X5,X5<77500)),$H5,VLOOKUP(X5,BDins,6,FALSE))))) -> 6.25
O8: =IF($K5>0,ROUND(O6*$E5/100,DpCU),IF(O9>10000,ROUND(HLOOKUP(O9,$O5:$X8,4,FALSE)/100*O6,DpCU),IF(OR(O5<20001,O5>95000,AND(60000<O5,O5<70001)),ROUND(ROUND(O6*JL/$C5,DcCU)*O7,DpCU),IF(OR(AND(20000<O5,O5<22501),AND(30000<O5,O5<50001),77500<O5),ROUND(O7*O6,DpCU),IF(OR(AND(22500<O5,O5<25001),AND(50000<O5,O5<53501),AND(70000<O5,O5<72501)),ROUND($F5/100*O6,DpCU),IF(OR(AND(25000<O5,O5<27501),AND(53500<O5,O5<57001),AND(72500<O5,O5<75001)),ROUND($G5/100*O6,DpCU),ROUND($H5/100*O6,DpCU))))))) -> 0.51 | P8: =IF($K5>0,ROUND(P6*$E5/100,DpCU),IF(P9>10000,ROUND(HLOOKUP(P9,$O5:$X8,4,FALSE)/100*P6,DpCU),IF(OR(P5<20001,P5>95000,AND(60000<P5,P5<70001)),ROUND(ROUND(P6*JL/$C5,DcCU)*P7,DpCU),IF(OR(AND(20000<P5,P5<22501),AND(30000<P5,P5<50001),77500<P5),ROUND(P7*P6,DpCU),IF(OR(AND(22500<P5,P5<25001),AND(50000<P5,P5<53501),AND(70000<P5,P5<72501)),ROUND($F5/100*P6,DpCU),IF(OR(AND(25000<P5,P5<27501),AND(53500<P5,P5<57001),AND(72500<P5,P5<75001)),ROUND($G5/100*P6,DpCU),ROUND($H5/100*P6,DpCU))))))) -> 0.7 | Q8: =IF($K5>0,ROUND(Q6*$E5/100,DpCU),IF(Q9>10000,ROUND(HLOOKUP(Q9,$O5:$X8,4,FALSE)/100*Q6,DpCU),IF(OR(Q5<20001,Q5>95000,AND(60000<Q5,Q5<70001)),ROUND(ROUND(Q6*JL/$C5,DcCU)*Q7,DpCU),IF(OR(AND(20000<Q5,Q5<22501),AND(30000<Q5,Q5<50001),77500<Q5),ROUND(Q7*Q6,DpCU),IF(OR(AND(22500<Q5,Q5<25001),AND(50000<Q5,Q5<53501),AND(70000<Q5,Q5<72501)),ROUND($F5/100*Q6,DpCU),IF(OR(AND(25000<Q5,Q5<27501),AND(53500<Q5,Q5<57001),AND(72500<Q5,Q5<75001)),ROUND($G5/100*Q6,DpCU),ROUND($H5/100*Q6,DpCU))))))) -> 0.49 | R8: =IF($K5>0,ROUND(R6*$E5/100,DpCU),IF(R9>10000,ROUND(HLOOKUP(R9,$O5:$X8,4,FALSE)/100*R6,DpCU),IF(OR(R5<20001,R5>95000,AND(60000<R5,R5<70001)),ROUND(ROUND(R6*JL/$C5,DcCU)*R7,DpCU),IF(OR(AND(20000<R5,R5<22501),AND(30000<R5,R5<50001),77500<R5),ROUND(R7*R6,DpCU),IF(OR(AND(22500<R5,R5<25001),AND(50000<R5,R5<53501),AND(70000<R5,R5<72501)),ROUND($F5/100*R6,DpCU),IF(OR(AND(25000<R5,R5<27501),AND(53500<R5,R5<57001),AND(72500<R5,R5<75001)),ROUND($G5/100*R6,DpCU),ROUND($H5/100*R6,DpCU))))))) -> 0.26 | S8: =IF($K5>0,ROUND(S6*$E5/100,DpCU),IF(S9>10000,ROUND(HLOOKUP(S9,$O5:$X8,4,FALSE)/100*S6,DpCU),IF(OR(S5<20001,S5>95000,AND(60000<S5,S5<70001)),ROUND(ROUND(S6*JL/$C5,DcCU)*S7,DpCU),IF(OR(AND(20000<S5,S5<22501),AND(30000<S5,S5<50001),77500<S5),ROUND(S7*S6,DpCU),IF(OR(AND(22500<S5,S5<25001),AND(50000<S5,S5<53501),AND(70000<S5,S5<72501)),ROUND($F5/100*S6,DpCU),IF(OR(AND(25000<S5,S5<27501),AND(53500<S5,S5<57001),AND(72500<S5,S5<75001)),ROUND($G5/100*S6,DpCU),ROUND($H5/100*S6,DpCU))))))) -> 0.4 | T8: =IF($K5>0,ROUND(T6*$E5/100,DpCU),IF(T9>10000,ROUND(HLOOKUP(T9,$O5:$X8,4,FALSE)/100*T6,DpCU),IF(OR(T5<20001,T5>95000,AND(60000<T5,T5<70001)),ROUND(ROUND(T6*JL/$C5,DcCU)*T7,DpCU),IF(OR(AND(20000<T5,T5<22501),AND(30000<T5,T5<50001),77500<T5),ROUND(T7*T6,DpCU),IF(OR(AND(22500<T5,T5<25001),AND(50000<T5,T5<53501),AND(70000<T5,T5<72501)),ROUND($F5/100*T6,DpCU),IF(OR(AND(25000<T5,T5<27501),AND(53500<T5,T5<57001),AND(72500<T5,T5<75001)),ROUND($G5/100*T6,DpCU),ROUND($H5/100*T6,DpCU))))))) -> 0.08 | U8: =IF($K5>0,ROUND(U6*$E5/100,DpCU),IF(U9>10000,ROUND(HLOOKUP(U9,$O5:$X8,4,FALSE)/100*U6,DpCU),IF(OR(U5<20001,U5>95000,AND(60000<U5,U5<70001)),ROUND(ROUND(U6*JL/$C5,DcCU)*U7,DpCU),IF(OR(AND(20000<U5,U5<22501),AND(30000<U5,U5<50001),77500<U5),ROUND(U7*U6,DpCU),IF(OR(AND(22500<U5,U5<25001),AND(50000<U5,U5<53501),AND(70000<U5,U5<72501)),ROUND($F5/100*U6,DpCU),IF(OR(AND(25000<U5,U5<27501),AND(53500<U5,U5<57001),AND(72500<U5,U5<75001)),ROUND($G5/100*U6,DpCU),ROUND($H5/100*U6,DpCU))))))) -> 0.14 | V8: =IF($K5>0,ROUND(V6*$E5/100,DpCU),IF(V9>10000,ROUND(HLOOKUP(V9,$O5:$X8,4,FALSE)/100*V6,DpCU),IF(OR(V5<20001,V5>95000,AND(60000<V5,V5<70001)),ROUND(ROUND(V6*JL/$C5,DcCU)*V7,DpCU),IF(OR(AND(20000<V5,V5<22501),AND(30000<V5,V5<50001),77500<V5),ROUND(V7*V6,DpCU),IF(OR(AND(22500<V5,V5<25001),AND(50000<V5,V5<53501),AND(70000<V5,V5<72501)),ROUND($F5/100*V6,DpCU),IF(OR(AND(25000<V5,V5<27501),AND(53500<V5,V5<57001),AND(72500<V5,V5<75001)),ROUND($G5/100*V6,DpCU),ROUND($H5/100*V6,DpCU))))))) -> 0.04 | ... X8: =IF($K5>0,ROUND(X6*$E5/100,DpCU),IF(X9>10000,ROUND(HLOOKUP(X9,$O5:$X8,4,FALSE)/100*X6,DpCU),IF(OR(X5<20001,X5>95000,AND(60000<X5,X5<70001)),ROUND(ROUND(X6*JL/$C5,DcCU)*X7,DpCU),IF(OR(AND(20000<X5,X5<22501),AND(30000<X5,X5<50001),77500<X5),ROUND(X7*X6,DpCU),IF(OR(AND(22500<X5,X5<25001),AND(50000<X5,X5<53501),AND(70000<X5,X5<72501)),ROUND($F5/100*X6,DpCU),IF(OR(AND(25000<X5,X5<27501),AND(53500<X5,X5<57001),AND(72500<X5,X5<75001)),ROUND($G5/100*X6,DpCU),ROUND($H5/100*X6,DpCU))))))) -> 0.25
B9: =A5&"r" -> 10001r
A10: 10002 | B10: TRAZO DURANTE LA EJECUCION DE LA OBRA (casco) | C10: =ROUND(J10*JL*Frto/8,4) -> 1 | D10: mes | E10: =SUM($O13:$T13) -> 5296.05 | F10: =SUMIF($O10:$T10,"<22501",$O13:$T13) -> 4081.05 | G10: =SUMIFS($O13:$T13,$O10:$T10,">30000",$O10:$T10,"<50001") -> 1215 | H10: =SUMIFS($O13:$T13,$O10:$T10,">60000",$O10:$T10,"<70001") -> 0 | I10: 6 | J10: 1 | O10: 10001 | P10: 10002 | Q10: 30004 | R10: 30005 | S10: 30007 | T10: 30008
B11: =A10&"C" -> 10002C | O11: 16.875 | P11: 16.875 | Q11: 1 | R11: 0.25 | S11: 15 | T11: 15
O12: =IF(O14>10000,HLOOKUP(O14,N10:$O13,4,FALSE),IF(OR(AND(22500<O10,O10<25001),AND(50000<O10,O10<53501),AND(70000<O10,O10<72501)),$F10,IF(OR(AND(25001<O10,O10<27501),AND(53500<O10,O10<57001),AND(72500<O10,O10<75001)),$G10,IF(OR(AND(27500<O10,O10<30001),AND(57000<O10,O10<60001),AND(75000<O10,O10<77500)),$H10,VLOOKUP(O10,BDins,6,FALSE))))) -> 12.64 | P12: =IF(P14>10000,HLOOKUP(P14,O10:$O13,4,FALSE),IF(OR(AND(22500<P10,P10<25001),AND(50000<P10,P10<53501),AND(70000<P10,P10<72501)),$F10,IF(OR(AND(25001<P10,P10<27501),AND(53500<P10,P10<57001),AND(72500<P10,P10<75001)),$G10,IF(OR(AND(27500<P10,P10<30001),AND(57000<P10,P10<60001),AND(75000<P10,P10<77500)),$H10,VLOOKUP(P10,BDins,6,FALSE))))) -> 17.59 | Q12: =IF(Q14>10000,HLOOKUP(Q14,$O10:P13,4,FALSE),IF(OR(AND(22500<Q10,Q10<25001),AND(50000<Q10,Q10<53501),AND(70000<Q10,Q10<72501)),$F10,IF(OR(AND(25001<Q10,Q10<27501),AND(53500<Q10,Q10<57001),AND(72500<Q10,Q10<75001)),$G10,IF(OR(AND(27500<Q10,Q10<30001),AND(57000<Q10,Q10<60001),AND(75000<Q10,Q10<77500)),$H10,VLOOKUP(Q10,BDins,6,FALSE))))) -> 8 | R12: =IF(R14>10000,HLOOKUP(R14,$O10:Q13,4,FALSE),IF(OR(AND(22500<R10,R10<25001),AND(50000<R10,R10<53501),AND(70000<R10,R10<72501)),$F10,IF(OR(AND(25001<R10,R10<27501),AND(53500<R10,R10<57001),AND(72500<R10,R10<75001)),$G10,IF(OR(AND(27500<R10,R10<30001),AND(57000<R10,R10<60001),AND(75000<R10,R10<77500)),$H10,VLOOKUP(R10,BDins,6,FALSE))))) -> 28 | S12: =IF(S14>10000,HLOOKUP(S14,$O10:R13,4,FALSE),IF(OR(AND(22500<S10,S10<25001),AND(50000<S10,S10<53501),AND(70000<S10,S10<72501)),$F10,IF(OR(AND(25001<S10,S10<27501),AND(53500<S10,S10<57001),AND(72500<S10,S10<75001)),$G10,IF(OR(AND(27500<S10,S10<30001),AND(57000<S10,S10<60001),AND(75000<S10,S10<77500)),$H10,VLOOKUP(S10,BDins,6,FALSE))))) -> 30 | T12: =IF(T14>10000,HLOOKUP(T14,$O10:S13,4,FALSE),IF(OR(AND(22500<T10,T10<25001),AND(50000<T10,T10<53501),AND(70000<T10,T10<72501)),$F10,IF(OR(AND(25001<T10,T10<27501),AND(53500<T10,T10<57001),AND(72500<T10,T10<75001)),$G10,IF(OR(AND(27500<T10,T10<30001),AND(57000<T10,T10<60001),AND(75000<T10,T10<77500)),$H10,VLOOKUP(T10,BDins,6,FALSE))))) -> 50
O13: =IF($K10>0,ROUND(O11*$E10/100,DpCU),IF(O14>10000,ROUND(HLOOKUP(O14,$O10:$T13,4,FALSE)/100*O11,DpCU),IF(OR(O10<20001,O10>95000,AND(60000<O10,O10<70001)),ROUND(ROUND(O11*JL/$C10,DcCU)*O12,DpCU),IF(OR(AND(20000<O10,O10<22501),AND(30000<O10,O10<50001),77500<O10),ROUND(O12*O11,DpCU),IF(OR(AND(22500<O10,O10<25001),AND(50000<O10,O10<53501),AND(70000<O10,O10<72501)),ROUND($F10/100*O11,DpCU),IF(OR(AND(25000<O10,O10<27501),AND(53500<O10,O10<57001),AND(72500<O10,O10<75001)),ROUND($G10/100*O11,DpCU),ROUND($H10/100*O11,DpCU))))))) -> 1706.4 | P13: =IF($K10>0,ROUND(P11*$E10/100,DpCU),IF(P14>10000,ROUND(HLOOKUP(P14,$O10:$T13,4,FALSE)/100*P11,DpCU),IF(OR(P10<20001,P10>95000,AND(60000<P10,P10<70001)),ROUND(ROUND(P11*JL/$C10,DcCU)*P12,DpCU),IF(OR(AND(20000<P10,P10<22501),AND(30000<P10,P10<50001),77500<P10),ROUND(P12*P11,DpCU),IF(OR(AND(22500<P10,P10<25001),AND(50000<P10,P10<53501),AND(70000<P10,P10<72501)),ROUND($F10/100*P11,DpCU),IF(OR(AND(25000<P10,P10<27501),AND(53500<P10,P10<57001),AND(72500<P10,P10<75001)),ROUND($G10/100*P11,DpCU),ROUND($H10/100*P11,DpCU))))))) -> 2374.65 | Q13: =IF($K10>0,ROUND(Q11*$E10/100,DpCU),IF(Q14>10000,ROUND(HLOOKUP(Q14,$O10:$T13,4,FALSE)/100*Q11,DpCU),IF(OR(Q10<20001,Q10>95000,AND(60000<Q10,Q10<70001)),ROUND(ROUND(Q11*JL/$C10,DcCU)*Q12,DpCU),IF(OR(AND(20000<Q10,Q10<22501),AND(30000<Q10,Q10<50001),77500<Q10),ROUND(Q12*Q11,DpCU),IF(OR(AND(22500<Q10,Q10<25001),AND(50000<Q10,Q10<53501),AND(70000<Q10,Q10<72501)),ROUND($F10/100*Q11,DpCU),IF(OR(AND(25000<Q10,Q10<27501),AND(53500<Q10,Q10<57001),AND(72500<Q10,Q10<75001)),ROUND($G10/100*Q11,DpCU),ROUND($H10/100*Q11,DpCU))))))) -> 8 | R13: =IF($K10>0,ROUND(R11*$E10/100,DpCU),IF(R14>10000,ROUND(HLOOKUP(R14,$O10:$T13,4,FALSE)/100*R11,DpCU),IF(OR(R10<20001,R10>95000,AND(60000<R10,R10<70001)),ROUND(ROUND(R11*JL/$C10,DcCU)*R12,DpCU),IF(OR(AND(20000<R10,R10<22501),AND(30000<R10,R10<50001),77500<R10),ROUND(R12*R11,DpCU),IF(OR(AND(22500<R10,R10<25001),AND(50000<R10,R10<53501),AND(70000<R10,R10<72501)),ROUND($F10/100*R11,DpCU),IF(OR(AND(25000<R10,R10<27501),AND(53500<R10,R10<57001),AND(72500<R10,R10<75001)),ROUND($G10/100*R11,DpCU),ROUND($H10/100*R11,DpCU))))))) -> 7 | S13: =IF($K10>0,ROUND(S11*$E10/100,DpCU),IF(S14>10000,ROUND(HLOOKUP(S14,$O10:$T13,4,FALSE)/100*S11,DpCU),IF(OR(S10<20001,S10>95000,AND(60000<S10,S10<70001)),ROUND(ROUND(S11*JL/$C10,DcCU)*S12,DpCU),IF(OR(AND(20000<S10,S10<22501),AND(30000<S10,S10<50001),77500<S10),ROUND(S12*S11,DpCU),IF(OR(AND(22500<S10,S10<25001),AND(50000<S10,S10<53501),AND(70000<S10,S10<72501)),ROUND($F10/100*S11,DpCU),IF(OR(AND(25000<S10,S10<27501),AND(53500<S10,S10<57001),AND(72500<S10,S10<75001)),ROUND($G10/100*S11,DpCU),ROUND($H10/100*S11,DpCU))))))) -> 450 | T13: =IF($K10>0,ROUND(T11*$E10/100,DpCU),IF(T14>10000,ROUND(HLOOKUP(T14,$O10:$T13,4,FALSE)/100*T11,DpCU),IF(OR(T10<20001,T10>95000,AND(60000<T10,T10<70001)),ROUND(ROUND(T11*JL/$C10,DcCU)*T12,DpCU),IF(OR(AND(20000<T10,T10<22501),AND(30000<T10,T10<50001),77500<T10),ROUND(T12*T11,DpCU),IF(OR(AND(22500<T10,T10<25001),AND(50000<T10,T10<53501),AND(70000<T10,T10<72501)),ROUND($F10/100*T11,DpCU),IF(OR(AND(25000<T10,T10<27501),AND(53500<T10,T10<57001),AND(72500<T10,T10<75001)),ROUND($G10/100*T11,DpCU),ROUND($H10/100*T11,DpCU))))))) -> 750
B14: =A10&"r" -> 10002r
A15: 10003 | B15: CARTEL DE OBRA | C15: =ROUND(J15*JL*Frto/8,4) -> 1 | D15: und | E15: =SUM($O18:$O18) -> 500 | F15: =SUMIF($O15:$O15,"<22501",$O18:$O18) -> 0 | G15: =SUMIFS($O18:$O18,$O15:$O15,">30000",$O15:$O15,"<50001") -> 0 | H15: =SUMIFS($O18:$O18,$O15:$O15,">60000",$O15:$O15,"<70001") -> 0 | I15: 1 | J15: 1 | O15: 80001
B16: =A15&"C" -> 10003C | O16: 1
O17: =IF(O19>10000,HLOOKUP(O19,N15:$O18,4,FALSE),IF(OR(AND(22500<O15,O15<25001),AND(50000<O15,O15<53501),AND(70000<O15,O15<72501)),$F15,IF(OR(AND(25001<O15,O15<27501),AND(53500<O15,O15<57001),AND(72500<O15,O15<75001)),$G15,IF(OR(AND(27500<O15,O15<30001),AND(57000<O15,O15<60001),AND(75000<O15,O15<77500)),$H15,VLOOKUP(O15,BDins,6,FALSE))))) -> 500
O18: =IF($K15>0,ROUND(O16*$E15/100,DpCU),IF(O19>10000,ROUND(HLOOKUP(O19,$O15:$O18,4,FALSE)/100*O16,DpCU),IF(OR(O15<20001,O15>95000,AND(60000<O15,O15<70001)),ROUND(ROUND(O16*JL/$C15,DcCU)*O17,DpCU),IF(OR(AND(20000<O15,O15<22501),AND(30000<O15,O15<50001),77500<O15),ROUND(O17*O16,DpCU),IF(OR(AND(22500<O15,O15<25001),AND(50000<O15,O15<53501),AND(70000<O15,O15<72501)),ROUND($F15/100*O16,DpCU),IF(OR(AND(25000<O15,O15<27501),AND(53500<O15,O15<57001),AND(72500<O15,O15<75001)),ROUND($G15/100*O16,DpCU),ROUND($H15/100*O16,DpCU))))))) -> 500
B19: =A15&"r" -> 10003r
A20: 10004 | B20: INSTALACIONES DE OFICINA Y ALMACEN PROVISIONALES | C20: =ROUND(J20*JL*Frto/8,4) -> 0.5 | D20: glb | E20: =SUM($O23:$U23) -> 2519.27 | F20: =SUMIF($O20:$U20,"<22501",$O23:$U23) -> 991.04 | G20: =SUMIFS($O23:$U23,$O20:$U20,">30000",$O20:$U20,"<50001") -> 1498.5 | H20: =SUMIFS($O23:$U23,$O20:$U20,">60000",$O20:$U20,"<70001") -> 0 | I20: 7 | J20: 0.5 | O20: 10001 | P20: 10003 | Q20: 10004 | R20: 30009 | S20: 30010 | T20: 30011 | U20: 70001
B21: =A20&"C" -> 10004C | O21: 1 | P21: 1 | Q21: 2 | R21: 1 | S21: 180 | T21: 8 | U21: 3
O22: =IF(O24>10000,HLOOKUP(O24,N20:$O23,4,FALSE),IF(OR(AND(22500<O20,O20<25001),AND(50000<O20,O20<53501),AND(70000<O20,O20<72501)),$F20,IF(OR(AND(25001<O20,O20<27501),AND(53500<O20,O20<57001),AND(72500<O20,O20<75001)),$G20,IF(OR(AND(27500<O20,O20<30001),AND(57000<O20,O20<60001),AND(75000<O20,O20<77500)),$H20,VLOOKUP(O20,BDins,6,FALSE))))) -> 12.64 | P22: =IF(P24>10000,HLOOKUP(P24,O20:$O23,4,FALSE),IF(OR(AND(22500<P20,P20<25001),AND(50000<P20,P20<53501),AND(70000<P20,P20<72501)),$F20,IF(OR(AND(25001<P20,P20<27501),AND(53500<P20,P20<57001),AND(72500<P20,P20<75001)),$G20,IF(OR(AND(27500<P20,P20<30001),AND(57000<P20,P20<60001),AND(75000<P20,P20<77500)),$H20,VLOOKUP(P20,BDins,6,FALSE))))) -> 14.12 | Q22: =IF(Q24>10000,HLOOKUP(Q24,$O20:P23,4,FALSE),IF(OR(AND(22500<Q20,Q20<25001),AND(50000<Q20,Q20<53501),AND(70000<Q20,Q20<72501)),$F20,IF(OR(AND(25001<Q20,Q20<27501),AND(53500<Q20,Q20<57001),AND(72500<Q20,Q20<75001)),$G20,IF(OR(AND(27500<Q20,Q20<30001),AND(57000<Q20,Q20<60001),AND(75000<Q20,Q20<77500)),$H20,VLOOKUP(Q20,BDins,6,FALSE))))) -> 17.59 | R22: =IF(R24>10000,HLOOKUP(R24,$O20:Q23,4,FALSE),IF(OR(AND(22500<R20,R20<25001),AND(50000<R20,R20<53501),AND(70000<R20,R20<72501)),$F20,IF(OR(AND(25001<R20,R20<27501),AND(53500<R20,R20<57001),AND(72500<R20,R20<75001)),$G20,IF(OR(AND(27500<R20,R20<30001),AND(57000<R20,R20<60001),AND(75000<R20,R20<77500)),$H20,VLOOKUP(R20,BDins,6,FALSE))))) -> 4.5 | S22: =IF(S24>10000,HLOOKUP(S24,$O20:R23,4,FALSE),IF(OR(AND(22500<S20,S20<25001),AND(50000<S20,S20<53501),AND(70000<S20,S20<72501)),$F20,IF(OR(AND(25001<S20,S20<27501),AND(53500<S20,S20<57001),AND(72500<S20,S20<75001)),$G20,IF(OR(AND(27500<S20,S20<30001),AND(57000<S20,S20<60001),AND(75000<S20,S20<77500)),$H20,VLOOKUP(S20,BDins,6,FALSE))))) -> 7.5 | T22: =IF(T24>10000,HLOOKUP(T24,$O20:S23,4,FALSE),IF(OR(AND(22500<T20,T20<25001),AND(50000<T20,T20<53501),AND(70000<T20,T20<72501)),$F20,IF(OR(AND(25001<T20,T20<27501),AND(53500<T20,T20<57001),AND(72500<T20,T20<75001)),$G20,IF(OR(AND(27500<T20,T20<30001),AND(57000<T20,T20<60001),AND(75000<T20,T20<77500)),$H20,VLOOKUP(T20,BDins,6,FALSE))))) -> 18 | U22: =IF(U24>10000,HLOOKUP(U24,$O20:T23,4,FALSE),IF(OR(AND(22500<U20,U20<25001),AND(50000<U20,U20<53501),AND(70000<U20,U20<72501)),$F20,IF(OR(AND(25001<U20,U20<27501),AND(53500<U20,U20<57001),AND(72500<U20,U20<75001)),$G20,IF(OR(AND(27500<U20,U20<30001),AND(57000<U20,U20<60001),AND(75000<U20,U20<77500)),$H20,VLOOKUP(U20,BDins,6,FALSE))))) -> 991.04
O23: =IF($K20>0,ROUND(O21*$E20/100,DpCU),IF(O24>10000,ROUND(HLOOKUP(O24,$O20:$U23,4,FALSE)/100*O21,DpCU),IF(OR(O20<20001,O20>95000,AND(60000<O20,O20<70001)),ROUND(ROUND(O21*JL/$C20,DcCU)*O22,DpCU),IF(OR(AND(20000<O20,O20<22501),AND(30000<O20,O20<50001),77500<O20),ROUND(O22*O21,DpCU),IF(OR(AND(22500<O20,O20<25001),AND(50000<O20,O20<53501),AND(70000<O20,O20<72501)),ROUND($F20/100*O21,DpCU),IF(OR(AND(25000<O20,O20<27501),AND(53500<O20,O20<57001),AND(72500<O20,O20<75001)),ROUND($G20/100*O21,DpCU),ROUND($H20/100*O21,DpCU))))))) -> 202.24 | P23: =IF($K20>0,ROUND(P21*$E20/100,DpCU),IF(P24>10000,ROUND(HLOOKUP(P24,$O20:$U23,4,FALSE)/100*P21,DpCU),IF(OR(P20<20001,P20>95000,AND(60000<P20,P20<70001)),ROUND(ROUND(P21*JL/$C20,DcCU)*P22,DpCU),IF(OR(AND(20000<P20,P20<22501),AND(30000<P20,P20<50001),77500<P20),ROUND(P22*P21,DpCU),IF(OR(AND(22500<P20,P20<25001),AND(50000<P20,P20<53501),AND(70000<P20,P20<72501)),ROUND($F20/100*P21,DpCU),IF(OR(AND(25000<P20,P20<27501),AND(53500<P20,P20<57001),AND(72500<P20,P20<75001)),ROUND($G20/100*P21,DpCU),ROUND($H20/100*P21,DpCU))))))) -> 225.92 | Q23: =IF($K20>0,ROUND(Q21*$E20/100,DpCU),IF(Q24>10000,ROUND(HLOOKUP(Q24,$O20:$U23,4,FALSE)/100*Q21,DpCU),IF(OR(Q20<20001,Q20>95000,AND(60000<Q20,Q20<70001)),ROUND(ROUND(Q21*JL/$C20,DcCU)*Q22,DpCU),IF(OR(AND(20000<Q20,Q20<22501),AND(30000<Q20,Q20<50001),77500<Q20),ROUND(Q22*Q21,DpCU),IF(OR(AND(22500<Q20,Q20<25001),AND(50000<Q20,Q20<53501),AND(70000<Q20,Q20<72501)),ROUND($F20/100*Q21,DpCU),IF(OR(AND(25000<Q20,Q20<27501),AND(53500<Q20,Q20<57001),AND(72500<Q20,Q20<75001)),ROUND($G20/100*Q21,DpCU),ROUND($H20/100*Q21,DpCU))))))) -> 562.88 | R23: =IF($K20>0,ROUND(R21*$E20/100,DpCU),IF(R24>10000,ROUND(HLOOKUP(R24,$O20:$U23,4,FALSE)/100*R21,DpCU),IF(OR(R20<20001,R20>95000,AND(60000<R20,R20<70001)),ROUND(ROUND(R21*JL/$C20,DcCU)*R22,DpCU),IF(OR(AND(20000<R20,R20<22501),AND(30000<R20,R20<50001),77500<R20),ROUND(R22*R21,DpCU),IF(OR(AND(22500<R20,R20<25001),AND(50000<R20,R20<53501),AND(70000<R20,R20<72501)),ROUND($F20/100*R21,DpCU),IF(OR(AND(25000<R20,R20<27501),AND(53500<R20,R20<57001),AND(72500<R20,R20<75001)),ROUND($G20/100*R21,DpCU),ROUND($H20/100*R21,DpCU))))))) -> 4.5 | S23: =IF($K20>0,ROUND(S21*$E20/100,DpCU),IF(S24>10000,ROUND(HLOOKUP(S24,$O20:$U23,4,FALSE)/100*S21,DpCU),IF(OR(S20<20001,S20>95000,AND(60000<S20,S20<70001)),ROUND(ROUND(S21*JL/$C20,DcCU)*S22,DpCU),IF(OR(AND(20000<S20,S20<22501),AND(30000<S20,S20<50001),77500<S20),ROUND(S22*S21,DpCU),IF(OR(AND(22500<S20,S20<25001),AND(50000<S20,S20<53501),AND(70000<S20,S20<72501)),ROUND($F20/100*S21,DpCU),IF(OR(AND(25000<S20,S20<27501),AND(53500<S20,S20<57001),AND(72500<S20,S20<75001)),ROUND($G20/100*S21,DpCU),ROUND($H20/100*S21,DpCU))))))) -> 1350 | T23: =IF($K20>0,ROUND(T21*$E20/100,DpCU),IF(T24>10000,ROUND(HLOOKUP(T24,$O20:$U23,4,FALSE)/100*T21,DpCU),IF(OR(T20<20001,T20>95000,AND(60000<T20,T20<70001)),ROUND(ROUND(T21*JL/$C20,DcCU)*T22,DpCU),IF(OR(AND(20000<T20,T20<22501),AND(30000<T20,T20<50001),77500<T20),ROUND(T22*T21,DpCU),IF(OR(AND(22500<T20,T20<25001),AND(50000<T20,T20<53501),AND(70000<T20,T20<72501)),ROUND($F20/100*T21,DpCU),IF(OR(AND(25000<T20,T20<27501),AND(53500<T20,T20<57001),AND(72500<T20,T20<75001)),ROUND($G20/100*T21,DpCU),ROUND($H20/100*T21,DpCU))))))) -> 144 | U23: =IF($K20>0,ROUND(U21*$E20/100,DpCU),IF(U24>10000,ROUND(HLOOKUP(U24,$O20:$U23,4,FALSE)/100*U21,DpCU),IF(OR(U20<20001,U20>95000,AND(60000<U20,U20<70001)),ROUND(ROUND(U21*JL/$C20,DcCU)*U22,DpCU),IF(OR(AND(20000<U20,U20<22501),AND(30000<U20,U20<50001),77500<U20),ROUND(U22*U21,DpCU),IF(OR(AND(22500<U20,U20<25001),AND(50000<U20,U20<53501),AND(70000<U20,U20<72501)),ROUND($F20/100*U21,DpCU),IF(OR(AND(25000<U20,U20<27501),AND(53500<U20,U20<57001),AND(72500<U20,U20<75001)),ROUND($G20/100*U21,DpCU),ROUND($H20/100*U21,DpCU))))))) -> 29.73
B24: =A20&"r" -> 10004r
A25: 10005 | B25: EQUIPOS DE PROTECCION PERSONAL (EPP'S) | C25: =ROUND(J25*JL*Frto/8,4) -> 1 | D25: glb | E25: =SUM($O28:$T28) -> 4635.75 | F25: =SUMIF($O25:$T25,"<22501",$O28:$T28) -> 0 | G25: =SUMIFS($O28:$T28,$O25:$T25,">30000",$O25:$T25,"<50001") -> 4635.75 | H25: =SUMIFS($O28:$T28,$O25:$T25,">60000",$O25:$T25,"<70001") -> 0 | I25: 6 | J25: 1 | O25: 30012 | P25: 30013 | Q25: 30014 | R25: 30015 | S25: 30016 | T25: 30017
B26: =A25&"C" -> 10005C | O26: 35 | P26: 35 | Q26: 35 | R26: 35 | S26: 35 | T26: 35
O27: =IF(O29>10000,HLOOKUP(O29,N25:$O28,4,FALSE),IF(OR(AND(22500<O25,O25<25001),AND(50000<O25,O25<53501),AND(70000<O25,O25<72501)),$F25,IF(OR(AND(25001<O25,O25<27501),AND(53500<O25,O25<57001),AND(72500<O25,O25<75001)),$G25,IF(OR(AND(27500<O25,O25<30001),AND(57000<O25,O25<60001),AND(75000<O25,O25<77500)),$H25,VLOOKUP(O25,BDins,6,FALSE))))) -> 18.5 | P27: =IF(P29>10000,HLOOKUP(P29,O25:$O28,4,FALSE),IF(OR(AND(22500<P25,P25<25001),AND(50000<P25,P25<53501),AND(70000<P25,P25<72501)),$F25,IF(OR(AND(25001<P25,P25<27501),AND(53500<P25,P25<57001),AND(72500<P25,P25<75001)),$G25,IF(OR(AND(27500<P25,P25<30001),AND(57000<P25,P25<60001),AND(75000<P25,P25<77500)),$H25,VLOOKUP(P25,BDins,6,FALSE))))) -> 48.5 | Q27: =IF(Q29>10000,HLOOKUP(Q29,$O25:P28,4,FALSE),IF(OR(AND(22500<Q25,Q25<25001),AND(50000<Q25,Q25<53501),AND(70000<Q25,Q25<72501)),$F25,IF(OR(AND(25001<Q25,Q25<27501),AND(53500<Q25,Q25<57001),AND(72500<Q25,Q25<75001)),$G25,IF(OR(AND(27500<Q25,Q25<30001),AND(57000<Q25,Q25<60001),AND(75000<Q25,Q25<77500)),$H25,VLOOKUP(Q25,BDins,6,FALSE))))) -> 12 | R27: =IF(R29>10000,HLOOKUP(R29,$O25:Q28,4,FALSE),IF(OR(AND(22500<R25,R25<25001),AND(50000<R25,R25<53501),AND(70000<R25,R25<72501)),$F25,IF(OR(AND(25001<R25,R25<27501),AND(53500<R25,R25<57001),AND(72500<R25,R25<75001)),$G25,IF(OR(AND(27500<R25,R25<30001),AND(57000<R25,R25<60001),AND(75000<R25,R25<77500)),$H25,VLOOKUP(R25,BDins,6,FALSE))))) -> 12.5 | S27: =IF(S29>10000,HLOOKUP(S29,$O25:R28,4,FALSE),IF(OR(AND(22500<S25,S25<25001),AND(50000<S25,S25<53501),AND(70000<S25,S25<72501)),$F25,IF(OR(AND(25001<S25,S25<27501),AND(53500<S25,S25<57001),AND(72500<S25,S25<75001)),$G25,IF(OR(AND(27500<S25,S25<30001),AND(57000<S25,S25<60001),AND(75000<S25,S25<77500)),$H25,VLOOKUP(S25,BDins,6,FALSE))))) -> 11.45 | T27: =IF(T29>10000,HLOOKUP(T29,$O25:S28,4,FALSE),IF(OR(AND(22500<T25,T25<25001),AND(50000<T25,T25<53501),AND(70000<T25,T25<72501)),$F25,IF(OR(AND(25001<T25,T25<27501),AND(53500<T25,T25<57001),AND(72500<T25,T25<75001)),$G25,IF(OR(AND(27500<T25,T25<30001),AND(57000<T25,T25<60001),AND(75000<T25,T25<77500)),$H25,VLOOKUP(T25,BDins,6,FALSE))))) -> 29.5
O28: =IF($K25>0,ROUND(O26*$E25/100,DpCU),IF(O29>10000,ROUND(HLOOKUP(O29,$O25:$T28,4,FALSE)/100*O26,DpCU),IF(OR(O25<20001,O25>95000,AND(60000<O25,O25<70001)),ROUND(ROUND(O26*JL/$C25,DcCU)*O27,DpCU),IF(OR(AND(20000<O25,O25<22501),AND(30000<O25,O25<50001),77500<O25),ROUND(O27*O26,DpCU),IF(OR(AND(22500<O25,O25<25001),AND(50000<O25,O25<53501),AND(70000<O25,O25<72501)),ROUND($F25/100*O26,DpCU),IF(OR(AND(25000<O25,O25<27501),AND(53500<O25,O25<57001),AND(72500<O25,O25<75001)),ROUND($G25/100*O26,DpCU),ROUND($H25/100*O26,DpCU))))))) -> 647.5 | P28: =IF($K25>0,ROUND(P26*$E25/100,DpCU),IF(P29>10000,ROUND(HLOOKUP(P29,$O25:$T28,4,FALSE)/100*P26,DpCU),IF(OR(P25<20001,P25>95000,AND(60000<P25,P25<70001)),ROUND(ROUND(P26*JL/$C25,DcCU)*P27,DpCU),IF(OR(AND(20000<P25,P25<22501),AND(30000<P25,P25<50001),77500<P25),ROUND(P27*P26,DpCU),IF(OR(AND(22500<P25,P25<25001),AND(50000<P25,P25<53501),AND(70000<P25,P25<72501)),ROUND($F25/100*P26,DpCU),IF(OR(AND(25000<P25,P25<27501),AND(53500<P25,P25<57001),AND(72500<P25,P25<75001)),ROUND($G25/100*P26,DpCU),ROUND($H25/100*P26,DpCU))))))) -> 1697.5 | Q28: =IF($K25>0,ROUND(Q26*$E25/100,DpCU),IF(Q29>10000,ROUND(HLOOKUP(Q29,$O25:$T28,4,FALSE)/100*Q26,DpCU),IF(OR(Q25<20001,Q25>95000,AND(60000<Q25,Q25<70001)),ROUND(ROUND(Q26*JL/$C25,DcCU)*Q27,DpCU),IF(OR(AND(20000<Q25,Q25<22501),AND(30000<Q25,Q25<50001),77500<Q25),ROUND(Q27*Q26,DpCU),IF(OR(AND(22500<Q25,Q25<25001),AND(50000<Q25,Q25<53501),AND(70000<Q25,Q25<72501)),ROUND($F25/100*Q26,DpCU),IF(OR(AND(25000<Q25,Q25<27501),AND(53500<Q25,Q25<57001),AND(72500<Q25,Q25<75001)),ROUND($G25/100*Q26,DpCU),ROUND($H25/100*Q26,DpCU))))))) -> 420 | R28: =IF($K25>0,ROUND(R26*$E25/100,DpCU),IF(R29>10000,ROUND(HLOOKUP(R29,$O25:$T28,4,FALSE)/100*R26,DpCU),IF(OR(R25<20001,R25>95000,AND(60000<R25,R25<70001)),ROUND(ROUND(R26*JL/$C25,DcCU)*R27,DpCU),IF(OR(AND(20000<R25,R25<22501),AND(30000<R25,R25<50001),77500<R25),ROUND(R27*R26,DpCU),IF(OR(AND(22500<R25,R25<25001),AND(50000<R25,R25<53501),AND(70000<R25,R25<72501)),ROUND($F25/100*R26,DpCU),IF(OR(AND(25000<R25,R25<27501),AND(53500<R25,R25<57001),AND(72500<R25,R25<75001)),ROUND($G25/100*R26,DpCU),ROUND($H25/100*R26,DpCU))))))) -> 437.5 | S28: =IF($K25>0,ROUND(S26*$E25/100,DpCU),IF(S29>10000,ROUND(HLOOKUP(S29,$O25:$T28,4,FALSE)/100*S26,DpCU),IF(OR(S25<20001,S25>95000,AND(60000<S25,S25<70001)),ROUND(ROUND(S26*JL/$C25,DcCU)*S27,DpCU),IF(OR(AND(20000<S25,S25<22501),AND(30000<S25,S25<50001),77500<S25),ROUND(S27*S26,DpCU),IF(OR(AND(22500<S25,S25<25001),AND(50000<S25,S25<53501),AND(70000<S25,S25<72501)),ROUND($F25/100*S26,DpCU),IF(OR(AND(25000<S25,S25<27501),AND(53500<S25,S25<57001),AND(72500<S25,S25<75001)),ROUND($G25/100*S26,DpCU),ROUND($H25/100*S26,DpCU))))))) -> 400.75 | T28: =IF($K25>0,ROUND(T26*$E25/100,DpCU),IF(T29>10000,ROUND(HLOOKUP(T29,$O25:$T28,4,FALSE)/100*T26,DpCU),IF(OR(T25<20001,T25>95000,AND(60000<T25,T25<70001)),ROUND(ROUND(T26*JL/$C25,DcCU)*T27,DpCU),IF(OR(AND(20000<T25,T25<22501),AND(30000<T25,T25<50001),77500<T25),ROUND(T27*T26,DpCU),IF(OR(AND(22500<T25,T25<25001),AND(50000<T25,T25<53501),AND(70000<T25,T25<72501)),ROUND($F25/100*T26,DpCU),IF(OR(AND(25000<T25,T25<27501),AND(53500<T25,T25<57001),AND(72500<T25,T25<75001)),ROUND($G25/100*T26,DpCU),ROUND($H25/100*T26,DpCU))))))) -> 1032.5
B29: =A25&"r" -> 10005r
A30: 10006 | B30: SEÑALIZACION | C30: =ROUND(J30*JL*Frto/8,4) -> 5 | D30: und | E30: =SUM($O33:$V33) -> 108.11 | F30: =SUMIF($O30:$V30,"<22501",$O33:$V33) -> 70.95 | G30: =SUMIFS($O33:$V33,$O30:$V30,">30000",$O30:$V30,"<50001") -> 35.03 | H30: =SUMIFS($O33:$V33,$O30:$V30,">60000",$O30:$V30,"<70001") -> 0 | I30: 8 | J30: 5 | O30: 10001 | P30: 10003 | Q30: 10004 | R30: 30005 | S30: 30018 | T30: 30019 | U30: 30020 | V30: 70001
B31: =A30&"C" -> 10006C | O31: 1 | P31: 1 | Q31: 1 | R31: 0.11 | S31: 1 | T31: 2 | U31: 1 | V31: 3
O32: =IF(O34>10000,HLOOKUP(O34,N30:$O33,4,FALSE),IF(OR(AND(22500<O30,O30<25001),AND(50000<O30,O30<53501),AND(70000<O30,O30<72501)),$F30,IF(OR(AND(25001<O30,O30<27501),AND(53500<O30,O30<57001),AND(72500<O30,O30<75001)),$G30,IF(OR(AND(27500<O30,O30<30001),AND(57000<O30,O30<60001),AND(75000<O30,O30<77500)),$H30,VLOOKUP(O30,BDins,6,FALSE))))) -> 12.64 | P32: =IF(P34>10000,HLOOKUP(P34,O30:$O33,4,FALSE),IF(OR(AND(22500<P30,P30<25001),AND(50000<P30,P30<53501),AND(70000<P30,P30<72501)),$F30,IF(OR(AND(25001<P30,P30<27501),AND(53500<P30,P30<57001),AND(72500<P30,P30<75001)),$G30,IF(OR(AND(27500<P30,P30<30001),AND(57000<P30,P30<60001),AND(75000<P30,P30<77500)),$H30,VLOOKUP(P30,BDins,6,FALSE))))) -> 14.12 | Q32: =IF(Q34>10000,HLOOKUP(Q34,$O30:P33,4,FALSE),IF(OR(AND(22500<Q30,Q30<25001),AND(50000<Q30,Q30<53501),AND(70000<Q30,Q30<72501)),$F30,IF(OR(AND(25001<Q30,Q30<27501),AND(53500<Q30,Q30<57001),AND(72500<Q30,Q30<75001)),$G30,IF(OR(AND(27500<Q30,Q30<30001),AND(57000<Q30,Q30<60001),AND(75000<Q30,Q30<77500)),$H30,VLOOKUP(Q30,BDins,6,FALSE))))) -> 17.59 | R32: =IF(R34>10000,HLOOKUP(R34,$O30:Q33,4,FALSE),IF(OR(AND(22500<R30,R30<25001),AND(50000<R30,R30<53501),AND(70000<R30,R30<72501)),$F30,IF(OR(AND(25001<R30,R30<27501),AND(53500<R30,R30<57001),AND(72500<R30,R30<75001)),$G30,IF(OR(AND(27500<R30,R30<30001),AND(57000<R30,R30<60001),AND(75000<R30,R30<77500)),$H30,VLOOKUP(R30,BDins,6,FALSE))))) -> 28 | S32: =IF(S34>10000,HLOOKUP(S34,$O30:R33,4,FALSE),IF(OR(AND(22500<S30,S30<25001),AND(50000<S30,S30<53501),AND(70000<S30,S30<72501)),$F30,IF(OR(AND(25001<S30,S30<27501),AND(53500<S30,S30<57001),AND(72500<S30,S30<75001)),$G30,IF(OR(AND(27500<S30,S30<30001),AND(57000<S30,S30<60001),AND(75000<S30,S30<77500)),$H30,VLOOKUP(S30,BDins,6,FALSE))))) -> 11.45 | T32: =IF(T34>10000,HLOOKUP(T34,$O30:S33,4,FALSE),IF(OR(AND(22500<T30,T30<25001),AND(50000<T30,T30<53501),AND(70000<T30,T30<72501)),$F30,IF(OR(AND(25001<T30,T30<27501),AND(53500<T30,T30<57001),AND(72500<T30,T30<75001)),$G30,IF(OR(AND(27500<T30,T30<30001),AND(57000<T30,T30<60001),AND(75000<T30,T30<77500)),$H30,VLOOKUP(T30,BDins,6,FALSE))))) -> 2.5 | U32: =IF(U34>10000,HLOOKUP(U34,$O30:T33,4,FALSE),IF(OR(AND(22500<U30,U30<25001),AND(50000<U30,U30<53501),AND(70000<U30,U30<72501)),$F30,IF(OR(AND(25001<U30,U30<27501),AND(53500<U30,U30<57001),AND(72500<U30,U30<75001)),$G30,IF(OR(AND(27500<U30,U30<30001),AND(57000<U30,U30<60001),AND(75000<U30,U30<77500)),$H30,VLOOKUP(U30,BDins,6,FALSE))))) -> 15.5 | V32: =IF(V34>10000,HLOOKUP(V34,$O30:U33,4,FALSE),IF(OR(AND(22500<V30,V30<25001),AND(50000<V30,V30<53501),AND(70000<V30,V30<72501)),$F30,IF(OR(AND(25001<V30,V30<27501),AND(53500<V30,V30<57001),AND(72500<V30,V30<75001)),$G30,IF(OR(AND(27500<V30,V30<30001),AND(57000<V30,V30<60001),AND(75000<V30,V30<77500)),$H30,VLOOKUP(V30,BDins,6,FALSE))))) -> 70.95
O33: =IF($K30>0,ROUND(O31*$E30/100,DpCU),IF(O34>10000,ROUND(HLOOKUP(O34,$O30:$V33,4,FALSE)/100*O31,DpCU),IF(OR(O30<20001,O30>95000,AND(60000<O30,O30<70001)),ROUND(ROUND(O31*JL/$C30,DcCU)*O32,DpCU),IF(OR(AND(20000<O30,O30<22501),AND(30000<O30,O30<50001),77500<O30),ROUND(O32*O31,DpCU),IF(OR(AND(22500<O30,O30<25001),AND(50000<O30,O30<53501),AND(70000<O30,O30<72501)),ROUND($F30/100*O31,DpCU),IF(OR(AND(25000<O30,O30<27501),AND(53500<O30,O30<57001),AND(72500<O30,O30<75001)),ROUND($G30/100*O31,DpCU),ROUND($H30/100*O31,DpCU))))))) -> 20.22 | P33: =IF($K30>0,ROUND(P31*$E30/100,DpCU),IF(P34>10000,ROUND(HLOOKUP(P34,$O30:$V33,4,FALSE)/100*P31,DpCU),IF(OR(P30<20001,P30>95000,AND(60000<P30,P30<70001)),ROUND(ROUND(P31*JL/$C30,DcCU)*P32,DpCU),IF(OR(AND(20000<P30,P30<22501),AND(30000<P30,P30<50001),77500<P30),ROUND(P32*P31,DpCU),IF(OR(AND(22500<P30,P30<25001),AND(50000<P30,P30<53501),AND(70000<P30,P30<72501)),ROUND($F30/100*P31,DpCU),IF(OR(AND(25000<P30,P30<27501),AND(53500<P30,P30<57001),AND(72500<P30,P30<75001)),ROUND($G30/100*P31,DpCU),ROUND($H30/100*P31,DpCU))))))) -> 22.59 | Q33: =IF($K30>0,ROUND(Q31*$E30/100,DpCU),IF(Q34>10000,ROUND(HLOOKUP(Q34,$O30:$V33,4,FALSE)/100*Q31,DpCU),IF(OR(Q30<20001,Q30>95000,AND(60000<Q30,Q30<70001)),ROUND(ROUND(Q31*JL/$C30,DcCU)*Q32,DpCU),IF(OR(AND(20000<Q30,Q30<22501),AND(30000<Q30,Q30<50001),77500<Q30),ROUND(Q32*Q31,DpCU),IF(OR(AND(22500<Q30,Q30<25001),AND(50000<Q30,Q30<53501),AND(70000<Q30,Q30<72501)),ROUND($F30/100*Q31,DpCU),IF(OR(AND(25000<Q30,Q30<27501),AND(53500<Q30,Q30<57001),AND(72500<Q30,Q30<75001)),ROUND($G30/100*Q31,DpCU),ROUND($H30/100*Q31,DpCU))))))) -> 28.14 | R33: =IF($K30>0,ROUND(R31*$E30/100,DpCU),IF(R34>10000,ROUND(HLOOKUP(R34,$O30:$V33,4,FALSE)/100*R31,DpCU),IF(OR(R30<20001,R30>95000,AND(60000<R30,R30<70001)),ROUND(ROUND(R31*JL/$C30,DcCU)*R32,DpCU),IF(OR(AND(20000<R30,R30<22501),AND(30000<R30,R30<50001),77500<R30),ROUND(R32*R31,DpCU),IF(OR(AND(22500<R30,R30<25001),AND(50000<R30,R30<53501),AND(70000<R30,R30<72501)),ROUND($F30/100*R31,DpCU),IF(OR(AND(25000<R30,R30<27501),AND(53500<R30,R30<57001),AND(72500<R30,R30<75001)),ROUND($G30/100*R31,DpCU),ROUND($H30/100*R31,DpCU))))))) -> 3.08 | S33: =IF($K30>0,ROUND(S31*$E30/100,DpCU),IF(S34>10000,ROUND(HLOOKUP(S34,$O30:$V33,4,FALSE)/100*S31,DpCU),IF(OR(S30<20001,S30>95000,AND(60000<S30,S30<70001)),ROUND(ROUND(S31*JL/$C30,DcCU)*S32,DpCU),IF(OR(AND(20000<S30,S30<22501),AND(30000<S30,S30<50001),77500<S30),ROUND(S32*S31,DpCU),IF(OR(AND(22500<S30,S30<25001),AND(50000<S30,S30<53501),AND(70000<S30,S30<72501)),ROUND($F30/100*S31,DpCU),IF(OR(AND(25000<S30,S30<27501),AND(53500<S30,S30<57001),AND(72500<S30,S30<75001)),ROUND($G30/100*S31,DpCU),ROUND($H30/100*S31,DpCU))))))) -> 11.45 | T33: =IF($K30>0,ROUND(T31*$E30/100,DpCU),IF(T34>10000,ROUND(HLOOKUP(T34,$O30:$V33,4,FALSE)/100*T31,DpCU),IF(OR(T30<20001,T30>95000,AND(60000<T30,T30<70001)),ROUND(ROUND(T31*JL/$C30,DcCU)*T32,DpCU),IF(OR(AND(20000<T30,T30<22501),AND(30000<T30,T30<50001),77500<T30),ROUND(T32*T31,DpCU),IF(OR(AND(22500<T30,T30<25001),AND(50000<T30,T30<53501),AND(70000<T30,T30<72501)),ROUND($F30/100*T31,DpCU),IF(OR(AND(25000<T30,T30<27501),AND(53500<T30,T30<57001),AND(72500<T30,T30<75001)),ROUND($G30/100*T31,DpCU),ROUND($H30/100*T31,DpCU))))))) -> 5 | U33: =IF($K30>0,ROUND(U31*$E30/100,DpCU),IF(U34>10000,ROUND(HLOOKUP(U34,$O30:$V33,4,FALSE)/100*U31,DpCU),IF(OR(U30<20001,U30>95000,AND(60000<U30,U30<70001)),ROUND(ROUND(U31*JL/$C30,DcCU)*U32,DpCU),IF(OR(AND(20000<U30,U30<22501),AND(30000<U30,U30<50001),77500<U30),ROUND(U32*U31,DpCU),IF(OR(AND(22500<U30,U30<25001),AND(50000<U30,U30<53501),AND(70000<U30,U30<72501)),ROUND($F30/100*U31,DpCU),IF(OR(AND(25000<U30,U30<27501),AND(53500<U30,U30<57001),AND(72500<U30,U30<75001)),ROUND($G30/100*U31,DpCU),ROUND($H30/100*U31,DpCU))))))) -> 15.5 | V33: =IF($K30>0,ROUND(V31*$E30/100,DpCU),IF(V34>10000,ROUND(HLOOKUP(V34,$O30:$V33,4,FALSE)/100*V31,DpCU),IF(OR(V30<20001,V30>95000,AND(60000<V30,V30<70001)),ROUND(ROUND(V31*JL/$C30,DcCU)*V32,DpCU),IF(OR(AND(20000<V30,V30<22501),AND(30000<V30,V30<50001),77500<V30),ROUND(V32*V31,DpCU),IF(OR(AND(22500<V30,V30<25001),AND(50000<V30,V30<53501),AND(70000<V30,V30<72501)),ROUND($F30/100*V31,DpCU),IF(OR(AND(25000<V30,V30<27501),AND(53500<V30,V30<57001),AND(72500<V30,V30<75001)),ROUND($G30/100*V31,DpCU),ROUND($H30/100*V31,DpCU))))))) -> 2.13
B34: =A30&"r" -> 10006r
A35: 10007 | B35: CHARLAS DE SEGURIDAD | C35: =ROUND(J35*JL*Frto/8,4) -> 1 | D35: sem | E35: =SUM($O38:$O38) -> 350 | F35: =SUMIF($O35:$O35,"<22501",$O38:$O38) -> 0 | G35: =SUMIFS($O38:$O38,$O35:$O35,">30000",$O35:$O35,"<50001") -> 350 | H35: =SUMIFS($O38:$O38,$O35:$O35,">60000",$O35:$O35,"<70001") -> 0 | I35: 1 | J35: 1 | O35: 30021
B36: =A35&"C" -> 10007C | O36: 1
O37: =IF(O39>10000,HLOOKUP(O39,N35:$O38,4,FALSE),IF(OR(AND(22500<O35,O35<25001),AND(50000<O35,O35<53501),AND(70000<O35,O35<72501)),$F35,IF(OR(AND(25001<O35,O35<27501),AND(53500<O35,O35<57001),AND(72500<O35,O35<75001)),$G35,IF(OR(AND(27500<O35,O35<30001),AND(57000<O35,O35<60001),AND(75000<O35,O35<77500)),$H35,VLOOKUP(O35,BDins,6,FALSE))))) -> 350
O38: =IF($K35>0,ROUND(O36*$E35/100,DpCU),IF(O39>10000,ROUND(HLOOKUP(O39,$O35:$O38,4,FALSE)/100*O36,DpCU),IF(OR(O35<20001,O35>95000,AND(60000<O35,O35<70001)),ROUND(ROUND(O36*JL/$C35,DcCU)*O37,DpCU),IF(OR(AND(20000<O35,O35<22501),AND(30000<O35,O35<50001),77500<O35),ROUND(O37*O36,DpCU),IF(OR(AND(22500<O35,O35<25001),AND(50000<O35,O35<53501),AND(70000<O35,O35<72501)),ROUND($F35/100*O36,DpCU),IF(OR(AND(25000<O35,O35<27501),AND(53500<O35,O35<57001),AND(72500<O35,O35<75001)),ROUND($G35/100*O36,DpCU),ROUND($H35/100*O36,DpCU))))))) -> 350
B39: =A35&"r" -> 10007r
A40: 10008 | B40: DEMOLICION CONSTRUCCION EXISTENTE | C40: =ROUND(J40*JL*Frto/8,4) -> 3 | D40: m3 | E40: =SUM($O43:$P43) -> 59.84 | F40: =SUMIF($O40:$P40,"<22501",$O43:$P43) -> 33.71 | G40: =SUMIFS($O43:$P43,$O40:$P40,">30000",$O40:$P40,"<50001") -> 0 | H40: =SUMIFS($O43:$P43,$O40:$P40,">60000",$O40:$P40,"<70001") -> 26.13 | I40: 2 | J40: 3 | O40: 10001 | P40: 60003
B41: =A40&"C" -> 10008C | O41: 1 | P41: 1
O42: =IF(O44>10000,HLOOKUP(O44,N40:$O43,4,FALSE),IF(OR(AND(22500<O40,O40<25001),AND(50000<O40,O40<53501),AND(70000<O40,O40<72501)),$F40,IF(OR(AND(25001<O40,O40<27501),AND(53500<O40,O40<57001),AND(72500<O40,O40<75001)),$G40,IF(OR(AND(27500<O40,O40<30001),AND(57000<O40,O40<60001),AND(75000<O40,O40<77500)),$H40,VLOOKUP(O40,BDins,6,FALSE))))) -> 12.64 | P42: =IF(P44>10000,HLOOKUP(P44,O40:$O43,4,FALSE),IF(OR(AND(22500<P40,P40<25001),AND(50000<P40,P40<53501),AND(70000<P40,P40<72501)),$F40,IF(OR(AND(25001<P40,P40<27501),AND(53500<P40,P40<57001),AND(72500<P40,P40<75001)),$G40,IF(OR(AND(27500<P40,P40<30001),AND(57000<P40,P40<60001),AND(75000<P40,P40<77500)),$H40,VLOOKUP(P40,BDins,6,FALSE))))) -> 9.8
O43: =IF($K40>0,ROUND(O41*$E40/100,DpCU),IF(O44>10000,ROUND(HLOOKUP(O44,$O40:$P43,4,FALSE)/100*O41,DpCU),IF(OR(O40<20001,O40>95000,AND(60000<O40,O40<70001)),ROUND(ROUND(O41*JL/$C40,DcCU)*O42,DpCU),IF(OR(AND(20000<O40,O40<22501),AND(30000<O40,O40<50001),77500<O40),ROUND(O42*O41,DpCU),IF(OR(AND(22500<O40,O40<25001),AND(50000<O40,O40<53501),AND(70000<O40,O40<72501)),ROUND($F40/100*O41,DpCU),IF(OR(AND(25000<O40,O40<27501),AND(53500<O40,O40<57001),AND(72500<O40,O40<75001)),ROUND($G40/100*O41,DpCU),ROUND($H40/100*O41,DpCU))))))) -> 33.71 | P43: =IF($K40>0,ROUND(P41*$E40/100,DpCU),IF(P44>10000,ROUND(HLOOKUP(P44,$O40:$P43,4,FALSE)/100*P41,DpCU),IF(OR(P40<20001,P40>95000,AND(60000<P40,P40<70001)),ROUND(ROUND(P41*JL/$C40,DcCU)*P42,DpCU),IF(OR(AND(20000<P40,P40<22501),AND(30000<P40,P40<50001),77500<P40),ROUND(P42*P41,DpCU),IF(OR(AND(22500<P40,P40<25001),AND(50000<P40,P40<53501),AND(70000<P40,P40<72501)),ROUND($F40/100*P41,DpCU),IF(OR(AND(25000<P40,P40<27501),AND(53500<P40,P40<57001),AND(72500<P40,P40<75001)),ROUND($G40/100*P41,DpCU),ROUND($H40/100*P41,DpCU))))))) -> 26.13
B44: =A40&"r" -> 10008r
A45: 10009 | B45: EXCAVACION MASIVA | C45: =ROUND(J45*JL*Frto/8,4) -> 100 | D45: m3 | E45: =SUM($O48:$P48) -> 15.01 | F45: =SUMIF($O45:$P45,"<22501",$O48:$P48) -> 1.01 | G45: =SUMIFS($O48:$P48,$O45:$P45,">30000",$O45:$P45,"<50001") -> 0 | H45: =SUMIFS($O48:$P48,$O45:$P45,">60000",$O45:$P45,"<70001") -> 14 | I45: 2 | J45: 100 | O45: 10001 | P45: 60004
B46: =A45&"C" -> 10009C | O46: 1 | P46: 1
O47: =IF(O49>10000,HLOOKUP(O49,N45:$O48,4,FALSE),IF(OR(AND(22500<O45,O45<25001),AND(50000<O45,O45<53501),AND(70000<O45,O45<72501)),$F45,IF(OR(AND(25001<O45,O45<27501),AND(53500<O45,O45<57001),AND(72500<O45,O45<75001)),$G45,IF(OR(AND(27500<O45,O45<30001),AND(57000<O45,O45<60001),AND(75000<O45,O45<77500)),$H45,VLOOKUP(O45,BDins,6,FALSE))))) -> 12.64 | P47: =IF(P49>10000,HLOOKUP(P49,O45:$O48,4,FALSE),IF(OR(AND(22500<P45,P45<25001),AND(50000<P45,P45<53501),AND(70000<P45,P45<72501)),$F45,IF(OR(AND(25001<P45,P45<27501),AND(53500<P45,P45<57001),AND(72500<P45,P45<75001)),$G45,IF(OR(AND(27500<P45,P45<30001),AND(57000<P45,P45<60001),AND(75000<P45,P45<77500)),$H45,VLOOKUP(P45,BDins,6,FALSE))))) -> 175
O48: =IF($K45>0,ROUND(O46*$E45/100,DpCU),IF(O49>10000,ROUND(HLOOKUP(O49,$O45:$P48,4,FALSE)/100*O46,DpCU),IF(OR(O45<20001,O45>95000,AND(60000<O45,O45<70001)),ROUND(ROUND(O46*JL/$C45,DcCU)*O47,DpCU),IF(OR(AND(20000<O45,O45<22501),AND(30000<O45,O45<50001),77500<O45),ROUND(O47*O46,DpCU),IF(OR(AND(22500<O45,O45<25001),AND(50000<O45,O45<53501),AND(70000<O45,O45<72501)),ROUND($F45/100*O46,DpCU),IF(OR(AND(25000<O45,O45<27501),AND(53500<O45,O45<57001),AND(72500<O45,O45<75001)),ROUND($G45/100*O46,DpCU),ROUND($H45/100*O46,DpCU))))))) -> 1.01 | P48: =IF($K45>0,ROUND(P46*$E45/100,DpCU),IF(P49>10000,ROUND(HLOOKUP(P49,$O45:$P48,4,FALSE)/100*P46,DpCU),IF(OR(P45<20001,P45>95000,AND(60000<P45,P45<70001)),ROUND(ROUND(P46*JL/$C45,DcCU)*P47,DpCU),IF(OR(AND(20000<P45,P45<22501),AND(30000<P45,P45<50001),77500<P45),ROUND(P47*P46,DpCU),IF(OR(AND(22500<P45,P45<25001),AND(50000<P45,P45<53501),AND(70000<P45,P45<72501)),ROUND($F45/100*P46,DpCU),IF(OR(AND(25000<P45,P45<27501),AND(53500<P45,P45<57001),AND(72500<P45,P45<75001)),ROUND($G45/100*P46,DpCU),ROUND($H45/100*P46,DpCU))))))) -> 14
B49: =A45&"r" -> 10009r
A50: 10010 | B50: EXCAVACION PARA ZAPATAS EN TERRENO NORMAL | C50: =ROUND(J50*JL*Frto/8,4) -> 3 | D50: m3 | E50: =SUM($O53:$P53) -> 34.72 | F50: =SUMIF($O50:$P50,"<22501",$O53:$P53) -> 33.71 | G50: =SUMIFS($O53:$P53,$O50:$P50,">30000",$O50:$P50,"<50001") -> 0 | H50: =SUMIFS($O53:$P53,$O50:$P50,">60000",$O50:$P50,"<70001") -> 0 | I50: 2 | J50: 3 | O50: 10001 | P50: 70001
B51: =A50&"C" -> 10010C | O51: 1 | P51: 3
O52: =IF(O54>10000,HLOOKUP(O54,N50:$O53,4,FALSE),IF(OR(AND(22500<O50,O50<25001),AND(50000<O50,O50<53501),AND(70000<O50,O50<72501)),$F50,IF(OR(AND(25001<O50,O50<27501),AND(53500<O50,O50<57001),AND(72500<O50,O50<75001)),$G50,IF(OR(AND(27500<O50,O50<30001),AND(57000<O50,O50<60001),AND(75000<O50,O50<77500)),$H50,VLOOKUP(O50,BDins,6,FALSE))))) -> 12.64 | P52: =IF(P54>10000,HLOOKUP(P54,O50:$O53,4,FALSE),IF(OR(AND(22500<P50,P50<25001),AND(50000<P50,P50<53501),AND(70000<P50,P50<72501)),$F50,IF(OR(AND(25001<P50,P50<27501),AND(53500<P50,P50<57001),AND(72500<P50,P50<75001)),$G50,IF(OR(AND(27500<P50,P50<30001),AND(57000<P50,P50<60001),AND(75000<P50,P50<77500)),$H50,VLOOKUP(P50,BDins,6,FALSE))))) -> 33.71
O53: =IF($K50>0,ROUND(O51*$E50/100,DpCU),IF(O54>10000,ROUND(HLOOKUP(O54,$O50:$P53,4,FALSE)/100*O51,DpCU),IF(OR(O50<20001,O50>95000,AND(60000<O50,O50<70001)),ROUND(ROUND(O51*JL/$C50,DcCU)*O52,DpCU),IF(OR(AND(20000<O50,O50<22501),AND(30000<O50,O50<50001),77500<O50),ROUND(O52*O51,DpCU),IF(OR(AND(22500<O50,O50<25001),AND(50000<O50,O50<53501),AND(70000<O50,O50<72501)),ROUND($F50/100*O51,DpCU),IF(OR(AND(25000<O50,O50<27501),AND(53500<O50,O50<57001),AND(72500<O50,O50<75001)),ROUND($G50/100*O51,DpCU),ROUND($H50/100*O51,DpCU))))))) -> 33.71 | P53: =IF($K50>0,ROUND(P51*$E50/100,DpCU),IF(P54>10000,ROUND(HLOOKUP(P54,$O50:$P53,4,FALSE)/100*P51,DpCU),IF(OR(P50<20001,P50>95000,AND(60000<P50,P50<70001)),ROUND(ROUND(P51*JL/$C50,DcCU)*P52,DpCU),IF(OR(AND(20000<P50,P50<22501),AND(30000<P50,P50<50001),77500<P50),ROUND(P52*P51,DpCU),IF(OR(AND(22500<P50,P50<25001),AND(50000<P50,P50<53501),AND(70000<P50,P50<72501)),ROUND($F50/100*P51,DpCU),IF(OR(AND(25000<P50,P50<27501),AND(53500<P50,P50<57001),AND(72500<P50,P50<75001)),ROUND($G50/100*P51,DpCU),ROUND($H50/100*P51,DpCU))))))) -> 1.01
B54: =A50&"r" -> 10010r
A55: 10011 | B55: EXCAVACION PARA ESTRUCTURA EN ROCA FIJA EQUIPO | C55: =ROUND(J55*JL*Frto/8,4) -> 80 | D55: m3 | E55: =SUM($O58:$R58) -> 25.31 | F55: =SUMIF($O55:$R55,"<22501",$O58:$R58) -> 5.06 | G55: =SUMIFS($O58:$R58,$O55:$R55,">30000",$O55:$R55,"<50001") -> 0 | H55: =SUMIFS($O58:$R58,$O55:$R55,">60000",$O55:$R55,"<70001") -> 20 | I55: 4 | J55: 80 | O55: 10001 | P55: 60005 | Q55: 60006 | R55: 70001
B56: =A55&"C" -> 10011C | O56: 4 | P56: 1 | Q56: 1 | R56: 5
O57: =IF(O59>10000,HLOOKUP(O59,N55:$O58,4,FALSE),IF(OR(AND(22500<O55,O55<25001),AND(50000<O55,O55<53501),AND(70000<O55,O55<72501)),$F55,IF(OR(AND(25001<O55,O55<27501),AND(53500<O55,O55<57001),AND(72500<O55,O55<75001)),$G55,IF(OR(AND(27500<O55,O55<30001),AND(57000<O55,O55<60001),AND(75000<O55,O55<77500)),$H55,VLOOKUP(O55,BDins,6,FALSE))))) -> 12.64 | P57: =IF(P59>10000,HLOOKUP(P59,O55:$O58,4,FALSE),IF(OR(AND(22500<P55,P55<25001),AND(50000<P55,P55<53501),AND(70000<P55,P55<72501)),$F55,IF(OR(AND(25001<P55,P55<27501),AND(53500<P55,P55<57001),AND(72500<P55,P55<75001)),$G55,IF(OR(AND(27500<P55,P55<30001),AND(57000<P55,P55<60001),AND(75000<P55,P55<77500)),$H55,VLOOKUP(P55,BDins,6,FALSE))))) -> 80 | Q57: =IF(Q59>10000,HLOOKUP(Q59,$O55:P58,4,FALSE),IF(OR(AND(22500<Q55,Q55<25001),AND(50000<Q55,Q55<53501),AND(70000<Q55,Q55<72501)),$F55,IF(OR(AND(25001<Q55,Q55<27501),AND(53500<Q55,Q55<57001),AND(72500<Q55,Q55<75001)),$G55,IF(OR(AND(27500<Q55,Q55<30001),AND(57000<Q55,Q55<60001),AND(75000<Q55,Q55<77500)),$H55,VLOOKUP(Q55,BDins,6,FALSE))))) -> 120 | R57: =IF(R59>10000,HLOOKUP(R59,$O55:Q58,4,FALSE),IF(OR(AND(22500<R55,R55<25001),AND(50000<R55,R55<53501),AND(70000<R55,R55<72501)),$F55,IF(OR(AND(25001<R55,R55<27501),AND(53500<R55,R55<57001),AND(72500<R55,R55<75001)),$G55,IF(OR(AND(27500<R55,R55<30001),AND(57000<R55,R55<60001),AND(75000<R55,R55<77500)),$H55,VLOOKUP(R55,BDins,6,FALSE))))) -> 5.06
O58: =IF($K55>0,ROUND(O56*$E55/100,DpCU),IF(O59>10000,ROUND(HLOOKUP(O59,$O55:$R58,4,FALSE)/100*O56,DpCU),IF(OR(O55<20001,O55>95000,AND(60000<O55,O55<70001)),ROUND(ROUND(O56*JL/$C55,DcCU)*O57,DpCU),IF(OR(AND(20000<O55,O55<22501),AND(30000<O55,O55<50001),77500<O55),ROUND(O57*O56,DpCU),IF(OR(AND(22500<O55,O55<25001),AND(50000<O55,O55<53501),AND(70000<O55,O55<72501)),ROUND($F55/100*O56,DpCU),IF(OR(AND(25000<O55,O55<27501),AND(53500<O55,O55<57001),AND(72500<O55,O55<75001)),ROUND($G55/100*O56,DpCU),ROUND($H55/100*O56,DpCU))))))) -> 5.06 | P58: =IF($K55>0,ROUND(P56*$E55/100,DpCU),IF(P59>10000,ROUND(HLOOKUP(P59,$O55:$R58,4,FALSE)/100*P56,DpCU),IF(OR(P55<20001,P55>95000,AND(60000<P55,P55<70001)),ROUND(ROUND(P56*JL/$C55,DcCU)*P57,DpCU),IF(OR(AND(20000<P55,P55<22501),AND(30000<P55,P55<50001),77500<P55),ROUND(P57*P56,DpCU),IF(OR(AND(22500<P55,P55<25001),AND(50000<P55,P55<53501),AND(70000<P55,P55<72501)),ROUND($F55/100*P56,DpCU),IF(OR(AND(25000<P55,P55<27501),AND(53500<P55,P55<57001),AND(72500<P55,P55<75001)),ROUND($G55/100*P56,DpCU),ROUND($H55/100*P56,DpCU))))))) -> 8 | Q58: =IF($K55>0,ROUND(Q56*$E55/100,DpCU),IF(Q59>10000,ROUND(HLOOKUP(Q59,$O55:$R58,4,FALSE)/100*Q56,DpCU),IF(OR(Q55<20001,Q55>95000,AND(60000<Q55,Q55<70001)),ROUND(ROUND(Q56*JL/$C55,DcCU)*Q57,DpCU),IF(OR(AND(20000<Q55,Q55<22501),AND(30000<Q55,Q55<50001),77500<Q55),ROUND(Q57*Q56,DpCU),IF(OR(AND(22500<Q55,Q55<25001),AND(50000<Q55,Q55<53501),AND(70000<Q55,Q55<72501)),ROUND($F55/100*Q56,DpCU),IF(OR(AND(25000<Q55,Q55<27501),AND(53500<Q55,Q55<57001),AND(72500<Q55,Q55<75001)),ROUND($G55/100*Q56,DpCU),ROUND($H55/100*Q56,DpCU))))))) -> 12 | R58: =IF($K55>0,ROUND(R56*$E55/100,DpCU),IF(R59>10000,ROUND(HLOOKUP(R59,$O55:$R58,4,FALSE)/100*R56,DpCU),IF(OR(R55<20001,R55>95000,AND(60000<R55,R55<70001)),ROUND(ROUND(R56*JL/$C55,DcCU)*R57,DpCU),IF(OR(AND(20000<R55,R55<22501),AND(30000<R55,R55<50001),77500<R55),ROUND(R57*R56,DpCU),IF(OR(AND(22500<R55,R55<25001),AND(50000<R55,R55<53501),AND(70000<R55,R55<72501)),ROUND($F55/100*R56,DpCU),IF(OR(AND(25000<R55,R55<27501),AND(53500<R55,R55<57001),AND(72500<R55,R55<75001)),ROUND($G55/100*R56,DpCU),ROUND($H55/100*R56,DpCU))))))) -> 0.25
B59: =A55&"r" -> 10011r
A60: 10012 | B60: EXCAVACION PARA CIMIENTOS Y ZANJAS EN TERRENO NORMAL | C60: =ROUND(J60*JL*Frto/8,4) -> 3 | D60: m3 | E60: =SUM($O63:$P63) -> 34.72 | F60: =SUMIF($O60:$P60,"<22501",$O63:$P63) -> 33.71 | G60: =SUMIFS($O63:$P63,$O60:$P60,">30000",$O60:$P60,"<50001") -> 0 | H60: =SUMIFS($O63:$P63,$O60:$P60,">60000",$O60:$P60,"<70001") -> 0 | I60: 2 | J60: 3 | O60: 10001 | P60: 70001
B61: =A60&"C" -> 10012C | O61: 1 | P61: 3
O62: =IF(O64>10000,HLOOKUP(O64,N60:$O63,4,FALSE),IF(OR(AND(22500<O60,O60<25001),AND(50000<O60,O60<53501),AND(70000<O60,O60<72501)),$F60,IF(OR(AND(25001<O60,O60<27501),AND(53500<O60,O60<57001),AND(72500<O60,O60<75001)),$G60,IF(OR(AND(27500<O60,O60<30001),AND(57000<O60,O60<60001),AND(75000<O60,O60<77500)),$H60,VLOOKUP(O60,BDins,6,FALSE))))) -> 12.64 | P62: =IF(P64>10000,HLOOKUP(P64,O60:$O63,4,FALSE),IF(OR(AND(22500<P60,P60<25001),AND(50000<P60,P60<53501),AND(70000<P60,P60<72501)),$F60,IF(OR(AND(25001<P60,P60<27501),AND(53500<P60,P60<57001),AND(72500<P60,P60<75001)),$G60,IF(OR(AND(27500<P60,P60<30001),AND(57000<P60,P60<60001),AND(75000<P60,P60<77500)),$H60,VLOOKUP(P60,BDins,6,FALSE))))) -> 33.71
O63: =IF($K60>0,ROUND(O61*$E60/100,DpCU),IF(O64>10000,ROUND(HLOOKUP(O64,$O60:$P63,4,FALSE)/100*O61,DpCU),IF(OR(O60<20001,O60>95000,AND(60000<O60,O60<70001)),ROUND(ROUND(O61*JL/$C60,DcCU)*O62,DpCU),IF(OR(AND(20000<O60,O60<22501),AND(30000<O60,O60<50001),77500<O60),ROUND(O62*O61,DpCU),IF(OR(AND(22500<O60,O60<25001),AND(50000<O60,O60<53501),AND(70000<O60,O60<72501)),ROUND($F60/100*O61,DpCU),IF(OR(AND(25000<O60,O60<27501),AND(53500<O60,O60<57001),AND(72500<O60,O60<75001)),ROUND($G60/100*O61,DpCU),ROUND($H60/100*O61,DpCU))))))) -> 33.71 | P63: =IF($K60>0,ROUND(P61*$E60/100,DpCU),IF(P64>10000,ROUND(HLOOKUP(P64,$O60:$P63,4,FALSE)/100*P61,DpCU),IF(OR(P60<20001,P60>95000,AND(60000<P60,P60<70001)),ROUND(ROUND(P61*JL/$C60,DcCU)*P62,DpCU),IF(OR(AND(20000<P60,P60<22501),AND(30000<P60,P60<50001),77500<P60),ROUND(P62*P61,DpCU),IF(OR(AND(22500<P60,P60<25001),AND(50000<P60,P60<53501),AND(70000<P60,P60<72501)),ROUND($F60/100*P61,DpCU),IF(OR(AND(25000<P60,P60<27501),AND(53500<P60,P60<57001),AND(72500<P60,P60<75001)),ROUND($G60/100*P61,DpCU),ROUND($H60/100*P61,DpCU))))))) -> 1.01
B64: =A60&"r" -> 10012r
A65: 10013 | B65: RELLENO DE ESTRUCTURAS CON MATERIAL PROPIO MANUAL | C65: =ROUND(J65*JL*Frto/8,4) -> 12 | D65: m3 | E65: =SUM($O68:$S68) -> 73.67 | F65: =SUMIF($O65:$S65,"<22501",$O68:$S68) -> 59.97 | G65: =SUMIFS($O68:$S68,$O65:$S65,">30000",$O65:$S65,"<50001") -> 0.7 | H65: =SUMIFS($O68:$S68,$O65:$S65,">60000",$O65:$S65,"<70001") -> 10 | I65: 5 | J65: 12 | O65: 10001 | P65: 10003 | Q65: 30022 | R65: 60007 | S65: 70001
B66: =A65&"C" -> 10013C | O66: 6 | P66: 1 | Q66: 0.2 | R66: 0.5 | S66: 5
O67: =IF(O69>10000,HLOOKUP(O69,N65:$O68,4,FALSE),IF(OR(AND(22500<O65,O65<25001),AND(50000<O65,O65<53501),AND(70000<O65,O65<72501)),$F65,IF(OR(AND(25001<O65,O65<27501),AND(53500<O65,O65<57001),AND(72500<O65,O65<75001)),$G65,IF(OR(AND(27500<O65,O65<30001),AND(57000<O65,O65<60001),AND(75000<O65,O65<77500)),$H65,VLOOKUP(O65,BDins,6,FALSE))))) -> 12.64 | P67: =IF(P69>10000,HLOOKUP(P69,O65:$O68,4,FALSE),IF(OR(AND(22500<P65,P65<25001),AND(50000<P65,P65<53501),AND(70000<P65,P65<72501)),$F65,IF(OR(AND(25001<P65,P65<27501),AND(53500<P65,P65<57001),AND(72500<P65,P65<75001)),$G65,IF(OR(AND(27500<P65,P65<30001),AND(57000<P65,P65<60001),AND(75000<P65,P65<77500)),$H65,VLOOKUP(P65,BDins,6,FALSE))))) -> 14.12 | Q67: =IF(Q69>10000,HLOOKUP(Q69,$O65:P68,4,FALSE),IF(OR(AND(22500<Q65,Q65<25001),AND(50000<Q65,Q65<53501),AND(70000<Q65,Q65<72501)),$F65,IF(OR(AND(25001<Q65,Q65<27501),AND(53500<Q65,Q65<57001),AND(72500<Q65,Q65<75001)),$G65,IF(OR(AND(27500<Q65,Q65<30001),AND(57000<Q65,Q65<60001),AND(75000<Q65,Q65<77500)),$H65,VLOOKUP(Q65,BDins,6,FALSE))))) -> 3.5 | R67: =IF(R69>10000,HLOOKUP(R69,$O65:Q68,4,FALSE),IF(OR(AND(22500<R65,R65<25001),AND(50000<R65,R65<53501),AND(70000<R65,R65<72501)),$F65,IF(OR(AND(25001<R65,R65<27501),AND(53500<R65,R65<57001),AND(72500<R65,R65<75001)),$G65,IF(OR(AND(27500<R65,R65<30001),AND(57000<R65,R65<60001),AND(75000<R65,R65<77500)),$H65,VLOOKUP(R65,BDins,6,FALSE))))) -> 30 | S67: =IF(S69>10000,HLOOKUP(S69,$O65:R68,4,FALSE),IF(OR(AND(22500<S65,S65<25001),AND(50000<S65,S65<53501),AND(70000<S65,S65<72501)),$F65,IF(OR(AND(25001<S65,S65<27501),AND(53500<S65,S65<57001),AND(72500<S65,S65<75001)),$G65,IF(OR(AND(27500<S65,S65<30001),AND(57000<S65,S65<60001),AND(75000<S65,S65<77500)),$H65,VLOOKUP(S65,BDins,6,FALSE))))) -> 59.97
O68: =IF($K65>0,ROUND(O66*$E65/100,DpCU),IF(O69>10000,ROUND(HLOOKUP(O69,$O65:$S68,4,FALSE)/100*O66,DpCU),IF(OR(O65<20001,O65>95000,AND(60000<O65,O65<70001)),ROUND(ROUND(O66*JL/$C65,DcCU)*O67,DpCU),IF(OR(AND(20000<O65,O65<22501),AND(30000<O65,O65<50001),77500<O65),ROUND(O67*O66,DpCU),IF(OR(AND(22500<O65,O65<25001),AND(50000<O65,O65<53501),AND(70000<O65,O65<72501)),ROUND($F65/100*O66,DpCU),IF(OR(AND(25000<O65,O65<27501),AND(53500<O65,O65<57001),AND(72500<O65,O65<75001)),ROUND($G65/100*O66,DpCU),ROUND($H65/100*O66,DpCU))))))) -> 50.56 | P68: =IF($K65>0,ROUND(P66*$E65/100,DpCU),IF(P69>10000,ROUND(HLOOKUP(P69,$O65:$S68,4,FALSE)/100*P66,DpCU),IF(OR(P65<20001,P65>95000,AND(60000<P65,P65<70001)),ROUND(ROUND(P66*JL/$C65,DcCU)*P67,DpCU),IF(OR(AND(20000<P65,P65<22501),AND(30000<P65,P65<50001),77500<P65),ROUND(P67*P66,DpCU),IF(OR(AND(22500<P65,P65<25001),AND(50000<P65,P65<53501),AND(70000<P65,P65<72501)),ROUND($F65/100*P66,DpCU),IF(OR(AND(25000<P65,P65<27501),AND(53500<P65,P65<57001),AND(72500<P65,P65<75001)),ROUND($G65/100*P66,DpCU),ROUND($H65/100*P66,DpCU))))))) -> 9.41 | Q68: =IF($K65>0,ROUND(Q66*$E65/100,DpCU),IF(Q69>10000,ROUND(HLOOKUP(Q69,$O65:$S68,4,FALSE)/100*Q66,DpCU),IF(OR(Q65<20001,Q65>95000,AND(60000<Q65,Q65<70001)),ROUND(ROUND(Q66*JL/$C65,DcCU)*Q67,DpCU),IF(OR(AND(20000<Q65,Q65<22501),AND(30000<Q65,Q65<50001),77500<Q65),ROUND(Q67*Q66,DpCU),IF(OR(AND(22500<Q65,Q65<25001),AND(50000<Q65,Q65<53501),AND(70000<Q65,Q65<72501)),ROUND($F65/100*Q66,DpCU),IF(OR(AND(25000<Q65,Q65<27501),AND(53500<Q65,Q65<57001),AND(72500<Q65,Q65<75001)),ROUND($G65/100*Q66,DpCU),ROUND($H65/100*Q66,DpCU))))))) -> 0.7 | R68: =IF($K65>0,ROUND(R66*$E65/100,DpCU),IF(R69>10000,ROUND(HLOOKUP(R69,$O65:$S68,4,FALSE)/100*R66,DpCU),IF(OR(R65<20001,R65>95000,AND(60000<R65,R65<70001)),ROUND(ROUND(R66*JL/$C65,DcCU)*R67,DpCU),IF(OR(AND(20000<R65,R65<22501),AND(30000<R65,R65<50001),77500<R65),ROUND(R67*R66,DpCU),IF(OR(AND(22500<R65,R65<25001),AND(50000<R65,R65<53501),AND(70000<R65,R65<72501)),ROUND($F65/100*R66,DpCU),IF(OR(AND(25000<R65,R65<27501),AND(53500<R65,R65<57001),AND(72500<R65,R65<75001)),ROUND($G65/100*R66,DpCU),ROUND($H65/100*R66,DpCU))))))) -> 10 | S68: =IF($K65>0,ROUND(S66*$E65/100,DpCU),IF(S69>10000,ROUND(HLOOKUP(S69,$O65:$S68,4,FALSE)/100*S66,DpCU),IF(OR(S65<20001,S65>95000,AND(60000<S65,S65<70001)),ROUND(ROUND(S66*JL/$C65,DcCU)*S67,DpCU),IF(OR(AND(20000<S65,S65<22501),AND(30000<S65,S65<50001),77500<S65),ROUND(S67*S66,DpCU),IF(OR(AND(22500<S65,S65<25001),AND(50000<S65,S65<53501),AND(70000<S65,S65<72501)),ROUND($F65/100*S66,DpCU),IF(OR(AND(25000<S65,S65<27501),AND(53500<S65,S65<57001),AND(72500<S65,S65<75001)),ROUND($G65/100*S66,DpCU),ROUND($H65/100*S66,DpCU))))))) -> 3
B69: =A65&"r" -> 10013r
A70: 10014 | B70: ELIMINACION DE MATERIAL EXCEDENTE CON VOLQUETES (SUBCONTRATO) | C70: =ROUND(J70*JL*Frto/8,4) -> 1 | D70: m3 | E70: =SUM($O73:$O73) -> 19.3 | F70: =SUMIF($O70:$O70,"<22501",$O73:$O73) -> 0 | G70: =SUMIFS($O73:$O73,$O70:$O70,">30000",$O70:$O70,"<50001") -> 0 | H70: =SUMIFS($O73:$O73,$O70:$O70,">60000",$O70:$O70,"<70001") -> 0 | I70: 1 | J70: 1 | O70: 80002
B71: =A70&"C" -> 10014C | O71: 1
O72: =IF(O74>10000,HLOOKUP(O74,N70:$O73,4,FALSE),IF(OR(AND(22500<O70,O70<25001),AND(50000<O70,O70<53501),AND(70000<O70,O70<72501)),$F70,IF(OR(AND(25001<O70,O70<27501),AND(53500<O70,O70<57001),AND(72500<O70,O70<75001)),$G70,IF(OR(AND(27500<O70,O70<30001),AND(57000<O70,O70<60001),AND(75000<O70,O70<77500)),$H70,VLOOKUP(O70,BDins,6,FALSE))))) -> 19.3
O73: =IF($K70>0,ROUND(O71*$E70/100,DpCU),IF(O74>10000,ROUND(HLOOKUP(O74,$O70:$O73,4,FALSE)/100*O71,DpCU),IF(OR(O70<20001,O70>95000,AND(60000<O70,O70<70001)),ROUND(ROUND(O71*JL/$C70,DcCU)*O72,DpCU),IF(OR(AND(20000<O70,O70<22501),AND(30000<O70,O70<50001),77500<O70),ROUND(O72*O71,DpCU),IF(OR(AND(22500<O70,O70<25001),AND(50000<O70,O70<53501),AND(70000<O70,O70<72501)),ROUND($F70/100*O71,DpCU),IF(OR(AND(25000<O70,O70<27501),AND(53500<O70,O70<57001),AND(72500<O70,O70<75001)),ROUND($G70/100*O71,DpCU),ROUND($H70/100*O71,DpCU))))))) -> 19.3
B74: =A70&"r" -> 10014r
A75: 10015 | B75: NIVELACION INTERIOR Y APISONADO | C75: =ROUND(J75*JL*Frto/8,4) -> 60 | D75: m2 | E75: =SUM($O78:$R78) -> 4.28 | F75: =SUMIF($O75:$R75,"<22501",$O78:$R78) -> 4.02 | G75: =SUMIFS($O78:$R78,$O75:$R75,">30000",$O75:$R75,"<50001") -> 0.14 | H75: =SUMIFS($O78:$R78,$O75:$R75,">60000",$O75:$R75,"<70001") -> 0 | I75: 4 | J75: 60 | O75: 10001 | P75: 10004 | Q75: 30023 | R75: 70001
B76: =A75&"C" -> 10015C | O76: 1 | P76: 1 | Q76: 0.03 | R76: 3
O77: =IF(O79>10000,HLOOKUP(O79,N75:$O78,4,FALSE),IF(OR(AND(22500<O75,O75<25001),AND(50000<O75,O75<53501),AND(70000<O75,O75<72501)),$F75,IF(OR(AND(25001<O75,O75<27501),AND(53500<O75,O75<57001),AND(72500<O75,O75<75001)),$G75,IF(OR(AND(27500<O75,O75<30001),AND(57000<O75,O75<60001),AND(75000<O75,O75<77500)),$H75,VLOOKUP(O75,BDins,6,FALSE))))) -> 12.64 | P77: =IF(P79>10000,HLOOKUP(P79,O75:$O78,4,FALSE),IF(OR(AND(22500<P75,P75<25001),AND(50000<P75,P75<53501),AND(70000<P75,P75<72501)),$F75,IF(OR(AND(25001<P75,P75<27501),AND(53500<P75,P75<57001),AND(72500<P75,P75<75001)),$G75,IF(OR(AND(27500<P75,P75<30001),AND(57000<P75,P75<60001),AND(75000<P75,P75<77500)),$H75,VLOOKUP(P75,BDins,6,FALSE))))) -> 17.59 | Q77: =IF(Q79>10000,HLOOKUP(Q79,$O75:P78,4,FALSE),IF(OR(AND(22500<Q75,Q75<25001),AND(50000<Q75,Q75<53501),AND(70000<Q75,Q75<72501)),$F75,IF(OR(AND(25001<Q75,Q75<27501),AND(53500<Q75,Q75<57001),AND(72500<Q75,Q75<75001)),$G75,IF(OR(AND(27500<Q75,Q75<30001),AND(57000<Q75,Q75<60001),AND(75000<Q75,Q75<77500)),$H75,VLOOKUP(Q75,BDins,6,FALSE))))) -> 4.5 | R77: =IF(R79>10000,HLOOKUP(R79,$O75:Q78,4,FALSE),IF(OR(AND(22500<R75,R75<25001),AND(50000<R75,R75<53501),AND(70000<R75,R75<72501)),$F75,IF(OR(AND(25001<R75,R75<27501),AND(53500<R75,R75<57001),AND(72500<R75,R75<75001)),$G75,IF(OR(AND(27500<R75,R75<30001),AND(57000<R75,R75<60001),AND(75000<R75,R75<77500)),$H75,VLOOKUP(R75,BDins,6,FALSE))))) -> 4.02
O78: =IF($K75>0,ROUND(O76*$E75/100,DpCU),IF(O79>10000,ROUND(HLOOKUP(O79,$O75:$R78,4,FALSE)/100*O76,DpCU),IF(OR(O75<20001,O75>95000,AND(60000<O75,O75<70001)),ROUND(ROUND(O76*JL/$C75,DcCU)*O77,DpCU),IF(OR(AND(20000<O75,O75<22501),AND(30000<O75,O75<50001),77500<O75),ROUND(O77*O76,DpCU),IF(OR(AND(22500<O75,O75<25001),AND(50000<O75,O75<53501),AND(70000<O75,O75<72501)),ROUND($F75/100*O76,DpCU),IF(OR(AND(25000<O75,O75<27501),AND(53500<O75,O75<57001),AND(72500<O75,O75<75001)),ROUND($G75/100*O76,DpCU),ROUND($H75/100*O76,DpCU))))))) -> 1.68 | P78: =IF($K75>0,ROUND(P76*$E75/100,DpCU),IF(P79>10000,ROUND(HLOOKUP(P79,$O75:$R78,4,FALSE)/100*P76,DpCU),IF(OR(P75<20001,P75>95000,AND(60000<P75,P75<70001)),ROUND(ROUND(P76*JL/$C75,DcCU)*P77,DpCU),IF(OR(AND(20000<P75,P75<22501),AND(30000<P75,P75<50001),77500<P75),ROUND(P77*P76,DpCU),IF(OR(AND(22500<P75,P75<25001),AND(50000<P75,P75<53501),AND(70000<P75,P75<72501)),ROUND($F75/100*P76,DpCU),IF(OR(AND(25000<P75,P75<27501),AND(53500<P75,P75<57001),AND(72500<P75,P75<75001)),ROUND($G75/100*P76,DpCU),ROUND($H75/100*P76,DpCU))))))) -> 2.34 | Q78: =IF($K75>0,ROUND(Q76*$E75/100,DpCU),IF(Q79>10000,ROUND(HLOOKUP(Q79,$O75:$R78,4,FALSE)/100*Q76,DpCU),IF(OR(Q75<20001,Q75>95000,AND(60000<Q75,Q75<70001)),ROUND(ROUND(Q76*JL/$C75,DcCU)*Q77,DpCU),IF(OR(AND(20000<Q75,Q75<22501),AND(30000<Q75,Q75<50001),77500<Q75),ROUND(Q77*Q76,DpCU),IF(OR(AND(22500<Q75,Q75<25001),AND(50000<Q75,Q75<53501),AND(70000<Q75,Q75<72501)),ROUND($F75/100*Q76,DpCU),IF(OR(AND(25000<Q75,Q75<27501),AND(53500<Q75,Q75<57001),AND(72500<Q75,Q75<75001)),ROUND($G75/100*Q76,DpCU),ROUND($H75/100*Q76,DpCU))))))) -> 0.14 | R78: =IF($K75>0,ROUND(R76*$E75/100,DpCU),IF(R79>10000,ROUND(HLOOKUP(R79,$O75:$R78,4,FALSE)/100*R76,DpCU),IF(OR(R75<20001,R75>95000,AND(60000<R75,R75<70001)),ROUND(ROUND(R76*JL/$C75,DcCU)*R77,DpCU),IF(OR(AND(20000<R75,R75<22501),AND(30000<R75,R75<50001),77500<R75),ROUND(R77*R76,DpCU),IF(OR(AND(22500<R75,R75<25001),AND(50000<R75,R75<53501),AND(70000<R75,R75<72501)),ROUND($F75/100*R76,DpCU),IF(OR(AND(25000<R75,R75<27501),AND(53500<R75,R75<57001),AND(72500<R75,R75<75001)),ROUND($G75/100*R76,DpCU),ROUND($H75/100*R76,DpCU))))))) -> 0.12
B79: =A75&"r" -> 10015r
A80: 10016 | B80: BASE GRANULAR E=0.15 m.COMPACTADA | C80: =ROUND(J80*JL*Frto/8,4) -> 180 | D80: m2 | E80: =SUM($O83:$V83) -> 16.37 | F80: =SUMIF($O80:$V80,"<22501",$O83:$V83) -> 2.31 | G80: =SUMIFS($O83:$V83,$O80:$V80,">30000",$O80:$V80,"<50001") -> 8.08 | H80: =SUMIFS($O83:$V83,$O80:$V80,">60000",$O80:$V80,"<70001") -> 5.98 | I80: 8 | J80: 180 | O80: 10001 | P80: 10003 | Q80: 30022 | R80: 30024 | S80: 30025 | T80: 60008 | U80: 60009 | V80: 60010
B81: =A80&"C" -> 10016C | O81: 3 | P81: 1 | Q81: 0.0156 | R81: 0.0333 | S81: 0.195 | T81: 1 | U81: 1 | V81: 1.05
O82: =IF(O84>10000,HLOOKUP(O84,N80:$O83,4,FALSE),IF(OR(AND(22500<O80,O80<25001),AND(50000<O80,O80<53501),AND(70000<O80,O80<72501)),$F80,IF(OR(AND(25001<O80,O80<27501),AND(53500<O80,O80<57001),AND(72500<O80,O80<75001)),$G80,IF(OR(AND(27500<O80,O80<30001),AND(57000<O80,O80<60001),AND(75000<O80,O80<77500)),$H80,VLOOKUP(O80,BDins,6,FALSE))))) -> 12.64 | P82: =IF(P84>10000,HLOOKUP(P84,O80:$O83,4,FALSE),IF(OR(AND(22500<P80,P80<25001),AND(50000<P80,P80<53501),AND(70000<P80,P80<72501)),$F80,IF(OR(AND(25001<P80,P80<27501),AND(53500<P80,P80<57001),AND(72500<P80,P80<75001)),$G80,IF(OR(AND(27500<P80,P80<30001),AND(57000<P80,P80<60001),AND(75000<P80,P80<77500)),$H80,VLOOKUP(P80,BDins,6,FALSE))))) -> 14.12 | Q82: =IF(Q84>10000,HLOOKUP(Q84,$O80:P83,4,FALSE),IF(OR(AND(22500<Q80,Q80<25001),AND(50000<Q80,Q80<53501),AND(70000<Q80,Q80<72501)),$F80,IF(OR(AND(25001<Q80,Q80<27501),AND(53500<Q80,Q80<57001),AND(72500<Q80,Q80<75001)),$G80,IF(OR(AND(27500<Q80,Q80<30001),AND(57000<Q80,Q80<60001),AND(75000<Q80,Q80<77500)),$H80,VLOOKUP(Q80,BDins,6,FALSE))))) -> 3.5 | R82: =IF(R84>10000,HLOOKUP(R84,$O80:Q83,4,FALSE),IF(OR(AND(22500<R80,R80<25001),AND(50000<R80,R80<53501),AND(70000<R80,R80<72501)),$F80,IF(OR(AND(25001<R80,R80<27501),AND(53500<R80,R80<57001),AND(72500<R80,R80<75001)),$G80,IF(OR(AND(27500<R80,R80<30001),AND(57000<R80,R80<60001),AND(75000<R80,R80<77500)),$H80,VLOOKUP(R80,BDins,6,FALSE))))) -> 13.2 | S82: =IF(S84>10000,HLOOKUP(S84,$O80:R83,4,FALSE),IF(OR(AND(22500<S80,S80<25001),AND(50000<S80,S80<53501),AND(70000<S80,S80<72501)),$F80,IF(OR(AND(25001<S80,S80<27501),AND(53500<S80,S80<57001),AND(72500<S80,S80<75001)),$G80,IF(OR(AND(27500<S80,S80<30001),AND(57000<S80,S80<60001),AND(75000<S80,S80<77500)),$H80,VLOOKUP(S80,BDins,6,FALSE))))) -> 38.94 | T82: =IF(T84>10000,HLOOKUP(T84,$O80:S83,4,FALSE),IF(OR(AND(22500<T80,T80<25001),AND(50000<T80,T80<53501),AND(70000<T80,T80<72501)),$F80,IF(OR(AND(25001<T80,T80<27501),AND(53500<T80,T80<57001),AND(72500<T80,T80<75001)),$G80,IF(OR(AND(27500<T80,T80<30001),AND(57000<T80,T80<60001),AND(75000<T80,T80<77500)),$H80,VLOOKUP(T80,BDins,6,FALSE))))) -> 15 | U82: =IF(U84>10000,HLOOKUP(U84,$O80:T83,4,FALSE),IF(OR(AND(22500<U80,U80<25001),AND(50000<U80,U80<53501),AND(70000<U80,U80<72501)),$F80,IF(OR(AND(25001<U80,U80<27501),AND(53500<U80,U80<57001),AND(72500<U80,U80<75001)),$G80,IF(OR(AND(27500<U80,U80<30001),AND(57000<U80,U80<60001),AND(75000<U80,U80<77500)),$H80,VLOOKUP(U80,BDins,6,FALSE))))) -> 115 | V82: =IF(V84>10000,HLOOKUP(V84,$O80:U83,4,FALSE),IF(OR(AND(22500<V80,V80<25001),AND(50000<V80,V80<53501),AND(70000<V80,V80<72501)),$F80,IF(OR(AND(25001<V80,V80<27501),AND(53500<V80,V80<57001),AND(72500<V80,V80<75001)),$G80,IF(OR(AND(27500<V80,V80<30001),AND(57000<V80,V80<60001),AND(75000<V80,V80<77500)),$H80,VLOOKUP(V80,BDins,6,FALSE))))) -> 4.37
O83: =IF($K80>0,ROUND(O81*$E80/100,DpCU),IF(O84>10000,ROUND(HLOOKUP(O84,$O80:$V83,4,FALSE)/100*O81,DpCU),IF(OR(O80<20001,O80>95000,AND(60000<O80,O80<70001)),ROUND(ROUND(O81*JL/$C80,DcCU)*O82,DpCU),IF(OR(AND(20000<O80,O80<22501),AND(30000<O80,O80<50001),77500<O80),ROUND(O82*O81,DpCU),IF(OR(AND(22500<O80,O80<25001),AND(50000<O80,O80<53501),AND(70000<O80,O80<72501)),ROUND($F80/100*O81,DpCU),IF(OR(AND(25000<O80,O80<27501),AND(53500<O80,O80<57001),AND(72500<O80,O80<75001)),ROUND($G80/100*O81,DpCU),ROUND($H80/100*O81,DpCU))))))) -> 1.68 | P83: =IF($K80>0,ROUND(P81*$E80/100,DpCU),IF(P84>10000,ROUND(HLOOKUP(P84,$O80:$V83,4,FALSE)/100*P81,DpCU),IF(OR(P80<20001,P80>95000,AND(60000<P80,P80<70001)),ROUND(ROUND(P81*JL/$C80,DcCU)*P82,DpCU),IF(OR(AND(20000<P80,P80<22501),AND(30000<P80,P80<50001),77500<P80),ROUND(P82*P81,DpCU),IF(OR(AND(22500<P80,P80<25001),AND(50000<P80,P80<53501),AND(70000<P80,P80<72501)),ROUND($F80/100*P81,DpCU),IF(OR(AND(25000<P80,P80<27501),AND(53500<P80,P80<57001),AND(72500<P80,P80<75001)),ROUND($G80/100*P81,DpCU),ROUND($H80/100*P81,DpCU))))))) -> 0.63 | Q83: =IF($K80>0,ROUND(Q81*$E80/100,DpCU),IF(Q84>10000,ROUND(HLOOKUP(Q84,$O80:$V83,4,FALSE)/100*Q81,DpCU),IF(OR(Q80<20001,Q80>95000,AND(60000<Q80,Q80<70001)),ROUND(ROUND(Q81*JL/$C80,DcCU)*Q82,DpCU),IF(OR(AND(20000<Q80,Q80<22501),AND(30000<Q80,Q80<50001),77500<Q80),ROUND(Q82*Q81,DpCU),IF(OR(AND(22500<Q80,Q80<25001),AND(50000<Q80,Q80<53501),AND(70000<Q80,Q80<72501)),ROUND($F80/100*Q81,DpCU),IF(OR(AND(25000<Q80,Q80<27501),AND(53500<Q80,Q80<57001),AND(72500<Q80,Q80<75001)),ROUND($G80/100*Q81,DpCU),ROUND($H80/100*Q81,DpCU))))))) -> 0.05 | R83: =IF($K80>0,ROUND(R81*$E80/100,DpCU),IF(R84>10000,ROUND(HLOOKUP(R84,$O80:$V83,4,FALSE)/100*R81,DpCU),IF(OR(R80<20001,R80>95000,AND(60000<R80,R80<70001)),ROUND(ROUND(R81*JL/$C80,DcCU)*R82,DpCU),IF(OR(AND(20000<R80,R80<22501),AND(30000<R80,R80<50001),77500<R80),ROUND(R82*R81,DpCU),IF(OR(AND(22500<R80,R80<25001),AND(50000<R80,R80<53501),AND(70000<R80,R80<72501)),ROUND($F80/100*R81,DpCU),IF(OR(AND(25000<R80,R80<27501),AND(53500<R80,R80<57001),AND(72500<R80,R80<75001)),ROUND($G80/100*R81,DpCU),ROUND($H80/100*R81,DpCU))))))) -> 0.44 | S83: =IF($K80>0,ROUND(S81*$E80/100,DpCU),IF(S84>10000,ROUND(HLOOKUP(S84,$O80:$V83,4,FALSE)/100*S81,DpCU),IF(OR(S80<20001,S80>95000,AND(60000<S80,S80<70001)),ROUND(ROUND(S81*JL/$C80,DcCU)*S82,DpCU),IF(OR(AND(20000<S80,S80<22501),AND(30000<S80,S80<50001),77500<S80),ROUND(S82*S81,DpCU),IF(OR(AND(22500<S80,S80<25001),AND(50000<S80,S80<53501),AND(70000<S80,S80<72501)),ROUND($F80/100*S81,DpCU),IF(OR(AND(25000<S80,S80<27501),AND(53500<S80,S80<57001),AND(72500<S80,S80<75001)),ROUND($G80/100*S81,DpCU),ROUND($H80/100*S81,DpCU))))))) -> 7.59 | T83: =IF($K80>0,ROUND(T81*$E80/100,DpCU),IF(T84>10000,ROUND(HLOOKUP(T84,$O80:$V83,4,FALSE)/100*T81,DpCU),IF(OR(T80<20001,T80>95000,AND(60000<T80,T80<70001)),ROUND(ROUND(T81*JL/$C80,DcCU)*T82,DpCU),IF(OR(AND(20000<T80,T80<22501),AND(30000<T80,T80<50001),77500<T80),ROUND(T82*T81,DpCU),IF(OR(AND(22500<T80,T80<25001),AND(50000<T80,T80<53501),AND(70000<T80,T80<72501)),ROUND($F80/100*T81,DpCU),IF(OR(AND(25000<T80,T80<27501),AND(53500<T80,T80<57001),AND(72500<T80,T80<75001)),ROUND($G80/100*T81,DpCU),ROUND($H80/100*T81,DpCU))))))) -> 0.67 | U83: =IF($K80>0,ROUND(U81*$E80/100,DpCU),IF(U84>10000,ROUND(HLOOKUP(U84,$O80:$V83,4,FALSE)/100*U81,DpCU),IF(OR(U80<20001,U80>95000,AND(60000<U80,U80<70001)),ROUND(ROUND(U81*JL/$C80,DcCU)*U82,DpCU),IF(OR(AND(20000<U80,U80<22501),AND(30000<U80,U80<50001),77500<U80),ROUND(U82*U81,DpCU),IF(OR(AND(22500<U80,U80<25001),AND(50000<U80,U80<53501),AND(70000<U80,U80<72501)),ROUND($F80/100*U81,DpCU),IF(OR(AND(25000<U80,U80<27501),AND(53500<U80,U80<57001),AND(72500<U80,U80<75001)),ROUND($G80/100*U81,DpCU),ROUND($H80/100*U81,DpCU))))))) -> 5.11 | V83: =IF($K80>0,ROUND(V81*$E80/100,DpCU),IF(V84>10000,ROUND(HLOOKUP(V84,$O80:$V83,4,FALSE)/100*V81,DpCU),IF(OR(V80<20001,V80>95000,AND(60000<V80,V80<70001)),ROUND(ROUND(V81*JL/$C80,DcCU)*V82,DpCU),IF(OR(AND(20000<V80,V80<22501),AND(30000<V80,V80<50001),77500<V80),ROUND(V82*V81,DpCU),IF(OR(AND(22500<V80,V80<25001),AND(50000<V80,V80<53501),AND(70000<V80,V80<72501)),ROUND($F80/100*V81,DpCU),IF(OR(AND(25000<V80,V80<27501),AND(53500<V80,V80<57001),AND(72500<V80,V80<75001)),ROUND($G80/100*V81,DpCU),ROUND($H80/100*V81,DpCU))))))) -> 0.2
B84: =A80&"r" -> 10016r
A85: 10017 | B85: SOLADO e=3" | C85: =ROUND(J85*JL*Frto/8,4) -> 100 | D85: m2 | E85: =SUM($O88:$V88) -> 27.38 | F85: =SUMIF($O85:$V85,"<22501",$O88:$V88) -> 10.18 | G85: =SUMIFS($O88:$V88,$O85:$V85,">30000",$O85:$V85,"<50001") -> 15.2 | H85: =SUMIFS($O88:$V88,$O85:$V85,">60000",$O85:$V85,"<70001") -> 2 | I85: 8 | J85: 100 | O85: 10001 | P85: 10003 | Q85: 10004 | R85: 30001 | S85: 30002 | T85: 30022 | U85: 30024 | V85: 60011
B86: =A85&"C" -> 10017C | O86: 7 | P86: 1.5 | Q86: 1 | R86: 0.396 | S86: 0.089 | T86: 0.01 | U86: 0.06 | V86: 1
O87: =IF(O89>10000,HLOOKUP(O89,N85:$O88,4,FALSE),IF(OR(AND(22500<O85,O85<25001),AND(50000<O85,O85<53501),AND(70000<O85,O85<72501)),$F85,IF(OR(AND(25001<O85,O85<27501),AND(53500<O85,O85<57001),AND(72500<O85,O85<75001)),$G85,IF(OR(AND(27500<O85,O85<30001),AND(57000<O85,O85<60001),AND(75000<O85,O85<77500)),$H85,VLOOKUP(O85,BDins,6,FALSE))))) -> 12.64 | P87: =IF(P89>10000,HLOOKUP(P89,O85:$O88,4,FALSE),IF(OR(AND(22500<P85,P85<25001),AND(50000<P85,P85<53501),AND(70000<P85,P85<72501)),$F85,IF(OR(AND(25001<P85,P85<27501),AND(53500<P85,P85<57001),AND(72500<P85,P85<75001)),$G85,IF(OR(AND(27500<P85,P85<30001),AND(57000<P85,P85<60001),AND(75000<P85,P85<77500)),$H85,VLOOKUP(P85,BDins,6,FALSE))))) -> 14.12 | Q87: =IF(Q89>10000,HLOOKUP(Q89,$O85:P88,4,FALSE),IF(OR(AND(22500<Q85,Q85<25001),AND(50000<Q85,Q85<53501),AND(70000<Q85,Q85<72501)),$F85,IF(OR(AND(25001<Q85,Q85<27501),AND(53500<Q85,Q85<57001),AND(72500<Q85,Q85<75001)),$G85,IF(OR(AND(27500<Q85,Q85<30001),AND(57000<Q85,Q85<60001),AND(75000<Q85,Q85<77500)),$H85,VLOOKUP(Q85,BDins,6,FALSE))))) -> 17.59 | R87: =IF(R89>10000,HLOOKUP(R89,$O85:Q88,4,FALSE),IF(OR(AND(22500<R85,R85<25001),AND(50000<R85,R85<53501),AND(70000<R85,R85<72501)),$F85,IF(OR(AND(25001<R85,R85<27501),AND(53500<R85,R85<57001),AND(72500<R85,R85<75001)),$G85,IF(OR(AND(27500<R85,R85<30001),AND(57000<R85,R85<60001),AND(75000<R85,R85<77500)),$H85,VLOOKUP(R85,BDins,6,FALSE))))) -> 27 | S87: =IF(S89>10000,HLOOKUP(S89,$O85:R88,4,FALSE),IF(OR(AND(22500<S85,S85<25001),AND(50000<S85,S85<53501),AND(70000<S85,S85<72501)),$F85,IF(OR(AND(25001<S85,S85<27501),AND(53500<S85,S85<57001),AND(72500<S85,S85<75001)),$G85,IF(OR(AND(27500<S85,S85<30001),AND(57000<S85,S85<60001),AND(75000<S85,S85<77500)),$H85,VLOOKUP(S85,BDins,6,FALSE))))) -> 41.3 | T87: =IF(T89>10000,HLOOKUP(T89,$O85:S88,4,FALSE),IF(OR(AND(22500<T85,T85<25001),AND(50000<T85,T85<53501),AND(70000<T85,T85<72501)),$F85,IF(OR(AND(25001<T85,T85<27501),AND(53500<T85,T85<57001),AND(72500<T85,T85<75001)),$G85,IF(OR(AND(27500<T85,T85<30001),AND(57000<T85,T85<60001),AND(75000<T85,T85<77500)),$H85,VLOOKUP(T85,BDins,6,FALSE))))) -> 3.5 | U87: =IF(U89>10000,HLOOKUP(U89,$O85:T88,4,FALSE),IF(OR(AND(22500<U85,U85<25001),AND(50000<U85,U85<53501),AND(70000<U85,U85<72501)),$F85,IF(OR(AND(25001<U85,U85<27501),AND(53500<U85,U85<57001),AND(72500<U85,U85<75001)),$G85,IF(OR(AND(27500<U85,U85<30001),AND(57000<U85,U85<60001),AND(75000<U85,U85<77500)),$H85,VLOOKUP(U85,BDins,6,FALSE))))) -> 13.2 | V87: =IF(V89>10000,HLOOKUP(V89,$O85:U88,4,FALSE),IF(OR(AND(22500<V85,V85<25001),AND(50000<V85,V85<53501),AND(70000<V85,V85<72501)),$F85,IF(OR(AND(25001<V85,V85<27501),AND(53500<V85,V85<57001),AND(72500<V85,V85<75001)),$G85,IF(OR(AND(27500<V85,V85<30001),AND(57000<V85,V85<60001),AND(75000<V85,V85<77500)),$H85,VLOOKUP(V85,BDins,6,FALSE))))) -> 25
O88: =IF($K85>0,ROUND(O86*$E85/100,DpCU),IF(O89>10000,ROUND(HLOOKUP(O89,$O85:$V88,4,FALSE)/100*O86,DpCU),IF(OR(O85<20001,O85>95000,AND(60000<O85,O85<70001)),ROUND(ROUND(O86*JL/$C85,DcCU)*O87,DpCU),IF(OR(AND(20000<O85,O85<22501),AND(30000<O85,O85<50001),77500<O85),ROUND(O87*O86,DpCU),IF(OR(AND(22500<O85,O85<25001),AND(50000<O85,O85<53501),AND(70000<O85,O85<72501)),ROUND($F85/100*O86,DpCU),IF(OR(AND(25000<O85,O85<27501),AND(53500<O85,O85<57001),AND(72500<O85,O85<75001)),ROUND($G85/100*O86,DpCU),ROUND($H85/100*O86,DpCU))))))) -> 7.08 | P88: =IF($K85>0,ROUND(P86*$E85/100,DpCU),IF(P89>10000,ROUND(HLOOKUP(P89,$O85:$V88,4,FALSE)/100*P86,DpCU),IF(OR(P85<20001,P85>95000,AND(60000<P85,P85<70001)),ROUND(ROUND(P86*JL/$C85,DcCU)*P87,DpCU),IF(OR(AND(20000<P85,P85<22501),AND(30000<P85,P85<50001),77500<P85),ROUND(P87*P86,DpCU),IF(OR(AND(22500<P85,P85<25001),AND(50000<P85,P85<53501),AND(70000<P85,P85<72501)),ROUND($F85/100*P86,DpCU),IF(OR(AND(25000<P85,P85<27501),AND(53500<P85,P85<57001),AND(72500<P85,P85<75001)),ROUND($G85/100*P86,DpCU),ROUND($H85/100*P86,DpCU))))))) -> 1.69 | Q88: =IF($K85>0,ROUND(Q86*$E85/100,DpCU),IF(Q89>10000,ROUND(HLOOKUP(Q89,$O85:$V88,4,FALSE)/100*Q86,DpCU),IF(OR(Q85<20001,Q85>95000,AND(60000<Q85,Q85<70001)),ROUND(ROUND(Q86*JL/$C85,DcCU)*Q87,DpCU),IF(OR(AND(20000<Q85,Q85<22501),AND(30000<Q85,Q85<50001),77500<Q85),ROUND(Q87*Q86,DpCU),IF(OR(AND(22500<Q85,Q85<25001),AND(50000<Q85,Q85<53501),AND(70000<Q85,Q85<72501)),ROUND($F85/100*Q86,DpCU),IF(OR(AND(25000<Q85,Q85<27501),AND(53500<Q85,Q85<57001),AND(72500<Q85,Q85<75001)),ROUND($G85/100*Q86,DpCU),ROUND($H85/100*Q86,DpCU))))))) -> 1.41 | R88: =IF($K85>0,ROUND(R86*$E85/100,DpCU),IF(R89>10000,ROUND(HLOOKUP(R89,$O85:$V88,4,FALSE)/100*R86,DpCU),IF(OR(R85<20001,R85>95000,AND(60000<R85,R85<70001)),ROUND(ROUND(R86*JL/$C85,DcCU)*R87,DpCU),IF(OR(AND(20000<R85,R85<22501),AND(30000<R85,R85<50001),77500<R85),ROUND(R87*R86,DpCU),IF(OR(AND(22500<R85,R85<25001),AND(50000<R85,R85<53501),AND(70000<R85,R85<72501)),ROUND($F85/100*R86,DpCU),IF(OR(AND(25000<R85,R85<27501),AND(53500<R85,R85<57001),AND(72500<R85,R85<75001)),ROUND($G85/100*R86,DpCU),ROUND($H85/100*R86,DpCU))))))) -> 10.69 | S88: =IF($K85>0,ROUND(S86*$E85/100,DpCU),IF(S89>10000,ROUND(HLOOKUP(S89,$O85:$V88,4,FALSE)/100*S86,DpCU),IF(OR(S85<20001,S85>95000,AND(60000<S85,S85<70001)),ROUND(ROUND(S86*JL/$C85,DcCU)*S87,DpCU),IF(OR(AND(20000<S85,S85<22501),AND(30000<S85,S85<50001),77500<S85),ROUND(S87*S86,DpCU),IF(OR(AND(22500<S85,S85<25001),AND(50000<S85,S85<53501),AND(70000<S85,S85<72501)),ROUND($F85/100*S86,DpCU),IF(OR(AND(25000<S85,S85<27501),AND(53500<S85,S85<57001),AND(72500<S85,S85<75001)),ROUND($G85/100*S86,DpCU),ROUND($H85/100*S86,DpCU))))))) -> 3.68 | T88: =IF($K85>0,ROUND(T86*$E85/100,DpCU),IF(T89>10000,ROUND(HLOOKUP(T89,$O85:$V88,4,FALSE)/100*T86,DpCU),IF(OR(T85<20001,T85>95000,AND(60000<T85,T85<70001)),ROUND(ROUND(T86*JL/$C85,DcCU)*T87,DpCU),IF(OR(AND(20000<T85,T85<22501),AND(30000<T85,T85<50001),77500<T85),ROUND(T87*T86,DpCU),IF(OR(AND(22500<T85,T85<25001),AND(50000<T85,T85<53501),AND(70000<T85,T85<72501)),ROUND($F85/100*T86,DpCU),IF(OR(AND(25000<T85,T85<27501),AND(53500<T85,T85<57001),AND(72500<T85,T85<75001)),ROUND($G85/100*T86,DpCU),ROUND($H85/100*T86,DpCU))))))) -> 0.04 | U88: =IF($K85>0,ROUND(U86*$E85/100,DpCU),IF(U89>10000,ROUND(HLOOKUP(U89,$O85:$V88,4,FALSE)/100*U86,DpCU),IF(OR(U85<20001,U85>95000,AND(60000<U85,U85<70001)),ROUND(ROUND(U86*JL/$C85,DcCU)*U87,DpCU),IF(OR(AND(20000<U85,U85<22501),AND(30000<U85,U85<50001),77500<U85),ROUND(U87*U86,DpCU),IF(OR(AND(22500<U85,U85<25001),AND(50000<U85,U85<53501),AND(70000<U85,U85<72501)),ROUND($F85/100*U86,DpCU),IF(OR(AND(25000<U85,U85<27501),AND(53500<U85,U85<57001),AND(72500<U85,U85<75001)),ROUND($G85/100*U86,DpCU),ROUND($H85/100*U86,DpCU))))))) -> 0.79 | V88: =IF($K85>0,ROUND(V86*$E85/100,DpCU),IF(V89>10000,ROUND(HLOOKUP(V89,$O85:$V88,4,FALSE)/100*V86,DpCU),IF(OR(V85<20001,V85>95000,AND(60000<V85,V85<70001)),ROUND(ROUND(V86*JL/$C85,DcCU)*V87,DpCU),IF(OR(AND(20000<V85,V85<22501),AND(30000<V85,V85<50001),77500<V85),ROUND(V87*V86,DpCU),IF(OR(AND(22500<V85,V85<25001),AND(50000<V85,V85<53501),AND(70000<V85,V85<72501)),ROUND($F85/100*V86,DpCU),IF(OR(AND(25000<V85,V85<27501),AND(53500<V85,V85<57001),AND(72500<V85,V85<75001)),ROUND($G85/100*V86,DpCU),ROUND($H85/100*V86,DpCU))))))) -> 2
B89: =A85&"r" -> 10017r
A90: 10018 | B90: CIMIENTOS CORRIDOS MEZCLA 1:10 CEMENTO-HORMIGON 30% PIEDRA | C90: =ROUND(J90*JL*Frto/8,4) -> 20 | D90: m3 | E90: =SUM($O93:$X93) -> 228.14 | F90: =SUMIF($O90:$X90,"<22501",$O93:$X93) -> 67.21 | G90: =SUMIFS($O93:$X93,$O90:$X90,">30000",$O90:$X90,"<50001") -> 148.91 | H90: =SUMIFS($O93:$X93,$O90:$X90,">60000",$O90:$X90,"<70001") -> 10 | I90: 10 | J90: 20 | O90: 10001 | P90: 10003 | Q90: 10004 | R90: 10005 | S90: 30001 | T90: 30002 | U90: 30022 | V90: 30026 | W90: 60012 | X90: 70001
B91: =A90&"C" -> 10018C | O91: 8 | P91: 1 | Q91: 2 | R91: 1 | S91: 3.05 | T91: 0.87 | U91: 0.18 | V91: 0.5 | W91: 1 | X91: 3
O92: =IF(O94>10000,HLOOKUP(O94,N90:$O93,4,FALSE),IF(OR(AND(22500<O90,O90<25001),AND(50000<O90,O90<53501),AND(70000<O90,O90<72501)),$F90,IF(OR(AND(25001<O90,O90<27501),AND(53500<O90,O90<57001),AND(72500<O90,O90<75001)),$G90,IF(OR(AND(27500<O90,O90<30001),AND(57000<O90,O90<60001),AND(75000<O90,O90<77500)),$H90,VLOOKUP(O90,BDins,6,FALSE))))) -> 12.64 | P92: =IF(P94>10000,HLOOKUP(P94,O90:$O93,4,FALSE),IF(OR(AND(22500<P90,P90<25001),AND(50000<P90,P90<53501),AND(70000<P90,P90<72501)),$F90,IF(OR(AND(25001<P90,P90<27501),AND(53500<P90,P90<57001),AND(72500<P90,P90<75001)),$G90,IF(OR(AND(27500<P90,P90<30001),AND(57000<P90,P90<60001),AND(75000<P90,P90<77500)),$H90,VLOOKUP(P90,BDins,6,FALSE))))) -> 14.12 | Q92: =IF(Q94>10000,HLOOKUP(Q94,$O90:P93,4,FALSE),IF(OR(AND(22500<Q90,Q90<25001),AND(50000<Q90,Q90<53501),AND(70000<Q90,Q90<72501)),$F90,IF(OR(AND(25001<Q90,Q90<27501),AND(53500<Q90,Q90<57001),AND(72500<Q90,Q90<75001)),$G90,IF(OR(AND(27500<Q90,Q90<30001),AND(57000<Q90,Q90<60001),AND(75000<Q90,Q90<77500)),$H90,VLOOKUP(Q90,BDins,6,FALSE))))) -> 17.59 | R92: =IF(R94>10000,HLOOKUP(R94,$O90:Q93,4,FALSE),IF(OR(AND(22500<R90,R90<25001),AND(50000<R90,R90<53501),AND(70000<R90,R90<72501)),$F90,IF(OR(AND(25001<R90,R90<27501),AND(53500<R90,R90<57001),AND(72500<R90,R90<75001)),$G90,IF(OR(AND(27500<R90,R90<30001),AND(57000<R90,R90<60001),AND(75000<R90,R90<77500)),$H90,VLOOKUP(R90,BDins,6,FALSE))))) -> 17.59 | S92: =IF(S94>10000,HLOOKUP(S94,$O90:R93,4,FALSE),IF(OR(AND(22500<S90,S90<25001),AND(50000<S90,S90<53501),AND(70000<S90,S90<72501)),$F90,IF(OR(AND(25001<S90,S90<27501),AND(53500<S90,S90<57001),AND(72500<S90,S90<75001)),$G90,IF(OR(AND(27500<S90,S90<30001),AND(57000<S90,S90<60001),AND(75000<S90,S90<77500)),$H90,VLOOKUP(S90,BDins,6,FALSE))))) -> 27 | T92: =IF(T94>10000,HLOOKUP(T94,$O90:S93,4,FALSE),IF(OR(AND(22500<T90,T90<25001),AND(50000<T90,T90<53501),AND(70000<T90,T90<72501)),$F90,IF(OR(AND(25001<T90,T90<27501),AND(53500<T90,T90<57001),AND(72500<T90,T90<75001)),$G90,IF(OR(AND(27500<T90,T90<30001),AND(57000<T90,T90<60001),AND(75000<T90,T90<77500)),$H90,VLOOKUP(T90,BDins,6,FALSE))))) -> 41.3 | U92: =IF(U94>10000,HLOOKUP(U94,$O90:T93,4,FALSE),IF(OR(AND(22500<U90,U90<25001),AND(50000<U90,U90<53501),AND(70000<U90,U90<72501)),$F90,IF(OR(AND(25001<U90,U90<27501),AND(53500<U90,U90<57001),AND(72500<U90,U90<75001)),$G90,IF(OR(AND(27500<U90,U90<30001),AND(57000<U90,U90<60001),AND(75000<U90,U90<77500)),$H90,VLOOKUP(U90,BDins,6,FALSE))))) -> 3.5 | V92: =IF(V94>10000,HLOOKUP(V94,$O90:U93,4,FALSE),IF(OR(AND(22500<V90,V90<25001),AND(50000<V90,V90<53501),AND(70000<V90,V90<72501)),$F90,IF(OR(AND(25001<V90,V90<27501),AND(53500<V90,V90<57001),AND(72500<V90,V90<75001)),$G90,IF(OR(AND(27500<V90,V90<30001),AND(57000<V90,V90<60001),AND(75000<V90,V90<77500)),$H90,VLOOKUP(V90,BDins,6,FALSE))))) -> 60 | W92: =IF(W94>10000,HLOOKUP(W94,$O90:V93,4,FALSE),IF(OR(AND(22500<W90,W90<25001),AND(50000<W90,W90<53501),AND(70000<W90,W90<72501)),$F90,IF(OR(AND(25001<W90,W90<27501),AND(53500<W90,W90<57001),AND(72500<W90,W90<75001)),$G90,IF(OR(AND(27500<W90,W90<30001),AND(57000<W90,W90<60001),AND(75000<W90,W90<77500)),$H90,VLOOKUP(W90,BDins,6,FALSE))))) -> 25 | X92: =IF(X94>10000,HLOOKUP(X94,$O90:W93,4,FALSE),IF(OR(AND(22500<X90,X90<25001),AND(50000<X90,X90<53501),AND(70000<X90,X90<72501)),$F90,IF(OR(AND(25001<X90,X90<27501),AND(53500<X90,X90<57001),AND(72500<X90,X90<75001)),$G90,IF(OR(AND(27500<X90,X90<30001),AND(57000<X90,X90<60001),AND(75000<X90,X90<77500)),$H90,VLOOKUP(X90,BDins,6,FALSE))))) -> 67.21
O93: =IF($K90>0,ROUND(O91*$E90/100,DpCU),IF(O94>10000,ROUND(HLOOKUP(O94,$O90:$X93,4,FALSE)/100*O91,DpCU),IF(OR(O90<20001,O90>95000,AND(60000<O90,O90<70001)),ROUND(ROUND(O91*JL/$C90,DcCU)*O92,DpCU),IF(OR(AND(20000<O90,O90<22501),AND(30000<O90,O90<50001),77500<O90),ROUND(O92*O91,DpCU),IF(OR(AND(22500<O90,O90<25001),AND(50000<O90,O90<53501),AND(70000<O90,O90<72501)),ROUND($F90/100*O91,DpCU),IF(OR(AND(25000<O90,O90<27501),AND(53500<O90,O90<57001),AND(72500<O90,O90<75001)),ROUND($G90/100*O91,DpCU),ROUND($H90/100*O91,DpCU))))))) -> 40.45 | P93: =IF($K90>0,ROUND(P91*$E90/100,DpCU),IF(P94>10000,ROUND(HLOOKUP(P94,$O90:$X93,4,FALSE)/100*P91,DpCU),IF(OR(P90<20001,P90>95000,AND(60000<P90,P90<70001)),ROUND(ROUND(P91*JL/$C90,DcCU)*P92,DpCU),IF(OR(AND(20000<P90,P90<22501),AND(30000<P90,P90<50001),77500<P90),ROUND(P92*P91,DpCU),IF(OR(AND(22500<P90,P90<25001),AND(50000<P90,P90<53501),AND(70000<P90,P90<72501)),ROUND($F90/100*P91,DpCU),IF(OR(AND(25000<P90,P90<27501),AND(53500<P90,P90<57001),AND(72500<P90,P90<75001)),ROUND($G90/100*P91,DpCU),ROUND($H90/100*P91,DpCU))))))) -> 5.65 | Q93: =IF($K90>0,ROUND(Q91*$E90/100,DpCU),IF(Q94>10000,ROUND(HLOOKUP(Q94,$O90:$X93,4,FALSE)/100*Q91,DpCU),IF(OR(Q90<20001,Q90>95000,AND(60000<Q90,Q90<70001)),ROUND(ROUND(Q91*JL/$C90,DcCU)*Q92,DpCU),IF(OR(AND(20000<Q90,Q90<22501),AND(30000<Q90,Q90<50001),77500<Q90),ROUND(Q92*Q91,DpCU),IF(OR(AND(22500<Q90,Q90<25001),AND(50000<Q90,Q90<53501),AND(70000<Q90,Q90<72501)),ROUND($F90/100*Q91,DpCU),IF(OR(AND(25000<Q90,Q90<27501),AND(53500<Q90,Q90<57001),AND(72500<Q90,Q90<75001)),ROUND($G90/100*Q91,DpCU),ROUND($H90/100*Q91,DpCU))))))) -> 14.07 | R93: =IF($K90>0,ROUND(R91*$E90/100,DpCU),IF(R94>10000,ROUND(HLOOKUP(R94,$O90:$X93,4,FALSE)/100*R91,DpCU),IF(OR(R90<20001,R90>95000,AND(60000<R90,R90<70001)),ROUND(ROUND(R91*JL/$C90,DcCU)*R92,DpCU),IF(OR(AND(20000<R90,R90<22501),AND(30000<R90,R90<50001),77500<R90),ROUND(R92*R91,DpCU),IF(OR(AND(22500<R90,R90<25001),AND(50000<R90,R90<53501),AND(70000<R90,R90<72501)),ROUND($F90/100*R91,DpCU),IF(OR(AND(25000<R90,R90<27501),AND(53500<R90,R90<57001),AND(72500<R90,R90<75001)),ROUND($G90/100*R91,DpCU),ROUND($H90/100*R91,DpCU))))))) -> 7.04 | S93: =IF($K90>0,ROUND(S91*$E90/100,DpCU),IF(S94>10000,ROUND(HLOOKUP(S94,$O90:$X93,4,FALSE)/100*S91,DpCU),IF(OR(S90<20001,S90>95000,AND(60000<S90,S90<70001)),ROUND(ROUND(S91*JL/$C90,DcCU)*S92,DpCU),IF(OR(AND(20000<S90,S90<22501),AND(30000<S90,S90<50001),77500<S90),ROUND(S92*S91,DpCU),IF(OR(AND(22500<S90,S90<25001),AND(50000<S90,S90<53501),AND(70000<S90,S90<72501)),ROUND($F90/100*S91,DpCU),IF(OR(AND(25000<S90,S90<27501),AND(53500<S90,S90<57001),AND(72500<S90,S90<75001)),ROUND($G90/100*S91,DpCU),ROUND($H90/100*S91,DpCU))))))) -> 82.35 | T93: =IF($K90>0,ROUND(T91*$E90/100,DpCU),IF(T94>10000,ROUND(HLOOKUP(T94,$O90:$X93,4,FALSE)/100*T91,DpCU),IF(OR(T90<20001,T90>95000,AND(60000<T90,T90<70001)),ROUND(ROUND(T91*JL/$C90,DcCU)*T92,DpCU),IF(OR(AND(20000<T90,T90<22501),AND(30000<T90,T90<50001),77500<T90),ROUND(T92*T91,DpCU),IF(OR(AND(22500<T90,T90<25001),AND(50000<T90,T90<53501),AND(70000<T90,T90<72501)),ROUND($F90/100*T91,DpCU),IF(OR(AND(25000<T90,T90<27501),AND(53500<T90,T90<57001),AND(72500<T90,T90<75001)),ROUND($G90/100*T91,DpCU),ROUND($H90/100*T91,DpCU))))))) -> 35.93 | U93: =IF($K90>0,ROUND(U91*$E90/100,DpCU),IF(U94>10000,ROUND(HLOOKUP(U94,$O90:$X93,4,FALSE)/100*U91,DpCU),IF(OR(U90<20001,U90>95000,AND(60000<U90,U90<70001)),ROUND(ROUND(U91*JL/$C90,DcCU)*U92,DpCU),IF(OR(AND(20000<U90,U90<22501),AND(30000<U90,U90<50001),77500<U90),ROUND(U92*U91,DpCU),IF(OR(AND(22500<U90,U90<25001),AND(50000<U90,U90<53501),AND(70000<U90,U90<72501)),ROUND($F90/100*U91,DpCU),IF(OR(AND(25000<U90,U90<27501),AND(53500<U90,U90<57001),AND(72500<U90,U90<75001)),ROUND($G90/100*U91,DpCU),ROUND($H90/100*U91,DpCU))))))) -> 0.63 | V93: =IF($K90>0,ROUND(V91*$E90/100,DpCU),IF(V94>10000,ROUND(HLOOKUP(V94,$O90:$X93,4,FALSE)/100*V91,DpCU),IF(OR(V90<20001,V90>95000,AND(60000<V90,V90<70001)),ROUND(ROUND(V91*JL/$C90,DcCU)*V92,DpCU),IF(OR(AND(20000<V90,V90<22501),AND(30000<V90,V90<50001),77500<V90),ROUND(V92*V91,DpCU),IF(OR(AND(22500<V90,V90<25001),AND(50000<V90,V90<53501),AND(70000<V90,V90<72501)),ROUND($F90/100*V91,DpCU),IF(OR(AND(25000<V90,V90<27501),AND(53500<V90,V90<57001),AND(72500<V90,V90<75001)),ROUND($G90/100*V91,DpCU),ROUND($H90/100*V91,DpCU))))))) -> 30 | ... X93: =IF($K90>0,ROUND(X91*$E90/100,DpCU),IF(X94>10000,ROUND(HLOOKUP(X94,$O90:$X93,4,FALSE)/100*X91,DpCU),IF(OR(X90<20001,X90>95000,AND(60000<X90,X90<70001)),ROUND(ROUND(X91*JL/$C90,DcCU)*X92,DpCU),IF(OR(AND(20000<X90,X90<22501),AND(30000<X90,X90<50001),77500<X90),ROUND(X92*X91,DpCU),IF(OR(AND(22500<X90,X90<25001),AND(50000<X90,X90<53501),AND(70000<X90,X90<72501)),ROUND($F90/100*X91,DpCU),IF(OR(AND(25000<X90,X90<27501),AND(53500<X90,X90<57001),AND(72500<X90,X90<75001)),ROUND($G90/100*X91,DpCU),ROUND($H90/100*X91,DpCU))))))) -> 2.02
B94: =A90&"r" -> 10018r
A95: 10019 | B95: CONCRETO 1:8+25% PM PARA SOBRECIMIENTOS | C95: =ROUND(J95*JL*Frto/8,4) -> 18 | D95: m3 | E95: =SUM($O98:$X98) -> 267.81 | F95: =SUMIF($O95:$X95,"<22501",$O98:$X98) -> 86.24 | G95: =SUMIFS($O98:$X98,$O95:$X95,">30000",$O95:$X95,"<50001") -> 167.87 | H95: =SUMIFS($O98:$X98,$O95:$X95,">60000",$O95:$X95,"<70001") -> 11.11 | I95: 10 | J95: 18 | O95: 10001 | P95: 10003 | Q95: 10004 | R95: 10005 | S95: 30001 | T95: 30002 | U95: 30027 | V95: 30028 | W95: 60012 | X95: 70001
B96: =A95&"C" -> 10019C | O96: 9.5 | P96: 1.5 | Q96: 2 | R96: 1 | S96: 4 | T96: 0.9061 | U96: 0.3 | V96: 0.3176 | W96: 1 | X96: 3
O97: =IF(O99>10000,HLOOKUP(O99,N95:$O98,4,FALSE),IF(OR(AND(22500<O95,O95<25001),AND(50000<O95,O95<53501),AND(70000<O95,O95<72501)),$F95,IF(OR(AND(25001<O95,O95<27501),AND(53500<O95,O95<57001),AND(72500<O95,O95<75001)),$G95,IF(OR(AND(27500<O95,O95<30001),AND(57000<O95,O95<60001),AND(75000<O95,O95<77500)),$H95,VLOOKUP(O95,BDins,6,FALSE))))) -> 12.64 | P97: =IF(P99>10000,HLOOKUP(P99,O95:$O98,4,FALSE),IF(OR(AND(22500<P95,P95<25001),AND(50000<P95,P95<53501),AND(70000<P95,P95<72501)),$F95,IF(OR(AND(25001<P95,P95<27501),AND(53500<P95,P95<57001),AND(72500<P95,P95<75001)),$G95,IF(OR(AND(27500<P95,P95<30001),AND(57000<P95,P95<60001),AND(75000<P95,P95<77500)),$H95,VLOOKUP(P95,BDins,6,FALSE))))) -> 14.12 | Q97: =IF(Q99>10000,HLOOKUP(Q99,$O95:P98,4,FALSE),IF(OR(AND(22500<Q95,Q95<25001),AND(50000<Q95,Q95<53501),AND(70000<Q95,Q95<72501)),$F95,IF(OR(AND(25001<Q95,Q95<27501),AND(53500<Q95,Q95<57001),AND(72500<Q95,Q95<75001)),$G95,IF(OR(AND(27500<Q95,Q95<30001),AND(57000<Q95,Q95<60001),AND(75000<Q95,Q95<77500)),$H95,VLOOKUP(Q95,BDins,6,FALSE))))) -> 17.59 | R97: =IF(R99>10000,HLOOKUP(R99,$O95:Q98,4,FALSE),IF(OR(AND(22500<R95,R95<25001),AND(50000<R95,R95<53501),AND(70000<R95,R95<72501)),$F95,IF(OR(AND(25001<R95,R95<27501),AND(53500<R95,R95<57001),AND(72500<R95,R95<75001)),$G95,IF(OR(AND(27500<R95,R95<30001),AND(57000<R95,R95<60001),AND(75000<R95,R95<77500)),$H95,VLOOKUP(R95,BDins,6,FALSE))))) -> 17.59 | S97: =IF(S99>10000,HLOOKUP(S99,$O95:R98,4,FALSE),IF(OR(AND(22500<S95,S95<25001),AND(50000<S95,S95<53501),AND(70000<S95,S95<72501)),$F95,IF(OR(AND(25001<S95,S95<27501),AND(53500<S95,S95<57001),AND(72500<S95,S95<75001)),$G95,IF(OR(AND(27500<S95,S95<30001),AND(57000<S95,S95<60001),AND(75000<S95,S95<77500)),$H95,VLOOKUP(S95,BDins,6,FALSE))))) -> 27 | T97: =IF(T99>10000,HLOOKUP(T99,$O95:S98,4,FALSE),IF(OR(AND(22500<T95,T95<25001),AND(50000<T95,T95<53501),AND(70000<T95,T95<72501)),$F95,IF(OR(AND(25001<T95,T95<27501),AND(53500<T95,T95<57001),AND(72500<T95,T95<75001)),$G95,IF(OR(AND(27500<T95,T95<30001),AND(57000<T95,T95<60001),AND(75000<T95,T95<77500)),$H95,VLOOKUP(T95,BDins,6,FALSE))))) -> 41.3 | U97: =IF(U99>10000,HLOOKUP(U99,$O95:T98,4,FALSE),IF(OR(AND(22500<U95,U95<25001),AND(50000<U95,U95<53501),AND(70000<U95,U95<72501)),$F95,IF(OR(AND(25001<U95,U95<27501),AND(53500<U95,U95<57001),AND(72500<U95,U95<75001)),$G95,IF(OR(AND(27500<U95,U95<30001),AND(57000<U95,U95<60001),AND(75000<U95,U95<77500)),$H95,VLOOKUP(U95,BDins,6,FALSE))))) -> 11.3 | V97: =IF(V99>10000,HLOOKUP(V99,$O95:U98,4,FALSE),IF(OR(AND(22500<V95,V95<25001),AND(50000<V95,V95<53501),AND(70000<V95,V95<72501)),$F95,IF(OR(AND(25001<V95,V95<27501),AND(53500<V95,V95<57001),AND(72500<V95,V95<75001)),$G95,IF(OR(AND(27500<V95,V95<30001),AND(57000<V95,V95<60001),AND(75000<V95,V95<77500)),$H95,VLOOKUP(V95,BDins,6,FALSE))))) -> 60 | W97: =IF(W99>10000,HLOOKUP(W99,$O95:V98,4,FALSE),IF(OR(AND(22500<W95,W95<25001),AND(50000<W95,W95<53501),AND(70000<W95,W95<72501)),$F95,IF(OR(AND(25001<W95,W95<27501),AND(53500<W95,W95<57001),AND(72500<W95,W95<75001)),$G95,IF(OR(AND(27500<W95,W95<30001),AND(57000<W95,W95<60001),AND(75000<W95,W95<77500)),$H95,VLOOKUP(W95,BDins,6,FALSE))))) -> 25 | X97: =IF(X99>10000,HLOOKUP(X99,$O95:W98,4,FALSE),IF(OR(AND(22500<X95,X95<25001),AND(50000<X95,X95<53501),AND(70000<X95,X95<72501)),$F95,IF(OR(AND(25001<X95,X95<27501),AND(53500<X95,X95<57001),AND(72500<X95,X95<75001)),$G95,IF(OR(AND(27500<X95,X95<30001),AND(57000<X95,X95<60001),AND(75000<X95,X95<77500)),$H95,VLOOKUP(X95,BDins,6,FALSE))))) -> 86.24
O98: =IF($K95>0,ROUND(O96*$E95/100,DpCU),IF(O99>10000,ROUND(HLOOKUP(O99,$O95:$X98,4,FALSE)/100*O96,DpCU),IF(OR(O95<20001,O95>95000,AND(60000<O95,O95<70001)),ROUND(ROUND(O96*JL/$C95,DcCU)*O97,DpCU),IF(OR(AND(20000<O95,O95<22501),AND(30000<O95,O95<50001),77500<O95),ROUND(O97*O96,DpCU),IF(OR(AND(22500<O95,O95<25001),AND(50000<O95,O95<53501),AND(70000<O95,O95<72501)),ROUND($F95/100*O96,DpCU),IF(OR(AND(25000<O95,O95<27501),AND(53500<O95,O95<57001),AND(72500<O95,O95<75001)),ROUND($G95/100*O96,DpCU),ROUND($H95/100*O96,DpCU))))))) -> 53.37 | P98: =IF($K95>0,ROUND(P96*$E95/100,DpCU),IF(P99>10000,ROUND(HLOOKUP(P99,$O95:$X98,4,FALSE)/100*P96,DpCU),IF(OR(P95<20001,P95>95000,AND(60000<P95,P95<70001)),ROUND(ROUND(P96*JL/$C95,DcCU)*P97,DpCU),IF(OR(AND(20000<P95,P95<22501),AND(30000<P95,P95<50001),77500<P95),ROUND(P97*P96,DpCU),IF(OR(AND(22500<P95,P95<25001),AND(50000<P95,P95<53501),AND(70000<P95,P95<72501)),ROUND($F95/100*P96,DpCU),IF(OR(AND(25000<P95,P95<27501),AND(53500<P95,P95<57001),AND(72500<P95,P95<75001)),ROUND($G95/100*P96,DpCU),ROUND($H95/100*P96,DpCU))))))) -> 9.41 | Q98: =IF($K95>0,ROUND(Q96*$E95/100,DpCU),IF(Q99>10000,ROUND(HLOOKUP(Q99,$O95:$X98,4,FALSE)/100*Q96,DpCU),IF(OR(Q95<20001,Q95>95000,AND(60000<Q95,Q95<70001)),ROUND(ROUND(Q96*JL/$C95,DcCU)*Q97,DpCU),IF(OR(AND(20000<Q95,Q95<22501),AND(30000<Q95,Q95<50001),77500<Q95),ROUND(Q97*Q96,DpCU),IF(OR(AND(22500<Q95,Q95<25001),AND(50000<Q95,Q95<53501),AND(70000<Q95,Q95<72501)),ROUND($F95/100*Q96,DpCU),IF(OR(AND(25000<Q95,Q95<27501),AND(53500<Q95,Q95<57001),AND(72500<Q95,Q95<75001)),ROUND($G95/100*Q96,DpCU),ROUND($H95/100*Q96,DpCU))))))) -> 15.64 | R98: =IF($K95>0,ROUND(R96*$E95/100,DpCU),IF(R99>10000,ROUND(HLOOKUP(R99,$O95:$X98,4,FALSE)/100*R96,DpCU),IF(OR(R95<20001,R95>95000,AND(60000<R95,R95<70001)),ROUND(ROUND(R96*JL/$C95,DcCU)*R97,DpCU),IF(OR(AND(20000<R95,R95<22501),AND(30000<R95,R95<50001),77500<R95),ROUND(R97*R96,DpCU),IF(OR(AND(22500<R95,R95<25001),AND(50000<R95,R95<53501),AND(70000<R95,R95<72501)),ROUND($F95/100*R96,DpCU),IF(OR(AND(25000<R95,R95<27501),AND(53500<R95,R95<57001),AND(72500<R95,R95<75001)),ROUND($G95/100*R96,DpCU),ROUND($H95/100*R96,DpCU))))))) -> 7.82 | S98: =IF($K95>0,ROUND(S96*$E95/100,DpCU),IF(S99>10000,ROUND(HLOOKUP(S99,$O95:$X98,4,FALSE)/100*S96,DpCU),IF(OR(S95<20001,S95>95000,AND(60000<S95,S95<70001)),ROUND(ROUND(S96*JL/$C95,DcCU)*S97,DpCU),IF(OR(AND(20000<S95,S95<22501),AND(30000<S95,S95<50001),77500<S95),ROUND(S97*S96,DpCU),IF(OR(AND(22500<S95,S95<25001),AND(50000<S95,S95<53501),AND(70000<S95,S95<72501)),ROUND($F95/100*S96,DpCU),IF(OR(AND(25000<S95,S95<27501),AND(53500<S95,S95<57001),AND(72500<S95,S95<75001)),ROUND($G95/100*S96,DpCU),ROUND($H95/100*S96,DpCU))))))) -> 108 | T98: =IF($K95>0,ROUND(T96*$E95/100,DpCU),IF(T99>10000,ROUND(HLOOKUP(T99,$O95:$X98,4,FALSE)/100*T96,DpCU),IF(OR(T95<20001,T95>95000,AND(60000<T95,T95<70001)),ROUND(ROUND(T96*JL/$C95,DcCU)*T97,DpCU),IF(OR(AND(20000<T95,T95<22501),AND(30000<T95,T95<50001),77500<T95),ROUND(T97*T96,DpCU),IF(OR(AND(22500<T95,T95<25001),AND(50000<T95,T95<53501),AND(70000<T95,T95<72501)),ROUND($F95/100*T96,DpCU),IF(OR(AND(25000<T95,T95<27501),AND(53500<T95,T95<57001),AND(72500<T95,T95<75001)),ROUND($G95/100*T96,DpCU),ROUND($H95/100*T96,DpCU))))))) -> 37.42 | U98: =IF($K95>0,ROUND(U96*$E95/100,DpCU),IF(U99>10000,ROUND(HLOOKUP(U99,$O95:$X98,4,FALSE)/100*U96,DpCU),IF(OR(U95<20001,U95>95000,AND(60000<U95,U95<70001)),ROUND(ROUND(U96*JL/$C95,DcCU)*U97,DpCU),IF(OR(AND(20000<U95,U95<22501),AND(30000<U95,U95<50001),77500<U95),ROUND(U97*U96,DpCU),IF(OR(AND(22500<U95,U95<25001),AND(50000<U95,U95<53501),AND(70000<U95,U95<72501)),ROUND($F95/100*U96,DpCU),IF(OR(AND(25000<U95,U95<27501),AND(53500<U95,U95<57001),AND(72500<U95,U95<75001)),ROUND($G95/100*U96,DpCU),ROUND($H95/100*U96,DpCU))))))) -> 3.39 | V98: =IF($K95>0,ROUND(V96*$E95/100,DpCU),IF(V99>10000,ROUND(HLOOKUP(V99,$O95:$X98,4,FALSE)/100*V96,DpCU),IF(OR(V95<20001,V95>95000,AND(60000<V95,V95<70001)),ROUND(ROUND(V96*JL/$C95,DcCU)*V97,DpCU),IF(OR(AND(20000<V95,V95<22501),AND(30000<V95,V95<50001),77500<V95),ROUND(V97*V96,DpCU),IF(OR(AND(22500<V95,V95<25001),AND(50000<V95,V95<53501),AND(70000<V95,V95<72501)),ROUND($F95/100*V96,DpCU),IF(OR(AND(25000<V95,V95<27501),AND(53500<V95,V95<57001),AND(72500<V95,V95<75001)),ROUND($G95/100*V96,DpCU),ROUND($H95/100*V96,DpCU))))))) -> 19.06 | ... X98: =IF($K95>0,ROUND(X96*$E95/100,DpCU),IF(X99>10000,ROUND(HLOOKUP(X99,$O95:$X98,4,FALSE)/100*X96,DpCU),IF(OR(X95<20001,X95>95000,AND(60000<X95,X95<70001)),ROUND(ROUND(X96*JL/$C95,DcCU)*X97,DpCU),IF(OR(AND(20000<X95,X95<22501),AND(30000<X95,X95<50001),77500<X95),ROUND(X97*X96,DpCU),IF(OR(AND(22500<X95,X95<25001),AND(50000<X95,X95<53501),AND(70000<X95,X95<72501)),ROUND($F95/100*X96,DpCU),IF(OR(AND(25000<X95,X95<27501),AND(53500<X95,X95<57001),AND(72500<X95,X95<75001)),ROUND($G95/100*X96,DpCU),ROUND($H95/100*X96,DpCU))))))) -> 2.59
B99: =A95&"r" -> 10019r
A100: 10020 | B100: ENCOFRADO Y DESENCOFRADO NORMAL PARA SOBRECIMIENTO HASTA 0.30 m | C100: =ROUND(J100*JL*Frto/8,4) -> 14.4 | D100: m2 | E100: =SUM($O103:$W103) -> 44.23 | F100: =SUMIF($O100:$W100,"<22501",$O103:$W103) -> 21.13 | G100: =SUMIFS($O103:$W103,$O100:$W100,">30000",$O100:$W100,"<50001") -> 22.47 | H100: =SUMIFS($O103:$W103,$O100:$W100,">60000",$O100:$W100,"<70001") -> 0 | I100: 9 | J100: 14.4 | O100: 10001 | P100: 10003 | Q100: 10004 | R100: 30010 | S100: 30027 | T100: 30029 | U100: 30030 | V100: 30031 | W100: 70001
...

Sheet Pto
B1: =Datos!C7 -> RW7o
B2: PRESUPUESTO GENERAL DEL PROYECTO
B3: Proyecto: | C3: =Datos!C2
B4: Lugar : | C4: =Datos!C3
B5: Cliente: | C5: =Datos!C4
B6: Fecha: | C6: =Datos!C5
C10: P A R T I D A S | D10: UND | E10: METRADO | F10: P.U. | G10: PARCIAL | I10: CODIGO | J10: ITEM | K10: TITULOS
B11: =J11 & " " & K11 -> 01 ESTRUCTURAS | G11: =SUMIF(Pto!$I12:$I63,">10000",G12:G63) -> 192093.68 | I11: T | J11: 01 | K11: ESTRUCTURAS
B12: =J12 & " " & K12 -> 01.01 OBRAS PRELIMINARES | G12: =SUM(G13:G16) -> 24807.47 | I12: ST1 | J12: 01.01 | K12: OBRAS PRELIMINARES
B13: =J13 & " " & VLOOKUP(I13,BDcuA,2,FALSE) -> 01.01.01 TRAZO Y REPLANTEO INICIAL | D13: =VLOOKUP(I13,BDcuA,4,FALSE) -> m2 | E13: 200 | F13: =VLOOKUP(I13,BDcuA,5,FALSE) -> 3.02 | G13: =ROUND(F13*E13,DpP) -> 604 | I13: 10001 | J13: 01.01.01
B14: =J14 & " " & VLOOKUP(I14,BDcuA,2,FALSE) -> 01.01.02 TRAZO DURANTE LA EJECUCION DE LA OBRA (casco) | D14: =VLOOKUP(I14,BDcuA,4,FALSE) -> mes | E14: 4 | F14: =VLOOKUP(I14,BDcuA,5,FALSE) -> 5296.05 | G14: =ROUND(F14*E14,DpP) -> 21184.2 | I14: 10002 | J14: 01.01.02
B15: =J15 & " " & VLOOKUP(I15,BDcuA,2,FALSE) -> 01.01.03 CARTEL DE OBRA | D15: =VLOOKUP(I15,BDcuA,4,FALSE) -> und | E15: 1 | F15: =VLOOKUP(I15,BDcuA,5,FALSE) -> 500 | G15: =ROUND(F15*E15,DpP) -> 500 | I15: 10003 | J15: 01.01.03
B16: =J16 & " " & VLOOKUP(I16,BDcuA,2,FALSE) -> 01.01.04 INSTALACIONES DE OFICINA Y ALMACEN PROVISIONALES | D16: =VLOOKUP(I16,BDcuA,4,FALSE) -> glb | E16: 1 | F16: =VLOOKUP(I16,BDcuA,5,FALSE) -> 2519.27 | G16: =ROUND(F16*E16,DpP) -> 2519.27 | I16: 10004 | J16: 01.01.04
B17: =J17 & " " & K17 -> 01.02 EQUIPOS DE PROTECCION PERSONAL, SEÑALIZACION Y CHARLAS DE SEGURIDAD | G17: =SUM(G18:G20) -> 11533.07 | I17: ST1 | J17: 01.02 | K17: EQUIPOS DE PROTECCION PERSONAL, SEÑALIZACION Y CHARLAS DE SEGURIDAD
B18: =J18 & " " & VLOOKUP(I18,BDcuA,2,FALSE) -> 01.02.01 EQUIPOS DE PROTECCION PERSONAL (EPP'S) | D18: =VLOOKUP(I18,BDcuA,4,FALSE) -> glb | E18: 1 | F18: =VLOOKUP(I18,BDcuA,5,FALSE) -> 4635.75 | G18: =ROUND(F18*E18,DpP) -> 4635.75 | I18: 10005 | J18: 01.02.01
B19: =J19 & " " & VLOOKUP(I19,BDcuA,2,FALSE) -> 01.02.02 SEÑALIZACION | D19: =VLOOKUP(I19,BDcuA,4,FALSE) -> und | E19: 12 | F19: =VLOOKUP(I19,BDcuA,5,FALSE) -> 108.11 | G19: =ROUND(F19*E19,DpP) -> 1297.32 | I19: 10006 | J19: 01.02.02
B20: =J20 & " " & VLOOKUP(I20,BDcuA,2,FALSE) -> 01.02.03 CHARLAS DE SEGURIDAD | D20: =VLOOKUP(I20,BDcuA,4,FALSE) -> sem | E20: 16 | F20: =VLOOKUP(I20,BDcuA,5,FALSE) -> 350 | G20: =ROUND(F20*E20,DpP) -> 5600 | I20: 10007 | J20: 01.02.03
B21: =J21 & " " & K21 -> 01.03 DEMOLICIONES | G21: =SUM(G22:G22) -> 2913.61 | I21: ST1 | J21: 01.03 | K21: DEMOLICIONES
B22: =J22 & " " & VLOOKUP(I22,BDcuA,2,FALSE) -> 01.03.01 DEMOLICION CONSTRUCCION EXISTENTE | D22: =VLOOKUP(I22,BDcuA,4,FALSE) -> m3 | E22: 48.69 | F22: =VLOOKUP(I22,BDcuA,5,FALSE) -> 59.84 | G22: =ROUND(F22*E22,DpP) -> 2913.61 | I22: 10008 | J22: 01.03.01
B23: =J23 & " " & K23 -> 01.04 MOVIMIENTO DE TIERRAS | G23: =SUM(G24:G31) -> 26451.4 | I23: ST1 | J23: 01.04 | K23: MOVIMIENTO DE TIERRAS
B24: =J24 & " " & VLOOKUP(I24,BDcuA,2,FALSE) -> 01.04.01 EXCAVACION MASIVA | D24: =VLOOKUP(I24,BDcuA,4,FALSE) -> m3 | E24: 182 | F24: =VLOOKUP(I24,BDcuA,5,FALSE) -> 15.01 | G24: =ROUND(F24*E24,DpP) -> 2731.82 | I24: 10009 | J24: 01.04.01
B25: =J25 & " " & VLOOKUP(I25,BDcuA,2,FALSE) -> 01.04.02 EXCAVACION PARA ZAPATAS EN TERRENO NORMAL | D25: =VLOOKUP(I25,BDcuA,4,FALSE) -> m3 | E25: 58.9 | F25: =VLOOKUP(I25,BDcuA,5,FALSE) -> 34.72 | G25: =ROUND(F25*E25,DpP) -> 2045.01 | I25: 10010 | J25: 01.04.02
B26: =J26 & " " & VLOOKUP(I26,BDcuA,2,FALSE) -> 01.04.03 EXCAVACION PARA ESTRUCTURA EN ROCA FIJA EQUIPO | D26: =VLOOKUP(I26,BDcuA,4,FALSE) -> m3 | E26: 17.67 | F26: =VLOOKUP(I26,BDcuA,5,FALSE) -> 25.31 | G26: =ROUND(F26*E26,DpP) -> 447.23 | I26: 10011 | J26: 01.04.03
B27: =J27 & " " & VLOOKUP(I27,BDcuA,2,FALSE) -> 01.04.04 EXCAVACION PARA CIMIENTOS Y ZANJAS EN TERRENO NORMAL | D27: =VLOOKUP(I27,BDcuA,4,FALSE) -> m3 | E27: 18 | F27: =VLOOKUP(I27,BDcuA,5,FALSE) -> 34.72 | G27: =ROUND(F27*E27,DpP) -> 624.96 | I27: 10012 | J27: 01.04.04
B28: =J28 & " " & VLOOKUP(I28,BDcuA,2,FALSE) -> 01.04.05 RELLENO DE ESTRUCTURAS CON MATERIAL PROPIO MANUAL | D28: =VLOOKUP(I28,BDcuA,4,FALSE) -> m3 | E28: 124 | F28: =VLOOKUP(I28,BDcuA,5,FALSE) -> 73.67 | G28: =ROUND(F28*E28,DpP) -> 9135.08 | I28: 10013 | J28: 01.04.05
B29: =J29 & " " & VLOOKUP(I29,BDcuA,2,FALSE) -> 01.04.06 ELIMINACION DE MATERIAL EXCEDENTE CON VOLQUETES (SUBCONTRATO) | D29: =VLOOKUP(I29,BDcuA,4,FALSE) -> m3 | E29: 399.43 | F29: =VLOOKUP(I29,BDcuA,5,FALSE) -> 19.3 | G29: =ROUND(F29*E29,DpP) -> 7709 | I29: 10014 | J29: 01.04.06
B30: =J30 & " " & VLOOKUP(I30,BDcuA,2,FALSE) -> 01.04.07 NIVELACION INTERIOR Y APISONADO | D30: =VLOOKUP(I30,BDcuA,4,FALSE) -> m2 | E30: 182 | F30: =VLOOKUP(I30,BDcuA,5,FALSE) -> 4.28 | G30: =ROUND(F30*E30,DpP) -> 778.96 | I30: 10015 | J30: 01.04.07
B31: =J31 & " " & VLOOKUP(I31,BDcuA,2,FALSE) -> 01.04.08 BASE GRANULAR E=0.15 m.COMPACTADA | D31: =VLOOKUP(I31,BDcuA,4,FALSE) -> m2 | E31: 182 | F31: =VLOOKUP(I31,BDcuA,5,FALSE) -> 16.37 | G31: =ROUND(F31*E31,DpP) -> 2979.34 | I31: 10016 | J31: 01.04.08
B32: =J32 & " " & K32 -> 01.05 CONCRETO SIMPLE | G32: =SUMIF(Pto!$I33:$I41,">10000",G33:G41) -> 12448.03 | I32: ST1 | J32: 01.05 | K32: CONCRETO SIMPLE
B33: =J33 & " " & K33 -> 01.05.01 SOLADOS | G33: =SUM(G34:G34) -> 4983.16 | I33: ST2 | J33: 01.05.01 | K33: SOLADOS
B34: =J34 & " " & VLOOKUP(I34,BDcuA,2,FALSE) -> 01.05.01.01 SOLADO e=3" | D34: =VLOOKUP(I34,BDcuA,4,FALSE) -> m2 | E34: 182 | F34: =VLOOKUP(I34,BDcuA,5,FALSE) -> 27.38 | G34: =ROUND(F34*E34,DpP) -> 4983.16 | I34: 10017 | J34: 01.05.01.01
B35: =J35 & " " & K35 -> 01.05.02 CIMIENTOS | G35: =SUM(G36:G36) -> 3449.48 | I35: ST2 | J35: 01.05.02 | K35: CIMIENTOS
B36: =J36 & " " & VLOOKUP(I36,BDcuA,2,FALSE) -> 01.05.02.01 CIMIENTOS CORRIDOS MEZCLA 1:10 CEMENTO-HORMIGON 30% PIEDRA | D36: =VLOOKUP(I36,BDcuA,4,FALSE) -> m3 | E36: 15.12 | F36: =VLOOKUP(I36,BDcuA,5,FALSE) -> 228.14 | G36: =ROUND(F36*E36,DpP) -> 3449.48 | I36: 10018 | J36: 01.05.02.01
B37: =J37 & " " & K37 -> 01.05.03 SOBRECIMIENTOS | G37: =SUM(G38:G39) -> 3468.66 | I37: ST2 | J37: 01.05.03 | K37: SOBRECIMIENTOS
B38: =J38 & " " & VLOOKUP(I38,BDcuA,2,FALSE) -> 01.05.03.01 CONCRETO 1:8+25% PM PARA SOBRECIMIENTOS | D38: =VLOOKUP(I38,BDcuA,4,FALSE) -> m3 | E38: 5.52 | F38: =VLOOKUP(I38,BDcuA,5,FALSE) -> 267.81 | G38: =ROUND(F38*E38,DpP) -> 1478.31 | I38: 10019 | J38: 01.05.03.01
B39: =J39 & " " & VLOOKUP(I39,BDcuA,2,FALSE) -> 01.05.03.02 ENCOFRADO Y DESENCOFRADO NORMAL PARA SOBRECIMIENTO HASTA 0.30 m | D39: =VLOOKUP(I39,BDcuA,4,FALSE) -> m2 | E39: 45 | F39: =VLOOKUP(I39,BDcuA,5,FALSE) -> 44.23 | G39: =ROUND(F39*E39,DpP) -> 1990.35 | I39: 10020 | J39: 01.05.03.02
B40: =J40 & " " & K40 -> 01.05.04 PISOS | G40: =SUM(G41:G41) -> 546.73 | I40: ST2 | J40: 01.05.04 | K40: PISOS
B41: =J41 & " " & VLOOKUP(I41,BDcuA,2,FALSE) -> 01.05.04.01 CONCRETO EN FALSOPISO MEZCLA 1:8 CEMENTO-HORMIGON E=4" | D41: =VLOOKUP(I41,BDcuA,4,FALSE) -> m2 | E41: 18.2 | F41: =VLOOKUP(I41,BDcuA,5,FALSE) -> 30.04 | G41: =ROUND(F41*E41,DpP) -> 546.73 | I41: 10021 | J41: 01.05.04.01
B42: =J42 & " " & K42 -> 01.06 CONCRETO ARMADO | G42: =SUMIF(Pto!$I43:$I63,">10000",G43:G63) -> 113940.1 | I42: ST1 | J42: 01.06 | K42: CONCRETO ARMADO
B43: =J43 & " " & K43 -> 01.06.01 ZAPATAS | G43: =SUM(G44:G46) -> 33576.49 | I43: ST2 | J43: 01.06.01 | K43: ZAPATAS
B44: =J44 & " " & VLOOKUP(I44,BDcuA,2,FALSE) -> 01.06.01.01 CONCRETO PARA ZAPATAS f'c=280 kg/cm2 | D44: =VLOOKUP(I44,BDcuA,4,FALSE) -> m3 | E44: 37.11 | F44: =VLOOKUP(I44,BDcuA,5,FALSE) -> 483.09 | G44: =ROUND(F44*E44,DpP) -> 17927.47 | I44: 10022 | J44: 01.06.01.01
B45: =J45 & " " & VLOOKUP(I45,BDcuA,2,FALSE) -> 01.06.01.02 ENCOFRADO DE ZAPATAS | D45: =VLOOKUP(I45,BDcuA,4,FALSE) -> m2 | E45: 68.95 | F45: =VLOOKUP(I45,BDcuA,5,FALSE) -> 41.52 | G45: =ROUND(F45*E45,DpP) -> 2862.8 | I45: 10023 | J45: 01.06.01.02
B46: =J46 & " " & VLOOKUP(I46,BDcuA,2,FALSE) -> 01.06.01.03 ACERO fy=4200 kg/cm2 GRADO 60 en ZAPATAS | D46: =VLOOKUP(I46,BDcuA,4,FALSE) -> kg | E46: 2686.18 | F46: =VLOOKUP(I46,BDcuA,5,FALSE) -> 4.76 | G46: =ROUND(F46*E46,DpP) -> 12786.22 | I46: 10024 | J46: 01.06.01.03
B47: =J47 & " " & K47 -> 01.06.02 COLUMNAS | G47: =SUM(G48:G50) -> 21713.94 | I47: ST2 | J47: 01.06.02 | K47: COLUMNAS
B48: =J48 & " " & VLOOKUP(I48,BDcuA,2,FALSE) -> 01.06.02.01 CONCRETO EN COLUMNAS f'c=280 kg/cm2 | D48: =VLOOKUP(I48,BDcuA,4,FALSE) -> m3 | E48: 11.18 | F48: =VLOOKUP(I48,BDcuA,5,FALSE) -> 466.41 | G48: =ROUND(F48*E48,DpP) -> 5214.46 | I48: 10025 | J48: 01.06.02.01
B49: =J49 & " " & VLOOKUP(I49,BDcuA,2,FALSE) -> 01.06.02.02 ENCOFRADO Y DESENCOFRADO NORMAL EN COLUMNAS | D49: =VLOOKUP(I49,BDcuA,4,FALSE) -> m2 | E49: 120.79 | F49: =VLOOKUP(I49,BDcuA,5,FALSE) -> 72.91 | G49: =ROUND(F49*E49,DpP) -> 8806.8 | I49: 10026 | J49: 01.06.02.02
B50: =J50 & " " & VLOOKUP(I50,BDcuA,2,FALSE) -> 01.06.02.03 ACERO fy=4200 kg/cm2 GRADO 60 en COLUMNAS | D50: =VLOOKUP(I50,BDcuA,4,FALSE) -> kg | E50: 1616.11 | F50: =VLOOKUP(I50,BDcuA,5,FALSE) -> 4.76 | G50: =ROUND(F50*E50,DpP) -> 7692.68 | I50: 10027 | J50: 01.06.02.03
B51: =J51 & " " & K51 -> 01.06.03 VIGAS | G51: =SUM(G52:G54) -> 28570.19 | I51: ST2 | J51: 01.06.03 | K51: VIGAS
B52: =J52 & " " & VLOOKUP(I52,BDcuA,2,FALSE) -> 01.06.03.01 CONCRETO EN VIGAS f'c=280 kg/cm2 | D52: =VLOOKUP(I52,BDcuA,4,FALSE) -> m3 | E52: 11.91 | F52: =VLOOKUP(I52,BDcuA,5,FALSE) -> 468.99 | G52: =ROUND(F52*E52,DpP) -> 5585.67 | I52: 10028 | J52: 01.06.03.01
B53: =J53 & " " & VLOOKUP(I53,BDcuA,2,FALSE) -> 01.06.03.02 ENCOFRADO Y DESENCOFRADO NORMAL EN VIGAS | D53: =VLOOKUP(I53,BDcuA,4,FALSE) -> m2 | E53: 110.76 | F53: =VLOOKUP(I53,BDcuA,5,FALSE) -> 101.71 | G53: =ROUND(F53*E53,DpP) -> 11265.4 | I53: 10029 | J53: 01.06.03.02
B54: =J54 & " " & VLOOKUP(I54,BDcuA,2,FALSE) -> 01.06.03.03 ACERO fy=4200 kg/cm2 GRADO 60 en VIGAS | D54: =VLOOKUP(I54,BDcuA,4,FALSE) -> kg | E54: 2462 | F54: =VLOOKUP(I54,BDcuA,5,FALSE) -> 4.76 | G54: =ROUND(F54*E54,DpP) -> 11719.12 | I54: 10030 | J54: 01.06.03.03
B55: =J55 & " " & K55 -> 01.06.04 LOSAS ALIGERADAS | G55: =SUM(G56:G59) -> 26079.43 | I55: ST2 | J55: 01.06.04 | K55: LOSAS ALIGERADAS
B56: =J56 & " " & VLOOKUP(I56,BDcuA,2,FALSE) -> 01.06.04.01 CONCRETO EN LOSAS ALIGERADA f'c= 280 kg/cm2 | D56: =VLOOKUP(I56,BDcuA,4,FALSE) -> m3 | E56: 12.69 | F56: =VLOOKUP(I56,BDcuA,5,FALSE) -> 475.51 | G56: =ROUND(F56*E56,DpP) -> 6034.22 | I56: 10031 | J56: 01.06.04.01
B57: =J57 & " " & VLOOKUP(I57,BDcuA,2,FALSE) -> 01.06.04.02 ENCOFRADO Y DESENCOFRADO NORMAL EN LOSAS ALIGERADAS | D57: =VLOOKUP(I57,BDcuA,4,FALSE) -> m2 | E57: 145.91 | F57: =VLOOKUP(I57,BDcuA,5,FALSE) -> 68.09 | G57: =ROUND(F57*E57,DpP) -> 9935.01 | I57: 10032 | J57: 01.06.04.02
B58: =J58 & " " & VLOOKUP(I58,BDcuA,2,FALSE) -> 01.06.04.03 LADRILLO HUECO DE ARCILLA h=15 cm PARA TECHO ALIGERADO | D58: =VLOOKUP(I58,BDcuA,4,FALSE) -> pza | E58: 1269.44 | F58: =VLOOKUP(I58,BDcuA,5,FALSE) -> 2.54 | G58: =ROUND(F58*E58,DpP) -> 3224.38 | I58: 10033 | J58: 01.06.04.03
B59: =J59 & " " & VLOOKUP(I59,BDcuA,2,FALSE) -> 01.06.04.04 ACERO fy=4200 kg/cm2 GRADO 60 en LOSAS ALIGERADAS | D59: =VLOOKUP(I59,BDcuA,4,FALSE) -> kg | E59: 1446.6 | F59: =VLOOKUP(I59,BDcuA,5,FALSE) -> 4.76 | G59: =ROUND(F59*E59,DpP) -> 6885.82 | I59: 10034 | J59: 01.06.04.04
B60: =J60 & " " & K60 -> 01.06.05 ESCALERAS y RAMPAS | G60: =SUM(G61:G63) -> 4000.05 | I60: ST2 | J60: 01.06.05 | K60: ESCALERAS y RAMPAS
B61: =J61 & " " & VLOOKUP(I61,BDcuA,2,FALSE) -> 01.06.05.01 CONCRETO EN ESCALERAS Y RAMPAS f'c=210 kg/cm2 | D61: =VLOOKUP(I61,BDcuA,4,FALSE) -> m3 | E61: 2.1 | F61: =VLOOKUP(I61,BDcuA,5,FALSE) -> 458.02 | G61: =ROUND(F61*E61,DpP) -> 961.84 | I61: 10035 | J61: 01.06.05.01
B62: =J62 & " " & VLOOKUP(I62,BDcuA,2,FALSE) -> 01.06.05.02 ENCOFRADO Y DESENCOFRADO NORMAL EN ESCALERAS Y RAMPAS | D62: =VLOOKUP(I62,BDcuA,4,FALSE) -> m2 | E62: 21.5 | F62: =VLOOKUP(I62,BDcuA,5,FALSE) -> 87.07 | G62: =ROUND(F62*E62,DpP) -> 1872.01 | I62: 10036 | J62: 01.06.05.02
B63: =J63 & " " & VLOOKUP(I63,BDcuA,2,FALSE) -> 01.06.05.03 ACERO fy=4200 kg/cm2 GRADO 60 en ESCALERAS Y RAMPAS | D63: =VLOOKUP(I63,BDcuA,4,FALSE) -> kg | E63: 245 | F63: =VLOOKUP(I63,BDcuA,5,FALSE) -> 4.76 | G63: =ROUND(F63*E63,DpP) -> 1166.2 | I63: 10037 | J63: 01.06.05.03
B64: =J64 & " " & K64 -> 02 ARQUITECTURA Y ACABADOS | G64: =SUMIF(Pto!$I65:$I112,">10000",G65:G112) -> 148553.19 | I64: T | J64: 02 | K64: ARQUITECTURA Y ACABADOS
B65: =J65 & " " & K65 -> 02.01 MUROS Y TABIQUES | G65: =SUM(G66:G67) -> 24813.64 | I65: ST1 | J65: 02.01 | K65: MUROS Y TABIQUES
B66: =J66 & " " & VLOOKUP(I66,BDcuA,2,FALSE) -> 02.01.01 MURO LADRILLO K.K DE ARCILLA 18H ( 09x013x0.24) AMARRE DE CABEZA, JUNTA 1.5 cm. MORTERO 1:1:5 | D66: =VLOOKUP(I66,BDcuA,4,FALSE) -> m2 | E66: 165.3 | F66: =VLOOKUP(I66,BDcuA,5,FALSE) -> 112.09 | G66: =ROUND(F66*E66,DpP) -> 18528.48 | I66: 10038 | J66: 02.01.01
B67: =J67 & " " & VLOOKUP(I67,BDcuA,2,FALSE) -> 02.01.02 MURO LADRILLO K.K.DE ARCILLA 18 H ( 0.09x0.13x0.24) AMARRE DE SOGA JUNTA 1.5 cm. MORTERO 1:1:5 | D67: =VLOOKUP(I67,BDcuA,4,FALSE) -> m2 | E67: 74.1 | F67: =VLOOKUP(I67,BDcuA,5,FALSE) -> 84.82 | G67: =ROUND(F67*E67,DpP) -> 6285.16 | I67: 10039 | J67: 02.01.02
B68: =J68 & " " & K68 -> 02.02 REVOQUES | G68: =SUM(G69:G74) -> 16571.17 | I68: ST1 | J68: 02.02 | K68: REVOQUES
B69: =J69 & " " & VLOOKUP(I69,BDcuA,2,FALSE) -> 02.02.01 TARRAJEO MUROS INTERIORES | D69: =VLOOKUP(I69,BDcuA,4,FALSE) -> m2 | E69: 257 | F69: =VLOOKUP(I69,BDcuA,5,FALSE) -> 22.74 | G69: =ROUND(F69*E69,DpP) -> 5844.18 | I69: 10040 | J69: 02.02.01
B70: =J70 & " " & VLOOKUP(I70,BDcuA,2,FALSE) -> 02.02.02 TARRAJEO MUROS EXTERIORES | D70: =VLOOKUP(I70,BDcuA,4,FALSE) -> m2 | E70: 79 | F70: =VLOOKUP(I70,BDcuA,5,FALSE) -> 34.22 | G70: =ROUND(F70*E70,DpP) -> 2703.38 | I70: 10041 | J70: 02.02.02
B71: =J71 & " " & VLOOKUP(I71,BDcuA,2,FALSE) -> 02.02.03 TARRAJEO COLUMNAS | D71: =VLOOKUP(I71,BDcuA,4,FALSE) -> m2 | E71: 55.67 | F71: =VLOOKUP(I71,BDcuA,5,FALSE) -> 44.13 | G71: =ROUND(F71*E71,DpP) -> 2456.72 | I71: 10042 | J71: 02.02.03
B72: =J72 & " " & VLOOKUP(I72,BDcuA,2,FALSE) -> 02.02.04 TARRAJEO DE VIGAS | D72: =VLOOKUP(I72,BDcuA,4,FALSE) -> m2 | E72: 44.2 | F72: =VLOOKUP(I72,BDcuA,5,FALSE) -> 44.13 | G72: =ROUND(F72*E72,DpP) -> 1950.55 | I72: 10043 | J72: 02.02.04
B73: =J73 & " " & VLOOKUP(I73,BDcuA,2,FALSE) -> 02.02.05 DERRAMES A=0.15 m.MORTERO 1:3 | D73: =VLOOKUP(I73,BDcuA,4,FALSE) -> m | E73: 125.05 | F73: =VLOOKUP(I73,BDcuA,5,FALSE) -> 16.7 | G73: =ROUND(F73*E73,DpP) -> 2088.34 | I73: 10044 | J73: 02.02.05
B74: =J74 & " " & VLOOKUP(I74,BDcuA,2,FALSE) -> 02.02.06 BRUÑAS DE 1 X 1 cm | D74: =VLOOKUP(I74,BDcuA,4,FALSE) -> m | E74: 200 | F74: =VLOOKUP(I74,BDcuA,5,FALSE) -> 7.64 | G74: =ROUND(F74*E74,DpP) -> 1528 | I74: 10046 | J74: 02.02.06
B75: =J75 & " " & K75 -> 02.03 CIELO RASOS | G75: =SUM(G76:G77) -> 7019.97 | I75: ST1 | J75: 02.03 | K75: CIELO RASOS
B76: =J76 & " " & VLOOKUP(I76,BDcuA,2,FALSE) -> 02.03.01 CIELO RASO DE MADERA MACHIHEMBRADA | D76: =VLOOKUP(I76,BDcuA,4,FALSE) -> m2 | E76: 8.96 | F76: =VLOOKUP(I76,BDcuA,5,FALSE) -> 148.51 | G76: =ROUND(F76*E76,DpP) -> 1330.65 | I76: 10047 | J76: 02.03.01
B77: =J77 & " " & VLOOKUP(I77,BDcuA,2,FALSE) -> 02.03.02 TARRAJEO DE CIELORASO | D77: =VLOOKUP(I77,BDcuA,4,FALSE) -> m2 | E77: 182 | F77: =VLOOKUP(I77,BDcuA,5,FALSE) -> 31.26 | G77: =ROUND(F77*E77,DpP) -> 5689.32 | I77: 10048 | J77: 02.03.02
B78: =J78 & " " & K78 -> 02.04 PISOS | G78: =SUM(G79:G82) -> 24027.98 | I78: ST1 | J78: 02.04 | K78: PISOS
B79: =J79 & " " & VLOOKUP(I79,BDcuA,2,FALSE) -> 02.04.01 CONTRAPISO DE 2" | D79: =VLOOKUP(I79,BDcuA,4,FALSE) -> m2 | E79: 165 | F79: =VLOOKUP(I79,BDcuA,5,FALSE) -> 27.81 | G79: =ROUND(F79*E79,DpP) -> 4588.65 | I79: 10049 | J79: 02.04.01
B80: =J80 & " " & VLOOKUP(I80,BDcuA,2,FALSE) -> 02.04.02 ENCHAPE DE PORCELANATO 30 X 30 cm EN PISO | D80: =VLOOKUP(I80,BDcuA,4,FALSE) -> m2 | E80: 154.84 | F80: =VLOOKUP(I80,BDcuA,5,FALSE) -> 62 | G80: =ROUND(F80*E80,DpP) -> 9600.08 | I80: 10050 | J80: 02.04.02
B81: =J81 & " " & VLOOKUP(I81,BDcuA,2,FALSE) -> 02.04.03 PISO CERAMICO ANTIDESLIZANTE CELIMA 30x30 (MOSAICO BLANCO Y/O CUPIRITA) | D81: =VLOOKUP(I81,BDcuA,4,FALSE) -> m2 | E81: 10 | F81: =VLOOKUP(I81,BDcuA,5,FALSE) -> 187.92 | G81: =ROUND(F81*E81,DpP) -> 1879.2 | I81: 10052 | J81: 02.04.03
B82: =J82 & " " & VLOOKUP(I82,BDcuA,2,FALSE) -> 02.04.04 PISO DE CEMENTO BARRIDO Y BRUÑADO E=0.04 m | D82: =VLOOKUP(I82,BDcuA,4,FALSE) -> m2 | E82: 285 | F82: =VLOOKUP(I82,BDcuA,5,FALSE) -> 27.93 | G82: =ROUND(F82*E82,DpP) -> 7960.05 | I82: 10053 | J82: 02.04.04
B83: =J83 & " " & K83 -> 02.05 SARDINELES Y VEREDAS | G83: =SUM(G84:G84) -> 2376.11 | I83: ST1 | J83: 02.05 | K83: SARDINELES Y VEREDAS
B84: =J84 & " " & VLOOKUP(I84,BDcuA,2,FALSE) -> 02.05.01 CONCRETO VEREDAS f'c=175 kg/cm2 UN SARDINEL INCORPORADO A=1.00 m. INCLUYE BASE DE AFIRMADO E=0.10 m. | D84: =VLOOKUP(I84,BDcuA,4,FALSE) -> m2 | E84: 37.8 | F84: =VLOOKUP(I84,BDcuA,5,FALSE) -> 62.86 | G84: =ROUND(F84*E84,DpP) -> 2376.11 | I84: 10055 | J84: 02.05.01
B85: =J85 & " " & K85 -> 02.06 CONTRAZOCALOS | G85: =SUM(G86:G86) -> 653.36 | I85: ST1 | J85: 02.06 | K85: CONTRAZOCALOS
B86: =J86 & " " & VLOOKUP(I86,BDcuA,2,FALSE) -> 02.06.01 CONTRAZOCALO CERAMICO 30X30 H=0.10 m. FRAGUA CON PORCELANA COLOR | D86: =VLOOKUP(I86,BDcuA,4,FALSE) -> m | E86: 33.42 | F86: =VLOOKUP(I86,BDcuA,5,FALSE) -> 19.55 | G86: =ROUND(F86*E86,DpP) -> 653.36 | I86: 10057 | J86: 02.06.01
B87: =J87 & " " & K87 -> 02.07 ZOCALOS | G87: =SUM(G88:G88) -> 6907.59 | I87: ST1 | J87: 02.07 | K87: ZOCALOS
B88: =J88 & " " & VLOOKUP(I88,BDcuA,2,FALSE) -> 02.07.01 ZOCALO DE CERAMICA 30 X 30 EN BAÑO O SIMILAR | D88: =VLOOKUP(I88,BDcuA,4,FALSE) -> m2 | E88: 56.68 | F88: =VLOOKUP(I88,BDcuA,5,FALSE) -> 121.87 | G88: =ROUND(F88*E88,DpP) -> 6907.59 | I88: 10058 | J88: 02.07.01
B89: =J89 & " " & K89 -> 02.08 ESCALERAS Y RAMPAS | G89: =SUM(G90:G91) -> 16371.5 | I89: ST1 | J89: 02.08 | K89: ESCALERAS Y RAMPAS
B90: =J90 & " " & VLOOKUP(I90,BDcuA,2,FALSE) -> 02.08.01 PISO DE CEMENTO BARRIDO Y BRUÑADO E=0.04 m | D90: =VLOOKUP(I90,BDcuA,4,FALSE) -> m2 | E90: 288 | F90: =VLOOKUP(I90,BDcuA,5,FALSE) -> 27.93 | G90: =ROUND(F90*E90,DpP) -> 8043.84 | I90: 10053 | J90: 02.08.01
B91: =J91 & " " & VLOOKUP(I91,BDcuA,2,FALSE) -> 02.08.02 TARRAJEO DE FONDO DE ESCALERAS Y RAMPAS MORTERO 1:5 | D91: =VLOOKUP(I91,BDcuA,4,FALSE) -> m2 | E91: 266.4 | F91: =VLOOKUP(I91,BDcuA,5,FALSE) -> 31.26 | G91: =ROUND(F91*E91,DpP) -> 8327.66 | I91: 10059 | J91: 02.08.02
B92: =J92 & " " & K92 -> 02.09 COBERTURAS | G92: =SUM(G93:G93) -> 867.95 | I92: ST1 | J92: 02.09 | K92: COBERTURAS
B93: =J93 & " " & VLOOKUP(I93,BDcuA,2,FALSE) -> 02.09.01 COBERTURA DE TEJA ANDINA | D93: =VLOOKUP(I93,BDcuA,4,FALSE) -> m2 | E93: 12.53 | F93: =VLOOKUP(I93,BDcuA,5,FALSE) -> 69.27 | G93: =ROUND(F93*E93,DpP) -> 867.95 | I93: 10060 | J93: 02.09.01
B94: =J94 & " " & K94 -> 02.10 CARPINTERIA DE MADERA | G94: =SUMIF(Pto!$I95:$I100,">10000",G95:G100) -> 11477.2 | I94: ST1 | J94: 02.10 | K94: CARPINTERIA DE MADERA
B95: =J95 & " " & K95 -> 02.10.01 PUERTAS DE MADERA | G95: =SUM(G96:G98) -> 6977.2 | I95: ST2 | J95: 02.10.01 | K95: PUERTAS DE MADERA
B96: =J96 & " " & VLOOKUP(I96,BDcuA,2,FALSE) -> 02.10.01.01 PUERTA PRINCIPAL DE MADERA TORNILLO APANELADA | D96: =VLOOKUP(I96,BDcuA,4,FALSE) -> und | E96: 1 | F96: =VLOOKUP(I96,BDcuA,5,FALSE) -> 1865.9 | G96: =ROUND(F96*E96,DpP) -> 1865.9 | I96: 10061 | J96: 02.10.01.01
B97: =J97 & " " & VLOOKUP(I97,BDcuA,2,FALSE) -> 02.10.01.02 PUERTA APANELADA DE MADERA TORNILLO | D97: =VLOOKUP(I97,BDcuA,4,FALSE) -> und | E97: 1 | F97: =VLOOKUP(I97,BDcuA,5,FALSE) -> 1325.9 | G97: =ROUND(F97*E97,DpP) -> 1325.9 | I97: 10062 | J97: 02.10.01.02
B98: =J98 & " " & VLOOKUP(I98,BDcuA,2,FALSE) -> 02.10.01.03 PUERTA CONTRAPLACADA MOLDEADA P-04' | D98: =VLOOKUP(I98,BDcuA,4,FALSE) -> und | E98: 6 | F98: =VLOOKUP(I98,BDcuA,5,FALSE) -> 630.9 | G98: =ROUND(F98*E98,DpP) -> 3785.4 | I98: 10063 | J98: 02.10.01.03
B99: =J99 & " " & K99 -> 02.10.02 CARPINTERIA DE MADERA | G99: =SUM(G100:G100) -> 4500 | I99: ST2 | J99: 02.10.02 | K99: CARPINTERIA DE MADERA
B100: =J100 & " " & VLOOKUP(I100,BDcuA,2,FALSE) -> 02.10.02.01 MUEBLE DE COCINA CON MELAMINE Y GRANITO (Area de usos multiples) | D100: =VLOOKUP(I100,BDcuA,4,FALSE) -> und | E100: 1 | F100: =VLOOKUP(I100,BDcuA,5,FALSE) -> 4500 | G100: =ROUND(F100*E100,DpP) -> 4500 | I100: 10064 | J100: 02.10.02.01
B101: =J101 & " " & K101 -> 02.11 CARPINTERIA METALICA | G101: =SUM(G102:G104) -> 19696.5 | I101: ST1 | J101: 02.11 | K101: CARPINTERIA METALICA
B102: =J102 & " " & VLOOKUP(I102,BDcuA,2,FALSE) -> 02.11.01 BARANDA DE FIERRO | D102: =VLOOKUP(I102,BDcuA,4,FALSE) -> m | E102: 50 | F102: =VLOOKUP(I102,BDcuA,5,FALSE) -> 180 | G102: =ROUND(F102*E102,DpP) -> 9000 | I102: 10065 | J102: 02.11.01
B103: =J103 & " " & VLOOKUP(I103,BDcuA,2,FALSE) -> 02.11.02 PUERTA METALICA | D103: =VLOOKUP(I103,BDcuA,4,FALSE) -> m2 | E103: 7.77 | F103: =VLOOKUP(I103,BDcuA,5,FALSE) -> 450 | G103: =ROUND(F103*E103,DpP) -> 3496.5 | I103: 10066 | J103: 02.11.02
...
