Workbook
Name APUb: #REF!
Name BDcodCU: ApuB!$A$5:$A$50005
Name BDcodINS: InsB!$A$16:$A$3015
Name BDcuA: ApuB!$A$5:$DJ$50005
Name BDcuB: ApuB!$B$5:$DJ$50005
Name BDins: InsB!$A$16:$M$3015
Name cellbimuser0EB30BF1602D56040B4019F3: 1714952548072
Name cellbimuser33120D4C9001780EE8508FEB: 1715181719314
Name CODc: #REF!&"C"
Name CODp: #REF!
Name CODr: #REF!&"P"
Name DcCU: Datos!$J$13
Name Dins: Datos!$J$15
Name DLS: Datos!$AJ$12:$AJ$18
Name DpCU: Datos!$J$12
Name DpP: Datos!$J$9
Name EQ: #REF!
Name Frto: Datos!$J$19
Name JL: Datos!$H$19
Name MA: #REF!
Name MO: #REF!
Name NO: Datos!$AJ$12:$AJ$18

Sheet Datos
AQ1: NO | AT1: Feriados
B2: PROYECTO | AQ2: SI | AT2: Comienzo | AU2: Fin | AV2: Descripcion
B3: UBICACIÓN | AQ3: SI
B4: CLIENTE | AQ4: SI
B5: FECHA | AI5: Soles | AJ5: S/ | AQ5: SI
F6: MONEDA | AI6: Dólares | AJ6: $
B7: LOGO | C7: RW7o | D7: =IF(J7=AI5,AJ5,AJ6) -> S/ | G7: Procesar el presupuesto utilizando la moneda en | J7: Soles
F8: NÚMERO DE DECIMALES PARA REDONDEO
B9: MODALIDAD DE E. | C9: CONTRATA | G9: Parciales de las partidas en la hoja de presupuesto | J9: 2 | AI9: CONTRATA | AQ9: NO
B10: IMPUESTO (IGV) | C10: 0.18 | G10: Total de los metrados en cada partida | J10: 2 | AI10: ADMINISTRACION DIRECTA | AO10: CALENDARIO | AR10: PIE DEL PRESUPUESTO
D11: =Pto!G474 -> 2400809 | AH11: 0 | AI11: 0 | AK11: 0 | AO11: Lunes | AP11: Laborable | AR11: VALOR FIJO
B12: COLOR DE TEXTOS: | G12: Parcial de los insumos en los APUs | J12: 2 | AI12: 1 | AJ12: 6 | AK12: 1 | AO12: Martes | AP12: Laborable | AR12: % COSTO DIRECTO
B13: Subpresupuesto | G13: Cantidad de MO y EQ en los APUs | J13: 4 | AI13: 2 | AJ13: 5 | AK13: 2 | AO13: Miercoles | AP13: Laborable | AR13: SUBTOTAL 1
B14: Título | D14: =VLOOKUP(C14,AL$10:AM$23,2,FALSE) -> #N/A | AI14: 3 | AK14: 3 | AO14: Jueves | AP14: Laborable | AR14: % SUBTOTAL 1
B15: Sub título de orden 1 | D15: =VLOOKUP(C15,AL$10:AM$23,2,FALSE) -> #N/A | G15: Precio de los insumos | J15: 2 | AI15: 4 | AK15: 4 | AO15: Viernes | AP15: Laborable | AR15: SUBTOTAL 2
B16: Sub título de orden 2 | D16: =VLOOKUP(C16,AL$10:AM$23,2,FALSE) -> #N/A | AI16: 5 | AK16: 5 | AO16: Sábado | AP16: Laborable | AR16: % SUBTOTAL 2
B17: Sub título de orden 3 | D17: =VLOOKUP(C17,AL$10:AM$23,2,FALSE) -> #N/A | F17: OTRAS OPCIONES | AI17: SI | AJ17: Parcial | AK17: 6 | AO17: Domingo | AP17: No laborable | AR17: SUBTOTAL 3
B18: Sub título de orden 4 | D18: =VLOOKUP(C18,AL$10:AM$23,2,FALSE) -> #N/A | I18: Factor costo mano de obra | J18: 1 | AI18: NO | AJ18: Cantidad | AK18: 7 | AR18: % SUBTOTAL 3
B19: Sub título de orden 5 | D19: =VLOOKUP(C19,AL$10:AM$23,2,FALSE) -> #N/A | G19: Jornada laboral | H19: 8 | I19: Factor para rendimiento | J19: 1 | AK19: 8 | AO19: TEXTO EN PANEL DE APUS | AR19: SUBTOTAL 4
B20: Sub título de orden 6 | D20: =VLOOKUP(C20,AL$10:AM$23,2,FALSE) -> #N/A | AI20: MO1 y EQ1 | AK20: 9 | AO20: Tamaño ET | AP20: 10 | AR20: % SUBTOTAL 4
B21: Sub título de orden 7 | D21: =VLOOKUP(C21,AL$10:AM$23,2,FALSE) -> #N/A | G21: Igualar el monto total de relación de insumos al CD | J21: SI | AI21: TODOS | AJ21: 1 | AO21: Fuente ET | AP21: Arial | AR21: % FILA ANTERIOR
B22: Sub título de orden 8 | D22: =VLOOKUP(C22,AL$10:AM$23,2,FALSE) -> #N/A | AO22: Tamaño DG | AP22: 9
B23: Sub título de orden 9 | D23: =VLOOKUP(C23,AL$10:AM$23,2,FALSE) -> #N/A | G23: Generar el gráfico de utilización de recursos para | J23: MO1 y EQ1 | AO23: Fuente DG | AP23: Arial
B25: Pie de presupuesto | G25: Al generar E.T. en Word usar IDEM en partidas repetidas | J25: SI
A26: CONTROL CONCURRENTE
A27: GESTION DEL PROYECTO | G27: Al generar E. T. en Word procesar UNIDAD | J27: SI
A28: GASTOS GENERALES
A29: UTILIDAD | G29: Al generar E.T. en Word procesar FORMA DE PAGO | J29: SI
A30: SUBTOTAL
A31: IMPUESTO (IGV) | G31: Calend. Adq. insumos de MO1 en DH y EQ1 en DM | J31: NO
A32: VALOR REFERENCIAL
A33: SUPERVISIÓN | G33: Al consolidar los insumos de las partidas calcular en base a | J33: Parcial
A34: EXPEDIENTE TÉCNICO
A35: LIQUIDACIÓN
A36: PIE DE PRESUPUESTO
A37: DESCRIPCIÓN | B37: SIM. | C37: VALOR | E37: TIPO
A38: GASTOS GENERALES | B38: GG | C38: 15 | E38: % COSTO DIRECTO
A39: UTILIDAD | B39: UT | C39: 10 | E39: % COSTO DIRECTO
A40: SUBTOTAL | B40: ST | E40: SUBTOTAL 1
A41: IMPUESTO (IGV) | B41: IM | C41: 18 | E41: % SUBTOTAL 1
A42: VALOR REFERENCIAL | B42: VR | E42: SUBTOTAL 2
A43: SUPERVISIÓN | B43: SU | C43: 2.5 | E43: % SUBTOTAL 2

Sheet InsB
A2: DATOS NECESARIOS PARA EL CALCULO DE FLETES
A3: INSUMOS | D3: FLETE CON VEHICULO | G3: FLETE CON ACEMILA Y PEON
D4: ORIGEN - DESTINO | F4: Prec. U. | G4: ORIGEN - DESTINO | K4: Prec. U. | L4: p.u.Cemento
A5: MATERIALES | D5: HUARAZ- HUARI | F5: 0.15 | G5: HUARI - OBRA(YUPAN) | K5: 0.06 | L5: 2.5
A6: AGREGADOS | F6: 0 | G6: HUARI - OBRA(YUPAN) | K6: 1.2 | L6: L | M6: A | N6: H
A7: TUBERIAS | F7: 0 | K7: 0 | L7: 6 | M7: 2.2 | N7: 1.5
A8: {=MAX(IF(BDcodINS<90001,BDcodINS,80000))} -> 80010 | B8: {=MAX(IF(BDcodINS<57001,BDcodINS,53500))} -> 53500 | C8: {=MAX(IF(BDcodINS<22501,BDcodINS,20000))} -> 20000
A9: {=MAX(IF(BDcodINS<80001,BDcodINS,77500))} -> 77513 | B9: {=MAX(IF(BDcodINS<53501,BDcodINS,50000))} -> 50000 | C9: {=MAX(IF(BDcodINS<77501,BDcodINS,75000))} -> 75000
A10: {=MAX(IF(BDcodINS<70001,BDcodINS,60000))} -> 60016 | B10: {=MAX(IF(BDcodINS<30001,BDcodINS,27500))} -> 27500 | C10: {=MAX(IF(BDcodINS<75001,BDcodINS,72500))} -> 72500
A11: {=MAX(IF(BDcodINS<50001,BDcodINS,30000))} -> 30429 | B11: {=MAX(IF(BDcodINS<27501,BDcodINS,25000))} -> 25000 | C11: {=MAX(IF(BDcodINS<72501,BDcodINS,70000))} -> 70001
A12: {=MAX(IF(BDcodINS<20001,BDcodINS,10000))} -> 10008 | B12: {=MAX(IF(BDcodINS<25001,BDcodINS,22500))} -> 22500 | C12: {=MAX(IF(BDcodINS<60001,BDcodINS,57000))} -> 57000 | N12: MONEDAS
A13: 70001 | B13: =MATCH($A$13,BDcodINS,0)+15 -> 24 | C13: {=MAX(IF(BDcodINS<95001,BDcodINS,90000))} -> 80010 | N13: =Datos!AI5 -> Soles | P13: =Datos!AI6 -> Dólares
A14: =COUNT(BDcodINS)+16 -> 493 | C14: {=MAX(IF(BDcodINS<100000,BDcodINS,95000))} -> 80010 | H14: SOLO TUBERIA | N14: Factor | O14: =1+Datos!$C$10 -> 1.18 | P14: 3.75 | Q14: =O14 -> 1.18
A15: Cod. | B15: IU | C15: Tipo | D15: Insumo | E15: Und | F15: =Datos!J7 -> Soles | G15: Peso unitario (kg) | H15: Long. (m) | I15: Ø ext. (mm) | J15: espesor (mm) | K15: Específica de Gastos | L15: Codigo de APU de SP | M15: Codigo insumo referido | N15: Adm. Directa | O15: Contrata | P15: Adm. Directa | Q15: Contrata
A16: 10001 | B16: 47 | C16: MO1 | D16: CAPATAZ | E16: hh | F16: =IF(AND($F$15=Datos!$AI$5,Datos!$C$9=Datos!$AI$10),IF(A16>30000,N16,ROUND(N16*Datos!$J$18,Dins)),IF(AND($F$15=Datos!$AI$5,Datos!$C$9=Datos!$AI$9),IF(A16>30000,O16,ROUND(O16*Datos!$J$18,Dins)),IF(AND($F$15=Datos!$AI$6,Datos!$C$9=Datos!$AI$10),IF(A16>30000,P16,ROUND(P16*Datos!$J$18,Dins)),IF(AND($F$15=Datos!$AI$6,Datos!$C$9=Datos!$AI$9),IF(A16>30000,Q16,ROUND(Q16*Datos!$J$18,Dins)))))) -> 24.97 | N16: 24.97 | O16: =IF(A16>30000,ROUND(N16/$O$14,Dins),ROUND(N16,Dins)) -> 24.97 | P16: =ROUND(N16/$P$14,Dins) -> 6.66 | Q16: =IF(A16>30000,ROUND(P16/$Q$14,Dins),ROUND(P16,Dins)) -> 6.66
A17: 10002 | B17: 47 | C17: MO1 | D17: OPERARIO | E17: hh | F17: =IF(AND($F$15=Datos!$AI$5,Datos!$C$9=Datos!$AI$10),IF(A17>30000,N17,ROUND(N17*Datos!$J$18,Dins)),IF(AND($F$15=Datos!$AI$5,Datos!$C$9=Datos!$AI$9),IF(A17>30000,O17,ROUND(O17*Datos!$J$18,Dins)),IF(AND($F$15=Datos!$AI$6,Datos!$C$9=Datos!$AI$10),IF(A17>30000,P17,ROUND(P17*Datos!$J$18,Dins)),IF(AND($F$15=Datos!$AI$6,Datos!$C$9=Datos!$AI$9),IF(A17>30000,Q17,ROUND(Q17*Datos!$J$18,Dins)))))) -> 20.81 | N17: 20.81 | O17: =IF(A17>30000,ROUND(N17/$O$14,Dins),ROUND(N17,Dins)) -> 20.81 | P17: =ROUND(N17/$P$14,Dins) -> 5.55 | Q17: =IF(A17>30000,ROUND(P17/$Q$14,Dins),ROUND(P17,Dins)) -> 5.55
A18: 10003 | B18: 47 | C18: MO1 | D18: PEON | E18: hh | F18: =IF(AND($F$15=Datos!$AI$5,Datos!$C$9=Datos!$AI$10),IF(A18>30000,N18,ROUND(N18*Datos!$J$18,Dins)),IF(AND($F$15=Datos!$AI$5,Datos!$C$9=Datos!$AI$9),IF(A18>30000,O18,ROUND(O18*Datos!$J$18,Dins)),IF(AND($F$15=Datos!$AI$6,Datos!$C$9=Datos!$AI$10),IF(A18>30000,P18,ROUND(P18*Datos!$J$18,Dins)),IF(AND($F$15=Datos!$AI$6,Datos!$C$9=Datos!$AI$9),IF(A18>30000,Q18,ROUND(Q18*Datos!$J$18,Dins)))))) -> 15.36 | N18: 15.36 | O18: =IF(A18>30000,ROUND(N18/$O$14,Dins),ROUND(N18,Dins)) -> 15.36 | P18: =ROUND(N18/$P$14,Dins) -> 4.1 | Q18: =IF(A18>30000,ROUND(P18/$Q$14,Dins),ROUND(P18,Dins)) -> 4.1
A19: 30001 | B19: 39 | C19: MA | D19: INSTALACIONES ELECTRICAS (ESTIMADO) | E19: est | F19: =IF(AND($F$15=Datos!$AI$5,Datos!$C$9=Datos!$AI$10),IF(A19>30000,N19,ROUND(N19*Datos!$J$18,Dins)),IF(AND($F$15=Datos!$AI$5,Datos!$C$9=Datos!$AI$9),IF(A19>30000,O19,ROUND(O19*Datos!$J$18,Dins)),IF(AND($F$15=Datos!$AI$6,Datos!$C$9=Datos!$AI$10),IF(A19>30000,P19,ROUND(P19*Datos!$J$18,Dins)),IF(AND($F$15=Datos!$AI$6,Datos!$C$9=Datos!$AI$9),IF(A19>30000,Q19,ROUND(Q19*Datos!$J$18,Dins)))))) -> 250 | G19: 0 | H19: 0 | I19: 0 | J19: 0 | N19: 295 | O19: =IF(A19>30000,ROUND(N19/$O$14,Dins),ROUND(N19,Dins)) -> 250 | P19: =ROUND(N19/$P$14,Dins) -> 78.67 | Q19: =IF(A19>30000,ROUND(P19/$Q$14,Dins),ROUND(P19,Dins)) -> 66.67
A20: 30002 | B20: 21 | C20: MA | D20: CEMENTO PORTLAND TIPO I (42.5KG) | E20: BOL | F20: =IF(AND($F$15=Datos!$AI$5,Datos!$C$9=Datos!$AI$10),IF(A20>30000,N20,ROUND(N20*Datos!$J$18,Dins)),IF(AND($F$15=Datos!$AI$5,Datos!$C$9=Datos!$AI$9),IF(A20>30000,O20,ROUND(O20*Datos!$J$18,Dins)),IF(AND($F$15=Datos!$AI$6,Datos!$C$9=Datos!$AI$10),IF(A20>30000,P20,ROUND(P20*Datos!$J$18,Dins)),IF(AND($F$15=Datos!$AI$6,Datos!$C$9=Datos!$AI$9),IF(A20>30000,Q20,ROUND(Q20*Datos!$J$18,Dins)))))) -> 18.5 | G20: 0 | H20: 0 | I20: 0 | J20: 0 | N20: 21.83 | O20: =IF(A20>30000,ROUND(N20/$O$14,Dins),ROUND(N20,Dins)) -> 18.5 | P20: =ROUND(N20/$P$14,Dins) -> 5.82 | Q20: =IF(A20>30000,ROUND(P20/$Q$14,Dins),ROUND(P20,Dins)) -> 4.93
A21: 30003 | B21: 26 | C21: MA | D21: CERRADURA DOS GOLPES FORTE -PARCHE MODELO 220 | E21: PZA | F21: =IF(AND($F$15=Datos!$AI$5,Datos!$C$9=Datos!$AI$10),IF(A21>30000,N21,ROUND(N21*Datos!$J$18,Dins)),IF(AND($F$15=Datos!$AI$5,Datos!$C$9=Datos!$AI$9),IF(A21>30000,O21,ROUND(O21*Datos!$J$18,Dins)),IF(AND($F$15=Datos!$AI$6,Datos!$C$9=Datos!$AI$10),IF(A21>30000,P21,ROUND(P21*Datos!$J$18,Dins)),IF(AND($F$15=Datos!$AI$6,Datos!$C$9=Datos!$AI$9),IF(A21>30000,Q21,ROUND(Q21*Datos!$J$18,Dins)))))) -> 45.8 | G21: 0 | H21: 0 | I21: 0 | J21: 0 | N21: 54.04 | O21: =IF(A21>30000,ROUND(N21/$O$14,Dins),ROUND(N21,Dins)) -> 45.8 | P21: =ROUND(N21/$P$14,Dins) -> 14.41 | Q21: =IF(A21>30000,ROUND(P21/$Q$14,Dins),ROUND(P21,Dins)) -> 12.21
A22: 30004 | B22: 38 | C22: MA | D22: HORMIGON | E22: M3 | F22: =IF(AND($F$15=Datos!$AI$5,Datos!$C$9=Datos!$AI$10),IF(A22>30000,N22,ROUND(N22*Datos!$J$18,Dins)),IF(AND($F$15=Datos!$AI$5,Datos!$C$9=Datos!$AI$9),IF(A22>30000,O22,ROUND(O22*Datos!$J$18,Dins)),IF(AND($F$15=Datos!$AI$6,Datos!$C$9=Datos!$AI$10),IF(A22>30000,P22,ROUND(P22*Datos!$J$18,Dins)),IF(AND($F$15=Datos!$AI$6,Datos!$C$9=Datos!$AI$9),IF(A22>30000,Q22,ROUND(Q22*Datos!$J$18,Dins)))))) -> 40 | G22: 0 | H22: 0 | I22: 0 | J22: 0 | N22: 47.2 | O22: =IF(A22>30000,ROUND(N22/$O$14,Dins),ROUND(N22,Dins)) -> 40 | P22: =ROUND(N22/$P$14,Dins) -> 12.59 | Q22: =IF(A22>30000,ROUND(P22/$Q$14,Dins),ROUND(P22,Dins)) -> 10.67
A23: 30005 | B23: 39 | C23: MA | D23: CASETA PREFABRICADA DE 3.0 X 3.0 M | E23: UND | F23: =IF(AND($F$15=Datos!$AI$5,Datos!$C$9=Datos!$AI$10),IF(A23>30000,N23,ROUND(N23*Datos!$J$18,Dins)),IF(AND($F$15=Datos!$AI$5,Datos!$C$9=Datos!$AI$9),IF(A23>30000,O23,ROUND(O23*Datos!$J$18,Dins)),IF(AND($F$15=Datos!$AI$6,Datos!$C$9=Datos!$AI$10),IF(A23>30000,P23,ROUND(P23*Datos!$J$18,Dins)),IF(AND($F$15=Datos!$AI$6,Datos!$C$9=Datos!$AI$9),IF(A23>30000,Q23,ROUND(Q23*Datos!$J$18,Dins)))))) -> 1500 | G23: 0 | H23: 0 | I23: 0 | J23: 0 | N23: 1770 | O23: =IF(A23>30000,ROUND(N23/$O$14,Dins),ROUND(N23,Dins)) -> 1500 | P23: =ROUND(N23/$P$14,Dins) -> 472 | Q23: =IF(A23>30000,ROUND(P23/$Q$14,Dins),ROUND(P23,Dins)) -> 400
A24: 70001 | B24: 37 | C24: EQ %MO | D24: HERRAMIENTAS MANUALES | E24: %MO | F24: =IF(AND($F$15=Datos!$AI$5,Datos!$C$9=Datos!$AI$10),IF(A24>30000,N24,ROUND(N24*Datos!$J$18,Dins)),IF(AND($F$15=Datos!$AI$5,Datos!$C$9=Datos!$AI$9),IF(A24>30000,O24,ROUND(O24*Datos!$J$18,Dins)),IF(AND($F$15=Datos!$AI$6,Datos!$C$9=Datos!$AI$10),IF(A24>30000,P24,ROUND(P24*Datos!$J$18,Dins)),IF(AND($F$15=Datos!$AI$6,Datos!$C$9=Datos!$AI$9),IF(A24>30000,Q24,ROUND(Q24*Datos!$J$18,Dins)))))) -> 34366.11 | N24: 40552.01 | O24: =IF(A24>30000,ROUND(N24/$O$14,Dins),ROUND(N24,Dins)) -> 34366.11 | P24: =ROUND(N24/$P$14,Dins) -> 10813.87 | Q24: =IF(A24>30000,ROUND(P24/$Q$14,Dins),ROUND(P24,Dins)) -> 9164.3
A25: 30006 | B25: 39 | C25: MA | D25: CASETA PREFABRICADA DE 3.0 X 4.5 M | E25: UND | F25: =IF(AND($F$15=Datos!$AI$5,Datos!$C$9=Datos!$AI$10),IF(A25>30000,N25,ROUND(N25*Datos!$J$18,Dins)),IF(AND($F$15=Datos!$AI$5,Datos!$C$9=Datos!$AI$9),IF(A25>30000,O25,ROUND(O25*Datos!$J$18,Dins)),IF(AND($F$15=Datos!$AI$6,Datos!$C$9=Datos!$AI$10),IF(A25>30000,P25,ROUND(P25*Datos!$J$18,Dins)),IF(AND($F$15=Datos!$AI$6,Datos!$C$9=Datos!$AI$9),IF(A25>30000,Q25,ROUND(Q25*Datos!$J$18,Dins)))))) -> 2025 | G25: 0 | H25: 0 | I25: 0 | J25: 0 | N25: 2389.5 | O25: =IF(A25>30000,ROUND(N25/$O$14,Dins),ROUND(N25,Dins)) -> 2025 | P25: =ROUND(N25/$P$14,Dins) -> 637.2 | Q25: =IF(A25>30000,ROUND(P25/$Q$14,Dins),ROUND(P25,Dins)) -> 540
A26: 30007 | B26: 2 | C26: MA | D26: CLAVOS DE ALAMBRE PARA MADERA C/C DE 3" | E26: KG | F26: =IF(AND($F$15=Datos!$AI$5,Datos!$C$9=Datos!$AI$10),IF(A26>30000,N26,ROUND(N26*Datos!$J$18,Dins)),IF(AND($F$15=Datos!$AI$5,Datos!$C$9=Datos!$AI$9),IF(A26>30000,O26,ROUND(O26*Datos!$J$18,Dins)),IF(AND($F$15=Datos!$AI$6,Datos!$C$9=Datos!$AI$10),IF(A26>30000,P26,ROUND(P26*Datos!$J$18,Dins)),IF(AND($F$15=Datos!$AI$6,Datos!$C$9=Datos!$AI$9),IF(A26>30000,Q26,ROUND(Q26*Datos!$J$18,Dins)))))) -> 3.65 | G26: 0 | H26: 0 | I26: 0 | J26: 0 | N26: 4.31 | O26: =IF(A26>30000,ROUND(N26/$O$14,Dins),ROUND(N26,Dins)) -> 3.65 | P26: =ROUND(N26/$P$14,Dins) -> 1.15 | Q26: =IF(A26>30000,ROUND(P26/$Q$14,Dins),ROUND(P26,Dins)) -> 0.97
A27: 30008 | B27: 10 | C27: MA | D27: APARATOS SANITARIOS Y ACCESORIOS | E27: GLB | F27: =IF(AND($F$15=Datos!$AI$5,Datos!$C$9=Datos!$AI$10),IF(A27>30000,N27,ROUND(N27*Datos!$J$18,Dins)),IF(AND($F$15=Datos!$AI$5,Datos!$C$9=Datos!$AI$9),IF(A27>30000,O27,ROUND(O27*Datos!$J$18,Dins)),IF(AND($F$15=Datos!$AI$6,Datos!$C$9=Datos!$AI$10),IF(A27>30000,P27,ROUND(P27*Datos!$J$18,Dins)),IF(AND($F$15=Datos!$AI$6,Datos!$C$9=Datos!$AI$9),IF(A27>30000,Q27,ROUND(Q27*Datos!$J$18,Dins)))))) -> 200 | G27: 0 | H27: 0 | I27: 0 | J27: 0 | N27: 236 | O27: =IF(A27>30000,ROUND(N27/$O$14,Dins),ROUND(N27,Dins)) -> 200 | P27: =ROUND(N27/$P$14,Dins) -> 62.93 | Q27: =IF(A27>30000,ROUND(P27/$Q$14,Dins),ROUND(P27,Dins)) -> 53.33
A28: 30009 | B28: 43 | C28: MA | D28: MADERA MOHENA EN BRUTO | E28: p2 | F28: =IF(AND($F$15=Datos!$AI$5,Datos!$C$9=Datos!$AI$10),IF(A28>30000,N28,ROUND(N28*Datos!$J$18,Dins)),IF(AND($F$15=Datos!$AI$5,Datos!$C$9=Datos!$AI$9),IF(A28>30000,O28,ROUND(O28*Datos!$J$18,Dins)),IF(AND($F$15=Datos!$AI$6,Datos!$C$9=Datos!$AI$10),IF(A28>30000,P28,ROUND(P28*Datos!$J$18,Dins)),IF(AND($F$15=Datos!$AI$6,Datos!$C$9=Datos!$AI$9),IF(A28>30000,Q28,ROUND(Q28*Datos!$J$18,Dins)))))) -> 3.7 | G28: 0 | H28: 0 | I28: 0 | J28: 0 | N28: 4.37 | O28: =IF(A28>30000,ROUND(N28/$O$14,Dins),ROUND(N28,Dins)) -> 3.7 | P28: =ROUND(N28/$P$14,Dins) -> 1.17 | Q28: =IF(A28>30000,ROUND(P28/$Q$14,Dins),ROUND(P28,Dins)) -> 0.99
A29: 30010 | B29: 45 | C29: MA | D29: TRIPLAY DE 4'x8'x 4 mm | E29: pln | F29: =IF(AND($F$15=Datos!$AI$5,Datos!$C$9=Datos!$AI$10),IF(A29>30000,N29,ROUND(N29*Datos!$J$18,Dins)),IF(AND($F$15=Datos!$AI$5,Datos!$C$9=Datos!$AI$9),IF(A29>30000,O29,ROUND(O29*Datos!$J$18,Dins)),IF(AND($F$15=Datos!$AI$6,Datos!$C$9=Datos!$AI$10),IF(A29>30000,P29,ROUND(P29*Datos!$J$18,Dins)),IF(AND($F$15=Datos!$AI$6,Datos!$C$9=Datos!$AI$9),IF(A29>30000,Q29,ROUND(Q29*Datos!$J$18,Dins)))))) -> 25 | G29: 0 | H29: 0 | I29: 0 | J29: 0 | N29: 29.5 | O29: =IF(A29>30000,ROUND(N29/$O$14,Dins),ROUND(N29,Dins)) -> 25 | P29: =ROUND(N29/$P$14,Dins) -> 7.87 | Q29: =IF(A29>30000,ROUND(P29/$Q$14,Dins),ROUND(P29,Dins)) -> 6.67
A30: 30011 | B30: 56 | C30: MA | D30: CALAMINA # 31 DE 1.83m x 0.83m x 2.7mm | E30: PZA | F30: =IF(AND($F$15=Datos!$AI$5,Datos!$C$9=Datos!$AI$10),IF(A30>30000,N30,ROUND(N30*Datos!$J$18,Dins)),IF(AND($F$15=Datos!$AI$5,Datos!$C$9=Datos!$AI$9),IF(A30>30000,O30,ROUND(O30*Datos!$J$18,Dins)),IF(AND($F$15=Datos!$AI$6,Datos!$C$9=Datos!$AI$10),IF(A30>30000,P30,ROUND(P30*Datos!$J$18,Dins)),IF(AND($F$15=Datos!$AI$6,Datos!$C$9=Datos!$AI$9),IF(A30>30000,Q30,ROUND(Q30*Datos!$J$18,Dins)))))) -> 15.5 | G30: 0 | H30: 0 | I30: 0 | J30: 0 | N30: 18.29 | O30: =IF(A30>30000,ROUND(N30/$O$14,Dins),ROUND(N30,Dins)) -> 15.5 | P30: =ROUND(N30/$P$14,Dins) -> 4.88 | Q30: =IF(A30>30000,ROUND(P30/$Q$14,Dins),ROUND(P30,Dins)) -> 4.14
A31: 30012 | B31: 72 | C31: MA | D31: TUBERIA Y ACCESORIOS PVC | E31: GLB | F31: =IF(AND($F$15=Datos!$AI$5,Datos!$C$9=Datos!$AI$10),IF(A31>30000,N31,ROUND(N31*Datos!$J$18,Dins)),IF(AND($F$15=Datos!$AI$5,Datos!$C$9=Datos!$AI$9),IF(A31>30000,O31,ROUND(O31*Datos!$J$18,Dins)),IF(AND($F$15=Datos!$AI$6,Datos!$C$9=Datos!$AI$10),IF(A31>30000,P31,ROUND(P31*Datos!$J$18,Dins)),IF(AND($F$15=Datos!$AI$6,Datos!$C$9=Datos!$AI$9),IF(A31>30000,Q31,ROUND(Q31*Datos!$J$18,Dins)))))) -> 500 | G31: 0 | H31: 0 | I31: 0 | J31: 0 | N31: 590 | O31: =IF(A31>30000,ROUND(N31/$O$14,Dins),ROUND(N31,Dins)) -> 500 | P31: =ROUND(N31/$P$14,Dins) -> 157.33 | Q31: =IF(A31>30000,ROUND(P31/$Q$14,Dins),ROUND(P31,Dins)) -> 133.33
A32: 10004 | B32: 47 | C32: MO1 | D32: OPERADOR DE EQUIPO LIVIANO | E32: hh | F32: =IF(AND($F$15=Datos!$AI$5,Datos!$C$9=Datos!$AI$10),IF(A32>30000,N32,ROUND(N32*Datos!$J$18,Dins)),IF(AND($F$15=Datos!$AI$5,Datos!$C$9=Datos!$AI$9),IF(A32>30000,O32,ROUND(O32*Datos!$J$18,Dins)),IF(AND($F$15=Datos!$AI$6,Datos!$C$9=Datos!$AI$10),IF(A32>30000,P32,ROUND(P32*Datos!$J$18,Dins)),IF(AND($F$15=Datos!$AI$6,Datos!$C$9=Datos!$AI$9),IF(A32>30000,Q32,ROUND(Q32*Datos!$J$18,Dins)))))) -> 20.81 | N32: 20.81 | O32: =IF(A32>30000,ROUND(N32/$O$14,Dins),ROUND(N32,Dins)) -> 20.81 | P32: =ROUND(N32/$P$14,Dins) -> 5.55 | Q32: =IF(A32>30000,ROUND(P32/$Q$14,Dins),ROUND(P32,Dins)) -> 5.55
A33: 10005 | B33: 47 | C33: MO1 | D33: OPERARIO ENCOFRADO | E33: hh | F33: =IF(AND($F$15=Datos!$AI$5,Datos!$C$9=Datos!$AI$10),IF(A33>30000,N33,ROUND(N33*Datos!$J$18,Dins)),IF(AND($F$15=Datos!$AI$5,Datos!$C$9=Datos!$AI$9),IF(A33>30000,O33,ROUND(O33*Datos!$J$18,Dins)),IF(AND($F$15=Datos!$AI$6,Datos!$C$9=Datos!$AI$10),IF(A33>30000,P33,ROUND(P33*Datos!$J$18,Dins)),IF(AND($F$15=Datos!$AI$6,Datos!$C$9=Datos!$AI$9),IF(A33>30000,Q33,ROUND(Q33*Datos!$J$18,Dins)))))) -> 20.81 | N33: 20.81 | O33: =IF(A33>30000,ROUND(N33/$O$14,Dins),ROUND(N33,Dins)) -> 20.81 | P33: =ROUND(N33/$P$14,Dins) -> 5.55 | Q33: =IF(A33>30000,ROUND(P33/$Q$14,Dins),ROUND(P33,Dins)) -> 5.55
A34: 30013 | B34: 43 | C34: MA | D34: MADERA TORNILLO DE 1 1/2" X 3" X 9' | E34: PZA | F34: =IF(AND($F$15=Datos!$AI$5,Datos!$C$9=Datos!$AI$10),IF(A34>30000,N34,ROUND(N34*Datos!$J$18,Dins)),IF(AND($F$15=Datos!$AI$5,Datos!$C$9=Datos!$AI$9),IF(A34>30000,O34,ROUND(O34*Datos!$J$18,Dins)),IF(AND($F$15=Datos!$AI$6,Datos!$C$9=Datos!$AI$10),IF(A34>30000,P34,ROUND(P34*Datos!$J$18,Dins)),IF(AND($F$15=Datos!$AI$6,Datos!$C$9=Datos!$AI$9),IF(A34>30000,Q34,ROUND(Q34*Datos!$J$18,Dins)))))) -> 11.7 | G34: 0 | H34: 0 | I34: 0 | J34: 0 | N34: 13.81 | O34: =IF(A34>30000,ROUND(N34/$O$14,Dins),ROUND(N34,Dins)) -> 11.7 | P34: =ROUND(N34/$P$14,Dins) -> 3.68 | Q34: =IF(A34>30000,ROUND(P34/$Q$14,Dins),ROUND(P34,Dins)) -> 3.12
A35: 30014 | B35: 39 | C35: MA | D35: WAYPE | E35: KG | F35: =IF(AND($F$15=Datos!$AI$5,Datos!$C$9=Datos!$AI$10),IF(A35>30000,N35,ROUND(N35*Datos!$J$18,Dins)),IF(AND($F$15=Datos!$AI$5,Datos!$C$9=Datos!$AI$9),IF(A35>30000,O35,ROUND(O35*Datos!$J$18,Dins)),IF(AND($F$15=Datos!$AI$6,Datos!$C$9=Datos!$AI$10),IF(A35>30000,P35,ROUND(P35*Datos!$J$18,Dins)),IF(AND($F$15=Datos!$AI$6,Datos!$C$9=Datos!$AI$9),IF(A35>30000,Q35,ROUND(Q35*Datos!$J$18,Dins)))))) -> 12 | G35: 0 | H35: 0 | I35: 0 | J35: 0 | N35: 14.16 | O35: =IF(A35>30000,ROUND(N35/$O$14,Dins),ROUND(N35,Dins)) -> 12 | P35: =ROUND(N35/$P$14,Dins) -> 3.78 | Q35: =IF(A35>30000,ROUND(P35/$Q$14,Dins),ROUND(P35,Dins)) -> 3.2
A36: 30015 | B36: 30 | C36: MA | D36: MASILLA GRIS VENCEACRIL 1/4 GLN | E36: UND | F36: =IF(AND($F$15=Datos!$AI$5,Datos!$C$9=Datos!$AI$10),IF(A36>30000,N36,ROUND(N36*Datos!$J$18,Dins)),IF(AND($F$15=Datos!$AI$5,Datos!$C$9=Datos!$AI$9),IF(A36>30000,O36,ROUND(O36*Datos!$J$18,Dins)),IF(AND($F$15=Datos!$AI$6,Datos!$C$9=Datos!$AI$10),IF(A36>30000,P36,ROUND(P36*Datos!$J$18,Dins)),IF(AND($F$15=Datos!$AI$6,Datos!$C$9=Datos!$AI$9),IF(A36>30000,Q36,ROUND(Q36*Datos!$J$18,Dins)))))) -> 7 | G36: 0 | H36: 0 | I36: 0 | J36: 0 | N36: 8.26 | O36: =IF(A36>30000,ROUND(N36/$O$14,Dins),ROUND(N36,Dins)) -> 7 | P36: =ROUND(N36/$P$14,Dins) -> 2.2 | Q36: =IF(A36>30000,ROUND(P36/$Q$14,Dins),ROUND(P36,Dins)) -> 1.86
A37: 30016 | B37: 30 | C37: MA | D37: SOLDADURA CELLOCORD P 3/16" | E37: KG | F37: =IF(AND($F$15=Datos!$AI$5,Datos!$C$9=Datos!$AI$10),IF(A37>30000,N37,ROUND(N37*Datos!$J$18,Dins)),IF(AND($F$15=Datos!$AI$5,Datos!$C$9=Datos!$AI$9),IF(A37>30000,O37,ROUND(O37*Datos!$J$18,Dins)),IF(AND($F$15=Datos!$AI$6,Datos!$C$9=Datos!$AI$10),IF(A37>30000,P37,ROUND(P37*Datos!$J$18,Dins)),IF(AND($F$15=Datos!$AI$6,Datos!$C$9=Datos!$AI$9),IF(A37>30000,Q37,ROUND(Q37*Datos!$J$18,Dins)))))) -> 8 | G37: 0 | H37: 0 | I37: 0 | J37: 0 | N37: 9.44 | O37: =IF(A37>30000,ROUND(N37/$O$14,Dins),ROUND(N37,Dins)) -> 8 | P37: =ROUND(N37/$P$14,Dins) -> 2.52 | Q37: =IF(A37>30000,ROUND(P37/$Q$14,Dins),ROUND(P37,Dins)) -> 2.14
A38: 30017 | B38: 26 | C38: MA | D38: ANGULO 1"x1"x3/16" x6m. AREQUIPA | E38: PZA | F38: =IF(AND($F$15=Datos!$AI$5,Datos!$C$9=Datos!$AI$10),IF(A38>30000,N38,ROUND(N38*Datos!$J$18,Dins)),IF(AND($F$15=Datos!$AI$5,Datos!$C$9=Datos!$AI$9),IF(A38>30000,O38,ROUND(O38*Datos!$J$18,Dins)),IF(AND($F$15=Datos!$AI$6,Datos!$C$9=Datos!$AI$10),IF(A38>30000,P38,ROUND(P38*Datos!$J$18,Dins)),IF(AND($F$15=Datos!$AI$6,Datos!$C$9=Datos!$AI$9),IF(A38>30000,Q38,ROUND(Q38*Datos!$J$18,Dins)))))) -> 15 | G38: 0 | H38: 0 | I38: 0 | J38: 0 | N38: 17.7 | O38: =IF(A38>30000,ROUND(N38/$O$14,Dins),ROUND(N38,Dins)) -> 15 | P38: =ROUND(N38/$P$14,Dins) -> 4.72 | Q38: =IF(A38>30000,ROUND(P38/$Q$14,Dins),ROUND(P38,Dins)) -> 4
A39: 30018 | B39: 48 | C39: MA | D39: THINER | E39: gln | F39: =IF(AND($F$15=Datos!$AI$5,Datos!$C$9=Datos!$AI$10),IF(A39>30000,N39,ROUND(N39*Datos!$J$18,Dins)),IF(AND($F$15=Datos!$AI$5,Datos!$C$9=Datos!$AI$9),IF(A39>30000,O39,ROUND(O39*Datos!$J$18,Dins)),IF(AND($F$15=Datos!$AI$6,Datos!$C$9=Datos!$AI$10),IF(A39>30000,P39,ROUND(P39*Datos!$J$18,Dins)),IF(AND($F$15=Datos!$AI$6,Datos!$C$9=Datos!$AI$9),IF(A39>30000,Q39,ROUND(Q39*Datos!$J$18,Dins)))))) -> 13.5 | G39: 0 | H39: 0 | I39: 0 | J39: 0 | N39: 15.93 | O39: =IF(A39>30000,ROUND(N39/$O$14,Dins),ROUND(N39,Dins)) -> 13.5 | P39: =ROUND(N39/$P$14,Dins) -> 4.25 | Q39: =IF(A39>30000,ROUND(P39/$Q$14,Dins),ROUND(P39,Dins)) -> 3.6
A40: 30019 | B40: 54 | C40: MA | D40: PINTURA ESMALTE | E40: gln | F40: =IF(AND($F$15=Datos!$AI$5,Datos!$C$9=Datos!$AI$10),IF(A40>30000,N40,ROUND(N40*Datos!$J$18,Dins)),IF(AND($F$15=Datos!$AI$5,Datos!$C$9=Datos!$AI$9),IF(A40>30000,O40,ROUND(O40*Datos!$J$18,Dins)),IF(AND($F$15=Datos!$AI$6,Datos!$C$9=Datos!$AI$10),IF(A40>30000,P40,ROUND(P40*Datos!$J$18,Dins)),IF(AND($F$15=Datos!$AI$6,Datos!$C$9=Datos!$AI$9),IF(A40>30000,Q40,ROUND(Q40*Datos!$J$18,Dins)))))) -> 40 | G40: 0 | H40: 0 | I40: 0 | J40: 0 | N40: 47.2 | O40: =IF(A40>30000,ROUND(N40/$O$14,Dins),ROUND(N40,Dins)) -> 40 | P40: =ROUND(N40/$P$14,Dins) -> 12.59 | Q40: =IF(A40>30000,ROUND(P40/$Q$14,Dins),ROUND(P40,Dins)) -> 10.67
A41: 30020 | B41: 54 | C41: MA | D41: PINTURA ZINCROMATO | E41: gln | F41: =IF(AND($F$15=Datos!$AI$5,Datos!$C$9=Datos!$AI$10),IF(A41>30000,N41,ROUND(N41*Datos!$J$18,Dins)),IF(AND($F$15=Datos!$AI$5,Datos!$C$9=Datos!$AI$9),IF(A41>30000,O41,ROUND(O41*Datos!$J$18,Dins)),IF(AND($F$15=Datos!$AI$6,Datos!$C$9=Datos!$AI$10),IF(A41>30000,P41,ROUND(P41*Datos!$J$18,Dins)),IF(AND($F$15=Datos!$AI$6,Datos!$C$9=Datos!$AI$9),IF(A41>30000,Q41,ROUND(Q41*Datos!$J$18,Dins)))))) -> 40 | G41: 0 | H41: 0 | I41: 0 | J41: 0 | N41: 47.2 | O41: =IF(A41>30000,ROUND(N41/$O$14,Dins),ROUND(N41,Dins)) -> 40 | P41: =ROUND(N41/$P$14,Dins) -> 12.59 | Q41: =IF(A41>30000,ROUND(P41/$Q$14,Dins),ROUND(P41,Dins)) -> 10.67
A42: 30021 | B42: 26 | C42: MA | D42: PLANCHA DE FIERRO 3/16 X 1.20 X 2.4 | E42: M2 | F42: =IF(AND($F$15=Datos!$AI$5,Datos!$C$9=Datos!$AI$10),IF(A42>30000,N42,ROUND(N42*Datos!$J$18,Dins)),IF(AND($F$15=Datos!$AI$5,Datos!$C$9=Datos!$AI$9),IF(A42>30000,O42,ROUND(O42*Datos!$J$18,Dins)),IF(AND($F$15=Datos!$AI$6,Datos!$C$9=Datos!$AI$10),IF(A42>30000,P42,ROUND(P42*Datos!$J$18,Dins)),IF(AND($F$15=Datos!$AI$6,Datos!$C$9=Datos!$AI$9),IF(A42>30000,Q42,ROUND(Q42*Datos!$J$18,Dins)))))) -> 50 | G42: 0 | H42: 0 | I42: 0 | J42: 0 | N42: 59 | O42: =IF(A42>30000,ROUND(N42/$O$14,Dins),ROUND(N42,Dins)) -> 50 | P42: =ROUND(N42/$P$14,Dins) -> 15.73 | Q42: =IF(A42>30000,ROUND(P42/$Q$14,Dins),ROUND(P42,Dins)) -> 13.33
A43: 30022 | B43: 65 | C43: MA | D43: TUBO ELECTROSOLDADO CUADRADO DE 2" X 2.0 MM X 6 M | E43: M | F43: =IF(AND($F$15=Datos!$AI$5,Datos!$C$9=Datos!$AI$10),IF(A43>30000,N43,ROUND(N43*Datos!$J$18,Dins)),IF(AND($F$15=Datos!$AI$5,Datos!$C$9=Datos!$AI$9),IF(A43>30000,O43,ROUND(O43*Datos!$J$18,Dins)),IF(AND($F$15=Datos!$AI$6,Datos!$C$9=Datos!$AI$10),IF(A43>30000,P43,ROUND(P43*Datos!$J$18,Dins)),IF(AND($F$15=Datos!$AI$6,Datos!$C$9=Datos!$AI$9),IF(A43>30000,Q43,ROUND(Q43*Datos!$J$18,Dins)))))) -> 30 | G43: 0 | H43: 0 | I43: 0 | J43: 0 | N43: 35.4 | O43: =IF(A43>30000,ROUND(N43/$O$14,Dins),ROUND(N43,Dins)) -> 30 | P43: =ROUND(N43/$P$14,Dins) -> 9.44 | Q43: =IF(A43>30000,ROUND(P43/$Q$14,Dins),ROUND(P43,Dins)) -> 8
A44: 60001 | B44: 49 | C44: EQ1 | D44: MAQUINA SOLDADORA | E44: hm | F44: =IF(AND($F$15=Datos!$AI$5,Datos!$C$9=Datos!$AI$10),IF(A44>30000,N44,ROUND(N44*Datos!$J$18,Dins)),IF(AND($F$15=Datos!$AI$5,Datos!$C$9=Datos!$AI$9),IF(A44>30000,O44,ROUND(O44*Datos!$J$18,Dins)),IF(AND($F$15=Datos!$AI$6,Datos!$C$9=Datos!$AI$10),IF(A44>30000,P44,ROUND(P44*Datos!$J$18,Dins)),IF(AND($F$15=Datos!$AI$6,Datos!$C$9=Datos!$AI$9),IF(A44>30000,Q44,ROUND(Q44*Datos!$J$18,Dins)))))) -> 10 | N44: 11.8 | O44: =IF(A44>30000,ROUND(N44/$O$14,Dins),ROUND(N44,Dins)) -> 10 | P44: =ROUND(N44/$P$14,Dins) -> 3.15 | Q44: =IF(A44>30000,ROUND(P44/$Q$14,Dins),ROUND(P44,Dins)) -> 2.67
A45: 30023 | B45: 39 | C45: MA | D45: AGUA | E45: MES | F45: =IF(AND($F$15=Datos!$AI$5,Datos!$C$9=Datos!$AI$10),IF(A45>30000,N45,ROUND(N45*Datos!$J$18,Dins)),IF(AND($F$15=Datos!$AI$5,Datos!$C$9=Datos!$AI$9),IF(A45>30000,O45,ROUND(O45*Datos!$J$18,Dins)),IF(AND($F$15=Datos!$AI$6,Datos!$C$9=Datos!$AI$10),IF(A45>30000,P45,ROUND(P45*Datos!$J$18,Dins)),IF(AND($F$15=Datos!$AI$6,Datos!$C$9=Datos!$AI$9),IF(A45>30000,Q45,ROUND(Q45*Datos!$J$18,Dins)))))) -> 150 | G45: 0 | H45: 0 | I45: 0 | J45: 0 | N45: 177 | O45: =IF(A45>30000,ROUND(N45/$O$14,Dins),ROUND(N45,Dins)) -> 150 | P45: =ROUND(N45/$P$14,Dins) -> 47.2 | Q45: =IF(A45>30000,ROUND(P45/$Q$14,Dins),ROUND(P45,Dins)) -> 40
A46: 30024 | B46: 39 | C46: MA | D46: INSTALACIONES PROVISIONALES DE ENERGIA ELECTRICA | E46: GLB | F46: =IF(AND($F$15=Datos!$AI$5,Datos!$C$9=Datos!$AI$10),IF(A46>30000,N46,ROUND(N46*Datos!$J$18,Dins)),IF(AND($F$15=Datos!$AI$5,Datos!$C$9=Datos!$AI$9),IF(A46>30000,O46,ROUND(O46*Datos!$J$18,Dins)),IF(AND($F$15=Datos!$AI$6,Datos!$C$9=Datos!$AI$10),IF(A46>30000,P46,ROUND(P46*Datos!$J$18,Dins)),IF(AND($F$15=Datos!$AI$6,Datos!$C$9=Datos!$AI$9),IF(A46>30000,Q46,ROUND(Q46*Datos!$J$18,Dins)))))) -> 1500 | G46: 0 | H46: 0 | I46: 0 | J46: 0 | N46: 1770 | O46: =IF(A46>30000,ROUND(N46/$O$14,Dins),ROUND(N46,Dins)) -> 1500 | P46: =ROUND(N46/$P$14,Dins) -> 472 | Q46: =IF(A46>30000,ROUND(P46/$Q$14,Dins),ROUND(P46,Dins)) -> 400
A47: 80001 | B47: 39 | C47: SERVICIO | D47: ENERGIA ELECTRICA 30 KW | E47: MES | F47: =IF(AND($F$15=Datos!$AI$5,Datos!$C$9=Datos!$AI$10),IF(A47>30000,N47,ROUND(N47*Datos!$J$18,Dins)),IF(AND($F$15=Datos!$AI$5,Datos!$C$9=Datos!$AI$9),IF(A47>30000,O47,ROUND(O47*Datos!$J$18,Dins)),IF(AND($F$15=Datos!$AI$6,Datos!$C$9=Datos!$AI$10),IF(A47>30000,P47,ROUND(P47*Datos!$J$18,Dins)),IF(AND($F$15=Datos!$AI$6,Datos!$C$9=Datos!$AI$9),IF(A47>30000,Q47,ROUND(Q47*Datos!$J$18,Dins)))))) -> 150 | G47: 0 | H47: 0 | I47: 0 | J47: 0 | N47: 177 | O47: =IF(A47>30000,ROUND(N47/$O$14,Dins),ROUND(N47,Dins)) -> 150 | P47: =ROUND(N47/$P$14,Dins) -> 47.2 | Q47: =IF(A47>30000,ROUND(P47/$Q$14,Dins),ROUND(P47,Dins)) -> 40
A48: 80002 | B48: 39 | C48: SERVICIO | D48: ELIMINACION DE EXCEDENTES | E48: M3 | F48: =IF(AND($F$15=Datos!$AI$5,Datos!$C$9=Datos!$AI$10),IF(A48>30000,N48,ROUND(N48*Datos!$J$18,Dins)),IF(AND($F$15=Datos!$AI$5,Datos!$C$9=Datos!$AI$9),IF(A48>30000,O48,ROUND(O48*Datos!$J$18,Dins)),IF(AND($F$15=Datos!$AI$6,Datos!$C$9=Datos!$AI$10),IF(A48>30000,P48,ROUND(P48*Datos!$J$18,Dins)),IF(AND($F$15=Datos!$AI$6,Datos!$C$9=Datos!$AI$9),IF(A48>30000,Q48,ROUND(Q48*Datos!$J$18,Dins)))))) -> 20 | N48: 23.6 | O48: =IF(A48>30000,ROUND(N48/$O$14,Dins),ROUND(N48,Dins)) -> 20 | P48: =ROUND(N48/$P$14,Dins) -> 6.29 | Q48: =IF(A48>30000,ROUND(P48/$Q$14,Dins),ROUND(P48,Dins)) -> 5.33
A49: 60002 | B49: 49 | C49: EQ1 | D49: MARTILLO DEMOLEDOR ELECTRICO DE 15 KG | E49: hm | F49: =IF(AND($F$15=Datos!$AI$5,Datos!$C$9=Datos!$AI$10),IF(A49>30000,N49,ROUND(N49*Datos!$J$18,Dins)),IF(AND($F$15=Datos!$AI$5,Datos!$C$9=Datos!$AI$9),IF(A49>30000,O49,ROUND(O49*Datos!$J$18,Dins)),IF(AND($F$15=Datos!$AI$6,Datos!$C$9=Datos!$AI$10),IF(A49>30000,P49,ROUND(P49*Datos!$J$18,Dins)),IF(AND($F$15=Datos!$AI$6,Datos!$C$9=Datos!$AI$9),IF(A49>30000,Q49,ROUND(Q49*Datos!$J$18,Dins)))))) -> 10 | N49: 11.8 | O49: =IF(A49>30000,ROUND(N49/$O$14,Dins),ROUND(N49,Dins)) -> 10 | P49: =ROUND(N49/$P$14,Dins) -> 3.15 | Q49: =IF(A49>30000,ROUND(P49/$Q$14,Dins),ROUND(P49,Dins)) -> 2.67
A50: 60003 | B50: 49 | C50: EQ1 | D50: CAMION VOLQUETE 4x2 140-210 HP 6 M3. | E50: hm | F50: =IF(AND($F$15=Datos!$AI$5,Datos!$C$9=Datos!$AI$10),IF(A50>30000,N50,ROUND(N50*Datos!$J$18,Dins)),IF(AND($F$15=Datos!$AI$5,Datos!$C$9=Datos!$AI$9),IF(A50>30000,O50,ROUND(O50*Datos!$J$18,Dins)),IF(AND($F$15=Datos!$AI$6,Datos!$C$9=Datos!$AI$10),IF(A50>30000,P50,ROUND(P50*Datos!$J$18,Dins)),IF(AND($F$15=Datos!$AI$6,Datos!$C$9=Datos!$AI$9),IF(A50>30000,Q50,ROUND(Q50*Datos!$J$18,Dins)))))) -> 178 | N50: 210.04 | O50: =IF(A50>30000,ROUND(N50/$O$14,Dins),ROUND(N50,Dins)) -> 178 | P50: =ROUND(N50/$P$14,Dins) -> 56.01 | Q50: =IF(A50>30000,ROUND(P50/$Q$14,Dins),ROUND(P50,Dins)) -> 47.47
A51: 10006 | B51: 47 | C51: MO1 | D51: TOPOGRAFO | E51: hh | F51: =IF(AND($F$15=Datos!$AI$5,Datos!$C$9=Datos!$AI$10),IF(A51>30000,N51,ROUND(N51*Datos!$J$18,Dins)),IF(AND($F$15=Datos!$AI$5,Datos!$C$9=Datos!$AI$9),IF(A51>30000,O51,ROUND(O51*Datos!$J$18,Dins)),IF(AND($F$15=Datos!$AI$6,Datos!$C$9=Datos!$AI$10),IF(A51>30000,P51,ROUND(P51*Datos!$J$18,Dins)),IF(AND($F$15=Datos!$AI$6,Datos!$C$9=Datos!$AI$9),IF(A51>30000,Q51,ROUND(Q51*Datos!$J$18,Dins)))))) -> 20.1 | N51: 20.1 | O51: =IF(A51>30000,ROUND(N51/$O$14,Dins),ROUND(N51,Dins)) -> 20.1 | P51: =ROUND(N51/$P$14,Dins) -> 5.36 | Q51: =IF(A51>30000,ROUND(P51/$Q$14,Dins),ROUND(P51,Dins)) -> 5.36
A52: 30025 | B52: 30 | C52: MA | D52: CAL HIDRATADA DE 30 Kg | E52: BOL | F52: =IF(AND($F$15=Datos!$AI$5,Datos!$C$9=Datos!$AI$10),IF(A52>30000,N52,ROUND(N52*Datos!$J$18,Dins)),IF(AND($F$15=Datos!$AI$5,Datos!$C$9=Datos!$AI$9),IF(A52>30000,O52,ROUND(O52*Datos!$J$18,Dins)),IF(AND($F$15=Datos!$AI$6,Datos!$C$9=Datos!$AI$10),IF(A52>30000,P52,ROUND(P52*Datos!$J$18,Dins)),IF(AND($F$15=Datos!$AI$6,Datos!$C$9=Datos!$AI$9),IF(A52>30000,Q52,ROUND(Q52*Datos!$J$18,Dins)))))) -> 20 | G52: 0 | H52: 0 | I52: 0 | J52: 0 | N52: 23.6 | O52: =IF(A52>30000,ROUND(N52/$O$14,Dins),ROUND(N52,Dins)) -> 20 | P52: =ROUND(N52/$P$14,Dins) -> 6.29 | Q52: =IF(A52>30000,ROUND(P52/$Q$14,Dins),ROUND(P52,Dins)) -> 5.33
A53: 30026 | B53: 43 | C53: MA | D53: MADERA TORNILLO CEPILLADA | E53: p2 | F53: =IF(AND($F$15=Datos!$AI$5,Datos!$C$9=Datos!$AI$10),IF(A53>30000,N53,ROUND(N53*Datos!$J$18,Dins)),IF(AND($F$15=Datos!$AI$5,Datos!$C$9=Datos!$AI$9),IF(A53>30000,O53,ROUND(O53*Datos!$J$18,Dins)),IF(AND($F$15=Datos!$AI$6,Datos!$C$9=Datos!$AI$10),IF(A53>30000,P53,ROUND(P53*Datos!$J$18,Dins)),IF(AND($F$15=Datos!$AI$6,Datos!$C$9=Datos!$AI$9),IF(A53>30000,Q53,ROUND(Q53*Datos!$J$18,Dins)))))) -> 3.9 | G53: 0 | H53: 0 | I53: 0 | J53: 0 | N53: 4.6 | O53: =IF(A53>30000,ROUND(N53/$O$14,Dins),ROUND(N53,Dins)) -> 3.9 | P53: =ROUND(N53/$P$14,Dins) -> 1.23 | Q53: =IF(A53>30000,ROUND(P53/$Q$14,Dins),ROUND(P53,Dins)) -> 1.04
A54: 60004 | B54: 49 | C54: EQ1 | D54: WINCHA DE 50m | E54: hm | F54: =IF(AND($F$15=Datos!$AI$5,Datos!$C$9=Datos!$AI$10),IF(A54>30000,N54,ROUND(N54*Datos!$J$18,Dins)),IF(AND($F$15=Datos!$AI$5,Datos!$C$9=Datos!$AI$9),IF(A54>30000,O54,ROUND(O54*Datos!$J$18,Dins)),IF(AND($F$15=Datos!$AI$6,Datos!$C$9=Datos!$AI$10),IF(A54>30000,P54,ROUND(P54*Datos!$J$18,Dins)),IF(AND($F$15=Datos!$AI$6,Datos!$C$9=Datos!$AI$9),IF(A54>30000,Q54,ROUND(Q54*Datos!$J$18,Dins)))))) -> 0.5 | N54: 0.59 | O54: =IF(A54>30000,ROUND(N54/$O$14,Dins),ROUND(N54,Dins)) -> 0.5 | P54: =ROUND(N54/$P$14,Dins) -> 0.16 | Q54: =IF(A54>30000,ROUND(P54/$Q$14,Dins),ROUND(P54,Dins)) -> 0.14
A55: 60005 | B55: 49 | C55: EQ1 | D55: NIVEL DE INGENIERO | E55: hm | F55: =IF(AND($F$15=Datos!$AI$5,Datos!$C$9=Datos!$AI$10),IF(A55>30000,N55,ROUND(N55*Datos!$J$18,Dins)),IF(AND($F$15=Datos!$AI$5,Datos!$C$9=Datos!$AI$9),IF(A55>30000,O55,ROUND(O55*Datos!$J$18,Dins)),IF(AND($F$15=Datos!$AI$6,Datos!$C$9=Datos!$AI$10),IF(A55>30000,P55,ROUND(P55*Datos!$J$18,Dins)),IF(AND($F$15=Datos!$AI$6,Datos!$C$9=Datos!$AI$9),IF(A55>30000,Q55,ROUND(Q55*Datos!$J$18,Dins)))))) -> 5 | N55: 5.9 | O55: =IF(A55>30000,ROUND(N55/$O$14,Dins),ROUND(N55,Dins)) -> 5 | P55: =ROUND(N55/$P$14,Dins) -> 1.57 | Q55: =IF(A55>30000,ROUND(P55/$Q$14,Dins),ROUND(P55,Dins)) -> 1.33
A56: 30027 | B56: 30 | C56: MA | D56: OCRE ROJO | E56: KG | F56: =IF(AND($F$15=Datos!$AI$5,Datos!$C$9=Datos!$AI$10),IF(A56>30000,N56,ROUND(N56*Datos!$J$18,Dins)),IF(AND($F$15=Datos!$AI$5,Datos!$C$9=Datos!$AI$9),IF(A56>30000,O56,ROUND(O56*Datos!$J$18,Dins)),IF(AND($F$15=Datos!$AI$6,Datos!$C$9=Datos!$AI$10),IF(A56>30000,P56,ROUND(P56*Datos!$J$18,Dins)),IF(AND($F$15=Datos!$AI$6,Datos!$C$9=Datos!$AI$9),IF(A56>30000,Q56,ROUND(Q56*Datos!$J$18,Dins)))))) -> 9.45 | G56: 0 | H56: 0 | I56: 0 | J56: 0 | N56: 11.15 | O56: =IF(A56>30000,ROUND(N56/$O$14,Dins),ROUND(N56,Dins)) -> 9.45 | P56: =ROUND(N56/$P$14,Dins) -> 2.97 | Q56: =IF(A56>30000,ROUND(P56/$Q$14,Dins),ROUND(P56,Dins)) -> 2.52
A57: 30028 | B57: 39 | C57: MA | D57: WINCHA | E57: UND | F57: =IF(AND($F$15=Datos!$AI$5,Datos!$C$9=Datos!$AI$10),IF(A57>30000,N57,ROUND(N57*Datos!$J$18,Dins)),IF(AND($F$15=Datos!$AI$5,Datos!$C$9=Datos!$AI$9),IF(A57>30000,O57,ROUND(O57*Datos!$J$18,Dins)),IF(AND($F$15=Datos!$AI$6,Datos!$C$9=Datos!$AI$10),IF(A57>30000,P57,ROUND(P57*Datos!$J$18,Dins)),IF(AND($F$15=Datos!$AI$6,Datos!$C$9=Datos!$AI$9),IF(A57>30000,Q57,ROUND(Q57*Datos!$J$18,Dins)))))) -> 80 | G57: 0 | H57: 0 | I57: 0 | J57: 0 | N57: 94.4 | O57: =IF(A57>30000,ROUND(N57/$O$14,Dins),ROUND(N57,Dins)) -> 80 | P57: =ROUND(N57/$P$14,Dins) -> 25.17 | Q57: =IF(A57>30000,ROUND(P57/$Q$14,Dins),ROUND(P57,Dins)) -> 21.33
A58: 60006 | B58: 49 | C58: EQ1 | D58: NIVEL | E58: hm | F58: =IF(AND($F$15=Datos!$AI$5,Datos!$C$9=Datos!$AI$10),IF(A58>30000,N58,ROUND(N58*Datos!$J$18,Dins)),IF(AND($F$15=Datos!$AI$5,Datos!$C$9=Datos!$AI$9),IF(A58>30000,O58,ROUND(O58*Datos!$J$18,Dins)),IF(AND($F$15=Datos!$AI$6,Datos!$C$9=Datos!$AI$10),IF(A58>30000,P58,ROUND(P58*Datos!$J$18,Dins)),IF(AND($F$15=Datos!$AI$6,Datos!$C$9=Datos!$AI$9),IF(A58>30000,Q58,ROUND(Q58*Datos!$J$18,Dins)))))) -> 5 | N58: 5.9 | O58: =IF(A58>30000,ROUND(N58/$O$14,Dins),ROUND(N58,Dins)) -> 5 | P58: =ROUND(N58/$P$14,Dins) -> 1.57 | Q58: =IF(A58>30000,ROUND(P58/$Q$14,Dins),ROUND(P58,Dins)) -> 1.33
A59: 30029 | B59: 39 | C59: MA | D59: ELABORACION DEL PLAN DE SEGURIDAD Y SALUD EN EL TRABAJO PARA LA OBRA | E59: GLB | F59: =IF(AND($F$15=Datos!$AI$5,Datos!$C$9=Datos!$AI$10),IF(A59>30000,N59,ROUND(N59*Datos!$J$18,Dins)),IF(AND($F$15=Datos!$AI$5,Datos!$C$9=Datos!$AI$9),IF(A59>30000,O59,ROUND(O59*Datos!$J$18,Dins)),IF(AND($F$15=Datos!$AI$6,Datos!$C$9=Datos!$AI$10),IF(A59>30000,P59,ROUND(P59*Datos!$J$18,Dins)),IF(AND($F$15=Datos!$AI$6,Datos!$C$9=Datos!$AI$9),IF(A59>30000,Q59,ROUND(Q59*Datos!$J$18,Dins)))))) -> 1271.19 | G59: 0 | H59: 0 | I59: 0 | J59: 0 | N59: 1500 | O59: =IF(A59>30000,ROUND(N59/$O$14,Dins),ROUND(N59,Dins)) -> 1271.19 | P59: =ROUND(N59/$P$14,Dins) -> 400 | Q59: =IF(A59>30000,ROUND(P59/$Q$14,Dins),ROUND(P59,Dins)) -> 338.98
A60: 30030 | B60: 39 | C60: MA | D60: PROTECTOR DE OIDOS | E60: PZA | F60: =IF(AND($F$15=Datos!$AI$5,Datos!$C$9=Datos!$AI$10),IF(A60>30000,N60,ROUND(N60*Datos!$J$18,Dins)),IF(AND($F$15=Datos!$AI$5,Datos!$C$9=Datos!$AI$9),IF(A60>30000,O60,ROUND(O60*Datos!$J$18,Dins)),IF(AND($F$15=Datos!$AI$6,Datos!$C$9=Datos!$AI$10),IF(A60>30000,P60,ROUND(P60*Datos!$J$18,Dins)),IF(AND($F$15=Datos!$AI$6,Datos!$C$9=Datos!$AI$9),IF(A60>30000,Q60,ROUND(Q60*Datos!$J$18,Dins)))))) -> 3.9 | G60: 0 | H60: 0 | I60: 0 | J60: 0 | N60: 4.6 | O60: =IF(A60>30000,ROUND(N60/$O$14,Dins),ROUND(N60,Dins)) -> 3.9 | P60: =ROUND(N60/$P$14,Dins) -> 1.23 | Q60: =IF(A60>30000,ROUND(P60/$Q$14,Dins),ROUND(P60,Dins)) -> 1.04
A61: 30031 | B61: 39 | C61: MA | D61: RESPIRADOR CONTRA POLVO | E61: UND | F61: =IF(AND($F$15=Datos!$AI$5,Datos!$C$9=Datos!$AI$10),IF(A61>30000,N61,ROUND(N61*Datos!$J$18,Dins)),IF(AND($F$15=Datos!$AI$5,Datos!$C$9=Datos!$AI$9),IF(A61>30000,O61,ROUND(O61*Datos!$J$18,Dins)),IF(AND($F$15=Datos!$AI$6,Datos!$C$9=Datos!$AI$10),IF(A61>30000,P61,ROUND(P61*Datos!$J$18,Dins)),IF(AND($F$15=Datos!$AI$6,Datos!$C$9=Datos!$AI$9),IF(A61>30000,Q61,ROUND(Q61*Datos!$J$18,Dins)))))) -> 2.2 | G61: 0 | H61: 0 | I61: 0 | J61: 0 | N61: 2.6 | O61: =IF(A61>30000,ROUND(N61/$O$14,Dins),ROUND(N61,Dins)) -> 2.2 | P61: =ROUND(N61/$P$14,Dins) -> 0.69 | Q61: =IF(A61>30000,ROUND(P61/$Q$14,Dins),ROUND(P61,Dins)) -> 0.58
A62: 30032 | B62: 39 | C62: MA | D62: CASCOS DE SEGURIDAD | E62: PZA | F62: =IF(AND($F$15=Datos!$AI$5,Datos!$C$9=Datos!$AI$10),IF(A62>30000,N62,ROUND(N62*Datos!$J$18,Dins)),IF(AND($F$15=Datos!$AI$5,Datos!$C$9=Datos!$AI$9),IF(A62>30000,O62,ROUND(O62*Datos!$J$18,Dins)),IF(AND($F$15=Datos!$AI$6,Datos!$C$9=Datos!$AI$10),IF(A62>30000,P62,ROUND(P62*Datos!$J$18,Dins)),IF(AND($F$15=Datos!$AI$6,Datos!$C$9=Datos!$AI$9),IF(A62>30000,Q62,ROUND(Q62*Datos!$J$18,Dins)))))) -> 15 | G62: 0 | H62: 0 | I62: 0 | J62: 0 | N62: 17.7 | O62: =IF(A62>30000,ROUND(N62/$O$14,Dins),ROUND(N62,Dins)) -> 15 | P62: =ROUND(N62/$P$14,Dins) -> 4.72 | Q62: =IF(A62>30000,ROUND(P62/$Q$14,Dins),ROUND(P62,Dins)) -> 4
A63: 30033 | B63: 39 | C63: MA | D63: CHALECOS | E63: PZA | F63: =IF(AND($F$15=Datos!$AI$5,Datos!$C$9=Datos!$AI$10),IF(A63>30000,N63,ROUND(N63*Datos!$J$18,Dins)),IF(AND($F$15=Datos!$AI$5,Datos!$C$9=Datos!$AI$9),IF(A63>30000,O63,ROUND(O63*Datos!$J$18,Dins)),IF(AND($F$15=Datos!$AI$6,Datos!$C$9=Datos!$AI$10),IF(A63>30000,P63,ROUND(P63*Datos!$J$18,Dins)),IF(AND($F$15=Datos!$AI$6,Datos!$C$9=Datos!$AI$9),IF(A63>30000,Q63,ROUND(Q63*Datos!$J$18,Dins)))))) -> 18.6 | G63: 0 | H63: 0 | I63: 0 | J63: 0 | N63: 21.95 | O63: =IF(A63>30000,ROUND(N63/$O$14,Dins),ROUND(N63,Dins)) -> 18.6 | P63: =ROUND(N63/$P$14,Dins) -> 5.85 | Q63: =IF(A63>30000,ROUND(P63/$Q$14,Dins),ROUND(P63,Dins)) -> 4.96
A64: 30034 | B64: 39 | C64: MA | D64: GUANTES DE CUERO | E64: PAR | F64: =IF(AND($F$15=Datos!$AI$5,Datos!$C$9=Datos!$AI$10),IF(A64>30000,N64,ROUND(N64*Datos!$J$18,Dins)),IF(AND($F$15=Datos!$AI$5,Datos!$C$9=Datos!$AI$9),IF(A64>30000,O64,ROUND(O64*Datos!$J$18,Dins)),IF(AND($F$15=Datos!$AI$6,Datos!$C$9=Datos!$AI$10),IF(A64>30000,P64,ROUND(P64*Datos!$J$18,Dins)),IF(AND($F$15=Datos!$AI$6,Datos!$C$9=Datos!$AI$9),IF(A64>30000,Q64,ROUND(Q64*Datos!$J$18,Dins)))))) -> 7.3 | G64: 0 | H64: 0 | I64: 0 | J64: 0 | N64: 8.61 | O64: =IF(A64>30000,ROUND(N64/$O$14,Dins),ROUND(N64,Dins)) -> 7.3 | P64: =ROUND(N64/$P$14,Dins) -> 2.3 | Q64: =IF(A64>30000,ROUND(P64/$Q$14,Dins),ROUND(P64,Dins)) -> 1.95
A65: 30035 | B65: 39 | C65: MA | D65: ZAPATOS DE SEGURIDAD | E65: PAR | F65: =IF(AND($F$15=Datos!$AI$5,Datos!$C$9=Datos!$AI$10),IF(A65>30000,N65,ROUND(N65*Datos!$J$18,Dins)),IF(AND($F$15=Datos!$AI$5,Datos!$C$9=Datos!$AI$9),IF(A65>30000,O65,ROUND(O65*Datos!$J$18,Dins)),IF(AND($F$15=Datos!$AI$6,Datos!$C$9=Datos!$AI$10),IF(A65>30000,P65,ROUND(P65*Datos!$J$18,Dins)),IF(AND($F$15=Datos!$AI$6,Datos!$C$9=Datos!$AI$9),IF(A65>30000,Q65,ROUND(Q65*Datos!$J$18,Dins)))))) -> 25 | G65: 0 | H65: 0 | I65: 0 | J65: 0 | N65: 29.5 | O65: =IF(A65>30000,ROUND(N65/$O$14,Dins),ROUND(N65,Dins)) -> 25 | P65: =ROUND(N65/$P$14,Dins) -> 7.87 | Q65: =IF(A65>30000,ROUND(P65/$Q$14,Dins),ROUND(P65,Dins)) -> 6.67
A66: 30036 | B66: 39 | C66: MA | D66: GUANTES DE JEBE | E66: PAR | F66: =IF(AND($F$15=Datos!$AI$5,Datos!$C$9=Datos!$AI$10),IF(A66>30000,N66,ROUND(N66*Datos!$J$18,Dins)),IF(AND($F$15=Datos!$AI$5,Datos!$C$9=Datos!$AI$9),IF(A66>30000,O66,ROUND(O66*Datos!$J$18,Dins)),IF(AND($F$15=Datos!$AI$6,Datos!$C$9=Datos!$AI$10),IF(A66>30000,P66,ROUND(P66*Datos!$J$18,Dins)),IF(AND($F$15=Datos!$AI$6,Datos!$C$9=Datos!$AI$9),IF(A66>30000,Q66,ROUND(Q66*Datos!$J$18,Dins)))))) -> 10 | G66: 0 | H66: 0 | I66: 0 | J66: 0 | N66: 11.8 | O66: =IF(A66>30000,ROUND(N66/$O$14,Dins),ROUND(N66,Dins)) -> 10 | P66: =ROUND(N66/$P$14,Dins) -> 3.15 | Q66: =IF(A66>30000,ROUND(P66/$Q$14,Dins),ROUND(P66,Dins)) -> 2.67
A67: 30037 | B67: 39 | C67: MA | D67: PANTALON Y CAMISA DE TRABAJO | E67: PZA | F67: =IF(AND($F$15=Datos!$AI$5,Datos!$C$9=Datos!$AI$10),IF(A67>30000,N67,ROUND(N67*Datos!$J$18,Dins)),IF(AND($F$15=Datos!$AI$5,Datos!$C$9=Datos!$AI$9),IF(A67>30000,O67,ROUND(O67*Datos!$J$18,Dins)),IF(AND($F$15=Datos!$AI$6,Datos!$C$9=Datos!$AI$10),IF(A67>30000,P67,ROUND(P67*Datos!$J$18,Dins)),IF(AND($F$15=Datos!$AI$6,Datos!$C$9=Datos!$AI$9),IF(A67>30000,Q67,ROUND(Q67*Datos!$J$18,Dins)))))) -> 50 | G67: 0 | H67: 0 | I67: 0 | J67: 0 | N67: 59 | O67: =IF(A67>30000,ROUND(N67/$O$14,Dins),ROUND(N67,Dins)) -> 50 | P67: =ROUND(N67/$P$14,Dins) -> 15.73 | Q67: =IF(A67>30000,ROUND(P67/$Q$14,Dins),ROUND(P67,Dins)) -> 13.33
A68: 30038 | B68: 39 | C68: MA | D68: LENTES DE PROTECCION | E68: PZA | F68: =IF(AND($F$15=Datos!$AI$5,Datos!$C$9=Datos!$AI$10),IF(A68>30000,N68,ROUND(N68*Datos!$J$18,Dins)),IF(AND($F$15=Datos!$AI$5,Datos!$C$9=Datos!$AI$9),IF(A68>30000,O68,ROUND(O68*Datos!$J$18,Dins)),IF(AND($F$15=Datos!$AI$6,Datos!$C$9=Datos!$AI$10),IF(A68>30000,P68,ROUND(P68*Datos!$J$18,Dins)),IF(AND($F$15=Datos!$AI$6,Datos!$C$9=Datos!$AI$9),IF(A68>30000,Q68,ROUND(Q68*Datos!$J$18,Dins)))))) -> 3.2 | G68: 0 | H68: 0 | I68: 0 | J68: 0 | N68: 3.78 | O68: =IF(A68>30000,ROUND(N68/$O$14,Dins),ROUND(N68,Dins)) -> 3.2 | P68: =ROUND(N68/$P$14,Dins) -> 1.01 | Q68: =IF(A68>30000,ROUND(P68/$Q$14,Dins),ROUND(P68,Dins)) -> 0.86
A69: 77501 | B69: 48 | C69: EQ2 | D69: ARNES DE SEGURIDAD CON LINEA DE VIDA | E69: UND | F69: =IF(AND($F$15=Datos!$AI$5,Datos!$C$9=Datos!$AI$10),IF(A69>30000,N69,ROUND(N69*Datos!$J$18,Dins)),IF(AND($F$15=Datos!$AI$5,Datos!$C$9=Datos!$AI$9),IF(A69>30000,O69,ROUND(O69*Datos!$J$18,Dins)),IF(AND($F$15=Datos!$AI$6,Datos!$C$9=Datos!$AI$10),IF(A69>30000,P69,ROUND(P69*Datos!$J$18,Dins)),IF(AND($F$15=Datos!$AI$6,Datos!$C$9=Datos!$AI$9),IF(A69>30000,Q69,ROUND(Q69*Datos!$J$18,Dins)))))) -> 250 | G69: 0 | H69: 0 | I69: 0 | J69: 0 | N69: 295 | O69: =IF(A69>30000,ROUND(N69/$O$14,Dins),ROUND(N69,Dins)) -> 250 | P69: =ROUND(N69/$P$14,Dins) -> 78.67 | Q69: =IF(A69>30000,ROUND(P69/$Q$14,Dins),ROUND(P69,Dins)) -> 66.67
A70: 30039 | B70: 39 | C70: MA | D70: SOGA DE NYLON DE 1/2" | E70: M | F70: =IF(AND($F$15=Datos!$AI$5,Datos!$C$9=Datos!$AI$10),IF(A70>30000,N70,ROUND(N70*Datos!$J$18,Dins)),IF(AND($F$15=Datos!$AI$5,Datos!$C$9=Datos!$AI$9),IF(A70>30000,O70,ROUND(O70*Datos!$J$18,Dins)),IF(AND($F$15=Datos!$AI$6,Datos!$C$9=Datos!$AI$10),IF(A70>30000,P70,ROUND(P70*Datos!$J$18,Dins)),IF(AND($F$15=Datos!$AI$6,Datos!$C$9=Datos!$AI$9),IF(A70>30000,Q70,ROUND(Q70*Datos!$J$18,Dins)))))) -> 0.5 | G70: 0 | H70: 0 | I70: 0 | J70: 0 | N70: 0.59 | O70: =IF(A70>30000,ROUND(N70/$O$14,Dins),ROUND(N70,Dins)) -> 0.5 | P70: =ROUND(N70/$P$14,Dins) -> 0.16 | Q70: =IF(A70>30000,ROUND(P70/$Q$14,Dins),ROUND(P70,Dins)) -> 0.14
... A79: 77503 | B79: 48 | C79: EQ2 | D79: CABALLETES DE MADERA PARA TRAFICO | E79: PZA | F79: =IF(AND($F$15=Datos!$AI$5,Datos!$C$9=Datos!$AI$10),IF(A79>30000,N79,ROUND(N79*Datos!$J$18,Dins)),IF(AND($F$15=Datos!$AI$5,Datos!$C$9=Datos!$AI$9),IF(A79>30000,O79,ROUND(O79*Datos!$J$18,Dins)),IF(AND($F$15=Datos!$AI$6,Datos!$C$9=Datos!$AI$10),IF(A79>30000,P79,ROUND(P79*Datos!$J$18,Dins)),IF(AND($F$15=Datos!$AI$6,Datos!$C$9=Datos!$AI$9),IF(A79>30000,Q79,ROUND(Q79*Datos!$J$18,Dins)))))) -> 80 | G79: 0 | H79: 0 | I79: 0 | J79: 0 | N79: 94.4 | O79: =IF(A79>30000,ROUND(N79/$O$14,Dins),ROUND(N79,Dins)) -> 80 | P79: =ROUND(N79/$P$14,Dins) -> 25.17 | Q79: =IF(A79>30000,ROUND(P79/$Q$14,Dins),ROUND(P79,Dins)) -> 21.33
A80: 80003 | B80: 39 | C80: SERVICIO | D80: CAPACITACION EN SEGURIDAD Y SALUD | E80: GLB | F80: =IF(AND($F$15=Datos!$AI$5,Datos!$C$9=Datos!$AI$10),IF(A80>30000,N80,ROUND(N80*Datos!$J$18,Dins)),IF(AND($F$15=Datos!$AI$5,Datos!$C$9=Datos!$AI$9),IF(A80>30000,O80,ROUND(O80*Datos!$J$18,Dins)),IF(AND($F$15=Datos!$AI$6,Datos!$C$9=Datos!$AI$10),IF(A80>30000,P80,ROUND(P80*Datos!$J$18,Dins)),IF(AND($F$15=Datos!$AI$6,Datos!$C$9=Datos!$AI$9),IF(A80>30000,Q80,ROUND(Q80*Datos!$J$18,Dins)))))) -> 1000 | N80: 1180 | O80: =IF(A80>30000,ROUND(N80/$O$14,Dins),ROUND(N80,Dins)) -> 1000 | P80: =ROUND(N80/$P$14,Dins) -> 314.67 | Q80: =IF(A80>30000,ROUND(P80/$Q$14,Dins),ROUND(P80,Dins)) -> 266.67
A81: 30047 | B81: 39 | C81: MA | D81: FRAZADA | E81: UND | F81: =IF(AND($F$15=Datos!$AI$5,Datos!$C$9=Datos!$AI$10),IF(A81>30000,N81,ROUND(N81*Datos!$J$18,Dins)),IF(AND($F$15=Datos!$AI$5,Datos!$C$9=Datos!$AI$9),IF(A81>30000,O81,ROUND(O81*Datos!$J$18,Dins)),IF(AND($F$15=Datos!$AI$6,Datos!$C$9=Datos!$AI$10),IF(A81>30000,P81,ROUND(P81*Datos!$J$18,Dins)),IF(AND($F$15=Datos!$AI$6,Datos!$C$9=Datos!$AI$9),IF(A81>30000,Q81,ROUND(Q81*Datos!$J$18,Dins)))))) -> 30 | G81: 0 | H81: 0 | I81: 0 | J81: 0 | N81: 35.4 | O81: =IF(A81>30000,ROUND(N81/$O$14,Dins),ROUND(N81,Dins)) -> 30 | P81: =ROUND(N81/$P$14,Dins) -> 9.44 | Q81: =IF(A81>30000,ROUND(P81/$Q$14,Dins),ROUND(P81,Dins)) -> 8
A82: 77504 | B82: 48 | C82: EQ2 | D82: BOTIQUIN DE PRIMEROS AUXILIOS | E82: UND | F82: =IF(AND($F$15=Datos!$AI$5,Datos!$C$9=Datos!$AI$10),IF(A82>30000,N82,ROUND(N82*Datos!$J$18,Dins)),IF(AND($F$15=Datos!$AI$5,Datos!$C$9=Datos!$AI$9),IF(A82>30000,O82,ROUND(O82*Datos!$J$18,Dins)),IF(AND($F$15=Datos!$AI$6,Datos!$C$9=Datos!$AI$10),IF(A82>30000,P82,ROUND(P82*Datos!$J$18,Dins)),IF(AND($F$15=Datos!$AI$6,Datos!$C$9=Datos!$AI$9),IF(A82>30000,Q82,ROUND(Q82*Datos!$J$18,Dins)))))) -> 100 | G82: 0 | H82: 0 | I82: 0 | J82: 0 | N82: 118 | O82: =IF(A82>30000,ROUND(N82/$O$14,Dins),ROUND(N82,Dins)) -> 100 | P82: =ROUND(N82/$P$14,Dins) -> 31.47 | Q82: =IF(A82>30000,ROUND(P82/$Q$14,Dins),ROUND(P82,Dins)) -> 26.67
A83: 77505 | B83: 48 | C83: EQ2 | D83: CAMILLA RIGIDA | E83: UND | F83: =IF(AND($F$15=Datos!$AI$5,Datos!$C$9=Datos!$AI$10),IF(A83>30000,N83,ROUND(N83*Datos!$J$18,Dins)),IF(AND($F$15=Datos!$AI$5,Datos!$C$9=Datos!$AI$9),IF(A83>30000,O83,ROUND(O83*Datos!$J$18,Dins)),IF(AND($F$15=Datos!$AI$6,Datos!$C$9=Datos!$AI$10),IF(A83>30000,P83,ROUND(P83*Datos!$J$18,Dins)),IF(AND($F$15=Datos!$AI$6,Datos!$C$9=Datos!$AI$9),IF(A83>30000,Q83,ROUND(Q83*Datos!$J$18,Dins)))))) -> 250 | G83: 0 | H83: 0 | I83: 0 | J83: 0 | N83: 295 | O83: =IF(A83>30000,ROUND(N83/$O$14,Dins),ROUND(N83,Dins)) -> 250 | P83: =ROUND(N83/$P$14,Dins) -> 78.67 | Q83: =IF(A83>30000,ROUND(P83/$Q$14,Dins),ROUND(P83,Dins)) -> 66.67
A84: 77506 | B84: 49 | C84: EQ2 | D84: EXTINGUIDOR DE 6 KG PQS ABC | E84: UND | F84: =IF(AND($F$15=Datos!$AI$5,Datos!$C$9=Datos!$AI$10),IF(A84>30000,N84,ROUND(N84*Datos!$J$18,Dins)),IF(AND($F$15=Datos!$AI$5,Datos!$C$9=Datos!$AI$9),IF(A84>30000,O84,ROUND(O84*Datos!$J$18,Dins)),IF(AND($F$15=Datos!$AI$6,Datos!$C$9=Datos!$AI$10),IF(A84>30000,P84,ROUND(P84*Datos!$J$18,Dins)),IF(AND($F$15=Datos!$AI$6,Datos!$C$9=Datos!$AI$9),IF(A84>30000,Q84,ROUND(Q84*Datos!$J$18,Dins)))))) -> 80 | G84: 0 | H84: 0 | I84: 0 | J84: 0 | N84: 94.4 | O84: =IF(A84>30000,ROUND(N84/$O$14,Dins),ROUND(N84,Dins)) -> 80 | P84: =ROUND(N84/$P$14,Dins) -> 25.17 | Q84: =IF(A84>30000,ROUND(P84/$Q$14,Dins),ROUND(P84,Dins)) -> 21.33
A85: 80004 | B85: 39 | C85: SERVICIO | D85: SERVICIO DE AMBULANCIA | E85: hm | F85: =IF(AND($F$15=Datos!$AI$5,Datos!$C$9=Datos!$AI$10),IF(A85>30000,N85,ROUND(N85*Datos!$J$18,Dins)),IF(AND($F$15=Datos!$AI$5,Datos!$C$9=Datos!$AI$9),IF(A85>30000,O85,ROUND(O85*Datos!$J$18,Dins)),IF(AND($F$15=Datos!$AI$6,Datos!$C$9=Datos!$AI$10),IF(A85>30000,P85,ROUND(P85*Datos!$J$18,Dins)),IF(AND($F$15=Datos!$AI$6,Datos!$C$9=Datos!$AI$9),IF(A85>30000,Q85,ROUND(Q85*Datos!$J$18,Dins)))))) -> 200 | N85: 236 | O85: =IF(A85>30000,ROUND(N85/$O$14,Dins),ROUND(N85,Dins)) -> 200 | P85: =ROUND(N85/$P$14,Dins) -> 62.93 | Q85: =IF(A85>30000,ROUND(P85/$Q$14,Dins),ROUND(P85,Dins)) -> 53.33
A86: 10007 | B86: 47 | C86: MO1 | D86: OPERADOR DE EQUIPO PESADO | E86: hh | F86: =IF(AND($F$15=Datos!$AI$5,Datos!$C$9=Datos!$AI$10),IF(A86>30000,N86,ROUND(N86*Datos!$J$18,Dins)),IF(AND($F$15=Datos!$AI$5,Datos!$C$9=Datos!$AI$9),IF(A86>30000,O86,ROUND(O86*Datos!$J$18,Dins)),IF(AND($F$15=Datos!$AI$6,Datos!$C$9=Datos!$AI$10),IF(A86>30000,P86,ROUND(P86*Datos!$J$18,Dins)),IF(AND($F$15=Datos!$AI$6,Datos!$C$9=Datos!$AI$9),IF(A86>30000,Q86,ROUND(Q86*Datos!$J$18,Dins)))))) -> 20.81 | N86: 20.81 | O86: =IF(A86>30000,ROUND(N86/$O$14,Dins),ROUND(N86,Dins)) -> 20.81 | P86: =ROUND(N86/$P$14,Dins) -> 5.55 | Q86: =IF(A86>30000,ROUND(P86/$Q$14,Dins),ROUND(P86,Dins)) -> 5.55
A87: 10008 | B87: 47 | C87: MO1 | D87: OFICIAL | E87: hh | F87: =IF(AND($F$15=Datos!$AI$5,Datos!$C$9=Datos!$AI$10),IF(A87>30000,N87,ROUND(N87*Datos!$J$18,Dins)),IF(AND($F$15=Datos!$AI$5,Datos!$C$9=Datos!$AI$9),IF(A87>30000,O87,ROUND(O87*Datos!$J$18,Dins)),IF(AND($F$15=Datos!$AI$6,Datos!$C$9=Datos!$AI$10),IF(A87>30000,P87,ROUND(P87*Datos!$J$18,Dins)),IF(AND($F$15=Datos!$AI$6,Datos!$C$9=Datos!$AI$9),IF(A87>30000,Q87,ROUND(Q87*Datos!$J$18,Dins)))))) -> 17.09 | N87: 17.09 | O87: =IF(A87>30000,ROUND(N87/$O$14,Dins),ROUND(N87,Dins)) -> 17.09 | P87: =ROUND(N87/$P$14,Dins) -> 4.56 | Q87: =IF(A87>30000,ROUND(P87/$Q$14,Dins),ROUND(P87,Dins)) -> 4.56
A88: 60007 | B88: 49 | C88: EQ1 | D88: CARGADOR RETROEXCAVADOR 62 HP 1 YD3 | E88: hm | F88: =IF(AND($F$15=Datos!$AI$5,Datos!$C$9=Datos!$AI$10),IF(A88>30000,N88,ROUND(N88*Datos!$J$18,Dins)),IF(AND($F$15=Datos!$AI$5,Datos!$C$9=Datos!$AI$9),IF(A88>30000,O88,ROUND(O88*Datos!$J$18,Dins)),IF(AND($F$15=Datos!$AI$6,Datos!$C$9=Datos!$AI$10),IF(A88>30000,P88,ROUND(P88*Datos!$J$18,Dins)),IF(AND($F$15=Datos!$AI$6,Datos!$C$9=Datos!$AI$9),IF(A88>30000,Q88,ROUND(Q88*Datos!$J$18,Dins)))))) -> 270 | N88: 318.6 | O88: =IF(A88>30000,ROUND(N88/$O$14,Dins),ROUND(N88,Dins)) -> 270 | P88: =ROUND(N88/$P$14,Dins) -> 84.96 | Q88: =IF(A88>30000,ROUND(P88/$Q$14,Dins),ROUND(P88,Dins)) -> 72
A89: 60008 | B89: 49 | C89: EQ1 | D89: COMPACTADOR VIBR. TIPO PLANCHA 5.8 HP | E89: hm | F89: =IF(AND($F$15=Datos!$AI$5,Datos!$C$9=Datos!$AI$10),IF(A89>30000,N89,ROUND(N89*Datos!$J$18,Dins)),IF(AND($F$15=Datos!$AI$5,Datos!$C$9=Datos!$AI$9),IF(A89>30000,O89,ROUND(O89*Datos!$J$18,Dins)),IF(AND($F$15=Datos!$AI$6,Datos!$C$9=Datos!$AI$10),IF(A89>30000,P89,ROUND(P89*Datos!$J$18,Dins)),IF(AND($F$15=Datos!$AI$6,Datos!$C$9=Datos!$AI$9),IF(A89>30000,Q89,ROUND(Q89*Datos!$J$18,Dins)))))) -> 22.95 | N89: 27.08 | O89: =IF(A89>30000,ROUND(N89/$O$14,Dins),ROUND(N89,Dins)) -> 22.95 | P89: =ROUND(N89/$P$14,Dins) -> 7.22 | Q89: =IF(A89>30000,ROUND(P89/$Q$14,Dins),ROUND(P89,Dins)) -> 6.12
A90: 30048 | B90: 43 | C90: MA | D90: REGLA DE MADERA | E90: p2 | F90: =IF(AND($F$15=Datos!$AI$5,Datos!$C$9=Datos!$AI$10),IF(A90>30000,N90,ROUND(N90*Datos!$J$18,Dins)),IF(AND($F$15=Datos!$AI$5,Datos!$C$9=Datos!$AI$9),IF(A90>30000,O90,ROUND(O90*Datos!$J$18,Dins)),IF(AND($F$15=Datos!$AI$6,Datos!$C$9=Datos!$AI$10),IF(A90>30000,P90,ROUND(P90*Datos!$J$18,Dins)),IF(AND($F$15=Datos!$AI$6,Datos!$C$9=Datos!$AI$9),IF(A90>30000,Q90,ROUND(Q90*Datos!$J$18,Dins)))))) -> 8.5 | G90: 0 | H90: 0 | I90: 0 | J90: 0 | N90: 10.03 | O90: =IF(A90>30000,ROUND(N90/$O$14,Dins),ROUND(N90,Dins)) -> 8.5 | P90: =ROUND(N90/$P$14,Dins) -> 2.67 | Q90: =IF(A90>30000,ROUND(P90/$Q$14,Dins),ROUND(P90,Dins)) -> 2.26
A91: 80005 | B91: 39 | C91: SERVICIO | D91: ELIMINACION DE MATERIAL EXCEDENTE, MANUAL | E91: M3 | F91: =IF(AND($F$15=Datos!$AI$5,Datos!$C$9=Datos!$AI$10),IF(A91>30000,N91,ROUND(N91*Datos!$J$18,Dins)),IF(AND($F$15=Datos!$AI$5,Datos!$C$9=Datos!$AI$9),IF(A91>30000,O91,ROUND(O91*Datos!$J$18,Dins)),IF(AND($F$15=Datos!$AI$6,Datos!$C$9=Datos!$AI$10),IF(A91>30000,P91,ROUND(P91*Datos!$J$18,Dins)),IF(AND($F$15=Datos!$AI$6,Datos!$C$9=Datos!$AI$9),IF(A91>30000,Q91,ROUND(Q91*Datos!$J$18,Dins)))))) -> 35 | N91: 41.3 | O91: =IF(A91>30000,ROUND(N91/$O$14,Dins),ROUND(N91,Dins)) -> 35 | P91: =ROUND(N91/$P$14,Dins) -> 11.01 | Q91: =IF(A91>30000,ROUND(P91/$Q$14,Dins),ROUND(P91,Dins)) -> 9.33
A92: 30049 | B92: 5 | C92: MA | D92: MATERIAL AFIRMADO | E92: M3 | F92: =IF(AND($F$15=Datos!$AI$5,Datos!$C$9=Datos!$AI$10),IF(A92>30000,N92,ROUND(N92*Datos!$J$18,Dins)),IF(AND($F$15=Datos!$AI$5,Datos!$C$9=Datos!$AI$9),IF(A92>30000,O92,ROUND(O92*Datos!$J$18,Dins)),IF(AND($F$15=Datos!$AI$6,Datos!$C$9=Datos!$AI$10),IF(A92>30000,P92,ROUND(P92*Datos!$J$18,Dins)),IF(AND($F$15=Datos!$AI$6,Datos!$C$9=Datos!$AI$9),IF(A92>30000,Q92,ROUND(Q92*Datos!$J$18,Dins)))))) -> 30 | G92: 0 | H92: 0 | I92: 0 | J92: 0 | N92: 35.4 | O92: =IF(A92>30000,ROUND(N92/$O$14,Dins),ROUND(N92,Dins)) -> 30 | P92: =ROUND(N92/$P$14,Dins) -> 9.44 | Q92: =IF(A92>30000,ROUND(P92/$Q$14,Dins),ROUND(P92,Dins)) -> 8
A93: 60009 | B93: 49 | C93: EQ1 | D93: PLANCHA COMPACTADORA | E93: hm | F93: =IF(AND($F$15=Datos!$AI$5,Datos!$C$9=Datos!$AI$10),IF(A93>30000,N93,ROUND(N93*Datos!$J$18,Dins)),IF(AND($F$15=Datos!$AI$5,Datos!$C$9=Datos!$AI$9),IF(A93>30000,O93,ROUND(O93*Datos!$J$18,Dins)),IF(AND($F$15=Datos!$AI$6,Datos!$C$9=Datos!$AI$10),IF(A93>30000,P93,ROUND(P93*Datos!$J$18,Dins)),IF(AND($F$15=Datos!$AI$6,Datos!$C$9=Datos!$AI$9),IF(A93>30000,Q93,ROUND(Q93*Datos!$J$18,Dins)))))) -> 22.95 | N93: 27.08 | O93: =IF(A93>30000,ROUND(N93/$O$14,Dins),ROUND(N93,Dins)) -> 22.95 | P93: =ROUND(N93/$P$14,Dins) -> 7.22 | Q93: =IF(A93>30000,ROUND(P93/$Q$14,Dins),ROUND(P93,Dins)) -> 6.12
A94: 30050 | B94: 5 | C94: MA | D94: PIEDRA GRANDE DE 8" | E94: M3 | F94: =IF(AND($F$15=Datos!$AI$5,Datos!$C$9=Datos!$AI$10),IF(A94>30000,N94,ROUND(N94*Datos!$J$18,Dins)),IF(AND($F$15=Datos!$AI$5,Datos!$C$9=Datos!$AI$9),IF(A94>30000,O94,ROUND(O94*Datos!$J$18,Dins)),IF(AND($F$15=Datos!$AI$6,Datos!$C$9=Datos!$AI$10),IF(A94>30000,P94,ROUND(P94*Datos!$J$18,Dins)),IF(AND($F$15=Datos!$AI$6,Datos!$C$9=Datos!$AI$9),IF(A94>30000,Q94,ROUND(Q94*Datos!$J$18,Dins)))))) -> 45 | G94: 0 | H94: 0 | I94: 0 | J94: 0 | N94: 53.1 | O94: =IF(A94>30000,ROUND(N94/$O$14,Dins),ROUND(N94,Dins)) -> 45 | P94: =ROUND(N94/$P$14,Dins) -> 14.16 | Q94: =IF(A94>30000,ROUND(P94/$Q$14,Dins),ROUND(P94,Dins)) -> 12
A95: 60010 | B95: 49 | C95: EQ1 | D95: MEZCLADORA CONCRETO TAMBOR 18HP 11P3 | E95: hm | F95: =IF(AND($F$15=Datos!$AI$5,Datos!$C$9=Datos!$AI$10),IF(A95>30000,N95,ROUND(N95*Datos!$J$18,Dins)),IF(AND($F$15=Datos!$AI$5,Datos!$C$9=Datos!$AI$9),IF(A95>30000,O95,ROUND(O95*Datos!$J$18,Dins)),IF(AND($F$15=Datos!$AI$6,Datos!$C$9=Datos!$AI$10),IF(A95>30000,P95,ROUND(P95*Datos!$J$18,Dins)),IF(AND($F$15=Datos!$AI$6,Datos!$C$9=Datos!$AI$9),IF(A95>30000,Q95,ROUND(Q95*Datos!$J$18,Dins)))))) -> 31.5 | N95: 37.17 | O95: =IF(A95>30000,ROUND(N95/$O$14,Dins),ROUND(N95,Dins)) -> 31.5 | P95: =ROUND(N95/$P$14,Dins) -> 9.91 | Q95: =IF(A95>30000,ROUND(P95/$Q$14,Dins),ROUND(P95,Dins)) -> 8.4
A96: 30051 | B96: 2 | C96: MA | D96: CLAVOS PARA MADERA C/C 3" | E96: KG | F96: =IF(AND($F$15=Datos!$AI$5,Datos!$C$9=Datos!$AI$10),IF(A96>30000,N96,ROUND(N96*Datos!$J$18,Dins)),IF(AND($F$15=Datos!$AI$5,Datos!$C$9=Datos!$AI$9),IF(A96>30000,O96,ROUND(O96*Datos!$J$18,Dins)),IF(AND($F$15=Datos!$AI$6,Datos!$C$9=Datos!$AI$10),IF(A96>30000,P96,ROUND(P96*Datos!$J$18,Dins)),IF(AND($F$15=Datos!$AI$6,Datos!$C$9=Datos!$AI$9),IF(A96>30000,Q96,ROUND(Q96*Datos!$J$18,Dins)))))) -> 3.5 | G96: 0 | H96: 0 | I96: 0 | J96: 0 | N96: 4.13 | O96: =IF(A96>30000,ROUND(N96/$O$14,Dins),ROUND(N96,Dins)) -> 3.5 | P96: =ROUND(N96/$P$14,Dins) -> 1.1 | Q96: =IF(A96>30000,ROUND(P96/$Q$14,Dins),ROUND(P96,Dins)) -> 0.93
A97: 30052 | B97: 2 | C97: MA | D97: ALAMBRE NEGRO N°8 | E97: KG | F97: =IF(AND($F$15=Datos!$AI$5,Datos!$C$9=Datos!$AI$10),IF(A97>30000,N97,ROUND(N97*Datos!$J$18,Dins)),IF(AND($F$15=Datos!$AI$5,Datos!$C$9=Datos!$AI$9),IF(A97>30000,O97,ROUND(O97*Datos!$J$18,Dins)),IF(AND($F$15=Datos!$AI$6,Datos!$C$9=Datos!$AI$10),IF(A97>30000,P97,ROUND(P97*Datos!$J$18,Dins)),IF(AND($F$15=Datos!$AI$6,Datos!$C$9=Datos!$AI$9),IF(A97>30000,Q97,ROUND(Q97*Datos!$J$18,Dins)))))) -> 3.5 | G97: 0 | H97: 0 | I97: 0 | J97: 0 | N97: 4.13 | O97: =IF(A97>30000,ROUND(N97/$O$14,Dins),ROUND(N97,Dins)) -> 3.5 | P97: =ROUND(N97/$P$14,Dins) -> 1.1 | Q97: =IF(A97>30000,ROUND(P97/$Q$14,Dins),ROUND(P97,Dins)) -> 0.93
A98: 30053 | B98: 43 | C98: MA | D98: MADERA TORNILLO | E98: p2 | F98: =IF(AND($F$15=Datos!$AI$5,Datos!$C$9=Datos!$AI$10),IF(A98>30000,N98,ROUND(N98*Datos!$J$18,Dins)),IF(AND($F$15=Datos!$AI$5,Datos!$C$9=Datos!$AI$9),IF(A98>30000,O98,ROUND(O98*Datos!$J$18,Dins)),IF(AND($F$15=Datos!$AI$6,Datos!$C$9=Datos!$AI$10),IF(A98>30000,P98,ROUND(P98*Datos!$J$18,Dins)),IF(AND($F$15=Datos!$AI$6,Datos!$C$9=Datos!$AI$9),IF(A98>30000,Q98,ROUND(Q98*Datos!$J$18,Dins)))))) -> 3.9 | G98: 0 | H98: 0 | I98: 0 | J98: 0 | N98: 4.6 | O98: =IF(A98>30000,ROUND(N98/$O$14,Dins),ROUND(N98,Dins)) -> 3.9 | P98: =ROUND(N98/$P$14,Dins) -> 1.23 | Q98: =IF(A98>30000,ROUND(P98/$Q$14,Dins),ROUND(P98,Dins)) -> 1.04
A99: 30054 | B99: 2 | C99: MA | D99: ALAMBRE NEGRO RECOCIDO # 8 | E99: KG | F99: =IF(AND($F$15=Datos!$AI$5,Datos!$C$9=Datos!$AI$10),IF(A99>30000,N99,ROUND(N99*Datos!$J$18,Dins)),IF(AND($F$15=Datos!$AI$5,Datos!$C$9=Datos!$AI$9),IF(A99>30000,O99,ROUND(O99*Datos!$J$18,Dins)),IF(AND($F$15=Datos!$AI$6,Datos!$C$9=Datos!$AI$10),IF(A99>30000,P99,ROUND(P99*Datos!$J$18,Dins)),IF(AND($F$15=Datos!$AI$6,Datos!$C$9=Datos!$AI$9),IF(A99>30000,Q99,ROUND(Q99*Datos!$J$18,Dins)))))) -> 3.5 | G99: 0 | H99: 0 | I99: 0 | J99: 0 | N99: 4.13 | O99: =IF(A99>30000,ROUND(N99/$O$14,Dins),ROUND(N99,Dins)) -> 3.5 | P99: =ROUND(N99/$P$14,Dins) -> 1.1 | Q99: =IF(A99>30000,ROUND(P99/$Q$14,Dins),ROUND(P99,Dins)) -> 0.93
A100: 30055 | B100: 43 | C100: MA | D100: MADERA TORNILLO INC.CORTE P/ENCOFRADO | E100: p2 | F100: =IF(AND($F$15=Datos!$AI$5,Datos!$C$9=Datos!$AI$10),IF(A100>30000,N100,ROUND(N100*Datos!$J$18,Dins)),IF(AND($F$15=Datos!$AI$5,Datos!$C$9=Datos!$AI$9),IF(A100>30000,O100,ROUND(O100*Datos!$J$18,Dins)),IF(AND($F$15=Datos!$AI$6,Datos!$C$9=Datos!$AI$10),IF(A100>30000,P100,ROUND(P100*Datos!$J$18,Dins)),IF(AND($F$15=Datos!$AI$6,Datos!$C$9=Datos!$AI$9),IF(A100>30000,Q100,ROUND(Q100*Datos!$J$18,Dins)))))) -> 3.9 | G100: 0 | H100: 0 | I100: 0 | J100: 0 | N100: 4.6 | O100: =IF(A100>30000,ROUND(N100/$O$14,Dins),ROUND(N100,Dins)) -> 3.9 | P100: =ROUND(N100/$P$14,Dins) -> 1.23 | Q100: =IF(A100>30000,ROUND(P100/$Q$14,Dins),ROUND(P100,Dins)) -> 1.04
A101: 30056 | B101: 4 | C101: MA | D101: ARENA GRUESA | E101: M3 | F101: =IF(AND($F$15=Datos!$AI$5,Datos!$C$9=Datos!$AI$10),IF(A101>30000,N101,ROUND(N101*Datos!$J$18,Dins)),IF(AND($F$15=Datos!$AI$5,Datos!$C$9=Datos!$AI$9),IF(A101>30000,O101,ROUND(O101*Datos!$J$18,Dins)),IF(AND($F$15=Datos!$AI$6,Datos!$C$9=Datos!$AI$10),IF(A101>30000,P101,ROUND(P101*Datos!$J$18,Dins)),IF(AND($F$15=Datos!$AI$6,Datos!$C$9=Datos!$AI$9),IF(A101>30000,Q101,ROUND(Q101*Datos!$J$18,Dins)))))) -> 45 | G101: 0 | H101: 0 | I101: 0 | J101: 0 | N101: 53.1 | O101: =IF(A101>30000,ROUND(N101/$O$14,Dins),ROUND(N101,Dins)) -> 45 | P101: =ROUND(N101/$P$14,Dins) -> 14.16 | Q101: =IF(A101>30000,ROUND(P101/$Q$14,Dins),ROUND(P101,Dins)) -> 12
A102: 30057 | B102: 5 | C102: MA | D102: PIEDRA ZARANDEADA DE 1" | E102: M3 | F102: =IF(AND($F$15=Datos!$AI$5,Datos!$C$9=Datos!$AI$10),IF(A102>30000,N102,ROUND(N102*Datos!$J$18,Dins)),IF(AND($F$15=Datos!$AI$5,Datos!$C$9=Datos!$AI$9),IF(A102>30000,O102,ROUND(O102*Datos!$J$18,Dins)),IF(AND($F$15=Datos!$AI$6,Datos!$C$9=Datos!$AI$10),IF(A102>30000,P102,ROUND(P102*Datos!$J$18,Dins)),IF(AND($F$15=Datos!$AI$6,Datos!$C$9=Datos!$AI$9),IF(A102>30000,Q102,ROUND(Q102*Datos!$J$18,Dins)))))) -> 45 | G102: 0 | H102: 0 | I102: 0 | J102: 0 | N102: 53.1 | O102: =IF(A102>30000,ROUND(N102/$O$14,Dins),ROUND(N102,Dins)) -> 45 | P102: =ROUND(N102/$P$14,Dins) -> 14.16 | Q102: =IF(A102>30000,ROUND(P102/$Q$14,Dins),ROUND(P102,Dins)) -> 12
A103: 30058 | B103: 21 | C103: MA | D103: CEMENTO PORTLAND TIPO I (EN FCA.)S-PUB | E103: BOL | F103: =IF(AND($F$15=Datos!$AI$5,Datos!$C$9=Datos!$AI$10),IF(A103>30000,N103,ROUND(N103*Datos!$J$18,Dins)),IF(AND($F$15=Datos!$AI$5,Datos!$C$9=Datos!$AI$9),IF(A103>30000,O103,ROUND(O103*Datos!$J$18,Dins)),IF(AND($F$15=Datos!$AI$6,Datos!$C$9=Datos!$AI$10),IF(A103>30000,P103,ROUND(P103*Datos!$J$18,Dins)),IF(AND($F$15=Datos!$AI$6,Datos!$C$9=Datos!$AI$9),IF(A103>30000,Q103,ROUND(Q103*Datos!$J$18,Dins)))))) -> 18.5 | G103: 0 | H103: 0 | I103: 0 | J103: 0 | N103: 21.83 | O103: =IF(A103>30000,ROUND(N103/$O$14,Dins),ROUND(N103,Dins)) -> 18.5 | P103: =ROUND(N103/$P$14,Dins) -> 5.82 | Q103: =IF(A103>30000,ROUND(P103/$Q$14,Dins),ROUND(P103,Dins)) -> 4.93
A104: 30059 | B104: 21 | C104: MA | D104: CEMENTO PORTLAND TIPO I (42.5KG) ATLAS | E104: BOL | F104: =IF(AND($F$15=Datos!$AI$5,Datos!$C$9=Datos!$AI$10),IF(A104>30000,N104,ROUND(N104*Datos!$J$18,Dins)),IF(AND($F$15=Datos!$AI$5,Datos!$C$9=Datos!$AI$9),IF(A104>30000,O104,ROUND(O104*Datos!$J$18,Dins)),IF(AND($F$15=Datos!$AI$6,Datos!$C$9=Datos!$AI$10),IF(A104>30000,P104,ROUND(P104*Datos!$J$18,Dins)),IF(AND($F$15=Datos!$AI$6,Datos!$C$9=Datos!$AI$9),IF(A104>30000,Q104,ROUND(Q104*Datos!$J$18,Dins)))))) -> 18.5 | G104: 0 | H104: 0 | I104: 0 | J104: 0 | N104: 21.83 | O104: =IF(A104>30000,ROUND(N104/$O$14,Dins),ROUND(N104,Dins)) -> 18.5 | P104: =ROUND(N104/$P$14,Dins) -> 5.82 | Q104: =IF(A104>30000,ROUND(P104/$Q$14,Dins),ROUND(P104,Dins)) -> 4.93
A105: 60011 | B105: 49 | C105: EQ1 | D105: MEZCLADORA CONCRETO TROMPO 8 HP 9 P3 | E105: hm | F105: =IF(AND($F$15=Datos!$AI$5,Datos!$C$9=Datos!$AI$10),IF(A105>30000,N105,ROUND(N105*Datos!$J$18,Dins)),IF(AND($F$15=Datos!$AI$5,Datos!$C$9=Datos!$AI$9),IF(A105>30000,O105,ROUND(O105*Datos!$J$18,Dins)),IF(AND($F$15=Datos!$AI$6,Datos!$C$9=Datos!$AI$10),IF(A105>30000,P105,ROUND(P105*Datos!$J$18,Dins)),IF(AND($F$15=Datos!$AI$6,Datos!$C$9=Datos!$AI$9),IF(A105>30000,Q105,ROUND(Q105*Datos!$J$18,Dins)))))) -> 15.05 | N105: 17.76 | O105: =IF(A105>30000,ROUND(N105/$O$14,Dins),ROUND(N105,Dins)) -> 15.05 | P105: =ROUND(N105/$P$14,Dins) -> 4.74 | Q105: =IF(A105>30000,ROUND(P105/$Q$14,Dins),ROUND(P105,Dins)) -> 4.02
A106: 30060 | B106: 1 | C106: MA | D106: ACEITE PARA MOTOR SAE-30 | E106: gln | F106: =IF(AND($F$15=Datos!$AI$5,Datos!$C$9=Datos!$AI$10),IF(A106>30000,N106,ROUND(N106*Datos!$J$18,Dins)),IF(AND($F$15=Datos!$AI$5,Datos!$C$9=Datos!$AI$9),IF(A106>30000,O106,ROUND(O106*Datos!$J$18,Dins)),IF(AND($F$15=Datos!$AI$6,Datos!$C$9=Datos!$AI$10),IF(A106>30000,P106,ROUND(P106*Datos!$J$18,Dins)),IF(AND($F$15=Datos!$AI$6,Datos!$C$9=Datos!$AI$9),IF(A106>30000,Q106,ROUND(Q106*Datos!$J$18,Dins)))))) -> 46.84 | G106: 0 | H106: 0 | I106: 0 | J106: 0 | N106: 55.27 | O106: =IF(A106>30000,ROUND(N106/$O$14,Dins),ROUND(N106,Dins)) -> 46.84 | P106: =ROUND(N106/$P$14,Dins) -> 14.74 | Q106: =IF(A106>30000,ROUND(P106/$Q$14,Dins),ROUND(P106,Dins)) -> 12.49
A107: 30061 | B107: 5 | C107: MA | D107: PIEDRA CHANCADA DE 1/2" | E107: M3 | F107: =IF(AND($F$15=Datos!$AI$5,Datos!$C$9=Datos!$AI$10),IF(A107>30000,N107,ROUND(N107*Datos!$J$18,Dins)),IF(AND($F$15=Datos!$AI$5,Datos!$C$9=Datos!$AI$9),IF(A107>30000,O107,ROUND(O107*Datos!$J$18,Dins)),IF(AND($F$15=Datos!$AI$6,Datos!$C$9=Datos!$AI$10),IF(A107>30000,P107,ROUND(P107*Datos!$J$18,Dins)),IF(AND($F$15=Datos!$AI$6,Datos!$C$9=Datos!$AI$9),IF(A107>30000,Q107,ROUND(Q107*Datos!$J$18,Dins)))))) -> 65 | G107: 0 | H107: 0 | I107: 0 | J107: 0 | N107: 76.7 | O107: =IF(A107>30000,ROUND(N107/$O$14,Dins),ROUND(N107,Dins)) -> 65 | P107: =ROUND(N107/$P$14,Dins) -> 20.45 | Q107: =IF(A107>30000,ROUND(P107/$Q$14,Dins),ROUND(P107,Dins)) -> 17.33
A108: 30062 | B108: 34 | C108: MA | D108: GASOLINA 84 OCTANOS | E108: gln | F108: =IF(AND($F$15=Datos!$AI$5,Datos!$C$9=Datos!$AI$10),IF(A108>30000,N108,ROUND(N108*Datos!$J$18,Dins)),IF(AND($F$15=Datos!$AI$5,Datos!$C$9=Datos!$AI$9),IF(A108>30000,O108,ROUND(O108*Datos!$J$18,Dins)),IF(AND($F$15=Datos!$AI$6,Datos!$C$9=Datos!$AI$10),IF(A108>30000,P108,ROUND(P108*Datos!$J$18,Dins)),IF(AND($F$15=Datos!$AI$6,Datos!$C$9=Datos!$AI$9),IF(A108>30000,Q108,ROUND(Q108*Datos!$J$18,Dins)))))) -> 10.5 | G108: 0 | H108: 0 | I108: 0 | J108: 0 | N108: 12.39 | O108: =IF(A108>30000,ROUND(N108/$O$14,Dins),ROUND(N108,Dins)) -> 10.5 | P108: =ROUND(N108/$P$14,Dins) -> 3.3 | Q108: =IF(A108>30000,ROUND(P108/$Q$14,Dins),ROUND(P108,Dins)) -> 2.8
A109: 60012 | B109: 49 | C109: EQ1 | D109: VIBRADOR DE CONCRETO 4 HP 2.40" | E109: hm | F109: =IF(AND($F$15=Datos!$AI$5,Datos!$C$9=Datos!$AI$10),IF(A109>30000,N109,ROUND(N109*Datos!$J$18,Dins)),IF(AND($F$15=Datos!$AI$5,Datos!$C$9=Datos!$AI$9),IF(A109>30000,O109,ROUND(O109*Datos!$J$18,Dins)),IF(AND($F$15=Datos!$AI$6,Datos!$C$9=Datos!$AI$10),IF(A109>30000,P109,ROUND(P109*Datos!$J$18,Dins)),IF(AND($F$15=Datos!$AI$6,Datos!$C$9=Datos!$AI$9),IF(A109>30000,Q109,ROUND(Q109*Datos!$J$18,Dins)))))) -> 5.9 | N109: 6.96 | O109: =IF(A109>30000,ROUND(N109/$O$14,Dins),ROUND(N109,Dins)) -> 5.9 | P109: =ROUND(N109/$P$14,Dins) -> 1.86 | Q109: =IF(A109>30000,ROUND(P109/$Q$14,Dins),ROUND(P109,Dins)) -> 1.58
...

Sheet ApuB
A1: 0 | B1: =MATCH($A$1,$A$5:$A$50004,0)+4 -> #N/A | C1: =#REF! -> #REF!
A2: =COUNT(BDcodCU)*5+5 -> 1510 | C2: =COUNT(BDcodCU) -> 301
A3: =MAX($A$5:$A$50004)+1 -> 10302 | B3: Cifra de redondeo decimal del parcial | C3: =Datos!J12 -> 2
A4: Cod | B4: Denominación | C4: RTOf | D4: UND | E4: PU | F4: MO | G4: MA | H4: EQ | I4: nINS | J4: RTOi | K4: P.EST. | M4: SP | N4: ET | O4: 1 | P4: 2 | Q4: 3 | R4: 4 | S4: 5 | T4: 6 | U4: 7 | V4: 8 | W4: 9 | X4: 10 | Y4: 11 | Z4: 12 | AA4: 13 | AB4: 14 | AC4: 15 | AD4: 16 | AE4: 17 | AF4: 18 | AG4: 19 | AH4: 20 | AI4: 21 | AJ4: 22 | AK4: 23 | AL4: 24 | AM4: 25 | AN4: 26 | AO4: 27 | AP4: 28 | AQ4: 29 | AR4: 30 | AS4: 31 | AT4: 32 | AU4: 33 | AV4: 34 | AW4: 35 | AX4: 36 | AY4: 37 | AZ4: 38 | BA4: 39 | BB4: 40 | BC4: 41 | BD4: 42 | BE4: 43 | BF4: 44 | BG4: 45 | BH4: 46 | BI4: 47 | BJ4: 48 | BK4: 49 | BL4: 50 | BM4: 51 | BN4: 52 | BO4: 53 | BP4: 54 | BQ4: 55 | BR4: 56 | BS4: 57 | BT4: 58 | BU4: 59 | BV4: 60 | BW4: 61 | BX4: 62 | BY4: 63 | BZ4: 64 | CA4: 65 | CB4: 66 | CC4: 67 | CD4: 68 | CE4: 69 | CF4: 70 | CG4: 71 | CH4: 72 | CI4: 73 | CJ4: 74 | CK4: 75 | CL4: 76 | CM4: 77 | CN4: 78 | CO4: 79 | CP4: 80 | CQ4: 81 | CR4: 82 | CS4: 83 | CT4: 84 | CU4: 85 | CV4: 86 | CW4: 87 | CX4: 88 | CY4: 89 | CZ4: 90 | DA4: 91 | DB4: 92 | DC4: 93 | DD4: 94 | DE4: 95 | DF4: 96 | DG4: 97 | DH4: 98 | DI4: 99 | DJ4: 100
A5: 10001 | B5: OFICINA | C5: =ROUND(J5*JL*Frto/8,4) -> 0.6 | D5: GLB | E5: =SUM($O8:$W8) -> 1232.64 | F5: =SUMIF($O5:$W5,"<22501",$O8:$W8) -> 515.56 | G5: =SUMIFS($O8:$W8,$O5:$W5,">30000",$O5:$W5,"<50001") -> 691.3 | H5: =SUMIFS($O8:$W8,$O5:$W5,">60000",$O5:$W5,"<70001") -> 0 | I5: 9 | J5: 0.6 | O5: 10001 | P5: 10002 | Q5: 10003 | R5: 30001 | S5: 30002 | T5: 30003 | U5: 30004 | V5: 30005 | W5: 70001
B6: =A5&"C" -> 10001C | O6: 0.1 | P6: 1 | Q6: 1 | R6: 1 | S6: 3 | T6: 1 | U6: 1 | V6: 0.2 | W6: 5
O7: =IF(O9>10000,HLOOKUP(O9,N5:$O8,4,FALSE),IF(OR(AND(22500<O5,O5<25001),AND(50000<O5,O5<53501),AND(70000<O5,O5<72501)),$F5,IF(OR(AND(25001<O5,O5<27501),AND(53500<O5,O5<57001),AND(72500<O5,O5<75001)),$G5,IF(OR(AND(27500<O5,O5<30001),AND(57000<O5,O5<60001),AND(75000<O5,O5<77500)),$H5,VLOOKUP(O5,BDins,6,FALSE))))) -> 24.97 | P7: =IF(P9>10000,HLOOKUP(P9,O5:$O8,4,FALSE),IF(OR(AND(22500<P5,P5<25001),AND(50000<P5,P5<53501),AND(70000<P5,P5<72501)),$F5,IF(OR(AND(25001<P5,P5<27501),AND(53500<P5,P5<57001),AND(72500<P5,P5<75001)),$G5,IF(OR(AND(27500<P5,P5<30001),AND(57000<P5,P5<60001),AND(75000<P5,P5<77500)),$H5,VLOOKUP(P5,BDins,6,FALSE))))) -> 20.81 | Q7: =IF(Q9>10000,HLOOKUP(Q9,$O5:P8,4,FALSE),IF(OR(AND(22500<Q5,Q5<25001),AND(50000<Q5,Q5<53501),AND(70000<Q5,Q5<72501)),$F5,IF(OR(AND(25001<Q5,Q5<27501),AND(53500<Q5,Q5<57001),AND(72500<Q5,Q5<75001)),$G5,IF(OR(AND(27500<Q5,Q5<30001),AND(57000<Q5,Q5<60001),AND(75000<Q5,Q5<77500)),$H5,VLOOKUP(Q5,BDins,6,FALSE))))) -> 15.36 | R7: =IF(R9>10000,HLOOKUP(R9,$O5:Q8,4,FALSE),IF(OR(AND(22500<R5,R5<25001),AND(50000<R5,R5<53501),AND(70000<R5,R5<72501)),$F5,IF(OR(AND(25001<R5,R5<27501),AND(53500<R5,R5<57001),AND(72500<R5,R5<75001)),$G5,IF(OR(AND(27500<R5,R5<30001),AND(57000<R5,R5<60001),AND(75000<R5,R5<77500)),$H5,VLOOKUP(R5,BDins,6,FALSE))))) -> 250 | S7: =IF(S9>10000,HLOOKUP(S9,$O5:R8,4,FALSE),IF(OR(AND(22500<S5,S5<25001),AND(50000<S5,S5<53501),AND(70000<S5,S5<72501)),$F5,IF(OR(AND(25001<S5,S5<27501),AND(53500<S5,S5<57001),AND(72500<S5,S5<75001)),$G5,IF(OR(AND(27500<S5,S5<30001),AND(57000<S5,S5<60001),AND(75000<S5,S5<77500)),$H5,VLOOKUP(S5,BDins,6,FALSE))))) -> 18.5 | T7: =IF(T9>10000,HLOOKUP(T9,$O5:S8,4,FALSE),IF(OR(AND(22500<T5,T5<25001),AND(50000<T5,T5<53501),AND(70000<T5,T5<72501)),$F5,IF(OR(AND(25001<T5,T5<27501),AND(53500<T5,T5<57001),AND(72500<T5,T5<75001)),$G5,IF(OR(AND(27500<T5,T5<30001),AND(57000<T5,T5<60001),AND(75000<T5,T5<77500)),$H5,VLOOKUP(T5,BDins,6,FALSE))))) -> 45.8 | U7: =IF(U9>10000,HLOOKUP(U9,$O5:T8,4,FALSE),IF(OR(AND(22500<U5,U5<25001),AND(50000<U5,U5<53501),AND(70000<U5,U5<72501)),$F5,IF(OR(AND(25001<U5,U5<27501),AND(53500<U5,U5<57001),AND(72500<U5,U5<75001)),$G5,IF(OR(AND(27500<U5,U5<30001),AND(57000<U5,U5<60001),AND(75000<U5,U5<77500)),$H5,VLOOKUP(U5,BDins,6,FALSE))))) -> 40 | V7: =IF(V9>10000,HLOOKUP(V9,$O5:U8,4,FALSE),IF(OR(AND(22500<V5,V5<25001),AND(50000<V5,V5<53501),AND(70000<V5,V5<72501)),$F5,IF(OR(AND(25001<V5,V5<27501),AND(53500<V5,V5<57001),AND(72500<V5,V5<75001)),$G5,IF(OR(AND(27500<V5,V5<30001),AND(57000<V5,V5<60001),AND(75000<V5,V5<77500)),$H5,VLOOKUP(V5,BDins,6,FALSE))))) -> 1500 | W7: =IF(W9>10000,HLOOKUP(W9,$O5:V8,4,FALSE),IF(OR(AND(22500<W5,W5<25001),AND(50000<W5,W5<53501),AND(70000<W5,W5<72501)),$F5,IF(OR(AND(25001<W5,W5<27501),AND(53500<W5,W5<57001),AND(72500<W5,W5<75001)),$G5,IF(OR(AND(27500<W5,W5<30001),AND(57000<W5,W5<60001),AND(75000<W5,W5<77500)),$H5,VLOOKUP(W5,BDins,6,FALSE))))) -> 515.56
O8: =IF($K5>0,ROUND(O6*$E5/100,DpCU),IF(O9>10000,ROUND(HLOOKUP(O9,$O5:$W8,4,FALSE)/100*O6,DpCU),IF(OR(O5<20001,O5>95000,AND(60000<O5,O5<70001)),ROUND(ROUND(O6*JL/$C5,DcCU)*O7,DpCU),IF(OR(AND(20000<O5,O5<22501),AND(30000<O5,O5<50001),77500<O5),ROUND(O7*O6,DpCU),IF(OR(AND(22500<O5,O5<25001),AND(50000<O5,O5<53501),AND(70000<O5,O5<72501)),ROUND($F5/100*O6,DpCU),IF(OR(AND(25000<O5,O5<27501),AND(53500<O5,O5<57001),AND(72500<O5,O5<75001)),ROUND($G5/100*O6,DpCU),ROUND($H5/100*O6,DpCU))))))) -> 33.29 | P8: =IF($K5>0,ROUND(P6*$E5/100,DpCU),IF(P9>10000,ROUND(HLOOKUP(P9,$O5:$W8,4,FALSE)/100*P6,DpCU),IF(OR(P5<20001,P5>95000,AND(60000<P5,P5<70001)),ROUND(ROUND(P6*JL/$C5,DcCU)*P7,DpCU),IF(OR(AND(20000<P5,P5<22501),AND(30000<P5,P5<50001),77500<P5),ROUND(P7*P6,DpCU),IF(OR(AND(22500<P5,P5<25001),AND(50000<P5,P5<53501),AND(70000<P5,P5<72501)),ROUND($F5/100*P6,DpCU),IF(OR(AND(25000<P5,P5<27501),AND(53500<P5,P5<57001),AND(72500<P5,P5<75001)),ROUND($G5/100*P6,DpCU),ROUND($H5/100*P6,DpCU))))))) -> 277.47 | Q8: =IF($K5>0,ROUND(Q6*$E5/100,DpCU),IF(Q9>10000,ROUND(HLOOKUP(Q9,$O5:$W8,4,FALSE)/100*Q6,DpCU),IF(OR(Q5<20001,Q5>95000,AND(60000<Q5,Q5<70001)),ROUND(ROUND(Q6*JL/$C5,DcCU)*Q7,DpCU),IF(OR(AND(20000<Q5,Q5<22501),AND(30000<Q5,Q5<50001),77500<Q5),ROUND(Q7*Q6,DpCU),IF(OR(AND(22500<Q5,Q5<25001),AND(50000<Q5,Q5<53501),AND(70000<Q5,Q5<72501)),ROUND($F5/100*Q6,DpCU),IF(OR(AND(25000<Q5,Q5<27501),AND(53500<Q5,Q5<57001),AND(72500<Q5,Q5<75001)),ROUND($G5/100*Q6,DpCU),ROUND($H5/100*Q6,DpCU))))))) -> 204.8 | R8: =IF($K5>0,ROUND(R6*$E5/100,DpCU),IF(R9>10000,ROUND(HLOOKUP(R9,$O5:$W8,4,FALSE)/100*R6,DpCU),IF(OR(R5<20001,R5>95000,AND(60000<R5,R5<70001)),ROUND(ROUND(R6*JL/$C5,DcCU)*R7,DpCU),IF(OR(AND(20000<R5,R5<22501),AND(30000<R5,R5<50001),77500<R5),ROUND(R7*R6,DpCU),IF(OR(AND(22500<R5,R5<25001),AND(50000<R5,R5<53501),AND(70000<R5,R5<72501)),ROUND($F5/100*R6,DpCU),IF(OR(AND(25000<R5,R5<27501),AND(53500<R5,R5<57001),AND(72500<R5,R5<75001)),ROUND($G5/100*R6,DpCU),ROUND($H5/100*R6,DpCU))))))) -> 250 | S8: =IF($K5>0,ROUND(S6*$E5/100,DpCU),IF(S9>10000,ROUND(HLOOKUP(S9,$O5:$W8,4,FALSE)/100*S6,DpCU),IF(OR(S5<20001,S5>95000,AND(60000<S5,S5<70001)),ROUND(ROUND(S6*JL/$C5,DcCU)*S7,DpCU),IF(OR(AND(20000<S5,S5<22501),AND(30000<S5,S5<50001),77500<S5),ROUND(S7*S6,DpCU),IF(OR(AND(22500<S5,S5<25001),AND(50000<S5,S5<53501),AND(70000<S5,S5<72501)),ROUND($F5/100*S6,DpCU),IF(OR(AND(25000<S5,S5<27501),AND(53500<S5,S5<57001),AND(72500<S5,S5<75001)),ROUND($G5/100*S6,DpCU),ROUND($H5/100*S6,DpCU))))))) -> 55.5 | T8: =IF($K5>0,ROUND(T6*$E5/100,DpCU),IF(T9>10000,ROUND(HLOOKUP(T9,$O5:$W8,4,FALSE)/100*T6,DpCU),IF(OR(T5<20001,T5>95000,AND(60000<T5,T5<70001)),ROUND(ROUND(T6*JL/$C5,DcCU)*T7,DpCU),IF(OR(AND(20000<T5,T5<22501),AND(30000<T5,T5<50001),77500<T5),ROUND(T7*T6,DpCU),IF(OR(AND(22500<T5,T5<25001),AND(50000<T5,T5<53501),AND(70000<T5,T5<72501)),ROUND($F5/100*T6,DpCU),IF(OR(AND(25000<T5,T5<27501),AND(53500<T5,T5<57001),AND(72500<T5,T5<75001)),ROUND($G5/100*T6,DpCU),ROUND($H5/100*T6,DpCU))))))) -> 45.8 | U8: =IF($K5>0,ROUND(U6*$E5/100,DpCU),IF(U9>10000,ROUND(HLOOKUP(U9,$O5:$W8,4,FALSE)/100*U6,DpCU),IF(OR(U5<20001,U5>95000,AND(60000<U5,U5<70001)),ROUND(ROUND(U6*JL/$C5,DcCU)*U7,DpCU),IF(OR(AND(20000<U5,U5<22501),AND(30000<U5,U5<50001),77500<U5),ROUND(U7*U6,DpCU),IF(OR(AND(22500<U5,U5<25001),AND(50000<U5,U5<53501),AND(70000<U5,U5<72501)),ROUND($F5/100*U6,DpCU),IF(OR(AND(25000<U5,U5<27501),AND(53500<U5,U5<57001),AND(72500<U5,U5<75001)),ROUND($G5/100*U6,DpCU),ROUND($H5/100*U6,DpCU))))))) -> 40 | V8: =IF($K5>0,ROUND(V6*$E5/100,DpCU),IF(V9>10000,ROUND(HLOOKUP(V9,$O5:$W8,4,FALSE)/100*V6,DpCU),IF(OR(V5<20001,V5>95000,AND(60000<V5,V5<70001)),ROUND(ROUND(V6*JL/$C5,DcCU)*V7,DpCU),IF(OR(AND(20000<V5,V5<22501),AND(30000<V5,V5<50001),77500<V5),ROUND(V7*V6,DpCU),IF(OR(AND(22500<V5,V5<25001),AND(50000<V5,V5<53501),AND(70000<V5,V5<72501)),ROUND($F5/100*V6,DpCU),IF(OR(AND(25000<V5,V5<27501),AND(53500<V5,V5<57001),AND(72500<V5,V5<75001)),ROUND($G5/100*V6,DpCU),ROUND($H5/100*V6,DpCU))))))) -> 300 | W8: =IF($K5>0,ROUND(W6*$E5/100,DpCU),IF(W9>10000,ROUND(HLOOKUP(W9,$O5:$W8,4,FALSE)/100*W6,DpCU),IF(OR(W5<20001,W5>95000,AND(60000<W5,W5<70001)),ROUND(ROUND(W6*JL/$C5,DcCU)*W7,DpCU),IF(OR(AND(20000<W5,W5<22501),AND(30000<W5,W5<50001),77500<W5),ROUND(W7*W6,DpCU),IF(OR(AND(22500<W5,W5<25001),AND(50000<W5,W5<53501),AND(70000<W5,W5<72501)),ROUND($F5/100*W6,DpCU),IF(OR(AND(25000<W5,W5<27501),AND(53500<W5,W5<57001),AND(72500<W5,W5<75001)),ROUND($G5/100*W6,DpCU),ROUND($H5/100*W6,DpCU))))))) -> 25.78
B9: =A5&"r" -> 10001r
A10: 10002 | B10: ALMACEN Y GUARDIANIA | C10: =ROUND(J10*JL*Frto/8,4) -> 0.6 | D10: GLB | E10: =SUM($O13:$W13) -> 1976.58 | F10: =SUMIF($O10:$W10,"<22501",$O13:$W13) -> 515.56 | G10: =SUMIFS($O13:$W13,$O10:$W10,">30000",$O10:$W10,"<50001") -> 1445.55 | H10: =SUMIFS($O13:$W13,$O10:$W10,">60000",$O10:$W10,"<70001") -> 0 | I10: 9 | J10: 0.6 | O10: 10001 | P10: 10002 | Q10: 10003 | R10: 30001 | S10: 30002 | T10: 30003 | U10: 30004 | V10: 30006 | W10: 70001
B11: =A10&"C" -> 10002C | O11: 0.1 | P11: 1 | Q11: 1 | R11: 1 | S11: 4.5 | T11: 1 | U11: 1.35 | V11: 0.5 | W11: 3
O12: =IF(O14>10000,HLOOKUP(O14,N10:$O13,4,FALSE),IF(OR(AND(22500<O10,O10<25001),AND(50000<O10,O10<53501),AND(70000<O10,O10<72501)),$F10,IF(OR(AND(25001<O10,O10<27501),AND(53500<O10,O10<57001),AND(72500<O10,O10<75001)),$G10,IF(OR(AND(27500<O10,O10<30001),AND(57000<O10,O10<60001),AND(75000<O10,O10<77500)),$H10,VLOOKUP(O10,BDins,6,FALSE))))) -> 24.97 | P12: =IF(P14>10000,HLOOKUP(P14,O10:$O13,4,FALSE),IF(OR(AND(22500<P10,P10<25001),AND(50000<P10,P10<53501),AND(70000<P10,P10<72501)),$F10,IF(OR(AND(25001<P10,P10<27501),AND(53500<P10,P10<57001),AND(72500<P10,P10<75001)),$G10,IF(OR(AND(27500<P10,P10<30001),AND(57000<P10,P10<60001),AND(75000<P10,P10<77500)),$H10,VLOOKUP(P10,BDins,6,FALSE))))) -> 20.81 | Q12: =IF(Q14>10000,HLOOKUP(Q14,$O10:P13,4,FALSE),IF(OR(AND(22500<Q10,Q10<25001),AND(50000<Q10,Q10<53501),AND(70000<Q10,Q10<72501)),$F10,IF(OR(AND(25001<Q10,Q10<27501),AND(53500<Q10,Q10<57001),AND(72500<Q10,Q10<75001)),$G10,IF(OR(AND(27500<Q10,Q10<30001),AND(57000<Q10,Q10<60001),AND(75000<Q10,Q10<77500)),$H10,VLOOKUP(Q10,BDins,6,FALSE))))) -> 15.36 | R12: =IF(R14>10000,HLOOKUP(R14,$O10:Q13,4,FALSE),IF(OR(AND(22500<R10,R10<25001),AND(50000<R10,R10<53501),AND(70000<R10,R10<72501)),$F10,IF(OR(AND(25001<R10,R10<27501),AND(53500<R10,R10<57001),AND(72500<R10,R10<75001)),$G10,IF(OR(AND(27500<R10,R10<30001),AND(57000<R10,R10<60001),AND(75000<R10,R10<77500)),$H10,VLOOKUP(R10,BDins,6,FALSE))))) -> 250 | S12: =IF(S14>10000,HLOOKUP(S14,$O10:R13,4,FALSE),IF(OR(AND(22500<S10,S10<25001),AND(50000<S10,S10<53501),AND(70000<S10,S10<72501)),$F10,IF(OR(AND(25001<S10,S10<27501),AND(53500<S10,S10<57001),AND(72500<S10,S10<75001)),$G10,IF(OR(AND(27500<S10,S10<30001),AND(57000<S10,S10<60001),AND(75000<S10,S10<77500)),$H10,VLOOKUP(S10,BDins,6,FALSE))))) -> 18.5 | T12: =IF(T14>10000,HLOOKUP(T14,$O10:S13,4,FALSE),IF(OR(AND(22500<T10,T10<25001),AND(50000<T10,T10<53501),AND(70000<T10,T10<72501)),$F10,IF(OR(AND(25001<T10,T10<27501),AND(53500<T10,T10<57001),AND(72500<T10,T10<75001)),$G10,IF(OR(AND(27500<T10,T10<30001),AND(57000<T10,T10<60001),AND(75000<T10,T10<77500)),$H10,VLOOKUP(T10,BDins,6,FALSE))))) -> 45.8 | U12: =IF(U14>10000,HLOOKUP(U14,$O10:T13,4,FALSE),IF(OR(AND(22500<U10,U10<25001),AND(50000<U10,U10<53501),AND(70000<U10,U10<72501)),$F10,IF(OR(AND(25001<U10,U10<27501),AND(53500<U10,U10<57001),AND(72500<U10,U10<75001)),$G10,IF(OR(AND(27500<U10,U10<30001),AND(57000<U10,U10<60001),AND(75000<U10,U10<77500)),$H10,VLOOKUP(U10,BDins,6,FALSE))))) -> 40 | V12: =IF(V14>10000,HLOOKUP(V14,$O10:U13,4,FALSE),IF(OR(AND(22500<V10,V10<25001),AND(50000<V10,V10<53501),AND(70000<V10,V10<72501)),$F10,IF(OR(AND(25001<V10,V10<27501),AND(53500<V10,V10<57001),AND(72500<V10,V10<75001)),$G10,IF(OR(AND(27500<V10,V10<30001),AND(57000<V10,V10<60001),AND(75000<V10,V10<77500)),$H10,VLOOKUP(V10,BDins,6,FALSE))))) -> 2025 | W12: =IF(W14>10000,HLOOKUP(W14,$O10:V13,4,FALSE),IF(OR(AND(22500<W10,W10<25001),AND(50000<W10,W10<53501),AND(70000<W10,W10<72501)),$F10,IF(OR(AND(25001<W10,W10<27501),AND(53500<W10,W10<57001),AND(72500<W10,W10<75001)),$G10,IF(OR(AND(27500<W10,W10<30001),AND(57000<W10,W10<60001),AND(75000<W10,W10<77500)),$H10,VLOOKUP(W10,BDins,6,FALSE))))) -> 515.56
O13: =IF($K10>0,ROUND(O11*$E10/100,DpCU),IF(O14>10000,ROUND(HLOOKUP(O14,$O10:$W13,4,FALSE)/100*O11,DpCU),IF(OR(O10<20001,O10>95000,AND(60000<O10,O10<70001)),ROUND(ROUND(O11*JL/$C10,DcCU)*O12,DpCU),IF(OR(AND(20000<O10,O10<22501),AND(30000<O10,O10<50001),77500<O10),ROUND(O12*O11,DpCU),IF(OR(AND(22500<O10,O10<25001),AND(50000<O10,O10<53501),AND(70000<O10,O10<72501)),ROUND($F10/100*O11,DpCU),IF(OR(AND(25000<O10,O10<27501),AND(53500<O10,O10<57001),AND(72500<O10,O10<75001)),ROUND($G10/100*O11,DpCU),ROUND($H10/100*O11,DpCU))))))) -> 33.29 | P13: =IF($K10>0,ROUND(P11*$E10/100,DpCU),IF(P14>10000,ROUND(HLOOKUP(P14,$O10:$W13,4,FALSE)/100*P11,DpCU),IF(OR(P10<20001,P10>95000,AND(60000<P10,P10<70001)),ROUND(ROUND(P11*JL/$C10,DcCU)*P12,DpCU),IF(OR(AND(20000<P10,P10<22501),AND(30000<P10,P10<50001),77500<P10),ROUND(P12*P11,DpCU),IF(OR(AND(22500<P10,P10<25001),AND(50000<P10,P10<53501),AND(70000<P10,P10<72501)),ROUND($F10/100*P11,DpCU),IF(OR(AND(25000<P10,P10<27501),AND(53500<P10,P10<57001),AND(72500<P10,P10<75001)),ROUND($G10/100*P11,DpCU),ROUND($H10/100*P11,DpCU))))))) -> 277.47 | Q13: =IF($K10>0,ROUND(Q11*$E10/100,DpCU),IF(Q14>10000,ROUND(HLOOKUP(Q14,$O10:$W13,4,FALSE)/100*Q11,DpCU),IF(OR(Q10<20001,Q10>95000,AND(60000<Q10,Q10<70001)),ROUND(ROUND(Q11*JL/$C10,DcCU)*Q12,DpCU),IF(OR(AND(20000<Q10,Q10<22501),AND(30000<Q10,Q10<50001),77500<Q10),ROUND(Q12*Q11,DpCU),IF(OR(AND(22500<Q10,Q10<25001),AND(50000<Q10,Q10<53501),AND(70000<Q10,Q10<72501)),ROUND($F10/100*Q11,DpCU),IF(OR(AND(25000<Q10,Q10<27501),AND(53500<Q10,Q10<57001),AND(72500<Q10,Q10<75001)),ROUND($G10/100*Q11,DpCU),ROUND($H10/100*Q11,DpCU))))))) -> 204.8 | R13: =IF($K10>0,ROUND(R11*$E10/100,DpCU),IF(R14>10000,ROUND(HLOOKUP(R14,$O10:$W13,4,FALSE)/100*R11,DpCU),IF(OR(R10<20001,R10>95000,AND(60000<R10,R10<70001)),ROUND(ROUND(R11*JL/$C10,DcCU)*R12,DpCU),IF(OR(AND(20000<R10,R10<22501),AND(30000<R10,R10<50001),77500<R10),ROUND(R12*R11,DpCU),IF(OR(AND(22500<R10,R10<25001),AND(50000<R10,R10<53501),AND(70000<R10,R10<72501)),ROUND($F10/100*R11,DpCU),IF(OR(AND(25000<R10,R10<27501),AND(53500<R10,R10<57001),AND(72500<R10,R10<75001)),ROUND($G10/100*R11,DpCU),ROUND($H10/100*R11,DpCU))))))) -> 250 | S13: =IF($K10>0,ROUND(S11*$E10/100,DpCU),IF(S14>10000,ROUND(HLOOKUP(S14,$O10:$W13,4,FALSE)/100*S11,DpCU),IF(OR(S10<20001,S10>95000,AND(60000<S10,S10<70001)),ROUND(ROUND(S11*JL/$C10,DcCU)*S12,DpCU),IF(OR(AND(20000<S10,S10<22501),AND(30000<S10,S10<50001),77500<S10),ROUND(S12*S11,DpCU),IF(OR(AND(22500<S10,S10<25001),AND(50000<S10,S10<53501),AND(70000<S10,S10<72501)),ROUND($F10/100*S11,DpCU),IF(OR(AND(25000<S10,S10<27501),AND(53500<S10,S10<57001),AND(72500<S10,S10<75001)),ROUND($G10/100*S11,DpCU),ROUND($H10/100*S11,DpCU))))))) -> 83.25 | T13: =IF($K10>0,ROUND(T11*$E10/100,DpCU),IF(T14>10000,ROUND(HLOOKUP(T14,$O10:$W13,4,FALSE)/100*T11,DpCU),IF(OR(T10<20001,T10>95000,AND(60000<T10,T10<70001)),ROUND(ROUND(T11*JL/$C10,DcCU)*T12,DpCU),IF(OR(AND(20000<T10,T10<22501),AND(30000<T10,T10<50001),77500<T10),ROUND(T12*T11,DpCU),IF(OR(AND(22500<T10,T10<25001),AND(50000<T10,T10<53501),AND(70000<T10,T10<72501)),ROUND($F10/100*T11,DpCU),IF(OR(AND(25000<T10,T10<27501),AND(53500<T10,T10<57001),AND(72500<T10,T10<75001)),ROUND($G10/100*T11,DpCU),ROUND($H10/100*T11,DpCU))))))) -> 45.8 | U13: =IF($K10>0,ROUND(U11*$E10/100,DpCU),IF(U14>10000,ROUND(HLOOKUP(U14,$O10:$W13,4,FALSE)/100*U11,DpCU),IF(OR(U10<20001,U10>95000,AND(60000<U10,U10<70001)),ROUND(ROUND(U11*JL/$C10,DcCU)*U12,DpCU),IF(OR(AND(20000<U10,U10<22501),AND(30000<U10,U10<50001),77500<U10),ROUND(U12*U11,DpCU),IF(OR(AND(22500<U10,U10<25001),AND(50000<U10,U10<53501),AND(70000<U10,U10<72501)),ROUND($F10/100*U11,DpCU),IF(OR(AND(25000<U10,U10<27501),AND(53500<U10,U10<57001),AND(72500<U10,U10<75001)),ROUND($G10/100*U11,DpCU),ROUND($H10/100*U11,DpCU))))))) -> 54 | V13: =IF($K10>0,ROUND(V11*$E10/100,DpCU),IF(V14>10000,ROUND(HLOOKUP(V14,$O10:$W13,4,FALSE)/100*V11,DpCU),IF(OR(V10<20001,V10>95000,AND(60000<V10,V10<70001)),ROUND(ROUND(V11*JL/$C10,DcCU)*V12,DpCU),IF(OR(AND(20000<V10,V10<22501),AND(30000<V10,V10<50001),77500<V10),ROUND(V12*V11,DpCU),IF(OR(AND(22500<V10,V10<25001),AND(50000<V10,V10<53501),AND(70000<V10,V10<72501)),ROUND($F10/100*V11,DpCU),IF(OR(AND(25000<V10,V10<27501),AND(53500<V10,V10<57001),AND(72500<V10,V10<75001)),ROUND($G10/100*V11,DpCU),ROUND($H10/100*V11,DpCU))))))) -> 1012.5 | W13: =IF($K10>0,ROUND(W11*$E10/100,DpCU),IF(W14>10000,ROUND(HLOOKUP(W14,$O10:$W13,4,FALSE)/100*W11,DpCU),IF(OR(W10<20001,W10>95000,AND(60000<W10,W10<70001)),ROUND(ROUND(W11*JL/$C10,DcCU)*W12,DpCU),IF(OR(AND(20000<W10,W10<22501),AND(30000<W10,W10<50001),77500<W10),ROUND(W12*W11,DpCU),IF(OR(AND(22500<W10,W10<25001),AND(50000<W10,W10<53501),AND(70000<W10,W10<72501)),ROUND($F10/100*W11,DpCU),IF(OR(AND(25000<W10,W10<27501),AND(53500<W10,W10<57001),AND(72500<W10,W10<75001)),ROUND($G10/100*W11,DpCU),ROUND($H10/100*W11,DpCU))))))) -> 15.47
B14: =A10&"r" -> 10002r
A15: 10003 | B15: SS. HH. PARA LA OBRA | C15: =ROUND(J15*JL*Frto/8,4) -> 2 | D15: GLB | E15: =SUM($O18:$AA18) -> 2001.68 | F15: =SUMIF($O15:$AA15,"<22501",$O18:$AA18) -> 444.03 | G15: =SUMIFS($O18:$AA18,$O15:$AA15,">30000",$O15:$AA15,"<50001") -> 1535.45 | H15: =SUMIFS($O18:$AA18,$O15:$AA15,">60000",$O15:$AA15,"<70001") -> 0 | I15: 13 | J15: 2 | O15: 10001 | P15: 10002 | Q15: 10003 | R15: 30001 | S15: 30002 | T15: 30004 | U15: 30007 | V15: 30008 | W15: 30009 | X15: 30010 | Y15: 30011 | Z15: 30012 | AA15: 70001
B16: =A15&"C" -> 10003C | O16: 0.1 | P16: 3 | Q16: 3 | R16: 0.5 | S16: 3 | T16: 0.9 | U16: 3 | V16: 1 | W16: 60 | X16: 8 | Y16: 12 | Z16: 1 | AA16: 5
O17: =IF(O19>10000,HLOOKUP(O19,N15:$O18,4,FALSE),IF(OR(AND(22500<O15,O15<25001),AND(50000<O15,O15<53501),AND(70000<O15,O15<72501)),$F15,IF(OR(AND(25001<O15,O15<27501),AND(53500<O15,O15<57001),AND(72500<O15,O15<75001)),$G15,IF(OR(AND(27500<O15,O15<30001),AND(57000<O15,O15<60001),AND(75000<O15,O15<77500)),$H15,VLOOKUP(O15,BDins,6,FALSE))))) -> 24.97 | P17: =IF(P19>10000,HLOOKUP(P19,O15:$O18,4,FALSE),IF(OR(AND(22500<P15,P15<25001),AND(50000<P15,P15<53501),AND(70000<P15,P15<72501)),$F15,IF(OR(AND(25001<P15,P15<27501),AND(53500<P15,P15<57001),AND(72500<P15,P15<75001)),$G15,IF(OR(AND(27500<P15,P15<30001),AND(57000<P15,P15<60001),AND(75000<P15,P15<77500)),$H15,VLOOKUP(P15,BDins,6,FALSE))))) -> 20.81 | Q17: =IF(Q19>10000,HLOOKUP(Q19,$O15:P18,4,FALSE),IF(OR(AND(22500<Q15,Q15<25001),AND(50000<Q15,Q15<53501),AND(70000<Q15,Q15<72501)),$F15,IF(OR(AND(25001<Q15,Q15<27501),AND(53500<Q15,Q15<57001),AND(72500<Q15,Q15<75001)),$G15,IF(OR(AND(27500<Q15,Q15<30001),AND(57000<Q15,Q15<60001),AND(75000<Q15,Q15<77500)),$H15,VLOOKUP(Q15,BDins,6,FALSE))))) -> 15.36 | R17: =IF(R19>10000,HLOOKUP(R19,$O15:Q18,4,FALSE),IF(OR(AND(22500<R15,R15<25001),AND(50000<R15,R15<53501),AND(70000<R15,R15<72501)),$F15,IF(OR(AND(25001<R15,R15<27501),AND(53500<R15,R15<57001),AND(72500<R15,R15<75001)),$G15,IF(OR(AND(27500<R15,R15<30001),AND(57000<R15,R15<60001),AND(75000<R15,R15<77500)),$H15,VLOOKUP(R15,BDins,6,FALSE))))) -> 250 | S17: =IF(S19>10000,HLOOKUP(S19,$O15:R18,4,FALSE),IF(OR(AND(22500<S15,S15<25001),AND(50000<S15,S15<53501),AND(70000<S15,S15<72501)),$F15,IF(OR(AND(25001<S15,S15<27501),AND(53500<S15,S15<57001),AND(72500<S15,S15<75001)),$G15,IF(OR(AND(27500<S15,S15<30001),AND(57000<S15,S15<60001),AND(75000<S15,S15<77500)),$H15,VLOOKUP(S15,BDins,6,FALSE))))) -> 18.5 | T17: =IF(T19>10000,HLOOKUP(T19,$O15:S18,4,FALSE),IF(OR(AND(22500<T15,T15<25001),AND(50000<T15,T15<53501),AND(70000<T15,T15<72501)),$F15,IF(OR(AND(25001<T15,T15<27501),AND(53500<T15,T15<57001),AND(72500<T15,T15<75001)),$G15,IF(OR(AND(27500<T15,T15<30001),AND(57000<T15,T15<60001),AND(75000<T15,T15<77500)),$H15,VLOOKUP(T15,BDins,6,FALSE))))) -> 40 | U17: =IF(U19>10000,HLOOKUP(U19,$O15:T18,4,FALSE),IF(OR(AND(22500<U15,U15<25001),AND(50000<U15,U15<53501),AND(70000<U15,U15<72501)),$F15,IF(OR(AND(25001<U15,U15<27501),AND(53500<U15,U15<57001),AND(72500<U15,U15<75001)),$G15,IF(OR(AND(27500<U15,U15<30001),AND(57000<U15,U15<60001),AND(75000<U15,U15<77500)),$H15,VLOOKUP(U15,BDins,6,FALSE))))) -> 3.65 | V17: =IF(V19>10000,HLOOKUP(V19,$O15:U18,4,FALSE),IF(OR(AND(22500<V15,V15<25001),AND(50000<V15,V15<53501),AND(70000<V15,V15<72501)),$F15,IF(OR(AND(25001<V15,V15<27501),AND(53500<V15,V15<57001),AND(72500<V15,V15<75001)),$G15,IF(OR(AND(27500<V15,V15<30001),AND(57000<V15,V15<60001),AND(75000<V15,V15<77500)),$H15,VLOOKUP(V15,BDins,6,FALSE))))) -> 200 | W17: =IF(W19>10000,HLOOKUP(W19,$O15:V18,4,FALSE),IF(OR(AND(22500<W15,W15<25001),AND(50000<W15,W15<53501),AND(70000<W15,W15<72501)),$F15,IF(OR(AND(25001<W15,W15<27501),AND(53500<W15,W15<57001),AND(72500<W15,W15<75001)),$G15,IF(OR(AND(27500<W15,W15<30001),AND(57000<W15,W15<60001),AND(75000<W15,W15<77500)),$H15,VLOOKUP(W15,BDins,6,FALSE))))) -> 3.7 | X17: =IF(X19>10000,HLOOKUP(X19,$O15:W18,4,FALSE),IF(OR(AND(22500<X15,X15<25001),AND(50000<X15,X15<53501),AND(70000<X15,X15<72501)),$F15,IF(OR(AND(25001<X15,X15<27501),AND(53500<X15,X15<57001),AND(72500<X15,X15<75001)),$G15,IF(OR(AND(27500<X15,X15<30001),AND(57000<X15,X15<60001),AND(75000<X15,X15<77500)),$H15,VLOOKUP(X15,BDins,6,FALSE))))) -> 25 | ... AA17: =IF(AA19>10000,HLOOKUP(AA19,$O15:Z18,4,FALSE),IF(OR(AND(22500<AA15,AA15<25001),AND(50000<AA15,AA15<53501),AND(70000<AA15,AA15<72501)),$F15,IF(OR(AND(25001<AA15,AA15<27501),AND(53500<AA15,AA15<57001),AND(72500<AA15,AA15<75001)),$G15,IF(OR(AND(27500<AA15,AA15<30001),AND(57000<AA15,AA15<60001),AND(75000<AA15,AA15<77500)),$H15,VLOOKUP(AA15,BDins,6,FALSE))))) -> 444.03
O18: =IF($K15>0,ROUND(O16*$E15/100,DpCU),IF(O19>10000,ROUND(HLOOKUP(O19,$O15:$AA18,4,FALSE)/100*O16,DpCU),IF(OR(O15<20001,O15>95000,AND(60000<O15,O15<70001)),ROUND(ROUND(O16*JL/$C15,DcCU)*O17,DpCU),IF(OR(AND(20000<O15,O15<22501),AND(30000<O15,O15<50001),77500<O15),ROUND(O17*O16,DpCU),IF(OR(AND(22500<O15,O15<25001),AND(50000<O15,O15<53501),AND(70000<O15,O15<72501)),ROUND($F15/100*O16,DpCU),IF(OR(AND(25000<O15,O15<27501),AND(53500<O15,O15<57001),AND(72500<O15,O15<75001)),ROUND($G15/100*O16,DpCU),ROUND($H15/100*O16,DpCU))))))) -> 9.99 | P18: =IF($K15>0,ROUND(P16*$E15/100,DpCU),IF(P19>10000,ROUND(HLOOKUP(P19,$O15:$AA18,4,FALSE)/100*P16,DpCU),IF(OR(P15<20001,P15>95000,AND(60000<P15,P15<70001)),ROUND(ROUND(P16*JL/$C15,DcCU)*P17,DpCU),IF(OR(AND(20000<P15,P15<22501),AND(30000<P15,P15<50001),77500<P15),ROUND(P17*P16,DpCU),IF(OR(AND(22500<P15,P15<25001),AND(50000<P15,P15<53501),AND(70000<P15,P15<72501)),ROUND($F15/100*P16,DpCU),IF(OR(AND(25000<P15,P15<27501),AND(53500<P15,P15<57001),AND(72500<P15,P15<75001)),ROUND($G15/100*P16,DpCU),ROUND($H15/100*P16,DpCU))))))) -> 249.72 | Q18: =IF($K15>0,ROUND(Q16*$E15/100,DpCU),IF(Q19>10000,ROUND(HLOOKUP(Q19,$O15:$AA18,4,FALSE)/100*Q16,DpCU),IF(OR(Q15<20001,Q15>95000,AND(60000<Q15,Q15<70001)),ROUND(ROUND(Q16*JL/$C15,DcCU)*Q17,DpCU),IF(OR(AND(20000<Q15,Q15<22501),AND(30000<Q15,Q15<50001),77500<Q15),ROUND(Q17*Q16,DpCU),IF(OR(AND(22500<Q15,Q15<25001),AND(50000<Q15,Q15<53501),AND(70000<Q15,Q15<72501)),ROUND($F15/100*Q16,DpCU),IF(OR(AND(25000<Q15,Q15<27501),AND(53500<Q15,Q15<57001),AND(72500<Q15,Q15<75001)),ROUND($G15/100*Q16,DpCU),ROUND($H15/100*Q16,DpCU))))))) -> 184.32 | R18: =IF($K15>0,ROUND(R16*$E15/100,DpCU),IF(R19>10000,ROUND(HLOOKUP(R19,$O15:$AA18,4,FALSE)/100*R16,DpCU),IF(OR(R15<20001,R15>95000,AND(60000<R15,R15<70001)),ROUND(ROUND(R16*JL/$C15,DcCU)*R17,DpCU),IF(OR(AND(20000<R15,R15<22501),AND(30000<R15,R15<50001),77500<R15),ROUND(R17*R16,DpCU),IF(OR(AND(22500<R15,R15<25001),AND(50000<R15,R15<53501),AND(70000<R15,R15<72501)),ROUND($F15/100*R16,DpCU),IF(OR(AND(25000<R15,R15<27501),AND(53500<R15,R15<57001),AND(72500<R15,R15<75001)),ROUND($G15/100*R16,DpCU),ROUND($H15/100*R16,DpCU))))))) -> 125 | S18: =IF($K15>0,ROUND(S16*$E15/100,DpCU),IF(S19>10000,ROUND(HLOOKUP(S19,$O15:$AA18,4,FALSE)/100*S16,DpCU),IF(OR(S15<20001,S15>95000,AND(60000<S15,S15<70001)),ROUND(ROUND(S16*JL/$C15,DcCU)*S17,DpCU),IF(OR(AND(20000<S15,S15<22501),AND(30000<S15,S15<50001),77500<S15),ROUND(S17*S16,DpCU),IF(OR(AND(22500<S15,S15<25001),AND(50000<S15,S15<53501),AND(70000<S15,S15<72501)),ROUND($F15/100*S16,DpCU),IF(OR(AND(25000<S15,S15<27501),AND(53500<S15,S15<57001),AND(72500<S15,S15<75001)),ROUND($G15/100*S16,DpCU),ROUND($H15/100*S16,DpCU))))))) -> 55.5 | T18: =IF($K15>0,ROUND(T16*$E15/100,DpCU),IF(T19>10000,ROUND(HLOOKUP(T19,$O15:$AA18,4,FALSE)/100*T16,DpCU),IF(OR(T15<20001,T15>95000,AND(60000<T15,T15<70001)),ROUND(ROUND(T16*JL/$C15,DcCU)*T17,DpCU),IF(OR(AND(20000<T15,T15<22501),AND(30000<T15,T15<50001),77500<T15),ROUND(T17*T16,DpCU),IF(OR(AND(22500<T15,T15<25001),AND(50000<T15,T15<53501),AND(70000<T15,T15<72501)),ROUND($F15/100*T16,DpCU),IF(OR(AND(25000<T15,T15<27501),AND(53500<T15,T15<57001),AND(72500<T15,T15<75001)),ROUND($G15/100*T16,DpCU),ROUND($H15/100*T16,DpCU))))))) -> 36 | U18: =IF($K15>0,ROUND(U16*$E15/100,DpCU),IF(U19>10000,ROUND(HLOOKUP(U19,$O15:$AA18,4,FALSE)/100*U16,DpCU),IF(OR(U15<20001,U15>95000,AND(60000<U15,U15<70001)),ROUND(ROUND(U16*JL/$C15,DcCU)*U17,DpCU),IF(OR(AND(20000<U15,U15<22501),AND(30000<U15,U15<50001),77500<U15),ROUND(U17*U16,DpCU),IF(OR(AND(22500<U15,U15<25001),AND(50000<U15,U15<53501),AND(70000<U15,U15<72501)),ROUND($F15/100*U16,DpCU),IF(OR(AND(25000<U15,U15<27501),AND(53500<U15,U15<57001),AND(72500<U15,U15<75001)),ROUND($G15/100*U16,DpCU),ROUND($H15/100*U16,DpCU))))))) -> 10.95 | V18: =IF($K15>0,ROUND(V16*$E15/100,DpCU),IF(V19>10000,ROUND(HLOOKUP(V19,$O15:$AA18,4,FALSE)/100*V16,DpCU),IF(OR(V15<20001,V15>95000,AND(60000<V15,V15<70001)),ROUND(ROUND(V16*JL/$C15,DcCU)*V17,DpCU),IF(OR(AND(20000<V15,V15<22501),AND(30000<V15,V15<50001),77500<V15),ROUND(V17*V16,DpCU),IF(OR(AND(22500<V15,V15<25001),AND(50000<V15,V15<53501),AND(70000<V15,V15<72501)),ROUND($F15/100*V16,DpCU),IF(OR(AND(25000<V15,V15<27501),AND(53500<V15,V15<57001),AND(72500<V15,V15<75001)),ROUND($G15/100*V16,DpCU),ROUND($H15/100*V16,DpCU))))))) -> 200 | ... AA18: =IF($K15>0,ROUND(AA16*$E15/100,DpCU),IF(AA19>10000,ROUND(HLOOKUP(AA19,$O15:$AA18,4,FALSE)/100*AA16,DpCU),IF(OR(AA15<20001,AA15>95000,AND(60000<AA15,AA15<70001)),ROUND(ROUND(AA16*JL/$C15,DcCU)*AA17,DpCU),IF(OR(AND(20000<AA15,AA15<22501),AND(30000<AA15,AA15<50001),77500<AA15),ROUND(AA17*AA16,DpCU),IF(OR(AND(22500<AA15,AA15<25001),AND(50000<AA15,AA15<53501),AND(70000<AA15,AA15<72501)),ROUND($F15/100*AA16,DpCU),IF(OR(AND(25000<AA15,AA15<27501),AND(53500<AA15,AA15<57001),AND(72500<AA15,AA15<75001)),ROUND($G15/100*AA16,DpCU),ROUND($H15/100*AA16,DpCU))))))) -> 22.2
B19: =A15&"r" -> 10003r
A20: 10004 | B20: TRANSPORTE VERTICAL DE MATERIALES | C20: =ROUND(J20*JL*Frto/8,4) -> 1 | D20: GLB | E20: =SUM($O23:$O23) -> 1664.8 | F20: =SUMIF($O20:$O20,"<22501",$O23:$O23) -> 1664.8 | G20: =SUMIFS($O23:$O23,$O20:$O20,">30000",$O20:$O20,"<50001") -> 0 | H20: =SUMIFS($O23:$O23,$O20:$O20,">60000",$O20:$O20,"<70001") -> 0 | I20: 1 | J20: 1 | O20: 10004
B21: =A20&"C" -> 10004C | O21: 10
O22: =IF(O24>10000,HLOOKUP(O24,N20:$O23,4,FALSE),IF(OR(AND(22500<O20,O20<25001),AND(50000<O20,O20<53501),AND(70000<O20,O20<72501)),$F20,IF(OR(AND(25001<O20,O20<27501),AND(53500<O20,O20<57001),AND(72500<O20,O20<75001)),$G20,IF(OR(AND(27500<O20,O20<30001),AND(57000<O20,O20<60001),AND(75000<O20,O20<77500)),$H20,VLOOKUP(O20,BDins,6,FALSE))))) -> 20.81
O23: =IF($K20>0,ROUND(O21*$E20/100,DpCU),IF(O24>10000,ROUND(HLOOKUP(O24,$O20:$O23,4,FALSE)/100*O21,DpCU),IF(OR(O20<20001,O20>95000,AND(60000<O20,O20<70001)),ROUND(ROUND(O21*JL/$C20,DcCU)*O22,DpCU),IF(OR(AND(20000<O20,O20<22501),AND(30000<O20,O20<50001),77500<O20),ROUND(O22*O21,DpCU),IF(OR(AND(22500<O20,O20<25001),AND(50000<O20,O20<53501),AND(70000<O20,O20<72501)),ROUND($F20/100*O21,DpCU),IF(OR(AND(25000<O20,O20<27501),AND(53500<O20,O20<57001),AND(72500<O20,O20<75001)),ROUND($G20/100*O21,DpCU),ROUND($H20/100*O21,DpCU))))))) -> 1664.8
B24: =A20&"r" -> 10004r
A25: 10005 | B25: PROTECCION DE LINDEROS DE PANELES DE TRIPLAY DE 1.20 X 2.40 M X 4 MM | C25: =ROUND(J25*JL*Frto/8,4) -> 10 | D25: M | E25: =SUM($O28:$T28) -> 76.53 | F25: =SUMIF($O25:$T25,"<22501",$O28:$T28) -> 43.23 | G25: =SUMIFS($O28:$T28,$O25:$T25,">30000",$O25:$T25,"<50001") -> 31.14 | H25: =SUMIFS($O28:$T28,$O25:$T25,">60000",$O25:$T25,"<70001") -> 0 | I25: 6 | J25: 10 | O25: 10001 | P25: 10003 | Q25: 10005 | R25: 30010 | S25: 30013 | T25: 70001
B26: =A25&"C" -> 10005C | O26: 0.1 | P26: 2 | Q26: 1 | R26: 0.45 | S26: 1.7 | T26: 5
O27: =IF(O29>10000,HLOOKUP(O29,N25:$O28,4,FALSE),IF(OR(AND(22500<O25,O25<25001),AND(50000<O25,O25<53501),AND(70000<O25,O25<72501)),$F25,IF(OR(AND(25001<O25,O25<27501),AND(53500<O25,O25<57001),AND(72500<O25,O25<75001)),$G25,IF(OR(AND(27500<O25,O25<30001),AND(57000<O25,O25<60001),AND(75000<O25,O25<77500)),$H25,VLOOKUP(O25,BDins,6,FALSE))))) -> 24.97 | P27: =IF(P29>10000,HLOOKUP(P29,O25:$O28,4,FALSE),IF(OR(AND(22500<P25,P25<25001),AND(50000<P25,P25<53501),AND(70000<P25,P25<72501)),$F25,IF(OR(AND(25001<P25,P25<27501),AND(53500<P25,P25<57001),AND(72500<P25,P25<75001)),$G25,IF(OR(AND(27500<P25,P25<30001),AND(57000<P25,P25<60001),AND(75000<P25,P25<77500)),$H25,VLOOKUP(P25,BDins,6,FALSE))))) -> 15.36 | Q27: =IF(Q29>10000,HLOOKUP(Q29,$O25:P28,4,FALSE),IF(OR(AND(22500<Q25,Q25<25001),AND(50000<Q25,Q25<53501),AND(70000<Q25,Q25<72501)),$F25,IF(OR(AND(25001<Q25,Q25<27501),AND(53500<Q25,Q25<57001),AND(72500<Q25,Q25<75001)),$G25,IF(OR(AND(27500<Q25,Q25<30001),AND(57000<Q25,Q25<60001),AND(75000<Q25,Q25<77500)),$H25,VLOOKUP(Q25,BDins,6,FALSE))))) -> 20.81 | R27: =IF(R29>10000,HLOOKUP(R29,$O25:Q28,4,FALSE),IF(OR(AND(22500<R25,R25<25001),AND(50000<R25,R25<53501),AND(70000<R25,R25<72501)),$F25,IF(OR(AND(25001<R25,R25<27501),AND(53500<R25,R25<57001),AND(72500<R25,R25<75001)),$G25,IF(OR(AND(27500<R25,R25<30001),AND(57000<R25,R25<60001),AND(75000<R25,R25<77500)),$H25,VLOOKUP(R25,BDins,6,FALSE))))) -> 25 | S27: =IF(S29>10000,HLOOKUP(S29,$O25:R28,4,FALSE),IF(OR(AND(22500<S25,S25<25001),AND(50000<S25,S25<53501),AND(70000<S25,S25<72501)),$F25,IF(OR(AND(25001<S25,S25<27501),AND(53500<S25,S25<57001),AND(72500<S25,S25<75001)),$G25,IF(OR(AND(27500<S25,S25<30001),AND(57000<S25,S25<60001),AND(75000<S25,S25<77500)),$H25,VLOOKUP(S25,BDins,6,FALSE))))) -> 11.7 | T27: =IF(T29>10000,HLOOKUP(T29,$O25:S28,4,FALSE),IF(OR(AND(22500<T25,T25<25001),AND(50000<T25,T25<53501),AND(70000<T25,T25<72501)),$F25,IF(OR(AND(25001<T25,T25<27501),AND(53500<T25,T25<57001),AND(72500<T25,T25<75001)),$G25,IF(OR(AND(27500<T25,T25<30001),AND(57000<T25,T25<60001),AND(75000<T25,T25<77500)),$H25,VLOOKUP(T25,BDins,6,FALSE))))) -> 43.23
O28: =IF($K25>0,ROUND(O26*$E25/100,DpCU),IF(O29>10000,ROUND(HLOOKUP(O29,$O25:$T28,4,FALSE)/100*O26,DpCU),IF(OR(O25<20001,O25>95000,AND(60000<O25,O25<70001)),ROUND(ROUND(O26*JL/$C25,DcCU)*O27,DpCU),IF(OR(AND(20000<O25,O25<22501),AND(30000<O25,O25<50001),77500<O25),ROUND(O27*O26,DpCU),IF(OR(AND(22500<O25,O25<25001),AND(50000<O25,O25<53501),AND(70000<O25,O25<72501)),ROUND($F25/100*O26,DpCU),IF(OR(AND(25000<O25,O25<27501),AND(53500<O25,O25<57001),AND(72500<O25,O25<75001)),ROUND($G25/100*O26,DpCU),ROUND($H25/100*O26,DpCU))))))) -> 2 | P28: =IF($K25>0,ROUND(P26*$E25/100,DpCU),IF(P29>10000,ROUND(HLOOKUP(P29,$O25:$T28,4,FALSE)/100*P26,DpCU),IF(OR(P25<20001,P25>95000,AND(60000<P25,P25<70001)),ROUND(ROUND(P26*JL/$C25,DcCU)*P27,DpCU),IF(OR(AND(20000<P25,P25<22501),AND(30000<P25,P25<50001),77500<P25),ROUND(P27*P26,DpCU),IF(OR(AND(22500<P25,P25<25001),AND(50000<P25,P25<53501),AND(70000<P25,P25<72501)),ROUND($F25/100*P26,DpCU),IF(OR(AND(25000<P25,P25<27501),AND(53500<P25,P25<57001),AND(72500<P25,P25<75001)),ROUND($G25/100*P26,DpCU),ROUND($H25/100*P26,DpCU))))))) -> 24.58 | Q28: =IF($K25>0,ROUND(Q26*$E25/100,DpCU),IF(Q29>10000,ROUND(HLOOKUP(Q29,$O25:$T28,4,FALSE)/100*Q26,DpCU),IF(OR(Q25<20001,Q25>95000,AND(60000<Q25,Q25<70001)),ROUND(ROUND(Q26*JL/$C25,DcCU)*Q27,DpCU),IF(OR(AND(20000<Q25,Q25<22501),AND(30000<Q25,Q25<50001),77500<Q25),ROUND(Q27*Q26,DpCU),IF(OR(AND(22500<Q25,Q25<25001),AND(50000<Q25,Q25<53501),AND(70000<Q25,Q25<72501)),ROUND($F25/100*Q26,DpCU),IF(OR(AND(25000<Q25,Q25<27501),AND(53500<Q25,Q25<57001),AND(72500<Q25,Q25<75001)),ROUND($G25/100*Q26,DpCU),ROUND($H25/100*Q26,DpCU))))))) -> 16.65 | R28: =IF($K25>0,ROUND(R26*$E25/100,DpCU),IF(R29>10000,ROUND(HLOOKUP(R29,$O25:$T28,4,FALSE)/100*R26,DpCU),IF(OR(R25<20001,R25>95000,AND(60000<R25,R25<70001)),ROUND(ROUND(R26*JL/$C25,DcCU)*R27,DpCU),IF(OR(AND(20000<R25,R25<22501),AND(30000<R25,R25<50001),77500<R25),ROUND(R27*R26,DpCU),IF(OR(AND(22500<R25,R25<25001),AND(50000<R25,R25<53501),AND(70000<R25,R25<72501)),ROUND($F25/100*R26,DpCU),IF(OR(AND(25000<R25,R25<27501),AND(53500<R25,R25<57001),AND(72500<R25,R25<75001)),ROUND($G25/100*R26,DpCU),ROUND($H25/100*R26,DpCU))))))) -> 11.25 | S28: =IF($K25>0,ROUND(S26*$E25/100,DpCU),IF(S29>10000,ROUND(HLOOKUP(S29,$O25:$T28,4,FALSE)/100*S26,DpCU),IF(OR(S25<20001,S25>95000,AND(60000<S25,S25<70001)),ROUND(ROUND(S26*JL/$C25,DcCU)*S27,DpCU),IF(OR(AND(20000<S25,S25<22501),AND(30000<S25,S25<50001),77500<S25),ROUND(S27*S26,DpCU),IF(OR(AND(22500<S25,S25<25001),AND(50000<S25,S25<53501),AND(70000<S25,S25<72501)),ROUND($F25/100*S26,DpCU),IF(OR(AND(25000<S25,S25<27501),AND(53500<S25,S25<57001),AND(72500<S25,S25<75001)),ROUND($G25/100*S26,DpCU),ROUND($H25/100*S26,DpCU))))))) -> 19.89 | T28: =IF($K25>0,ROUND(T26*$E25/100,DpCU),IF(T29>10000,ROUND(HLOOKUP(T29,$O25:$T28,4,FALSE)/100*T26,DpCU),IF(OR(T25<20001,T25>95000,AND(60000<T25,T25<70001)),ROUND(ROUND(T26*JL/$C25,DcCU)*T27,DpCU),IF(OR(AND(20000<T25,T25<22501),AND(30000<T25,T25<50001),77500<T25),ROUND(T27*T26,DpCU),IF(OR(AND(22500<T25,T25<25001),AND(50000<T25,T25<53501),AND(70000<T25,T25<72501)),ROUND($F25/100*T26,DpCU),IF(OR(AND(25000<T25,T25<27501),AND(53500<T25,T25<57001),AND(72500<T25,T25<75001)),ROUND($G25/100*T26,DpCU),ROUND($H25/100*T26,DpCU))))))) -> 2.16
B29: =A25&"r" -> 10005r
A30: 10006 | B30: LIMPIEZA PERMANENTE DE LA OBRA | C30: =ROUND(J30*JL*Frto/8,4) -> 6 | D30: GLB | E30: =SUM($O33:$Q33) -> 2153.9 | F30: =SUMIF($O30:$Q30,"<22501",$O33:$Q33) -> 2051.33 | G30: =SUMIFS($O33:$Q33,$O30:$Q30,">30000",$O30:$Q30,"<50001") -> 0 | H30: =SUMIFS($O33:$Q33,$O30:$Q30,">60000",$O30:$Q30,"<70001") -> 0 | I30: 3 | J30: 6 | O30: 10001 | P30: 10003 | Q30: 70001
B31: =A30&"C" -> 10006C | O31: 0.1 | P31: 100 | Q31: 5
O32: =IF(O34>10000,HLOOKUP(O34,N30:$O33,4,FALSE),IF(OR(AND(22500<O30,O30<25001),AND(50000<O30,O30<53501),AND(70000<O30,O30<72501)),$F30,IF(OR(AND(25001<O30,O30<27501),AND(53500<O30,O30<57001),AND(72500<O30,O30<75001)),$G30,IF(OR(AND(27500<O30,O30<30001),AND(57000<O30,O30<60001),AND(75000<O30,O30<77500)),$H30,VLOOKUP(O30,BDins,6,FALSE))))) -> 24.97 | P32: =IF(P34>10000,HLOOKUP(P34,O30:$O33,4,FALSE),IF(OR(AND(22500<P30,P30<25001),AND(50000<P30,P30<53501),AND(70000<P30,P30<72501)),$F30,IF(OR(AND(25001<P30,P30<27501),AND(53500<P30,P30<57001),AND(72500<P30,P30<75001)),$G30,IF(OR(AND(27500<P30,P30<30001),AND(57000<P30,P30<60001),AND(75000<P30,P30<77500)),$H30,VLOOKUP(P30,BDins,6,FALSE))))) -> 15.36 | Q32: =IF(Q34>10000,HLOOKUP(Q34,$O30:P33,4,FALSE),IF(OR(AND(22500<Q30,Q30<25001),AND(50000<Q30,Q30<53501),AND(70000<Q30,Q30<72501)),$F30,IF(OR(AND(25001<Q30,Q30<27501),AND(53500<Q30,Q30<57001),AND(72500<Q30,Q30<75001)),$G30,IF(OR(AND(27500<Q30,Q30<30001),AND(57000<Q30,Q30<60001),AND(75000<Q30,Q30<77500)),$H30,VLOOKUP(Q30,BDins,6,FALSE))))) -> 2051.33
O33: =IF($K30>0,ROUND(O31*$E30/100,DpCU),IF(O34>10000,ROUND(HLOOKUP(O34,$O30:$Q33,4,FALSE)/100*O31,DpCU),IF(OR(O30<20001,O30>95000,AND(60000<O30,O30<70001)),ROUND(ROUND(O31*JL/$C30,DcCU)*O32,DpCU),IF(OR(AND(20000<O30,O30<22501),AND(30000<O30,O30<50001),77500<O30),ROUND(O32*O31,DpCU),IF(OR(AND(22500<O30,O30<25001),AND(50000<O30,O30<53501),AND(70000<O30,O30<72501)),ROUND($F30/100*O31,DpCU),IF(OR(AND(25000<O30,O30<27501),AND(53500<O30,O30<57001),AND(72500<O30,O30<75001)),ROUND($G30/100*O31,DpCU),ROUND($H30/100*O31,DpCU))))))) -> 3.33 | P33: =IF($K30>0,ROUND(P31*$E30/100,DpCU),IF(P34>10000,ROUND(HLOOKUP(P34,$O30:$Q33,4,FALSE)/100*P31,DpCU),IF(OR(P30<20001,P30>95000,AND(60000<P30,P30<70001)),ROUND(ROUND(P31*JL/$C30,DcCU)*P32,DpCU),IF(OR(AND(20000<P30,P30<22501),AND(30000<P30,P30<50001),77500<P30),ROUND(P32*P31,DpCU),IF(OR(AND(22500<P30,P30<25001),AND(50000<P30,P30<53501),AND(70000<P30,P30<72501)),ROUND($F30/100*P31,DpCU),IF(OR(AND(25000<P30,P30<27501),AND(53500<P30,P30<57001),AND(72500<P30,P30<75001)),ROUND($G30/100*P31,DpCU),ROUND($H30/100*P31,DpCU))))))) -> 2048 | Q33: =IF($K30>0,ROUND(Q31*$E30/100,DpCU),IF(Q34>10000,ROUND(HLOOKUP(Q34,$O30:$Q33,4,FALSE)/100*Q31,DpCU),IF(OR(Q30<20001,Q30>95000,AND(60000<Q30,Q30<70001)),ROUND(ROUND(Q31*JL/$C30,DcCU)*Q32,DpCU),IF(OR(AND(20000<Q30,Q30<22501),AND(30000<Q30,Q30<50001),77500<Q30),ROUND(Q32*Q31,DpCU),IF(OR(AND(22500<Q30,Q30<25001),AND(50000<Q30,Q30<53501),AND(70000<Q30,Q30<72501)),ROUND($F30/100*Q31,DpCU),IF(OR(AND(25000<Q30,Q30<27501),AND(53500<Q30,Q30<57001),AND(72500<Q30,Q30<75001)),ROUND($G30/100*Q31,DpCU),ROUND($H30/100*Q31,DpCU))))))) -> 102.57
B34: =A30&"r" -> 10006r
A35: 10007 | B35: CERCO METALICO PLANCHA ACANALADA | C35: =ROUND(J35*JL*Frto/8,4) -> 20 | D35: M | E35: =SUM($O38:$AB38) -> 251.98 | F35: =SUMIF($O35:$AB35,"<22501",$O38:$AB38) -> 15.46 | G35: =SUMIFS($O38:$AB38,$O35:$AB35,">30000",$O35:$AB35,"<50001") -> 232.2 | H35: =SUMIFS($O38:$AB38,$O35:$AB35,">60000",$O35:$AB35,"<70001") -> 2 | I35: 14 | J35: 20 | O35: 10001 | P35: 10002 | Q35: 10003 | R35: 30014 | S35: 30015 | T35: 30016 | U35: 30017 | V35: 30018 | W35: 30019 | X35: 30020 | Y35: 30021 | Z35: 30022 | AA35: 60001 | AB35: 70001
B36: =A35&"C" -> 10007C | O36: 0.1 | P36: 1 | Q36: 1 | R36: 0.1 | S36: 0.25 | T36: 5 | U36: 2 | V36: 0.5 | W36: 0.2 | X36: 0.2 | Y36: 2.55 | Z36: 0.3 | AA36: 0.5 | AB36: 15
O37: =IF(O39>10000,HLOOKUP(O39,N35:$O38,4,FALSE),IF(OR(AND(22500<O35,O35<25001),AND(50000<O35,O35<53501),AND(70000<O35,O35<72501)),$F35,IF(OR(AND(25001<O35,O35<27501),AND(53500<O35,O35<57001),AND(72500<O35,O35<75001)),$G35,IF(OR(AND(27500<O35,O35<30001),AND(57000<O35,O35<60001),AND(75000<O35,O35<77500)),$H35,VLOOKUP(O35,BDins,6,FALSE))))) -> 24.97 | P37: =IF(P39>10000,HLOOKUP(P39,O35:$O38,4,FALSE),IF(OR(AND(22500<P35,P35<25001),AND(50000<P35,P35<53501),AND(70000<P35,P35<72501)),$F35,IF(OR(AND(25001<P35,P35<27501),AND(53500<P35,P35<57001),AND(72500<P35,P35<75001)),$G35,IF(OR(AND(27500<P35,P35<30001),AND(57000<P35,P35<60001),AND(75000<P35,P35<77500)),$H35,VLOOKUP(P35,BDins,6,FALSE))))) -> 20.81 | Q37: =IF(Q39>10000,HLOOKUP(Q39,$O35:P38,4,FALSE),IF(OR(AND(22500<Q35,Q35<25001),AND(50000<Q35,Q35<53501),AND(70000<Q35,Q35<72501)),$F35,IF(OR(AND(25001<Q35,Q35<27501),AND(53500<Q35,Q35<57001),AND(72500<Q35,Q35<75001)),$G35,IF(OR(AND(27500<Q35,Q35<30001),AND(57000<Q35,Q35<60001),AND(75000<Q35,Q35<77500)),$H35,VLOOKUP(Q35,BDins,6,FALSE))))) -> 15.36 | R37: =IF(R39>10000,HLOOKUP(R39,$O35:Q38,4,FALSE),IF(OR(AND(22500<R35,R35<25001),AND(50000<R35,R35<53501),AND(70000<R35,R35<72501)),$F35,IF(OR(AND(25001<R35,R35<27501),AND(53500<R35,R35<57001),AND(72500<R35,R35<75001)),$G35,IF(OR(AND(27500<R35,R35<30001),AND(57000<R35,R35<60001),AND(75000<R35,R35<77500)),$H35,VLOOKUP(R35,BDins,6,FALSE))))) -> 12 | S37: =IF(S39>10000,HLOOKUP(S39,$O35:R38,4,FALSE),IF(OR(AND(22500<S35,S35<25001),AND(50000<S35,S35<53501),AND(70000<S35,S35<72501)),$F35,IF(OR(AND(25001<S35,S35<27501),AND(53500<S35,S35<57001),AND(72500<S35,S35<75001)),$G35,IF(OR(AND(27500<S35,S35<30001),AND(57000<S35,S35<60001),AND(75000<S35,S35<77500)),$H35,VLOOKUP(S35,BDins,6,FALSE))))) -> 7 | T37: =IF(T39>10000,HLOOKUP(T39,$O35:S38,4,FALSE),IF(OR(AND(22500<T35,T35<25001),AND(50000<T35,T35<53501),AND(70000<T35,T35<72501)),$F35,IF(OR(AND(25001<T35,T35<27501),AND(53500<T35,T35<57001),AND(72500<T35,T35<75001)),$G35,IF(OR(AND(27500<T35,T35<30001),AND(57000<T35,T35<60001),AND(75000<T35,T35<77500)),$H35,VLOOKUP(T35,BDins,6,FALSE))))) -> 8 | U37: =IF(U39>10000,HLOOKUP(U39,$O35:T38,4,FALSE),IF(OR(AND(22500<U35,U35<25001),AND(50000<U35,U35<53501),AND(70000<U35,U35<72501)),$F35,IF(OR(AND(25001<U35,U35<27501),AND(53500<U35,U35<57001),AND(72500<U35,U35<75001)),$G35,IF(OR(AND(27500<U35,U35<30001),AND(57000<U35,U35<60001),AND(75000<U35,U35<77500)),$H35,VLOOKUP(U35,BDins,6,FALSE))))) -> 15 | V37: =IF(V39>10000,HLOOKUP(V39,$O35:U38,4,FALSE),IF(OR(AND(22500<V35,V35<25001),AND(50000<V35,V35<53501),AND(70000<V35,V35<72501)),$F35,IF(OR(AND(25001<V35,V35<27501),AND(53500<V35,V35<57001),AND(72500<V35,V35<75001)),$G35,IF(OR(AND(27500<V35,V35<30001),AND(57000<V35,V35<60001),AND(75000<V35,V35<77500)),$H35,VLOOKUP(V35,BDins,6,FALSE))))) -> 13.5 | W37: =IF(W39>10000,HLOOKUP(W39,$O35:V38,4,FALSE),IF(OR(AND(22500<W35,W35<25001),AND(50000<W35,W35<53501),AND(70000<W35,W35<72501)),$F35,IF(OR(AND(25001<W35,W35<27501),AND(53500<W35,W35<57001),AND(72500<W35,W35<75001)),$G35,IF(OR(AND(27500<W35,W35<30001),AND(57000<W35,W35<60001),AND(75000<W35,W35<77500)),$H35,VLOOKUP(W35,BDins,6,FALSE))))) -> 40 | X37: =IF(X39>10000,HLOOKUP(X39,$O35:W38,4,FALSE),IF(OR(AND(22500<X35,X35<25001),AND(50000<X35,X35<53501),AND(70000<X35,X35<72501)),$F35,IF(OR(AND(25001<X35,X35<27501),AND(53500<X35,X35<57001),AND(72500<X35,X35<75001)),$G35,IF(OR(AND(27500<X35,X35<30001),AND(57000<X35,X35<60001),AND(75000<X35,X35<77500)),$H35,VLOOKUP(X35,BDins,6,FALSE))))) -> 40 | ... AB37: =IF(AB39>10000,HLOOKUP(AB39,$O35:AA38,4,FALSE),IF(OR(AND(22500<AB35,AB35<25001),AND(50000<AB35,AB35<53501),AND(70000<AB35,AB35<72501)),$F35,IF(OR(AND(25001<AB35,AB35<27501),AND(53500<AB35,AB35<57001),AND(72500<AB35,AB35<75001)),$G35,IF(OR(AND(27500<AB35,AB35<30001),AND(57000<AB35,AB35<60001),AND(75000<AB35,AB35<77500)),$H35,VLOOKUP(AB35,BDins,6,FALSE))))) -> 15.46
O38: =IF($K35>0,ROUND(O36*$E35/100,DpCU),IF(O39>10000,ROUND(HLOOKUP(O39,$O35:$AB38,4,FALSE)/100*O36,DpCU),IF(OR(O35<20001,O35>95000,AND(60000<O35,O35<70001)),ROUND(ROUND(O36*JL/$C35,DcCU)*O37,DpCU),IF(OR(AND(20000<O35,O35<22501),AND(30000<O35,O35<50001),77500<O35),ROUND(O37*O36,DpCU),IF(OR(AND(22500<O35,O35<25001),AND(50000<O35,O35<53501),AND(70000<O35,O35<72501)),ROUND($F35/100*O36,DpCU),IF(OR(AND(25000<O35,O35<27501),AND(53500<O35,O35<57001),AND(72500<O35,O35<75001)),ROUND($G35/100*O36,DpCU),ROUND($H35/100*O36,DpCU))))))) -> 1 | P38: =IF($K35>0,ROUND(P36*$E35/100,DpCU),IF(P39>10000,ROUND(HLOOKUP(P39,$O35:$AB38,4,FALSE)/100*P36,DpCU),IF(OR(P35<20001,P35>95000,AND(60000<P35,P35<70001)),ROUND(ROUND(P36*JL/$C35,DcCU)*P37,DpCU),IF(OR(AND(20000<P35,P35<22501),AND(30000<P35,P35<50001),77500<P35),ROUND(P37*P36,DpCU),IF(OR(AND(22500<P35,P35<25001),AND(50000<P35,P35<53501),AND(70000<P35,P35<72501)),ROUND($F35/100*P36,DpCU),IF(OR(AND(25000<P35,P35<27501),AND(53500<P35,P35<57001),AND(72500<P35,P35<75001)),ROUND($G35/100*P36,DpCU),ROUND($H35/100*P36,DpCU))))))) -> 8.32 | Q38: =IF($K35>0,ROUND(Q36*$E35/100,DpCU),IF(Q39>10000,ROUND(HLOOKUP(Q39,$O35:$AB38,4,FALSE)/100*Q36,DpCU),IF(OR(Q35<20001,Q35>95000,AND(60000<Q35,Q35<70001)),ROUND(ROUND(Q36*JL/$C35,DcCU)*Q37,DpCU),IF(OR(AND(20000<Q35,Q35<22501),AND(30000<Q35,Q35<50001),77500<Q35),ROUND(Q37*Q36,DpCU),IF(OR(AND(22500<Q35,Q35<25001),AND(50000<Q35,Q35<53501),AND(70000<Q35,Q35<72501)),ROUND($F35/100*Q36,DpCU),IF(OR(AND(25000<Q35,Q35<27501),AND(53500<Q35,Q35<57001),AND(72500<Q35,Q35<75001)),ROUND($G35/100*Q36,DpCU),ROUND($H35/100*Q36,DpCU))))))) -> 6.14 | R38: =IF($K35>0,ROUND(R36*$E35/100,DpCU),IF(R39>10000,ROUND(HLOOKUP(R39,$O35:$AB38,4,FALSE)/100*R36,DpCU),IF(OR(R35<20001,R35>95000,AND(60000<R35,R35<70001)),ROUND(ROUND(R36*JL/$C35,DcCU)*R37,DpCU),IF(OR(AND(20000<R35,R35<22501),AND(30000<R35,R35<50001),77500<R35),ROUND(R37*R36,DpCU),IF(OR(AND(22500<R35,R35<25001),AND(50000<R35,R35<53501),AND(70000<R35,R35<72501)),ROUND($F35/100*R36,DpCU),IF(OR(AND(25000<R35,R35<27501),AND(53500<R35,R35<57001),AND(72500<R35,R35<75001)),ROUND($G35/100*R36,DpCU),ROUND($H35/100*R36,DpCU))))))) -> 1.2 | S38: =IF($K35>0,ROUND(S36*$E35/100,DpCU),IF(S39>10000,ROUND(HLOOKUP(S39,$O35:$AB38,4,FALSE)/100*S36,DpCU),IF(OR(S35<20001,S35>95000,AND(60000<S35,S35<70001)),ROUND(ROUND(S36*JL/$C35,DcCU)*S37,DpCU),IF(OR(AND(20000<S35,S35<22501),AND(30000<S35,S35<50001),77500<S35),ROUND(S37*S36,DpCU),IF(OR(AND(22500<S35,S35<25001),AND(50000<S35,S35<53501),AND(70000<S35,S35<72501)),ROUND($F35/100*S36,DpCU),IF(OR(AND(25000<S35,S35<27501),AND(53500<S35,S35<57001),AND(72500<S35,S35<75001)),ROUND($G35/100*S36,DpCU),ROUND($H35/100*S36,DpCU))))))) -> 1.75 | T38: =IF($K35>0,ROUND(T36*$E35/100,DpCU),IF(T39>10000,ROUND(HLOOKUP(T39,$O35:$AB38,4,FALSE)/100*T36,DpCU),IF(OR(T35<20001,T35>95000,AND(60000<T35,T35<70001)),ROUND(ROUND(T36*JL/$C35,DcCU)*T37,DpCU),IF(OR(AND(20000<T35,T35<22501),AND(30000<T35,T35<50001),77500<T35),ROUND(T37*T36,DpCU),IF(OR(AND(22500<T35,T35<25001),AND(50000<T35,T35<53501),AND(70000<T35,T35<72501)),ROUND($F35/100*T36,DpCU),IF(OR(AND(25000<T35,T35<27501),AND(53500<T35,T35<57001),AND(72500<T35,T35<75001)),ROUND($G35/100*T36,DpCU),ROUND($H35/100*T36,DpCU))))))) -> 40 | U38: =IF($K35>0,ROUND(U36*$E35/100,DpCU),IF(U39>10000,ROUND(HLOOKUP(U39,$O35:$AB38,4,FALSE)/100*U36,DpCU),IF(OR(U35<20001,U35>95000,AND(60000<U35,U35<70001)),ROUND(ROUND(U36*JL/$C35,DcCU)*U37,DpCU),IF(OR(AND(20000<U35,U35<22501),AND(30000<U35,U35<50001),77500<U35),ROUND(U37*U36,DpCU),IF(OR(AND(22500<U35,U35<25001),AND(50000<U35,U35<53501),AND(70000<U35,U35<72501)),ROUND($F35/100*U36,DpCU),IF(OR(AND(25000<U35,U35<27501),AND(53500<U35,U35<57001),AND(72500<U35,U35<75001)),ROUND($G35/100*U36,DpCU),ROUND($H35/100*U36,DpCU))))))) -> 30 | V38: =IF($K35>0,ROUND(V36*$E35/100,DpCU),IF(V39>10000,ROUND(HLOOKUP(V39,$O35:$AB38,4,FALSE)/100*V36,DpCU),IF(OR(V35<20001,V35>95000,AND(60000<V35,V35<70001)),ROUND(ROUND(V36*JL/$C35,DcCU)*V37,DpCU),IF(OR(AND(20000<V35,V35<22501),AND(30000<V35,V35<50001),77500<V35),ROUND(V37*V36,DpCU),IF(OR(AND(22500<V35,V35<25001),AND(50000<V35,V35<53501),AND(70000<V35,V35<72501)),ROUND($F35/100*V36,DpCU),IF(OR(AND(25000<V35,V35<27501),AND(53500<V35,V35<57001),AND(72500<V35,V35<75001)),ROUND($G35/100*V36,DpCU),ROUND($H35/100*V36,DpCU))))))) -> 6.75 | ... AB38: =IF($K35>0,ROUND(AB36*$E35/100,DpCU),IF(AB39>10000,ROUND(HLOOKUP(AB39,$O35:$AB38,4,FALSE)/100*AB36,DpCU),IF(OR(AB35<20001,AB35>95000,AND(60000<AB35,AB35<70001)),ROUND(ROUND(AB36*JL/$C35,DcCU)*AB37,DpCU),IF(OR(AND(20000<AB35,AB35<22501),AND(30000<AB35,AB35<50001),77500<AB35),ROUND(AB37*AB36,DpCU),IF(OR(AND(22500<AB35,AB35<25001),AND(50000<AB35,AB35<53501),AND(70000<AB35,AB35<72501)),ROUND($F35/100*AB36,DpCU),IF(OR(AND(25000<AB35,AB35<27501),AND(53500<AB35,AB35<57001),AND(72500<AB35,AB35<75001)),ROUND($G35/100*AB36,DpCU),ROUND($H35/100*AB36,DpCU))))))) -> 2.32
B39: =A35&"r" -> 10007r
A40: 10008 | B40: CONSUMO DE AGUA POTABLE DURANTE LA OBRA | C40: =ROUND(J40*JL*Frto/8,4) -> 8 | D40: MES | E40: =SUM($O43:$O43) -> 150 | F40: =SUMIF($O40:$O40,"<22501",$O43:$O43) -> 0 | G40: =SUMIFS($O43:$O43,$O40:$O40,">30000",$O40:$O40,"<50001") -> 150 | H40: =SUMIFS($O43:$O43,$O40:$O40,">60000",$O40:$O40,"<70001") -> 0 | I40: 1 | J40: 8 | O40: 30023
B41: =A40&"C" -> 10008C | O41: 1
O42: =IF(O44>10000,HLOOKUP(O44,N40:$O43,4,FALSE),IF(OR(AND(22500<O40,O40<25001),AND(50000<O40,O40<53501),AND(70000<O40,O40<72501)),$F40,IF(OR(AND(25001<O40,O40<27501),AND(53500<O40,O40<57001),AND(72500<O40,O40<75001)),$G40,IF(OR(AND(27500<O40,O40<30001),AND(57000<O40,O40<60001),AND(75000<O40,O40<77500)),$H40,VLOOKUP(O40,BDins,6,FALSE))))) -> 150
O43: =IF($K40>0,ROUND(O41*$E40/100,DpCU),IF(O44>10000,ROUND(HLOOKUP(O44,$O40:$O43,4,FALSE)/100*O41,DpCU),IF(OR(O40<20001,O40>95000,AND(60000<O40,O40<70001)),ROUND(ROUND(O41*JL/$C40,DcCU)*O42,DpCU),IF(OR(AND(20000<O40,O40<22501),AND(30000<O40,O40<50001),77500<O40),ROUND(O42*O41,DpCU),IF(OR(AND(22500<O40,O40<25001),AND(50000<O40,O40<53501),AND(70000<O40,O40<72501)),ROUND($F40/100*O41,DpCU),IF(OR(AND(25000<O40,O40<27501),AND(53500<O40,O40<57001),AND(72500<O40,O40<75001)),ROUND($G40/100*O41,DpCU),ROUND($H40/100*O41,DpCU))))))) -> 150
B44: =A40&"r" -> 10008r
A45: 10009 | B45: INSTALACIONES PROVISIONALES DE ENERGIA ELECTRICA | C45: =ROUND(J45*JL*Frto/8,4) -> 1 | D45: GLB | E45: =SUM($O48:$O48) -> 1500 | F45: =SUMIF($O45:$O45,"<22501",$O48:$O48) -> 0 | G45: =SUMIFS($O48:$O48,$O45:$O45,">30000",$O45:$O45,"<50001") -> 1500 | H45: =SUMIFS($O48:$O48,$O45:$O45,">60000",$O45:$O45,"<70001") -> 0 | I45: 1 | J45: 1 | O45: 30024
B46: =A45&"C" -> 10009C | O46: 1
O47: =IF(O49>10000,HLOOKUP(O49,N45:$O48,4,FALSE),IF(OR(AND(22500<O45,O45<25001),AND(50000<O45,O45<53501),AND(70000<O45,O45<72501)),$F45,IF(OR(AND(25001<O45,O45<27501),AND(53500<O45,O45<57001),AND(72500<O45,O45<75001)),$G45,IF(OR(AND(27500<O45,O45<30001),AND(57000<O45,O45<60001),AND(75000<O45,O45<77500)),$H45,VLOOKUP(O45,BDins,6,FALSE))))) -> 1500
O48: =IF($K45>0,ROUND(O46*$E45/100,DpCU),IF(O49>10000,ROUND(HLOOKUP(O49,$O45:$O48,4,FALSE)/100*O46,DpCU),IF(OR(O45<20001,O45>95000,AND(60000<O45,O45<70001)),ROUND(ROUND(O46*JL/$C45,DcCU)*O47,DpCU),IF(OR(AND(20000<O45,O45<22501),AND(30000<O45,O45<50001),77500<O45),ROUND(O47*O46,DpCU),IF(OR(AND(22500<O45,O45<25001),AND(50000<O45,O45<53501),AND(70000<O45,O45<72501)),ROUND($F45/100*O46,DpCU),IF(OR(AND(25000<O45,O45<27501),AND(53500<O45,O45<57001),AND(72500<O45,O45<75001)),ROUND($G45/100*O46,DpCU),ROUND($H45/100*O46,DpCU))))))) -> 1500
B49: =A45&"r" -> 10009r
A50: 10010 | B50: CONSUMO DE ENERGIA ELECTRICA DURANTE LA OBRA | C50: =ROUND(J50*JL*Frto/8,4) -> 1 | D50: MES | E50: =SUM($O53:$O53) -> 150 | F50: =SUMIF($O50:$O50,"<22501",$O53:$O53) -> 0 | G50: =SUMIFS($O53:$O53,$O50:$O50,">30000",$O50:$O50,"<50001") -> 0 | H50: =SUMIFS($O53:$O53,$O50:$O50,">60000",$O50:$O50,"<70001") -> 0 | I50: 1 | J50: 1 | O50: 80001
B51: =A50&"C" -> 10010C | O51: 1
O52: =IF(O54>10000,HLOOKUP(O54,N50:$O53,4,FALSE),IF(OR(AND(22500<O50,O50<25001),AND(50000<O50,O50<53501),AND(70000<O50,O50<72501)),$F50,IF(OR(AND(25001<O50,O50<27501),AND(53500<O50,O50<57001),AND(72500<O50,O50<75001)),$G50,IF(OR(AND(27500<O50,O50<30001),AND(57000<O50,O50<60001),AND(75000<O50,O50<77500)),$H50,VLOOKUP(O50,BDins,6,FALSE))))) -> 150
O53: =IF($K50>0,ROUND(O51*$E50/100,DpCU),IF(O54>10000,ROUND(HLOOKUP(O54,$O50:$O53,4,FALSE)/100*O51,DpCU),IF(OR(O50<20001,O50>95000,AND(60000<O50,O50<70001)),ROUND(ROUND(O51*JL/$C50,DcCU)*O52,DpCU),IF(OR(AND(20000<O50,O50<22501),AND(30000<O50,O50<50001),77500<O50),ROUND(O52*O51,DpCU),IF(OR(AND(22500<O50,O50<25001),AND(50000<O50,O50<53501),AND(70000<O50,O50<72501)),ROUND($F50/100*O51,DpCU),IF(OR(AND(25000<O50,O50<27501),AND(53500<O50,O50<57001),AND(72500<O50,O50<75001)),ROUND($G50/100*O51,DpCU),ROUND($H50/100*O51,DpCU))))))) -> 150
B54: =A50&"r" -> 10010r
A55: 10011 | B55: LIMPIEZA TERRENO | C55: =ROUND(J55*JL*Frto/8,4) -> 400 | D55: M3 | E55: =SUM($O58:$R58) -> 1000.69 | F55: =SUMIF($O55:$R55,"<22501",$O58:$R58) -> 0.66 | G55: =SUMIFS($O58:$R58,$O55:$R55,">30000",$O55:$R55,"<50001") -> 0 | H55: =SUMIFS($O58:$R58,$O55:$R55,">60000",$O55:$R55,"<70001") -> 0 | I55: 4 | J55: 400 | O55: 10001 | P55: 10003 | Q55: 70001 | R55: 80002
B56: =A55&"C" -> 10011C | O56: 0.1 | P56: 2 | Q56: 5 | R56: 50
O57: =IF(O59>10000,HLOOKUP(O59,N55:$O58,4,FALSE),IF(OR(AND(22500<O55,O55<25001),AND(50000<O55,O55<53501),AND(70000<O55,O55<72501)),$F55,IF(OR(AND(25001<O55,O55<27501),AND(53500<O55,O55<57001),AND(72500<O55,O55<75001)),$G55,IF(OR(AND(27500<O55,O55<30001),AND(57000<O55,O55<60001),AND(75000<O55,O55<77500)),$H55,VLOOKUP(O55,BDins,6,FALSE))))) -> 24.97 | P57: =IF(P59>10000,HLOOKUP(P59,O55:$O58,4,FALSE),IF(OR(AND(22500<P55,P55<25001),AND(50000<P55,P55<53501),AND(70000<P55,P55<72501)),$F55,IF(OR(AND(25001<P55,P55<27501),AND(53500<P55,P55<57001),AND(72500<P55,P55<75001)),$G55,IF(OR(AND(27500<P55,P55<30001),AND(57000<P55,P55<60001),AND(75000<P55,P55<77500)),$H55,VLOOKUP(P55,BDins,6,FALSE))))) -> 15.36 | Q57: =IF(Q59>10000,HLOOKUP(Q59,$O55:P58,4,FALSE),IF(OR(AND(22500<Q55,Q55<25001),AND(50000<Q55,Q55<53501),AND(70000<Q55,Q55<72501)),$F55,IF(OR(AND(25001<Q55,Q55<27501),AND(53500<Q55,Q55<57001),AND(72500<Q55,Q55<75001)),$G55,IF(OR(AND(27500<Q55,Q55<30001),AND(57000<Q55,Q55<60001),AND(75000<Q55,Q55<77500)),$H55,VLOOKUP(Q55,BDins,6,FALSE))))) -> 0.66 | R57: =IF(R59>10000,HLOOKUP(R59,$O55:Q58,4,FALSE),IF(OR(AND(22500<R55,R55<25001),AND(50000<R55,R55<53501),AND(70000<R55,R55<72501)),$F55,IF(OR(AND(25001<R55,R55<27501),AND(53500<R55,R55<57001),AND(72500<R55,R55<75001)),$G55,IF(OR(AND(27500<R55,R55<30001),AND(57000<R55,R55<60001),AND(75000<R55,R55<77500)),$H55,VLOOKUP(R55,BDins,6,FALSE))))) -> 20
O58: =IF($K55>0,ROUND(O56*$E55/100,DpCU),IF(O59>10000,ROUND(HLOOKUP(O59,$O55:$R58,4,FALSE)/100*O56,DpCU),IF(OR(O55<20001,O55>95000,AND(60000<O55,O55<70001)),ROUND(ROUND(O56*JL/$C55,DcCU)*O57,DpCU),IF(OR(AND(20000<O55,O55<22501),AND(30000<O55,O55<50001),77500<O55),ROUND(O57*O56,DpCU),IF(OR(AND(22500<O55,O55<25001),AND(50000<O55,O55<53501),AND(70000<O55,O55<72501)),ROUND($F55/100*O56,DpCU),IF(OR(AND(25000<O55,O55<27501),AND(53500<O55,O55<57001),AND(72500<O55,O55<75001)),ROUND($G55/100*O56,DpCU),ROUND($H55/100*O56,DpCU))))))) -> 0.05 | P58: =IF($K55>0,ROUND(P56*$E55/100,DpCU),IF(P59>10000,ROUND(HLOOKUP(P59,$O55:$R58,4,FALSE)/100*P56,DpCU),IF(OR(P55<20001,P55>95000,AND(60000<P55,P55<70001)),ROUND(ROUND(P56*JL/$C55,DcCU)*P57,DpCU),IF(OR(AND(20000<P55,P55<22501),AND(30000<P55,P55<50001),77500<P55),ROUND(P57*P56,DpCU),IF(OR(AND(22500<P55,P55<25001),AND(50000<P55,P55<53501),AND(70000<P55,P55<72501)),ROUND($F55/100*P56,DpCU),IF(OR(AND(25000<P55,P55<27501),AND(53500<P55,P55<57001),AND(72500<P55,P55<75001)),ROUND($G55/100*P56,DpCU),ROUND($H55/100*P56,DpCU))))))) -> 0.61 | Q58: =IF($K55>0,ROUND(Q56*$E55/100,DpCU),IF(Q59>10000,ROUND(HLOOKUP(Q59,$O55:$R58,4,FALSE)/100*Q56,DpCU),IF(OR(Q55<20001,Q55>95000,AND(60000<Q55,Q55<70001)),ROUND(ROUND(Q56*JL/$C55,DcCU)*Q57,DpCU),IF(OR(AND(20000<Q55,Q55<22501),AND(30000<Q55,Q55<50001),77500<Q55),ROUND(Q57*Q56,DpCU),IF(OR(AND(22500<Q55,Q55<25001),AND(50000<Q55,Q55<53501),AND(70000<Q55,Q55<72501)),ROUND($F55/100*Q56,DpCU),IF(OR(AND(25000<Q55,Q55<27501),AND(53500<Q55,Q55<57001),AND(72500<Q55,Q55<75001)),ROUND($G55/100*Q56,DpCU),ROUND($H55/100*Q56,DpCU))))))) -> 0.03 | R58: =IF($K55>0,ROUND(R56*$E55/100,DpCU),IF(R59>10000,ROUND(HLOOKUP(R59,$O55:$R58,4,FALSE)/100*R56,DpCU),IF(OR(R55<20001,R55>95000,AND(60000<R55,R55<70001)),ROUND(ROUND(R56*JL/$C55,DcCU)*R57,DpCU),IF(OR(AND(20000<R55,R55<22501),AND(30000<R55,R55<50001),77500<R55),ROUND(R57*R56,DpCU),IF(OR(AND(22500<R55,R55<25001),AND(50000<R55,R55<53501),AND(70000<R55,R55<72501)),ROUND($F55/100*R56,DpCU),IF(OR(AND(25000<R55,R55<27501),AND(53500<R55,R55<57001),AND(72500<R55,R55<75001)),ROUND($G55/100*R56,DpCU),ROUND($H55/100*R56,DpCU))))))) -> 1000
B59: =A55&"r" -> 10011r
A60: 10012 | B60: DEMOLICION DE CIMIENTO DE CONCRETO CICLOPEO | C60: =ROUND(J60*JL*Frto/8,4) -> 1 | D60: M3 | E60: =SUM($O63:$R63) -> 304.73 | F60: =SUMIF($O60:$R60,"<22501",$O63:$R63) -> 204.3 | G60: =SUMIFS($O63:$R63,$O60:$R60,">30000",$O60:$R60,"<50001") -> 0 | H60: =SUMIFS($O63:$R63,$O60:$R60,">60000",$O60:$R60,"<70001") -> 80 | I60: 4 | J60: 1 | O60: 10001 | P60: 10003 | Q60: 60002 | R60: 70001
B61: =A60&"C" -> 10012C | O61: 0.1 | P61: 1.5 | Q61: 1 | R61: 10
O62: =IF(O64>10000,HLOOKUP(O64,N60:$O63,4,FALSE),IF(OR(AND(22500<O60,O60<25001),AND(50000<O60,O60<53501),AND(70000<O60,O60<72501)),$F60,IF(OR(AND(25001<O60,O60<27501),AND(53500<O60,O60<57001),AND(72500<O60,O60<75001)),$G60,IF(OR(AND(27500<O60,O60<30001),AND(57000<O60,O60<60001),AND(75000<O60,O60<77500)),$H60,VLOOKUP(O60,BDins,6,FALSE))))) -> 24.97 | P62: =IF(P64>10000,HLOOKUP(P64,O60:$O63,4,FALSE),IF(OR(AND(22500<P60,P60<25001),AND(50000<P60,P60<53501),AND(70000<P60,P60<72501)),$F60,IF(OR(AND(25001<P60,P60<27501),AND(53500<P60,P60<57001),AND(72500<P60,P60<75001)),$G60,IF(OR(AND(27500<P60,P60<30001),AND(57000<P60,P60<60001),AND(75000<P60,P60<77500)),$H60,VLOOKUP(P60,BDins,6,FALSE))))) -> 15.36 | Q62: =IF(Q64>10000,HLOOKUP(Q64,$O60:P63,4,FALSE),IF(OR(AND(22500<Q60,Q60<25001),AND(50000<Q60,Q60<53501),AND(70000<Q60,Q60<72501)),$F60,IF(OR(AND(25001<Q60,Q60<27501),AND(53500<Q60,Q60<57001),AND(72500<Q60,Q60<75001)),$G60,IF(OR(AND(27500<Q60,Q60<30001),AND(57000<Q60,Q60<60001),AND(75000<Q60,Q60<77500)),$H60,VLOOKUP(Q60,BDins,6,FALSE))))) -> 10 | R62: =IF(R64>10000,HLOOKUP(R64,$O60:Q63,4,FALSE),IF(OR(AND(22500<R60,R60<25001),AND(50000<R60,R60<53501),AND(70000<R60,R60<72501)),$F60,IF(OR(AND(25001<R60,R60<27501),AND(53500<R60,R60<57001),AND(72500<R60,R60<75001)),$G60,IF(OR(AND(27500<R60,R60<30001),AND(57000<R60,R60<60001),AND(75000<R60,R60<77500)),$H60,VLOOKUP(R60,BDins,6,FALSE))))) -> 204.3
O63: =IF($K60>0,ROUND(O61*$E60/100,DpCU),IF(O64>10000,ROUND(HLOOKUP(O64,$O60:$R63,4,FALSE)/100*O61,DpCU),IF(OR(O60<20001,O60>95000,AND(60000<O60,O60<70001)),ROUND(ROUND(O61*JL/$C60,DcCU)*O62,DpCU),IF(OR(AND(20000<O60,O60<22501),AND(30000<O60,O60<50001),77500<O60),ROUND(O62*O61,DpCU),IF(OR(AND(22500<O60,O60<25001),AND(50000<O60,O60<53501),AND(70000<O60,O60<72501)),ROUND($F60/100*O61,DpCU),IF(OR(AND(25000<O60,O60<27501),AND(53500<O60,O60<57001),AND(72500<O60,O60<75001)),ROUND($G60/100*O61,DpCU),ROUND($H60/100*O61,DpCU))))))) -> 19.98 | P63: =IF($K60>0,ROUND(P61*$E60/100,DpCU),IF(P64>10000,ROUND(HLOOKUP(P64,$O60:$R63,4,FALSE)/100*P61,DpCU),IF(OR(P60<20001,P60>95000,AND(60000<P60,P60<70001)),ROUND(ROUND(P61*JL/$C60,DcCU)*P62,DpCU),IF(OR(AND(20000<P60,P60<22501),AND(30000<P60,P60<50001),77500<P60),ROUND(P62*P61,DpCU),IF(OR(AND(22500<P60,P60<25001),AND(50000<P60,P60<53501),AND(70000<P60,P60<72501)),ROUND($F60/100*P61,DpCU),IF(OR(AND(25000<P60,P60<27501),AND(53500<P60,P60<57001),AND(72500<P60,P60<75001)),ROUND($G60/100*P61,DpCU),ROUND($H60/100*P61,DpCU))))))) -> 184.32 | Q63: =IF($K60>0,ROUND(Q61*$E60/100,DpCU),IF(Q64>10000,ROUND(HLOOKUP(Q64,$O60:$R63,4,FALSE)/100*Q61,DpCU),IF(OR(Q60<20001,Q60>95000,AND(60000<Q60,Q60<70001)),ROUND(ROUND(Q61*JL/$C60,DcCU)*Q62,DpCU),IF(OR(AND(20000<Q60,Q60<22501),AND(30000<Q60,Q60<50001),77500<Q60),ROUND(Q62*Q61,DpCU),IF(OR(AND(22500<Q60,Q60<25001),AND(50000<Q60,Q60<53501),AND(70000<Q60,Q60<72501)),ROUND($F60/100*Q61,DpCU),IF(OR(AND(25000<Q60,Q60<27501),AND(53500<Q60,Q60<57001),AND(72500<Q60,Q60<75001)),ROUND($G60/100*Q61,DpCU),ROUND($H60/100*Q61,DpCU))))))) -> 80 | R63: =IF($K60>0,ROUND(R61*$E60/100,DpCU),IF(R64>10000,ROUND(HLOOKUP(R64,$O60:$R63,4,FALSE)/100*R61,DpCU),IF(OR(R60<20001,R60>95000,AND(60000<R60,R60<70001)),ROUND(ROUND(R61*JL/$C60,DcCU)*R62,DpCU),IF(OR(AND(20000<R60,R60<22501),AND(30000<R60,R60<50001),77500<R60),ROUND(R62*R61,DpCU),IF(OR(AND(22500<R60,R60<25001),AND(50000<R60,R60<53501),AND(70000<R60,R60<72501)),ROUND($F60/100*R61,DpCU),IF(OR(AND(25000<R60,R60<27501),AND(53500<R60,R60<57001),AND(72500<R60,R60<75001)),ROUND($G60/100*R61,DpCU),ROUND($H60/100*R61,DpCU))))))) -> 20.43
B64: =A60&"r" -> 10012r
A65: 10013 | B65: DEMOLICION DE SOBRECIMIENTOS | C65: =ROUND(J65*JL*Frto/8,4) -> 1.25 | D65: M3 | E65: =SUM($O68:$R68) -> 189.71 | F65: =SUMIF($O65:$R65,"<22501",$O68:$R68) -> 114.28 | G65: =SUMIFS($O68:$R68,$O65:$R65,">30000",$O65:$R65,"<50001") -> 0 | H65: =SUMIFS($O68:$R68,$O65:$R65,">60000",$O65:$R65,"<70001") -> 64 | I65: 4 | J65: 1.25 | O65: 10001 | P65: 10003 | Q65: 60002 | R65: 70001
B66: =A65&"C" -> 10013C | O66: 0.1 | P66: 1 | Q66: 1 | R66: 10
O67: =IF(O69>10000,HLOOKUP(O69,N65:$O68,4,FALSE),IF(OR(AND(22500<O65,O65<25001),AND(50000<O65,O65<53501),AND(70000<O65,O65<72501)),$F65,IF(OR(AND(25001<O65,O65<27501),AND(53500<O65,O65<57001),AND(72500<O65,O65<75001)),$G65,IF(OR(AND(27500<O65,O65<30001),AND(57000<O65,O65<60001),AND(75000<O65,O65<77500)),$H65,VLOOKUP(O65,BDins,6,FALSE))))) -> 24.97 | P67: =IF(P69>10000,HLOOKUP(P69,O65:$O68,4,FALSE),IF(OR(AND(22500<P65,P65<25001),AND(50000<P65,P65<53501),AND(70000<P65,P65<72501)),$F65,IF(OR(AND(25001<P65,P65<27501),AND(53500<P65,P65<57001),AND(72500<P65,P65<75001)),$G65,IF(OR(AND(27500<P65,P65<30001),AND(57000<P65,P65<60001),AND(75000<P65,P65<77500)),$H65,VLOOKUP(P65,BDins,6,FALSE))))) -> 15.36 | Q67: =IF(Q69>10000,HLOOKUP(Q69,$O65:P68,4,FALSE),IF(OR(AND(22500<Q65,Q65<25001),AND(50000<Q65,Q65<53501),AND(70000<Q65,Q65<72501)),$F65,IF(OR(AND(25001<Q65,Q65<27501),AND(53500<Q65,Q65<57001),AND(72500<Q65,Q65<75001)),$G65,IF(OR(AND(27500<Q65,Q65<30001),AND(57000<Q65,Q65<60001),AND(75000<Q65,Q65<77500)),$H65,VLOOKUP(Q65,BDins,6,FALSE))))) -> 10 | R67: =IF(R69>10000,HLOOKUP(R69,$O65:Q68,4,FALSE),IF(OR(AND(22500<R65,R65<25001),AND(50000<R65,R65<53501),AND(70000<R65,R65<72501)),$F65,IF(OR(AND(25001<R65,R65<27501),AND(53500<R65,R65<57001),AND(72500<R65,R65<75001)),$G65,IF(OR(AND(27500<R65,R65<30001),AND(57000<R65,R65<60001),AND(75000<R65,R65<77500)),$H65,VLOOKUP(R65,BDins,6,FALSE))))) -> 114.28
O68: =IF($K65>0,ROUND(O66*$E65/100,DpCU),IF(O69>10000,ROUND(HLOOKUP(O69,$O65:$R68,4,FALSE)/100*O66,DpCU),IF(OR(O65<20001,O65>95000,AND(60000<O65,O65<70001)),ROUND(ROUND(O66*JL/$C65,DcCU)*O67,DpCU),IF(OR(AND(20000<O65,O65<22501),AND(30000<O65,O65<50001),77500<O65),ROUND(O67*O66,DpCU),IF(OR(AND(22500<O65,O65<25001),AND(50000<O65,O65<53501),AND(70000<O65,O65<72501)),ROUND($F65/100*O66,DpCU),IF(OR(AND(25000<O65,O65<27501),AND(53500<O65,O65<57001),AND(72500<O65,O65<75001)),ROUND($G65/100*O66,DpCU),ROUND($H65/100*O66,DpCU))))))) -> 15.98 | P68: =IF($K65>0,ROUND(P66*$E65/100,DpCU),IF(P69>10000,ROUND(HLOOKUP(P69,$O65:$R68,4,FALSE)/100*P66,DpCU),IF(OR(P65<20001,P65>95000,AND(60000<P65,P65<70001)),ROUND(ROUND(P66*JL/$C65,DcCU)*P67,DpCU),IF(OR(AND(20000<P65,P65<22501),AND(30000<P65,P65<50001),77500<P65),ROUND(P67*P66,DpCU),IF(OR(AND(22500<P65,P65<25001),AND(50000<P65,P65<53501),AND(70000<P65,P65<72501)),ROUND($F65/100*P66,DpCU),IF(OR(AND(25000<P65,P65<27501),AND(53500<P65,P65<57001),AND(72500<P65,P65<75001)),ROUND($G65/100*P66,DpCU),ROUND($H65/100*P66,DpCU))))))) -> 98.3 | Q68: =IF($K65>0,ROUND(Q66*$E65/100,DpCU),IF(Q69>10000,ROUND(HLOOKUP(Q69,$O65:$R68,4,FALSE)/100*Q66,DpCU),IF(OR(Q65<20001,Q65>95000,AND(60000<Q65,Q65<70001)),ROUND(ROUND(Q66*JL/$C65,DcCU)*Q67,DpCU),IF(OR(AND(20000<Q65,Q65<22501),AND(30000<Q65,Q65<50001),77500<Q65),ROUND(Q67*Q66,DpCU),IF(OR(AND(22500<Q65,Q65<25001),AND(50000<Q65,Q65<53501),AND(70000<Q65,Q65<72501)),ROUND($F65/100*Q66,DpCU),IF(OR(AND(25000<Q65,Q65<27501),AND(53500<Q65,Q65<57001),AND(72500<Q65,Q65<75001)),ROUND($G65/100*Q66,DpCU),ROUND($H65/100*Q66,DpCU))))))) -> 64 | R68: =IF($K65>0,ROUND(R66*$E65/100,DpCU),IF(R69>10000,ROUND(HLOOKUP(R69,$O65:$R68,4,FALSE)/100*R66,DpCU),IF(OR(R65<20001,R65>95000,AND(60000<R65,R65<70001)),ROUND(ROUND(R66*JL/$C65,DcCU)*R67,DpCU),IF(OR(AND(20000<R65,R65<22501),AND(30000<R65,R65<50001),77500<R65),ROUND(R67*R66,DpCU),IF(OR(AND(22500<R65,R65<25001),AND(50000<R65,R65<53501),AND(70000<R65,R65<72501)),ROUND($F65/100*R66,DpCU),IF(OR(AND(25000<R65,R65<27501),AND(53500<R65,R65<57001),AND(72500<R65,R65<75001)),ROUND($G65/100*R66,DpCU),ROUND($H65/100*R66,DpCU))))))) -> 11.43
B69: =A65&"r" -> 10013r
A70: 10014 | B70: ELIMINACION DE MATERIAL EXCEDENTE PROV. DE DEMOLICIONES | C70: =ROUND(J70*JL*Frto/8,4) -> 87 | D70: M3 | E70: =SUM($O73:$O73) -> 217.5 | F70: =SUMIF($O70:$O70,"<22501",$O73:$O73) -> 0 | G70: =SUMIFS($O73:$O73,$O70:$O70,">30000",$O70:$O70,"<50001") -> 0 | H70: =SUMIFS($O73:$O73,$O70:$O70,">60000",$O70:$O70,"<70001") -> 0 | I70: 1 | J70: 87 | O70: 80002
B71: =A70&"C" -> 10014C | O71: 10.875
O72: =IF(O74>10000,HLOOKUP(O74,N70:$O73,4,FALSE),IF(OR(AND(22500<O70,O70<25001),AND(50000<O70,O70<53501),AND(70000<O70,O70<72501)),$F70,IF(OR(AND(25001<O70,O70<27501),AND(53500<O70,O70<57001),AND(72500<O70,O70<75001)),$G70,IF(OR(AND(27500<O70,O70<30001),AND(57000<O70,O70<60001),AND(75000<O70,O70<77500)),$H70,VLOOKUP(O70,BDins,6,FALSE))))) -> 20
O73: =IF($K70>0,ROUND(O71*$E70/100,DpCU),IF(O74>10000,ROUND(HLOOKUP(O74,$O70:$O73,4,FALSE)/100*O71,DpCU),IF(OR(O70<20001,O70>95000,AND(60000<O70,O70<70001)),ROUND(ROUND(O71*JL/$C70,DcCU)*O72,DpCU),IF(OR(AND(20000<O70,O70<22501),AND(30000<O70,O70<50001),77500<O70),ROUND(O72*O71,DpCU),IF(OR(AND(22500<O70,O70<25001),AND(50000<O70,O70<53501),AND(70000<O70,O70<72501)),ROUND($F70/100*O71,DpCU),IF(OR(AND(25000<O70,O70<27501),AND(53500<O70,O70<57001),AND(72500<O70,O70<75001)),ROUND($G70/100*O71,DpCU),ROUND($H70/100*O71,DpCU))))))) -> 217.5
B74: =A70&"r" -> 10014r
A75: 10015 | B75: MOVILIZACION Y DESMOVILIZACION DE MAQUINARIA Y HERRAMIENTAS | C75: =ROUND(J75*JL*Frto/8,4) -> 3.5 | D75: GLB | E75: =SUM($O78:$R78) -> 2276.92 | F75: =SUMIF($O75:$R75,"<22501",$O78:$R78) -> 235.56 | G75: =SUMIFS($O78:$R78,$O75:$R75,">30000",$O75:$R75,"<50001") -> 0 | H75: =SUMIFS($O78:$R78,$O75:$R75,">60000",$O75:$R75,"<70001") -> 2034.29 | I75: 4 | J75: 3.5 | O75: 10002 | P75: 10003 | Q75: 60003 | R75: 70001
B76: =A75&"C" -> 10015C | O76: 2 | P76: 4 | Q76: 5 | R76: 3
O77: =IF(O79>10000,HLOOKUP(O79,N75:$O78,4,FALSE),IF(OR(AND(22500<O75,O75<25001),AND(50000<O75,O75<53501),AND(70000<O75,O75<72501)),$F75,IF(OR(AND(25001<O75,O75<27501),AND(53500<O75,O75<57001),AND(72500<O75,O75<75001)),$G75,IF(OR(AND(27500<O75,O75<30001),AND(57000<O75,O75<60001),AND(75000<O75,O75<77500)),$H75,VLOOKUP(O75,BDins,6,FALSE))))) -> 20.81 | P77: =IF(P79>10000,HLOOKUP(P79,O75:$O78,4,FALSE),IF(OR(AND(22500<P75,P75<25001),AND(50000<P75,P75<53501),AND(70000<P75,P75<72501)),$F75,IF(OR(AND(25001<P75,P75<27501),AND(53500<P75,P75<57001),AND(72500<P75,P75<75001)),$G75,IF(OR(AND(27500<P75,P75<30001),AND(57000<P75,P75<60001),AND(75000<P75,P75<77500)),$H75,VLOOKUP(P75,BDins,6,FALSE))))) -> 15.36 | Q77: =IF(Q79>10000,HLOOKUP(Q79,$O75:P78,4,FALSE),IF(OR(AND(22500<Q75,Q75<25001),AND(50000<Q75,Q75<53501),AND(70000<Q75,Q75<72501)),$F75,IF(OR(AND(25001<Q75,Q75<27501),AND(53500<Q75,Q75<57001),AND(72500<Q75,Q75<75001)),$G75,IF(OR(AND(27500<Q75,Q75<30001),AND(57000<Q75,Q75<60001),AND(75000<Q75,Q75<77500)),$H75,VLOOKUP(Q75,BDins,6,FALSE))))) -> 178 | R77: =IF(R79>10000,HLOOKUP(R79,$O75:Q78,4,FALSE),IF(OR(AND(22500<R75,R75<25001),AND(50000<R75,R75<53501),AND(70000<R75,R75<72501)),$F75,IF(OR(AND(25001<R75,R75<27501),AND(53500<R75,R75<57001),AND(72500<R75,R75<75001)),$G75,IF(OR(AND(27500<R75,R75<30001),AND(57000<R75,R75<60001),AND(75000<R75,R75<77500)),$H75,VLOOKUP(R75,BDins,6,FALSE))))) -> 235.56
O78: =IF($K75>0,ROUND(O76*$E75/100,DpCU),IF(O79>10000,ROUND(HLOOKUP(O79,$O75:$R78,4,FALSE)/100*O76,DpCU),IF(OR(O75<20001,O75>95000,AND(60000<O75,O75<70001)),ROUND(ROUND(O76*JL/$C75,DcCU)*O77,DpCU),IF(OR(AND(20000<O75,O75<22501),AND(30000<O75,O75<50001),77500<O75),ROUND(O77*O76,DpCU),IF(OR(AND(22500<O75,O75<25001),AND(50000<O75,O75<53501),AND(70000<O75,O75<72501)),ROUND($F75/100*O76,DpCU),IF(OR(AND(25000<O75,O75<27501),AND(53500<O75,O75<57001),AND(72500<O75,O75<75001)),ROUND($G75/100*O76,DpCU),ROUND($H75/100*O76,DpCU))))))) -> 95.13 | P78: =IF($K75>0,ROUND(P76*$E75/100,DpCU),IF(P79>10000,ROUND(HLOOKUP(P79,$O75:$R78,4,FALSE)/100*P76,DpCU),IF(OR(P75<20001,P75>95000,AND(60000<P75,P75<70001)),ROUND(ROUND(P76*JL/$C75,DcCU)*P77,DpCU),IF(OR(AND(20000<P75,P75<22501),AND(30000<P75,P75<50001),77500<P75),ROUND(P77*P76,DpCU),IF(OR(AND(22500<P75,P75<25001),AND(50000<P75,P75<53501),AND(70000<P75,P75<72501)),ROUND($F75/100*P76,DpCU),IF(OR(AND(25000<P75,P75<27501),AND(53500<P75,P75<57001),AND(72500<P75,P75<75001)),ROUND($G75/100*P76,DpCU),ROUND($H75/100*P76,DpCU))))))) -> 140.43 | Q78: =IF($K75>0,ROUND(Q76*$E75/100,DpCU),IF(Q79>10000,ROUND(HLOOKUP(Q79,$O75:$R78,4,FALSE)/100*Q76,DpCU),IF(OR(Q75<20001,Q75>95000,AND(60000<Q75,Q75<70001)),ROUND(ROUND(Q76*JL/$C75,DcCU)*Q77,DpCU),IF(OR(AND(20000<Q75,Q75<22501),AND(30000<Q75,Q75<50001),77500<Q75),ROUND(Q77*Q76,DpCU),IF(OR(AND(22500<Q75,Q75<25001),AND(50000<Q75,Q75<53501),AND(70000<Q75,Q75<72501)),ROUND($F75/100*Q76,DpCU),IF(OR(AND(25000<Q75,Q75<27501),AND(53500<Q75,Q75<57001),AND(72500<Q75,Q75<75001)),ROUND($G75/100*Q76,DpCU),ROUND($H75/100*Q76,DpCU))))))) -> 2034.29 | R78: =IF($K75>0,ROUND(R76*$E75/100,DpCU),IF(R79>10000,ROUND(HLOOKUP(R79,$O75:$R78,4,FALSE)/100*R76,DpCU),IF(OR(R75<20001,R75>95000,AND(60000<R75,R75<70001)),ROUND(ROUND(R76*JL/$C75,DcCU)*R77,DpCU),IF(OR(AND(20000<R75,R75<22501),AND(30000<R75,R75<50001),77500<R75),ROUND(R77*R76,DpCU),IF(OR(AND(22500<R75,R75<25001),AND(50000<R75,R75<53501),AND(70000<R75,R75<72501)),ROUND($F75/100*R76,DpCU),IF(OR(AND(25000<R75,R75<27501),AND(53500<R75,R75<57001),AND(72500<R75,R75<75001)),ROUND($G75/100*R76,DpCU),ROUND($H75/100*R76,DpCU))))))) -> 7.07
B79: =A75&"r" -> 10015r
A80: 10016 | B80: TRAZO, NIVELES Y REPLANTEO PRELIMINAR CON VALLAS AISLADAS | C80: =ROUND(J80*JL*Frto/8,4) -> 225 | D80: M2 | E80: =SUM($O83:$V83) -> 3.95 | F80: =SUMIF($O80:$V80,"<22501",$O83:$V83) -> 2.45 | G80: =SUMIFS($O83:$V83,$O80:$V80,">30000",$O80:$V80,"<50001") -> 1.39 | H80: =SUMIFS($O83:$V83,$O80:$V80,">60000",$O80:$V80,"<70001") -> 0.04 | I80: 8 | J80: 225 | O80: 10001 | P80: 10003 | Q80: 10006 | R80: 30025 | S80: 30026 | T80: 60004 | U80: 60005 | V80: 70001
B81: =A80&"C" -> 10016C | O81: 0.1 | P81: 3 | Q81: 1 | R81: 0.05 | S81: 0.1 | T81: 1 | U81: 0.125 | V81: 3
O82: =IF(O84>10000,HLOOKUP(O84,N80:$O83,4,FALSE),IF(OR(AND(22500<O80,O80<25001),AND(50000<O80,O80<53501),AND(70000<O80,O80<72501)),$F80,IF(OR(AND(25001<O80,O80<27501),AND(53500<O80,O80<57001),AND(72500<O80,O80<75001)),$G80,IF(OR(AND(27500<O80,O80<30001),AND(57000<O80,O80<60001),AND(75000<O80,O80<77500)),$H80,VLOOKUP(O80,BDins,6,FALSE))))) -> 24.97 | P82: =IF(P84>10000,HLOOKUP(P84,O80:$O83,4,FALSE),IF(OR(AND(22500<P80,P80<25001),AND(50000<P80,P80<53501),AND(70000<P80,P80<72501)),$F80,IF(OR(AND(25001<P80,P80<27501),AND(53500<P80,P80<57001),AND(72500<P80,P80<75001)),$G80,IF(OR(AND(27500<P80,P80<30001),AND(57000<P80,P80<60001),AND(75000<P80,P80<77500)),$H80,VLOOKUP(P80,BDins,6,FALSE))))) -> 15.36 | Q82: =IF(Q84>10000,HLOOKUP(Q84,$O80:P83,4,FALSE),IF(OR(AND(22500<Q80,Q80<25001),AND(50000<Q80,Q80<53501),AND(70000<Q80,Q80<72501)),$F80,IF(OR(AND(25001<Q80,Q80<27501),AND(53500<Q80,Q80<57001),AND(72500<Q80,Q80<75001)),$G80,IF(OR(AND(27500<Q80,Q80<30001),AND(57000<Q80,Q80<60001),AND(75000<Q80,Q80<77500)),$H80,VLOOKUP(Q80,BDins,6,FALSE))))) -> 20.1 | R82: =IF(R84>10000,HLOOKUP(R84,$O80:Q83,4,FALSE),IF(OR(AND(22500<R80,R80<25001),AND(50000<R80,R80<53501),AND(70000<R80,R80<72501)),$F80,IF(OR(AND(25001<R80,R80<27501),AND(53500<R80,R80<57001),AND(72500<R80,R80<75001)),$G80,IF(OR(AND(27500<R80,R80<30001),AND(57000<R80,R80<60001),AND(75000<R80,R80<77500)),$H80,VLOOKUP(R80,BDins,6,FALSE))))) -> 20 | S82: =IF(S84>10000,HLOOKUP(S84,$O80:R83,4,FALSE),IF(OR(AND(22500<S80,S80<25001),AND(50000<S80,S80<53501),AND(70000<S80,S80<72501)),$F80,IF(OR(AND(25001<S80,S80<27501),AND(53500<S80,S80<57001),AND(72500<S80,S80<75001)),$G80,IF(OR(AND(27500<S80,S80<30001),AND(57000<S80,S80<60001),AND(75000<S80,S80<77500)),$H80,VLOOKUP(S80,BDins,6,FALSE))))) -> 3.9 | T82: =IF(T84>10000,HLOOKUP(T84,$O80:S83,4,FALSE),IF(OR(AND(22500<T80,T80<25001),AND(50000<T80,T80<53501),AND(70000<T80,T80<72501)),$F80,IF(OR(AND(25001<T80,T80<27501),AND(53500<T80,T80<57001),AND(72500<T80,T80<75001)),$G80,IF(OR(AND(27500<T80,T80<30001),AND(57000<T80,T80<60001),AND(75000<T80,T80<77500)),$H80,VLOOKUP(T80,BDins,6,FALSE))))) -> 0.5 | U82: =IF(U84>10000,HLOOKUP(U84,$O80:T83,4,FALSE),IF(OR(AND(22500<U80,U80<25001),AND(50000<U80,U80<53501),AND(70000<U80,U80<72501)),$F80,IF(OR(AND(25001<U80,U80<27501),AND(53500<U80,U80<57001),AND(72500<U80,U80<75001)),$G80,IF(OR(AND(27500<U80,U80<30001),AND(57000<U80,U80<60001),AND(75000<U80,U80<77500)),$H80,VLOOKUP(U80,BDins,6,FALSE))))) -> 5 | V82: =IF(V84>10000,HLOOKUP(V84,$O80:U83,4,FALSE),IF(OR(AND(22500<V80,V80<25001),AND(50000<V80,V80<53501),AND(70000<V80,V80<72501)),$F80,IF(OR(AND(25001<V80,V80<27501),AND(53500<V80,V80<57001),AND(72500<V80,V80<75001)),$G80,IF(OR(AND(27500<V80,V80<30001),AND(57000<V80,V80<60001),AND(75000<V80,V80<77500)),$H80,VLOOKUP(V80,BDins,6,FALSE))))) -> 2.45
O83: =IF($K80>0,ROUND(O81*$E80/100,DpCU),IF(O84>10000,ROUND(HLOOKUP(O84,$O80:$V83,4,FALSE)/100*O81,DpCU),IF(OR(O80<20001,O80>95000,AND(60000<O80,O80<70001)),ROUND(ROUND(O81*JL/$C80,DcCU)*O82,DpCU),IF(OR(AND(20000<O80,O80<22501),AND(30000<O80,O80<50001),77500<O80),ROUND(O82*O81,DpCU),IF(OR(AND(22500<O80,O80<25001),AND(50000<O80,O80<53501),AND(70000<O80,O80<72501)),ROUND($F80/100*O81,DpCU),IF(OR(AND(25000<O80,O80<27501),AND(53500<O80,O80<57001),AND(72500<O80,O80<75001)),ROUND($G80/100*O81,DpCU),ROUND($H80/100*O81,DpCU))))))) -> 0.09 | P83: =IF($K80>0,ROUND(P81*$E80/100,DpCU),IF(P84>10000,ROUND(HLOOKUP(P84,$O80:$V83,4,FALSE)/100*P81,DpCU),IF(OR(P80<20001,P80>95000,AND(60000<P80,P80<70001)),ROUND(ROUND(P81*JL/$C80,DcCU)*P82,DpCU),IF(OR(AND(20000<P80,P80<22501),AND(30000<P80,P80<50001),77500<P80),ROUND(P82*P81,DpCU),IF(OR(AND(22500<P80,P80<25001),AND(50000<P80,P80<53501),AND(70000<P80,P80<72501)),ROUND($F80/100*P81,DpCU),IF(OR(AND(25000<P80,P80<27501),AND(53500<P80,P80<57001),AND(72500<P80,P80<75001)),ROUND($G80/100*P81,DpCU),ROUND($H80/100*P81,DpCU))))))) -> 1.64 | Q83: =IF($K80>0,ROUND(Q81*$E80/100,DpCU),IF(Q84>10000,ROUND(HLOOKUP(Q84,$O80:$V83,4,FALSE)/100*Q81,DpCU),IF(OR(Q80<20001,Q80>95000,AND(60000<Q80,Q80<70001)),ROUND(ROUND(Q81*JL/$C80,DcCU)*Q82,DpCU),IF(OR(AND(20000<Q80,Q80<22501),AND(30000<Q80,Q80<50001),77500<Q80),ROUND(Q82*Q81,DpCU),IF(OR(AND(22500<Q80,Q80<25001),AND(50000<Q80,Q80<53501),AND(70000<Q80,Q80<72501)),ROUND($F80/100*Q81,DpCU),IF(OR(AND(25000<Q80,Q80<27501),AND(53500<Q80,Q80<57001),AND(72500<Q80,Q80<75001)),ROUND($G80/100*Q81,DpCU),ROUND($H80/100*Q81,DpCU))))))) -> 0.72 | R83: =IF($K80>0,ROUND(R81*$E80/100,DpCU),IF(R84>10000,ROUND(HLOOKUP(R84,$O80:$V83,4,FALSE)/100*R81,DpCU),IF(OR(R80<20001,R80>95000,AND(60000<R80,R80<70001)),ROUND(ROUND(R81*JL/$C80,DcCU)*R82,DpCU),IF(OR(AND(20000<R80,R80<22501),AND(30000<R80,R80<50001),77500<R80),ROUND(R82*R81,DpCU),IF(OR(AND(22500<R80,R80<25001),AND(50000<R80,R80<53501),AND(70000<R80,R80<72501)),ROUND($F80/100*R81,DpCU),IF(OR(AND(25000<R80,R80<27501),AND(53500<R80,R80<57001),AND(72500<R80,R80<75001)),ROUND($G80/100*R81,DpCU),ROUND($H80/100*R81,DpCU))))))) -> 1 | S83: =IF($K80>0,ROUND(S81*$E80/100,DpCU),IF(S84>10000,ROUND(HLOOKUP(S84,$O80:$V83,4,FALSE)/100*S81,DpCU),IF(OR(S80<20001,S80>95000,AND(60000<S80,S80<70001)),ROUND(ROUND(S81*JL/$C80,DcCU)*S82,DpCU),IF(OR(AND(20000<S80,S80<22501),AND(30000<S80,S80<50001),77500<S80),ROUND(S82*S81,DpCU),IF(OR(AND(22500<S80,S80<25001),AND(50000<S80,S80<53501),AND(70000<S80,S80<72501)),ROUND($F80/100*S81,DpCU),IF(OR(AND(25000<S80,S80<27501),AND(53500<S80,S80<57001),AND(72500<S80,S80<75001)),ROUND($G80/100*S81,DpCU),ROUND($H80/100*S81,DpCU))))))) -> 0.39 | T83: =IF($K80>0,ROUND(T81*$E80/100,DpCU),IF(T84>10000,ROUND(HLOOKUP(T84,$O80:$V83,4,FALSE)/100*T81,DpCU),IF(OR(T80<20001,T80>95000,AND(60000<T80,T80<70001)),ROUND(ROUND(T81*JL/$C80,DcCU)*T82,DpCU),IF(OR(AND(20000<T80,T80<22501),AND(30000<T80,T80<50001),77500<T80),ROUND(T82*T81,DpCU),IF(OR(AND(22500<T80,T80<25001),AND(50000<T80,T80<53501),AND(70000<T80,T80<72501)),ROUND($F80/100*T81,DpCU),IF(OR(AND(25000<T80,T80<27501),AND(53500<T80,T80<57001),AND(72500<T80,T80<75001)),ROUND($G80/100*T81,DpCU),ROUND($H80/100*T81,DpCU))))))) -> 0.02 | U83: =IF($K80>0,ROUND(U81*$E80/100,DpCU),IF(U84>10000,ROUND(HLOOKUP(U84,$O80:$V83,4,FALSE)/100*U81,DpCU),IF(OR(U80<20001,U80>95000,AND(60000<U80,U80<70001)),ROUND(ROUND(U81*JL/$C80,DcCU)*U82,DpCU),IF(OR(AND(20000<U80,U80<22501),AND(30000<U80,U80<50001),77500<U80),ROUND(U82*U81,DpCU),IF(OR(AND(22500<U80,U80<25001),AND(50000<U80,U80<53501),AND(70000<U80,U80<72501)),ROUND($F80/100*U81,DpCU),IF(OR(AND(25000<U80,U80<27501),AND(53500<U80,U80<57001),AND(72500<U80,U80<75001)),ROUND($G80/100*U81,DpCU),ROUND($H80/100*U81,DpCU))))))) -> 0.02 | V83: =IF($K80>0,ROUND(V81*$E80/100,DpCU),IF(V84>10000,ROUND(HLOOKUP(V84,$O80:$V83,4,FALSE)/100*V81,DpCU),IF(OR(V80<20001,V80>95000,AND(60000<V80,V80<70001)),ROUND(ROUND(V81*JL/$C80,DcCU)*V82,DpCU),IF(OR(AND(20000<V80,V80<22501),AND(30000<V80,V80<50001),77500<V80),ROUND(V82*V81,DpCU),IF(OR(AND(22500<V80,V80<25001),AND(50000<V80,V80<53501),AND(70000<V80,V80<72501)),ROUND($F80/100*V81,DpCU),IF(OR(AND(25000<V80,V80<27501),AND(53500<V80,V80<57001),AND(72500<V80,V80<75001)),ROUND($G80/100*V81,DpCU),ROUND($H80/100*V81,DpCU))))))) -> 0.07
B84: =A80&"r" -> 10016r
A85: 10017 | B85: TRAZO Y REPLANTEO DURANTE EL PROCESO DE LA OBRA | C85: =ROUND(J85*JL*Frto/8,4) -> 100 | D85: M2 | E85: =SUM($O88:$U88) -> 3.76 | F85: =SUMIF($O85:$U85,"<22501",$O88:$U88) -> 3.04 | G85: =SUMIFS($O88:$U88,$O85:$U85,">30000",$O85:$U85,"<50001") -> 0.17 | H85: =SUMIFS($O88:$U88,$O85:$U85,">60000",$O85:$U85,"<70001") -> 0.4 | I85: 7 | J85: 100 | O85: 10001 | P85: 10003 | Q85: 10006 | R85: 30027 | S85: 30028 | T85: 60006 | U85: 70001
B86: =A85&"C" -> 10017C | O86: 0.1 | P86: 1 | Q86: 1 | R86: 0.01 | S86: 0.001 | T86: 1 | U86: 5
O87: =IF(O89>10000,HLOOKUP(O89,N85:$O88,4,FALSE),IF(OR(AND(22500<O85,O85<25001),AND(50000<O85,O85<53501),AND(70000<O85,O85<72501)),$F85,IF(OR(AND(25001<O85,O85<27501),AND(53500<O85,O85<57001),AND(72500<O85,O85<75001)),$G85,IF(OR(AND(27500<O85,O85<30001),AND(57000<O85,O85<60001),AND(75000<O85,O85<77500)),$H85,VLOOKUP(O85,BDins,6,FALSE))))) -> 24.97 | P87: =IF(P89>10000,HLOOKUP(P89,O85:$O88,4,FALSE),IF(OR(AND(22500<P85,P85<25001),AND(50000<P85,P85<53501),AND(70000<P85,P85<72501)),$F85,IF(OR(AND(25001<P85,P85<27501),AND(53500<P85,P85<57001),AND(72500<P85,P85<75001)),$G85,IF(OR(AND(27500<P85,P85<30001),AND(57000<P85,P85<60001),AND(75000<P85,P85<77500)),$H85,VLOOKUP(P85,BDins,6,FALSE))))) -> 15.36 | Q87: =IF(Q89>10000,HLOOKUP(Q89,$O85:P88,4,FALSE),IF(OR(AND(22500<Q85,Q85<25001),AND(50000<Q85,Q85<53501),AND(70000<Q85,Q85<72501)),$F85,IF(OR(AND(25001<Q85,Q85<27501),AND(53500<Q85,Q85<57001),AND(72500<Q85,Q85<75001)),$G85,IF(OR(AND(27500<Q85,Q85<30001),AND(57000<Q85,Q85<60001),AND(75000<Q85,Q85<77500)),$H85,VLOOKUP(Q85,BDins,6,FALSE))))) -> 20.1 | R87: =IF(R89>10000,HLOOKUP(R89,$O85:Q88,4,FALSE),IF(OR(AND(22500<R85,R85<25001),AND(50000<R85,R85<53501),AND(70000<R85,R85<72501)),$F85,IF(OR(AND(25001<R85,R85<27501),AND(53500<R85,R85<57001),AND(72500<R85,R85<75001)),$G85,IF(OR(AND(27500<R85,R85<30001),AND(57000<R85,R85<60001),AND(75000<R85,R85<77500)),$H85,VLOOKUP(R85,BDins,6,FALSE))))) -> 9.45 | S87: =IF(S89>10000,HLOOKUP(S89,$O85:R88,4,FALSE),IF(OR(AND(22500<S85,S85<25001),AND(50000<S85,S85<53501),AND(70000<S85,S85<72501)),$F85,IF(OR(AND(25001<S85,S85<27501),AND(53500<S85,S85<57001),AND(72500<S85,S85<75001)),$G85,IF(OR(AND(27500<S85,S85<30001),AND(57000<S85,S85<60001),AND(75000<S85,S85<77500)),$H85,VLOOKUP(S85,BDins,6,FALSE))))) -> 80 | T87: =IF(T89>10000,HLOOKUP(T89,$O85:S88,4,FALSE),IF(OR(AND(22500<T85,T85<25001),AND(50000<T85,T85<53501),AND(70000<T85,T85<72501)),$F85,IF(OR(AND(25001<T85,T85<27501),AND(53500<T85,T85<57001),AND(72500<T85,T85<75001)),$G85,IF(OR(AND(27500<T85,T85<30001),AND(57000<T85,T85<60001),AND(75000<T85,T85<77500)),$H85,VLOOKUP(T85,BDins,6,FALSE))))) -> 5 | U87: =IF(U89>10000,HLOOKUP(U89,$O85:T88,4,FALSE),IF(OR(AND(22500<U85,U85<25001),AND(50000<U85,U85<53501),AND(70000<U85,U85<72501)),$F85,IF(OR(AND(25001<U85,U85<27501),AND(53500<U85,U85<57001),AND(72500<U85,U85<75001)),$G85,IF(OR(AND(27500<U85,U85<30001),AND(57000<U85,U85<60001),AND(75000<U85,U85<77500)),$H85,VLOOKUP(U85,BDins,6,FALSE))))) -> 3.04
O88: =IF($K85>0,ROUND(O86*$E85/100,DpCU),IF(O89>10000,ROUND(HLOOKUP(O89,$O85:$U88,4,FALSE)/100*O86,DpCU),IF(OR(O85<20001,O85>95000,AND(60000<O85,O85<70001)),ROUND(ROUND(O86*JL/$C85,DcCU)*O87,DpCU),IF(OR(AND(20000<O85,O85<22501),AND(30000<O85,O85<50001),77500<O85),ROUND(O87*O86,DpCU),IF(OR(AND(22500<O85,O85<25001),AND(50000<O85,O85<53501),AND(70000<O85,O85<72501)),ROUND($F85/100*O86,DpCU),IF(OR(AND(25000<O85,O85<27501),AND(53500<O85,O85<57001),AND(72500<O85,O85<75001)),ROUND($G85/100*O86,DpCU),ROUND($H85/100*O86,DpCU))))))) -> 0.2 | P88: =IF($K85>0,ROUND(P86*$E85/100,DpCU),IF(P89>10000,ROUND(HLOOKUP(P89,$O85:$U88,4,FALSE)/100*P86,DpCU),IF(OR(P85<20001,P85>95000,AND(60000<P85,P85<70001)),ROUND(ROUND(P86*JL/$C85,DcCU)*P87,DpCU),IF(OR(AND(20000<P85,P85<22501),AND(30000<P85,P85<50001),77500<P85),ROUND(P87*P86,DpCU),IF(OR(AND(22500<P85,P85<25001),AND(50000<P85,P85<53501),AND(70000<P85,P85<72501)),ROUND($F85/100*P86,DpCU),IF(OR(AND(25000<P85,P85<27501),AND(53500<P85,P85<57001),AND(72500<P85,P85<75001)),ROUND($G85/100*P86,DpCU),ROUND($H85/100*P86,DpCU))))))) -> 1.23 | Q88: =IF($K85>0,ROUND(Q86*$E85/100,DpCU),IF(Q89>10000,ROUND(HLOOKUP(Q89,$O85:$U88,4,FALSE)/100*Q86,DpCU),IF(OR(Q85<20001,Q85>95000,AND(60000<Q85,Q85<70001)),ROUND(ROUND(Q86*JL/$C85,DcCU)*Q87,DpCU),IF(OR(AND(20000<Q85,Q85<22501),AND(30000<Q85,Q85<50001),77500<Q85),ROUND(Q87*Q86,DpCU),IF(OR(AND(22500<Q85,Q85<25001),AND(50000<Q85,Q85<53501),AND(70000<Q85,Q85<72501)),ROUND($F85/100*Q86,DpCU),IF(OR(AND(25000<Q85,Q85<27501),AND(53500<Q85,Q85<57001),AND(72500<Q85,Q85<75001)),ROUND($G85/100*Q86,DpCU),ROUND($H85/100*Q86,DpCU))))))) -> 1.61 | R88: =IF($K85>0,ROUND(R86*$E85/100,DpCU),IF(R89>10000,ROUND(HLOOKUP(R89,$O85:$U88,4,FALSE)/100*R86,DpCU),IF(OR(R85<20001,R85>95000,AND(60000<R85,R85<70001)),ROUND(ROUND(R86*JL/$C85,DcCU)*R87,DpCU),IF(OR(AND(20000<R85,R85<22501),AND(30000<R85,R85<50001),77500<R85),ROUND(R87*R86,DpCU),IF(OR(AND(22500<R85,R85<25001),AND(50000<R85,R85<53501),AND(70000<R85,R85<72501)),ROUND($F85/100*R86,DpCU),IF(OR(AND(25000<R85,R85<27501),AND(53500<R85,R85<57001),AND(72500<R85,R85<75001)),ROUND($G85/100*R86,DpCU),ROUND($H85/100*R86,DpCU))))))) -> 0.09 | S88: =IF($K85>0,ROUND(S86*$E85/100,DpCU),IF(S89>10000,ROUND(HLOOKUP(S89,$O85:$U88,4,FALSE)/100*S86,DpCU),IF(OR(S85<20001,S85>95000,AND(60000<S85,S85<70001)),ROUND(ROUND(S86*JL/$C85,DcCU)*S87,DpCU),IF(OR(AND(20000<S85,S85<22501),AND(30000<S85,S85<50001),77500<S85),ROUND(S87*S86,DpCU),IF(OR(AND(22500<S85,S85<25001),AND(50000<S85,S85<53501),AND(70000<S85,S85<72501)),ROUND($F85/100*S86,DpCU),IF(OR(AND(25000<S85,S85<27501),AND(53500<S85,S85<57001),AND(72500<S85,S85<75001)),ROUND($G85/100*S86,DpCU),ROUND($H85/100*S86,DpCU))))))) -> 0.08 | T88: =IF($K85>0,ROUND(T86*$E85/100,DpCU),IF(T89>10000,ROUND(HLOOKUP(T89,$O85:$U88,4,FALSE)/100*T86,DpCU),IF(OR(T85<20001,T85>95000,AND(60000<T85,T85<70001)),ROUND(ROUND(T86*JL/$C85,DcCU)*T87,DpCU),IF(OR(AND(20000<T85,T85<22501),AND(30000<T85,T85<50001),77500<T85),ROUND(T87*T86,DpCU),IF(OR(AND(22500<T85,T85<25001),AND(50000<T85,T85<53501),AND(70000<T85,T85<72501)),ROUND($F85/100*T86,DpCU),IF(OR(AND(25000<T85,T85<27501),AND(53500<T85,T85<57001),AND(72500<T85,T85<75001)),ROUND($G85/100*T86,DpCU),ROUND($H85/100*T86,DpCU))))))) -> 0.4 | U88: =IF($K85>0,ROUND(U86*$E85/100,DpCU),IF(U89>10000,ROUND(HLOOKUP(U89,$O85:$U88,4,FALSE)/100*U86,DpCU),IF(OR(U85<20001,U85>95000,AND(60000<U85,U85<70001)),ROUND(ROUND(U86*JL/$C85,DcCU)*U87,DpCU),IF(OR(AND(20000<U85,U85<22501),AND(30000<U85,U85<50001),77500<U85),ROUND(U87*U86,DpCU),IF(OR(AND(22500<U85,U85<25001),AND(50000<U85,U85<53501),AND(70000<U85,U85<72501)),ROUND($F85/100*U86,DpCU),IF(OR(AND(25000<U85,U85<27501),AND(53500<U85,U85<57001),AND(72500<U85,U85<75001)),ROUND($G85/100*U86,DpCU),ROUND($H85/100*U86,DpCU))))))) -> 0.15
B89: =A85&"r" -> 10017r
A90: 10018 | B90: ELABORACION, IMPLEMENTACION Y ADMINISTRACION DEL PLAN DE SEGURIDAD Y SALUD EN EL TRABAJO | C90: =ROUND(J90*JL*Frto/8,4) -> 1 | D90: GLB | E90: =SUM($O93:$O93) -> 1271.19 | F90: =SUMIF($O90:$O90,"<22501",$O93:$O93) -> 0 | G90: =SUMIFS($O93:$O93,$O90:$O90,">30000",$O90:$O90,"<50001") -> 1271.19 | H90: =SUMIFS($O93:$O93,$O90:$O90,">60000",$O90:$O90,"<70001") -> 0 | I90: 1 | J90: 1 | O90: 30029
B91: =A90&"C" -> 10018C | O91: 1
O92: =IF(O94>10000,HLOOKUP(O94,N90:$O93,4,FALSE),IF(OR(AND(22500<O90,O90<25001),AND(50000<O90,O90<53501),AND(70000<O90,O90<72501)),$F90,IF(OR(AND(25001<O90,O90<27501),AND(53500<O90,O90<57001),AND(72500<O90,O90<75001)),$G90,IF(OR(AND(27500<O90,O90<30001),AND(57000<O90,O90<60001),AND(75000<O90,O90<77500)),$H90,VLOOKUP(O90,BDins,6,FALSE))))) -> 1271.19
O93: =IF($K90>0,ROUND(O91*$E90/100,DpCU),IF(O94>10000,ROUND(HLOOKUP(O94,$O90:$O93,4,FALSE)/100*O91,DpCU),IF(OR(O90<20001,O90>95000,AND(60000<O90,O90<70001)),ROUND(ROUND(O91*JL/$C90,DcCU)*O92,DpCU),IF(OR(AND(20000<O90,O90<22501),AND(30000<O90,O90<50001),77500<O90),ROUND(O92*O91,DpCU),IF(OR(AND(22500<O90,O90<25001),AND(50000<O90,O90<53501),AND(70000<O90,O90<72501)),ROUND($F90/100*O91,DpCU),IF(OR(AND(25000<O90,O90<27501),AND(53500<O90,O90<57001),AND(72500<O90,O90<75001)),ROUND($G90/100*O91,DpCU),ROUND($H90/100*O91,DpCU))))))) -> 1271.19
B94: =A90&"r" -> 10018r
A95: 10019 | B95: EQUIPOS DE PROTECCION INDIVIDUAL | C95: =ROUND(J95*JL*Frto/8,4) -> 1 | D95: UND | E95: =SUM($O98:$X98) -> 38.34 | F95: =SUMIF($O95:$X95,"<22501",$O98:$X98) -> 0 | G95: =SUMIFS($O98:$X98,$O95:$X95,">30000",$O95:$X95,"<50001") -> 32.09 | H95: =SUMIFS($O98:$X98,$O95:$X95,">60000",$O95:$X95,"<70001") -> 0 | I95: 10 | J95: 1 | O95: 30030 | P95: 30031 | Q95: 30032 | R95: 30033 | S95: 30034 | T95: 30035 | U95: 30036 | V95: 30037 | W95: 30038 | X95: 77501
B96: =A95&"C" -> 10019C | O96: 0.25 | P96: 0.625 | Q96: 0.125 | R96: 0.0125 | S96: 0.625 | T96: 0.25 | U96: 0.03125 | V96: 0.25 | W96: 1.25 | X96: 0.025
O97: =IF(O99>10000,HLOOKUP(O99,N95:$O98,4,FALSE),IF(OR(AND(22500<O95,O95<25001),AND(50000<O95,O95<53501),AND(70000<O95,O95<72501)),$F95,IF(OR(AND(25001<O95,O95<27501),AND(53500<O95,O95<57001),AND(72500<O95,O95<75001)),$G95,IF(OR(AND(27500<O95,O95<30001),AND(57000<O95,O95<60001),AND(75000<O95,O95<77500)),$H95,VLOOKUP(O95,BDins,6,FALSE))))) -> 3.9 | P97: =IF(P99>10000,HLOOKUP(P99,O95:$O98,4,FALSE),IF(OR(AND(22500<P95,P95<25001),AND(50000<P95,P95<53501),AND(70000<P95,P95<72501)),$F95,IF(OR(AND(25001<P95,P95<27501),AND(53500<P95,P95<57001),AND(72500<P95,P95<75001)),$G95,IF(OR(AND(27500<P95,P95<30001),AND(57000<P95,P95<60001),AND(75000<P95,P95<77500)),$H95,VLOOKUP(P95,BDins,6,FALSE))))) -> 2.2 | Q97: =IF(Q99>10000,HLOOKUP(Q99,$O95:P98,4,FALSE),IF(OR(AND(22500<Q95,Q95<25001),AND(50000<Q95,Q95<53501),AND(70000<Q95,Q95<72501)),$F95,IF(OR(AND(25001<Q95,Q95<27501),AND(53500<Q95,Q95<57001),AND(72500<Q95,Q95<75001)),$G95,IF(OR(AND(27500<Q95,Q95<30001),AND(57000<Q95,Q95<60001),AND(75000<Q95,Q95<77500)),$H95,VLOOKUP(Q95,BDins,6,FALSE))))) -> 15 | R97: =IF(R99>10000,HLOOKUP(R99,$O95:Q98,4,FALSE),IF(OR(AND(22500<R95,R95<25001),AND(50000<R95,R95<53501),AND(70000<R95,R95<72501)),$F95,IF(OR(AND(25001<R95,R95<27501),AND(53500<R95,R95<57001),AND(72500<R95,R95<75001)),$G95,IF(OR(AND(27500<R95,R95<30001),AND(57000<R95,R95<60001),AND(75000<R95,R95<77500)),$H95,VLOOKUP(R95,BDins,6,FALSE))))) -> 18.6 | S97: =IF(S99>10000,HLOOKUP(S99,$O95:R98,4,FALSE),IF(OR(AND(22500<S95,S95<25001),AND(50000<S95,S95<53501),AND(70000<S95,S95<72501)),$F95,IF(OR(AND(25001<S95,S95<27501),AND(53500<S95,S95<57001),AND(72500<S95,S95<75001)),$G95,IF(OR(AND(27500<S95,S95<30001),AND(57000<S95,S95<60001),AND(75000<S95,S95<77500)),$H95,VLOOKUP(S95,BDins,6,FALSE))))) -> 7.3 | T97: =IF(T99>10000,HLOOKUP(T99,$O95:S98,4,FALSE),IF(OR(AND(22500<T95,T95<25001),AND(50000<T95,T95<53501),AND(70000<T95,T95<72501)),$F95,IF(OR(AND(25001<T95,T95<27501),AND(53500<T95,T95<57001),AND(72500<T95,T95<75001)),$G95,IF(OR(AND(27500<T95,T95<30001),AND(57000<T95,T95<60001),AND(75000<T95,T95<77500)),$H95,VLOOKUP(T95,BDins,6,FALSE))))) -> 25 | U97: =IF(U99>10000,HLOOKUP(U99,$O95:T98,4,FALSE),IF(OR(AND(22500<U95,U95<25001),AND(50000<U95,U95<53501),AND(70000<U95,U95<72501)),$F95,IF(OR(AND(25001<U95,U95<27501),AND(53500<U95,U95<57001),AND(72500<U95,U95<75001)),$G95,IF(OR(AND(27500<U95,U95<30001),AND(57000<U95,U95<60001),AND(75000<U95,U95<77500)),$H95,VLOOKUP(U95,BDins,6,FALSE))))) -> 10 | V97: =IF(V99>10000,HLOOKUP(V99,$O95:U98,4,FALSE),IF(OR(AND(22500<V95,V95<25001),AND(50000<V95,V95<53501),AND(70000<V95,V95<72501)),$F95,IF(OR(AND(25001<V95,V95<27501),AND(53500<V95,V95<57001),AND(72500<V95,V95<75001)),$G95,IF(OR(AND(27500<V95,V95<30001),AND(57000<V95,V95<60001),AND(75000<V95,V95<77500)),$H95,VLOOKUP(V95,BDins,6,FALSE))))) -> 50 | W97: =IF(W99>10000,HLOOKUP(W99,$O95:V98,4,FALSE),IF(OR(AND(22500<W95,W95<25001),AND(50000<W95,W95<53501),AND(70000<W95,W95<72501)),$F95,IF(OR(AND(25001<W95,W95<27501),AND(53500<W95,W95<57001),AND(72500<W95,W95<75001)),$G95,IF(OR(AND(27500<W95,W95<30001),AND(57000<W95,W95<60001),AND(75000<W95,W95<77500)),$H95,VLOOKUP(W95,BDins,6,FALSE))))) -> 3.2 | X97: =IF(X99>10000,HLOOKUP(X99,$O95:W98,4,FALSE),IF(OR(AND(22500<X95,X95<25001),AND(50000<X95,X95<53501),AND(70000<X95,X95<72501)),$F95,IF(OR(AND(25001<X95,X95<27501),AND(53500<X95,X95<57001),AND(72500<X95,X95<75001)),$G95,IF(OR(AND(27500<X95,X95<30001),AND(57000<X95,X95<60001),AND(75000<X95,X95<77500)),$H95,VLOOKUP(X95,BDins,6,FALSE))))) -> 250
O98: =IF($K95>0,ROUND(O96*$E95/100,DpCU),IF(O99>10000,ROUND(HLOOKUP(O99,$O95:$X98,4,FALSE)/100*O96,DpCU),IF(OR(O95<20001,O95>95000,AND(60000<O95,O95<70001)),ROUND(ROUND(O96*JL/$C95,DcCU)*O97,DpCU),IF(OR(AND(20000<O95,O95<22501),AND(30000<O95,O95<50001),77500<O95),ROUND(O97*O96,DpCU),IF(OR(AND(22500<O95,O95<25001),AND(50000<O95,O95<53501),AND(70000<O95,O95<72501)),ROUND($F95/100*O96,DpCU),IF(OR(AND(25000<O95,O95<27501),AND(53500<O95,O95<57001),AND(72500<O95,O95<75001)),ROUND($G95/100*O96,DpCU),ROUND($H95/100*O96,DpCU))))))) -> 0.98 | P98: =IF($K95>0,ROUND(P96*$E95/100,DpCU),IF(P99>10000,ROUND(HLOOKUP(P99,$O95:$X98,4,FALSE)/100*P96,DpCU),IF(OR(P95<20001,P95>95000,AND(60000<P95,P95<70001)),ROUND(ROUND(P96*JL/$C95,DcCU)*P97,DpCU),IF(OR(AND(20000<P95,P95<22501),AND(30000<P95,P95<50001),77500<P95),ROUND(P97*P96,DpCU),IF(OR(AND(22500<P95,P95<25001),AND(50000<P95,P95<53501),AND(70000<P95,P95<72501)),ROUND($F95/100*P96,DpCU),IF(OR(AND(25000<P95,P95<27501),AND(53500<P95,P95<57001),AND(72500<P95,P95<75001)),ROUND($G95/100*P96,DpCU),ROUND($H95/100*P96,DpCU))))))) -> 1.38 | Q98: =IF($K95>0,ROUND(Q96*$E95/100,DpCU),IF(Q99>10000,ROUND(HLOOKUP(Q99,$O95:$X98,4,FALSE)/100*Q96,DpCU),IF(OR(Q95<20001,Q95>95000,AND(60000<Q95,Q95<70001)),ROUND(ROUND(Q96*JL/$C95,DcCU)*Q97,DpCU),IF(OR(AND(20000<Q95,Q95<22501),AND(30000<Q95,Q95<50001),77500<Q95),ROUND(Q97*Q96,DpCU),IF(OR(AND(22500<Q95,Q95<25001),AND(50000<Q95,Q95<53501),AND(70000<Q95,Q95<72501)),ROUND($F95/100*Q96,DpCU),IF(OR(AND(25000<Q95,Q95<27501),AND(53500<Q95,Q95<57001),AND(72500<Q95,Q95<75001)),ROUND($G95/100*Q96,DpCU),ROUND($H95/100*Q96,DpCU))))))) -> 1.88 | R98: =IF($K95>0,ROUND(R96*$E95/100,DpCU),IF(R99>10000,ROUND(HLOOKUP(R99,$O95:$X98,4,FALSE)/100*R96,DpCU),IF(OR(R95<20001,R95>95000,AND(60000<R95,R95<70001)),ROUND(ROUND(R96*JL/$C95,DcCU)*R97,DpCU),IF(OR(AND(20000<R95,R95<22501),AND(30000<R95,R95<50001),77500<R95),ROUND(R97*R96,DpCU),IF(OR(AND(22500<R95,R95<25001),AND(50000<R95,R95<53501),AND(70000<R95,R95<72501)),ROUND($F95/100*R96,DpCU),IF(OR(AND(25000<R95,R95<27501),AND(53500<R95,R95<57001),AND(72500<R95,R95<75001)),ROUND($G95/100*R96,DpCU),ROUND($H95/100*R96,DpCU))))))) -> 0.23 | S98: =IF($K95>0,ROUND(S96*$E95/100,DpCU),IF(S99>10000,ROUND(HLOOKUP(S99,$O95:$X98,4,FALSE)/100*S96,DpCU),IF(OR(S95<20001,S95>95000,AND(60000<S95,S95<70001)),ROUND(ROUND(S96*JL/$C95,DcCU)*S97,DpCU),IF(OR(AND(20000<S95,S95<22501),AND(30000<S95,S95<50001),77500<S95),ROUND(S97*S96,DpCU),IF(OR(AND(22500<S95,S95<25001),AND(50000<S95,S95<53501),AND(70000<S95,S95<72501)),ROUND($F95/100*S96,DpCU),IF(OR(AND(25000<S95,S95<27501),AND(53500<S95,S95<57001),AND(72500<S95,S95<75001)),ROUND($G95/100*S96,DpCU),ROUND($H95/100*S96,DpCU))))))) -> 4.56 | T98: =IF($K95>0,ROUND(T96*$E95/100,DpCU),IF(T99>10000,ROUND(HLOOKUP(T99,$O95:$X98,4,FALSE)/100*T96,DpCU),IF(OR(T95<20001,T95>95000,AND(60000<T95,T95<70001)),ROUND(ROUND(T96*JL/$C95,DcCU)*T97,DpCU),IF(OR(AND(20000<T95,T95<22501),AND(30000<T95,T95<50001),77500<T95),ROUND(T97*T96,DpCU),IF(OR(AND(22500<T95,T95<25001),AND(50000<T95,T95<53501),AND(70000<T95,T95<72501)),ROUND($F95/100*T96,DpCU),IF(OR(AND(25000<T95,T95<27501),AND(53500<T95,T95<57001),AND(72500<T95,T95<75001)),ROUND($G95/100*T96,DpCU),ROUND($H95/100*T96,DpCU))))))) -> 6.25 | U98: =IF($K95>0,ROUND(U96*$E95/100,DpCU),IF(U99>10000,ROUND(HLOOKUP(U99,$O95:$X98,4,FALSE)/100*U96,DpCU),IF(OR(U95<20001,U95>95000,AND(60000<U95,U95<70001)),ROUND(ROUND(U96*JL/$C95,DcCU)*U97,DpCU),IF(OR(AND(20000<U95,U95<22501),AND(30000<U95,U95<50001),77500<U95),ROUND(U97*U96,DpCU),IF(OR(AND(22500<U95,U95<25001),AND(50000<U95,U95<53501),AND(70000<U95,U95<72501)),ROUND($F95/100*U96,DpCU),IF(OR(AND(25000<U95,U95<27501),AND(53500<U95,U95<57001),AND(72500<U95,U95<75001)),ROUND($G95/100*U96,DpCU),ROUND($H95/100*U96,DpCU))))))) -> 0.31 | V98: =IF($K95>0,ROUND(V96*$E95/100,DpCU),IF(V99>10000,ROUND(HLOOKUP(V99,$O95:$X98,4,FALSE)/100*V96,DpCU),IF(OR(V95<20001,V95>95000,AND(60000<V95,V95<70001)),ROUND(ROUND(V96*JL/$C95,DcCU)*V97,DpCU),IF(OR(AND(20000<V95,V95<22501),AND(30000<V95,V95<50001),77500<V95),ROUND(V97*V96,DpCU),IF(OR(AND(22500<V95,V95<25001),AND(50000<V95,V95<53501),AND(70000<V95,V95<72501)),ROUND($F95/100*V96,DpCU),IF(OR(AND(25000<V95,V95<27501),AND(53500<V95,V95<57001),AND(72500<V95,V95<75001)),ROUND($G95/100*V96,DpCU),ROUND($H95/100*V96,DpCU))))))) -> 12.5 | ... X98: =IF($K95>0,ROUND(X96*$E95/100,DpCU),IF(X99>10000,ROUND(HLOOKUP(X99,$O95:$X98,4,FALSE)/100*X96,DpCU),IF(OR(X95<20001,X95>95000,AND(60000<X95,X95<70001)),ROUND(ROUND(X96*JL/$C95,DcCU)*X97,DpCU),IF(OR(AND(20000<X95,X95<22501),AND(30000<X95,X95<50001),77500<X95),ROUND(X97*X96,DpCU),IF(OR(AND(22500<X95,X95<25001),AND(50000<X95,X95<53501),AND(70000<X95,X95<72501)),ROUND($F95/100*X96,DpCU),IF(OR(AND(25000<X95,X95<27501),AND(53500<X95,X95<57001),AND(72500<X95,X95<75001)),ROUND($G95/100*X96,DpCU),ROUND($H95/100*X96,DpCU))))))) -> 6.25
B99: =A95&"r" -> 10019r
A100: 10020 | B100: EQUIPOS DE PROTECCION COLECTIVA | C100: =ROUND(J100*JL*Frto/8,4) -> 1 | D100: GLB | E100: =SUM($O103:$T103) -> 485.63 | F100: =SUMIF($O100:$T100,"<22501",$O103:$T103) -> 0 | G100: =SUMIFS($O103:$T103,$O100:$T100,">30000",$O100:$T100,"<50001") -> 360.63 | H100: =SUMIFS($O103:$T103,$O100:$T100,">60000",$O100:$T100,"<70001") -> 0 | I100: 6 | J100: 1 | O100: 30039 | P100: 30040 | Q100: 30041 | R100: 30042 | S100: 30043 | T100: 77502
...

Sheet Pto
B1: =Datos!C7 -> RW7o
B2: PRESUPUESTO GENERAL DEL PROYECTO
B3: Proyecto: | C3: =Datos!C2
B4: Lugar : | C4: =Datos!C3
B5: Cliente: | C5: =Datos!C4
B6: Fecha: | C6: =Datos!C5
C10: P A R T I D A S | D10: UND | E10: METRADO | F10: P.U. | G10: PARCIAL | I10: CODIGO | J10: ITEM | K10: TITULOS
B11: =J11 & " " & K11 -> 01 OBRAS PROVISIONALES, TRABAJOS PRELIMINARES, SEGURIDAD Y SALUD | G11: =SUMIF(Pto!$I12:$I44,">10000",G12:G44) -> 171443.52 | I11: T | J11: 01 | K11: OBRAS PROVISIONALES, TRABAJOS PRELIMINARES, SEGURIDAD Y SALUD
B12: =J12 & " " & K12 -> 01.01 OBRAS PROVISIONALES Y TRABAJOS PRELIMINARES | G12: =SUMIF(Pto!$I13:$I37,">10000",G13:G37) -> 166153.25 | I12: ST1 | J12: 01.01 | K12: OBRAS PROVISIONALES Y TRABAJOS PRELIMINARES
B13: =J13 & " " & K13 -> 01.01.01 CONSTRUCCIONES PROVISIONALES | G13: =SUM(G14:G20) -> 84943.88 | I13: ST2 | J13: 01.01.01 | K13: CONSTRUCCIONES PROVISIONALES
B14: =J14 & " " & VLOOKUP(I14,BDcuA,2,FALSE) -> 01.01.01.01 OFICINA | D14: =VLOOKUP(I14,BDcuA,4,FALSE) -> GLB | E14: 1 | F14: =VLOOKUP(I14,BDcuA,5,FALSE) -> 1232.64 | G14: =ROUND(F14*E14,DpP) -> 1232.64 | I14: 10001 | J14: 01.01.01.01
B15: =J15 & " " & VLOOKUP(I15,BDcuA,2,FALSE) -> 01.01.01.02 ALMACEN Y GUARDIANIA | D15: =VLOOKUP(I15,BDcuA,4,FALSE) -> GLB | E15: 1 | F15: =VLOOKUP(I15,BDcuA,5,FALSE) -> 1976.58 | G15: =ROUND(F15*E15,DpP) -> 1976.58 | I15: 10002 | J15: 01.01.01.02
B16: =J16 & " " & VLOOKUP(I16,BDcuA,2,FALSE) -> 01.01.01.03 SS. HH. PARA LA OBRA | D16: =VLOOKUP(I16,BDcuA,4,FALSE) -> GLB | E16: 33.5 | F16: =VLOOKUP(I16,BDcuA,5,FALSE) -> 2001.68 | G16: =ROUND(F16*E16,DpP) -> 67056.28 | I16: 10003 | J16: 01.01.01.03
B17: =J17 & " " & VLOOKUP(I17,BDcuA,2,FALSE) -> 01.01.01.04 TRANSPORTE VERTICAL DE MATERIALES | D17: =VLOOKUP(I17,BDcuA,4,FALSE) -> GLB | E17: 1 | F17: =VLOOKUP(I17,BDcuA,5,FALSE) -> 1664.8 | G17: =ROUND(F17*E17,DpP) -> 1664.8 | I17: 10004 | J17: 01.01.01.04
B18: =J18 & " " & VLOOKUP(I18,BDcuA,2,FALSE) -> 01.01.01.05 PROTECCION DE LINDEROS DE PANELES DE TRIPLAY DE 1.20 X 2.40 M X 4 MM | D18: =VLOOKUP(I18,BDcuA,4,FALSE) -> M | E18: 31.6 | F18: =VLOOKUP(I18,BDcuA,5,FALSE) -> 76.53 | G18: =ROUND(F18*E18,DpP) -> 2418.35 | I18: 10005 | J18: 01.01.01.05
B19: =J19 & " " & VLOOKUP(I19,BDcuA,2,FALSE) -> 01.01.01.06 LIMPIEZA PERMANENTE DE LA OBRA | D19: =VLOOKUP(I19,BDcuA,4,FALSE) -> GLB | E19: 1 | F19: =VLOOKUP(I19,BDcuA,5,FALSE) -> 2153.9 | G19: =ROUND(F19*E19,DpP) -> 2153.9 | I19: 10006 | J19: 01.01.01.06
B20: =J20 & " " & VLOOKUP(I20,BDcuA,2,FALSE) -> 01.01.01.07 CERCO METALICO PLANCHA ACANALADA | D20: =VLOOKUP(I20,BDcuA,4,FALSE) -> M | E20: 33.5 | F20: =VLOOKUP(I20,BDcuA,5,FALSE) -> 251.98 | G20: =ROUND(F20*E20,DpP) -> 8441.33 | I20: 10007 | J20: 01.01.01.07
B21: =J21 & " " & K21 -> 01.01.02 INSTALACIONES PROVISIONALES | G21: =SUMIF(Pto!$I22:$I26,">10000",G22:G26) -> 3900 | I21: ST2 | J21: 01.01.02 | K21: INSTALACIONES PROVISIONALES
B22: =J22 & " " & K22 -> 01.01.02.01 AGUA PARA LA CONSTRUCCION | G22: =SUM(G23:G23) -> 1200 | I22: ST3 | J22: 01.01.02.01 | K22: AGUA PARA LA CONSTRUCCION
B23: =J23 & " " & VLOOKUP(I23,BDcuA,2,FALSE) -> 01.01.02.01.01 CONSUMO DE AGUA POTABLE DURANTE LA OBRA | D23: =VLOOKUP(I23,BDcuA,4,FALSE) -> MES | E23: 8 | F23: =VLOOKUP(I23,BDcuA,5,FALSE) -> 150 | G23: =ROUND(F23*E23,DpP) -> 1200 | I23: 10008 | J23: 01.01.02.01.01
B24: =J24 & " " & K24 -> 01.01.02.02 ENERGIA ELECTRICA PARA LA OBRA | G24: =SUM(G25:G26) -> 2700 | I24: ST3 | J24: 01.01.02.02 | K24: ENERGIA ELECTRICA PARA LA OBRA
B25: =J25 & " " & VLOOKUP(I25,BDcuA,2,FALSE) -> 01.01.02.02.01 INSTALACIONES PROVISIONALES DE ENERGIA ELECTRICA | D25: =VLOOKUP(I25,BDcuA,4,FALSE) -> GLB | E25: 1 | F25: =VLOOKUP(I25,BDcuA,5,FALSE) -> 1500 | G25: =ROUND(F25*E25,DpP) -> 1500 | I25: 10009 | J25: 01.01.02.02.01
B26: =J26 & " " & VLOOKUP(I26,BDcuA,2,FALSE) -> 01.01.02.02.02 CONSUMO DE ENERGIA ELECTRICA DURANTE LA OBRA | D26: =VLOOKUP(I26,BDcuA,4,FALSE) -> MES | E26: 8 | F26: =VLOOKUP(I26,BDcuA,5,FALSE) -> 150 | G26: =ROUND(F26*E26,DpP) -> 1200 | I26: 10010 | J26: 01.01.02.02.02
B27: =J27 & " " & K27 -> 01.01.03 TRABAJOS PRELIMINARES | G27: =SUM(G28:G28) -> 70248.44 | I27: ST2 | J27: 01.01.03 | K27: TRABAJOS PRELIMINARES
B28: =J28 & " " & VLOOKUP(I28,BDcuA,2,FALSE) -> 01.01.03.01 LIMPIEZA TERRENO | D28: =VLOOKUP(I28,BDcuA,4,FALSE) -> M3 | E28: 70.2 | F28: =VLOOKUP(I28,BDcuA,5,FALSE) -> 1000.69 | G28: =ROUND(F28*E28,DpP) -> 70248.44 | I28: 10011 | J28: 01.01.03.01
B29: =J29 & " " & K29 -> 01.01.04 DEMOLICIONES | G29: =SUM(G30:G32) -> 1666.87 | I29: ST2 | J29: 01.01.04 | K29: DEMOLICIONES
B30: =J30 & " " & VLOOKUP(I30,BDcuA,2,FALSE) -> 01.01.04.01 DEMOLICION DE CIMIENTO DE CONCRETO CICLOPEO | D30: =VLOOKUP(I30,BDcuA,4,FALSE) -> M3 | E30: 2 | F30: =VLOOKUP(I30,BDcuA,5,FALSE) -> 304.73 | G30: =ROUND(F30*E30,DpP) -> 609.46 | I30: 10012 | J30: 01.01.04.01
B31: =J31 & " " & VLOOKUP(I31,BDcuA,2,FALSE) -> 01.01.04.02 DEMOLICION DE SOBRECIMIENTOS | D31: =VLOOKUP(I31,BDcuA,4,FALSE) -> M3 | E31: 0.3 | F31: =VLOOKUP(I31,BDcuA,5,FALSE) -> 189.71 | G31: =ROUND(F31*E31,DpP) -> 56.91 | I31: 10013 | J31: 01.01.04.02
B32: =J32 & " " & VLOOKUP(I32,BDcuA,2,FALSE) -> 01.01.04.03 ELIMINACION DE MATERIAL EXCEDENTE PROV. DE DEMOLICIONES | D32: =VLOOKUP(I32,BDcuA,4,FALSE) -> M3 | E32: 4.6 | F32: =VLOOKUP(I32,BDcuA,5,FALSE) -> 217.5 | G32: =ROUND(F32*E32,DpP) -> 1000.5 | I32: 10014 | J32: 01.01.04.03
B33: =J33 & " " & K33 -> 01.01.05 MOVILIZACION DE CAMPAMENTO, MAQUINARIAS Y HERRAMIENTAS | G33: =SUM(G34:G34) -> 2276.92 | I33: ST2 | J33: 01.01.05 | K33: MOVILIZACION DE CAMPAMENTO, MAQUINARIAS Y HERRAMIENTAS
B34: =J34 & " " & VLOOKUP(I34,BDcuA,2,FALSE) -> 01.01.05.01 MOVILIZACION Y DESMOVILIZACION DE MAQUINARIA Y HERRAMIENTAS | D34: =VLOOKUP(I34,BDcuA,4,FALSE) -> GLB | E34: 1 | F34: =VLOOKUP(I34,BDcuA,5,FALSE) -> 2276.92 | G34: =ROUND(F34*E34,DpP) -> 2276.92 | I34: 10015 | J34: 01.01.05.01
B35: =J35 & " " & K35 -> 01.01.06 TRAZOS, NIVELES Y REPLANTEO | G35: =SUM(G36:G37) -> 3117.14 | I35: ST2 | J35: 01.01.06 | K35: TRAZOS, NIVELES Y REPLANTEO
B36: =J36 & " " & VLOOKUP(I36,BDcuA,2,FALSE) -> 01.01.06.01 TRAZO, NIVELES Y REPLANTEO PRELIMINAR CON VALLAS AISLADAS | D36: =VLOOKUP(I36,BDcuA,4,FALSE) -> M2 | E36: 451.1 | F36: =VLOOKUP(I36,BDcuA,5,FALSE) -> 3.95 | G36: =ROUND(F36*E36,DpP) -> 1781.85 | I36: 10016 | J36: 01.01.06.01
B37: =J37 & " " & VLOOKUP(I37,BDcuA,2,FALSE) -> 01.01.06.02 TRAZO Y REPLANTEO DURANTE EL PROCESO DE LA OBRA | D37: =VLOOKUP(I37,BDcuA,4,FALSE) -> M2 | E37: 355.13 | F37: =VLOOKUP(I37,BDcuA,5,FALSE) -> 3.76 | G37: =ROUND(F37*E37,DpP) -> 1335.29 | I37: 10017 | J37: 01.01.06.02
B38: =J38 & " " & K38 -> 01.02 SEGURIDAD Y SALUD | G38: =SUM(G39:G44) -> 5290.27 | I38: ST1 | J38: 01.02 | K38: SEGURIDAD Y SALUD
B39: =J39 & " " & VLOOKUP(I39,BDcuA,2,FALSE) -> 01.02.01 ELABORACION, IMPLEMENTACION Y ADMINISTRACION DEL PLAN DE SEGURIDAD Y SALUD EN EL TRABAJO | D39: =VLOOKUP(I39,BDcuA,4,FALSE) -> GLB | E39: 1 | F39: =VLOOKUP(I39,BDcuA,5,FALSE) -> 1271.19 | G39: =ROUND(F39*E39,DpP) -> 1271.19 | I39: 10018 | J39: 01.02.01
B40: =J40 & " " & VLOOKUP(I40,BDcuA,2,FALSE) -> 01.02.02 EQUIPOS DE PROTECCION INDIVIDUAL | D40: =VLOOKUP(I40,BDcuA,4,FALSE) -> UND | E40: 80 | F40: =VLOOKUP(I40,BDcuA,5,FALSE) -> 38.34 | G40: =ROUND(F40*E40,DpP) -> 3067.2 | I40: 10019 | J40: 01.02.02
B41: =J41 & " " & VLOOKUP(I41,BDcuA,2,FALSE) -> 01.02.03 EQUIPOS DE PROTECCION COLECTIVA | D41: =VLOOKUP(I41,BDcuA,4,FALSE) -> GLB | E41: 1 | F41: =VLOOKUP(I41,BDcuA,5,FALSE) -> 485.63 | G41: =ROUND(F41*E41,DpP) -> 485.63 | I41: 10020 | J41: 01.02.03
B42: =J42 & " " & VLOOKUP(I42,BDcuA,2,FALSE) -> 01.02.04 SEÑALIZACION TEMPORAL DE SEGURIDAD | D42: =VLOOKUP(I42,BDcuA,4,FALSE) -> GLB | E42: 1 | F42: =VLOOKUP(I42,BDcuA,5,FALSE) -> 158.75 | G42: =ROUND(F42*E42,DpP) -> 158.75 | I42: 10021 | J42: 01.02.04
B43: =J43 & " " & VLOOKUP(I43,BDcuA,2,FALSE) -> 01.02.05 CAPACITACION EN SEGURIDAD Y SALUD | D43: =VLOOKUP(I43,BDcuA,4,FALSE) -> GLB | E43: 1 | F43: =VLOOKUP(I43,BDcuA,5,FALSE) -> 125 | G43: =ROUND(F43*E43,DpP) -> 125 | I43: 10022 | J43: 01.02.05
B44: =J44 & " " & VLOOKUP(I44,BDcuA,2,FALSE) -> 01.02.06 RECURSOS PARA RESPUESTAS ANTE EMERGENCIA | D44: =VLOOKUP(I44,BDcuA,4,FALSE) -> GLB | E44: 1 | F44: =VLOOKUP(I44,BDcuA,5,FALSE) -> 182.5 | G44: =ROUND(F44*E44,DpP) -> 182.5 | I44: 10023 | J44: 01.02.06
B45: =J45 & " " & K45 -> 02 ESTRUCTURAS | G45: =SUMIF(Pto!$I46:$I143,">10000",G46:G143) -> 1447369.4 | I45: T | J45: 02 | K45: ESTRUCTURAS
B46: =J46 & " " & K46 -> 02.01 MOVIMIENTO DE TIERRAS | G46: =SUMIF(Pto!$I47:$I61,">10000",G47:G61) -> 449014.28 | I46: ST1 | J46: 02.01 | K46: MOVIMIENTO DE TIERRAS
B47: =J47 & " " & K47 -> 02.01.01 EXCAVACIONES | G47: =SUM(G48:G53) -> 30777.47 | I47: ST2 | J47: 02.01.01 | K47: EXCAVACIONES
B48: =J48 & " " & VLOOKUP(I48,BDcuA,2,FALSE) -> 02.01.01.01 EXCAVACION MASIVA A MAQUINA EN TERRENO NORMAL"C"/RETRO .5Y3 | D48: =VLOOKUP(I48,BDcuA,4,FALSE) -> M3 | E48: 666.12 | F48: =VLOOKUP(I48,BDcuA,5,FALSE) -> 21.71 | G48: =ROUND(F48*E48,DpP) -> 14461.47 | I48: 10024 | J48: 02.01.01.01
B49: =J49 & " " & VLOOKUP(I49,BDcuA,2,FALSE) -> 02.01.01.02 EXCAVACION DE PARA CALZADURAS | D49: =VLOOKUP(I49,BDcuA,4,FALSE) -> M3 | E49: 196.84 | F49: =VLOOKUP(I49,BDcuA,5,FALSE) -> 60 | G49: =ROUND(F49*E49,DpP) -> 11810.4 | I49: 10025 | J49: 02.01.01.02
B50: =J50 & " " & VLOOKUP(I50,BDcuA,2,FALSE) -> 02.01.01.03 EXCAVACION PARA CIMIENTOS HASTA 1.40 MT TERRENO NORMAL | D50: =VLOOKUP(I50,BDcuA,4,FALSE) -> M3 | E50: 6.38 | F50: =VLOOKUP(I50,BDcuA,5,FALSE) -> 50 | G50: =ROUND(F50*E50,DpP) -> 319 | I50: 10026 | J50: 02.01.01.03
B51: =J51 & " " & VLOOKUP(I51,BDcuA,2,FALSE) -> 02.01.01.04 EXCAVACION PARA ZAPATAS DE 1.00 MT A 1.40 MT DE PROFUNDIDAD | D51: =VLOOKUP(I51,BDcuA,4,FALSE) -> M3 | E51: 62.86 | F51: =VLOOKUP(I51,BDcuA,5,FALSE) -> 50 | G51: =ROUND(F51*E51,DpP) -> 3143 | I51: 10027 | J51: 02.01.01.04
B52: =J52 & " " & VLOOKUP(I52,BDcuA,2,FALSE) -> 02.01.01.05 EXCAVACION PARA CISTERNA HASTA 2 MTS DE PROFUNDIDAD | D52: =VLOOKUP(I52,BDcuA,4,FALSE) -> M3 | E52: 19.72 | F52: =VLOOKUP(I52,BDcuA,5,FALSE) -> 50 | G52: =ROUND(F52*E52,DpP) -> 986 | I52: 10028 | J52: 02.01.01.05
B53: =J53 & " " & VLOOKUP(I53,BDcuA,2,FALSE) -> 02.01.01.06 EXCAVACION PARA VIGAS DE CIMENTACION | D53: =VLOOKUP(I53,BDcuA,4,FALSE) -> M3 | E53: 0.96 | F53: =VLOOKUP(I53,BDcuA,5,FALSE) -> 60 | G53: =ROUND(F53*E53,DpP) -> 57.6 | I53: 10029 | J53: 02.01.01.06
B54: =J54 & " " & K54 -> 02.01.02 RELLENOS | G54: =SUM(G55:G56) -> 7703.32 | I54: ST2 | J54: 02.01.02 | K54: RELLENOS
B55: =J55 & " " & VLOOKUP(I55,BDcuA,2,FALSE) -> 02.01.02.01 RELLENO COMPACTADO PARA ESTRUCTURAS CON MATERIAL PROPIO | D55: =VLOOKUP(I55,BDcuA,4,FALSE) -> M3 | E55: 108.5 | F55: =VLOOKUP(I55,BDcuA,5,FALSE) -> 47.03 | G55: =ROUND(F55*E55,DpP) -> 5102.76 | I55: 10030 | J55: 02.01.02.01
B56: =J56 & " " & VLOOKUP(I56,BDcuA,2,FALSE) -> 02.01.02.02 NIVELACION INTERIOR APISONADO C/EQUIPO | D56: =VLOOKUP(I56,BDcuA,4,FALSE) -> M2 | E56: 217.62 | F56: =VLOOKUP(I56,BDcuA,5,FALSE) -> 11.95 | G56: =ROUND(F56*E56,DpP) -> 2600.56 | I56: 10031 | J56: 02.01.02.02
B57: =J57 & " " & K57 -> 02.01.03 ACARREOS Y ELIMINACIONES | G57: =SUM(G58:G59) -> 407679.19 | I57: ST2 | J57: 02.01.03 | K57: ACARREOS Y ELIMINACIONES
B58: =J58 & " " & VLOOKUP(I58,BDcuA,2,FALSE) -> 02.01.03.01 ACARREO DE MATERIAL EXCEDENTE DE EXCAVACION DE CISTERNA, ZANJAS, ZAPATAS | D58: =VLOOKUP(I58,BDcuA,4,FALSE) -> M3 | E58: 230.49 | F58: =VLOOKUP(I58,BDcuA,5,FALSE) -> 18.75 | G58: =ROUND(F58*E58,DpP) -> 4321.69 | I58: 10032 | J58: 02.01.03.01
B59: =J59 & " " & VLOOKUP(I59,BDcuA,2,FALSE) -> 02.01.03.02 ELIMINACION DE MATERIAL EXEDENTE DE EXCAVACIONES | D59: =VLOOKUP(I59,BDcuA,4,FALSE) -> M3 | E59: 230.49 | F59: =VLOOKUP(I59,BDcuA,5,FALSE) -> 1750 | G59: =ROUND(F59*E59,DpP) -> 403357.5 | I59: 10033 | J59: 02.01.03.02
B60: =J60 & " " & K60 -> 02.01.04 BASES PARA PISOS | G60: =SUM(G61:G61) -> 2854.3 | I60: ST2 | J60: 02.01.04 | K60: BASES PARA PISOS
B61: =J61 & " " & VLOOKUP(I61,BDcuA,2,FALSE) -> 02.01.04.01 BASE DE MATERIAL AFIRMADO DE 4" , CON COMPACTADORA MANUAL | D61: =VLOOKUP(I61,BDcuA,4,FALSE) -> M2 | E61: 194.7 | F61: =VLOOKUP(I61,BDcuA,5,FALSE) -> 14.66 | G61: =ROUND(F61*E61,DpP) -> 2854.3 | I61: 10034 | J61: 02.01.04.01
B62: =J62 & " " & K62 -> 02.02 OBRAS DE CONCRETO SIMPLE | G62: =SUMIF(Pto!$I63:$I83,">10000",G63:G83) -> 50581.24 | I62: ST1 | J62: 02.02 | K62: OBRAS DE CONCRETO SIMPLE
B63: =J63 & " " & K63 -> 02.02.01 CALZADURAS | G63: =SUM(G64:G65) -> 30046.61 | I63: ST2 | J63: 02.02.01 | K63: CALZADURAS
B64: =J64 & " " & VLOOKUP(I64,BDcuA,2,FALSE) -> 02.02.01.01 CONCRETO F'C=100 KG/CM2 + 30% DE P.G. PARA CALZADURAS | D64: =VLOOKUP(I64,BDcuA,4,FALSE) -> M3 | E64: 92.6 | F64: =VLOOKUP(I64,BDcuA,5,FALSE) -> 256.45 | G64: =ROUND(F64*E64,DpP) -> 23747.27 | I64: 10035 | J64: 02.02.01.01
B65: =J65 & " " & VLOOKUP(I65,BDcuA,2,FALSE) -> 02.02.01.02 ENCOFRADO PARA CALZADURAS HASTA 2.00 M | D65: =VLOOKUP(I65,BDcuA,4,FALSE) -> M2 | E65: 124.37 | F65: =VLOOKUP(I65,BDcuA,5,FALSE) -> 50.65 | G65: =ROUND(F65*E65,DpP) -> 6299.34 | I65: 10036 | J65: 02.02.01.02
B66: =J66 & " " & K66 -> 02.02.02 FALSO CIMIENTOS | G66: =SUM(G67:G68) -> 3365.12 | I66: ST2 | J66: 02.02.02 | K66: FALSO CIMIENTOS
B67: =J67 & " " & VLOOKUP(I67,BDcuA,2,FALSE) -> 02.02.02.01 CONCRETO F'C=100 KG/CM2 PARA FALSO CIMIENTO | D67: =VLOOKUP(I67,BDcuA,4,FALSE) -> M3 | E67: 11.86 | F67: =VLOOKUP(I67,BDcuA,5,FALSE) -> 243.01 | G67: =ROUND(F67*E67,DpP) -> 2882.1 | I67: 10037 | J67: 02.02.02.01
B68: =J68 & " " & VLOOKUP(I68,BDcuA,2,FALSE) -> 02.02.02.02 ENCOFRADO Y DEDESENCOFRADO DE FALSO CIMIENTO | D68: =VLOOKUP(I68,BDcuA,4,FALSE) -> M2 | E68: 10.31 | F68: =VLOOKUP(I68,BDcuA,5,FALSE) -> 46.85 | G68: =ROUND(F68*E68,DpP) -> 483.02 | I68: 10038 | J68: 02.02.02.02
B69: =J69 & " " & K69 -> 02.02.03 CIMIENTOS CORRIDOS | G69: =SUM(G70:G70) -> 791.46 | I69: ST2 | J69: 02.02.03 | K69: CIMIENTOS CORRIDOS
B70: =J70 & " " & VLOOKUP(I70,BDcuA,2,FALSE) -> 02.02.03.01 CONCRETO FC=100 KG/CM2 + 30% P.G. PARA CIMIENTOS CORRIDOS | D70: =VLOOKUP(I70,BDcuA,4,FALSE) -> M3 | E70: 2.87 | F70: =VLOOKUP(I70,BDcuA,5,FALSE) -> 275.77 | G70: =ROUND(F70*E70,DpP) -> 791.46 | I70: 10039 | J70: 02.02.03.01
B71: =J71 & " " & K71 -> 02.02.04 SOBRECIMIENTOS | G71: =SUM(G72:G73) -> 1311.48 | I71: ST2 | J71: 02.02.04 | K71: SOBRECIMIENTOS
B72: =J72 & " " & VLOOKUP(I72,BDcuA,2,FALSE) -> 02.02.04.01 CONCRETO CEMENTO-HORMIGON 1:8 PARA SOBRECIMIENTOS | D72: =VLOOKUP(I72,BDcuA,4,FALSE) -> M3 | E72: 1.44 | F72: =VLOOKUP(I72,BDcuA,5,FALSE) -> 280.19 | G72: =ROUND(F72*E72,DpP) -> 403.47 | I72: 10040 | J72: 02.02.04.01
B73: =J73 & " " & VLOOKUP(I73,BDcuA,2,FALSE) -> 02.02.04.02 ENCOFRADO Y DESENCOF. SOBRECIMIENTO DE 0.30 A 0.60 MT | D73: =VLOOKUP(I73,BDcuA,4,FALSE) -> M2 | E73: 19 | F73: =VLOOKUP(I73,BDcuA,5,FALSE) -> 47.79 | G73: =ROUND(F73*E73,DpP) -> 908.01 | I73: 10041 | J73: 02.02.04.02
B74: =J74 & " " & K74 -> 02.02.05 GRADAS DE ESCALERAS | G74: =SUM(G75:G76) -> 1617.6 | I74: ST2 | J74: 02.02.05 | K74: GRADAS DE ESCALERAS
B75: =J75 & " " & VLOOKUP(I75,BDcuA,2,FALSE) -> 02.02.05.01 CONCRETO CEMENTO-HORMIGON 1:8 PARA GRADAS (APOYADAS SOBRE EL TERRENO) | D75: =VLOOKUP(I75,BDcuA,4,FALSE) -> M3 | E75: 5 | F75: =VLOOKUP(I75,BDcuA,5,FALSE) -> 280.73 | G75: =ROUND(F75*E75,DpP) -> 1403.65 | I75: 10042 | J75: 02.02.05.01
B76: =J76 & " " & VLOOKUP(I76,BDcuA,2,FALSE) -> 02.02.05.02 ENCOFRADO Y DESENCOFRADO PARA GRADAS (APOYADAS SOBRE TERRENO) | D76: =VLOOKUP(I76,BDcuA,4,FALSE) -> M2 | E76: 5 | F76: =VLOOKUP(I76,BDcuA,5,FALSE) -> 42.79 | G76: =ROUND(F76*E76,DpP) -> 213.95 | I76: 10043 | J76: 02.02.05.02
B77: =J77 & " " & K77 -> 02.02.06 SOLADOS | G77: =SUM(G78:G78) -> 2089.4 | I77: ST2 | J77: 02.02.06 | K77: SOLADOS
B78: =J78 & " " & VLOOKUP(I78,BDcuA,2,FALSE) -> 02.02.06.01 SOLADO PARA ZAPATAS DE 2" MEZCLA 1:12 CEMENTO-HORMIGON | D78: =VLOOKUP(I78,BDcuA,4,FALSE) -> M2 | E78: 98.93 | F78: =VLOOKUP(I78,BDcuA,5,FALSE) -> 21.12 | G78: =ROUND(F78*E78,DpP) -> 2089.4 | I78: 10044 | J78: 02.02.06.01
B79: =J79 & " " & K79 -> 02.02.07 LOSAS MACIZAS DE PISO | G79: =SUM(G80:G81) -> 4267.1 | I79: ST2 | J79: 02.02.07 | K79: LOSAS MACIZAS DE PISO
B80: =J80 & " " & VLOOKUP(I80,BDcuA,2,FALSE) -> 02.02.07.01 CONCRETO EN LOSA DE PISO F'C= 210 KG/CM2, H=0.10 M | D80: =VLOOKUP(I80,BDcuA,4,FALSE) -> M2 | E80: 88 | F80: =VLOOKUP(I80,BDcuA,5,FALSE) -> 44.15 | G80: =ROUND(F80*E80,DpP) -> 3885.2 | I80: 10045 | J80: 02.02.07.01
B81: =J81 & " " & VLOOKUP(I81,BDcuA,2,FALSE) -> 02.02.07.02 ENCOFRADO Y DESENCOFRADO LOSA DE PISO | D81: =VLOOKUP(I81,BDcuA,4,FALSE) -> M2 | E81: 10 | F81: =VLOOKUP(I81,BDcuA,5,FALSE) -> 38.19 | G81: =ROUND(F81*E81,DpP) -> 381.9 | I81: 10046 | J81: 02.02.07.02
B82: =J82 & " " & K82 -> 02.02.08 FALSOS PISOS | G82: =SUM(G83:G83) -> 7092.47 | I82: ST2 | J82: 02.02.08 | K82: FALSOS PISOS
B83: =J83 & " " & VLOOKUP(I83,BDcuA,2,FALSE) -> 02.02.08.01 FALSO PISO CONCRETO F'C=100 KG/CM2, E=0.10 M | D83: =VLOOKUP(I83,BDcuA,4,FALSE) -> M2 | E83: 106.75 | F83: =VLOOKUP(I83,BDcuA,5,FALSE) -> 66.44 | G83: =ROUND(F83*E83,DpP) -> 7092.47 | I83: 10047 | J83: 02.02.08.01
B84: =J84 & " " & K84 -> 02.03 OBRAS DE CONCRETO ARMADO | G84: =SUMIF(Pto!$I85:$I139,">10000",G85:G139) -> 947009.58 | I84: ST1 | J84: 02.03 | K84: OBRAS DE CONCRETO ARMADO
B85: =J85 & " " & K85 -> 02.03.01 CIMIENTOS CORRIDOS REFORZADOS | G85: =SUM(G86:G86) -> 1674.15 | I85: ST2 | J85: 02.03.01 | K85: CIMIENTOS CORRIDOS REFORZADOS
B86: =J86 & " " & VLOOKUP(I86,BDcuA,2,FALSE) -> 02.03.01.01 CONCRETO EN CIMIENTOS CORRIDOS F'C= 210 KG/CM2 | D86: =VLOOKUP(I86,BDcuA,4,FALSE) -> M3 | E86: 5 | F86: =VLOOKUP(I86,BDcuA,5,FALSE) -> 334.83 | G86: =ROUND(F86*E86,DpP) -> 1674.15 | I86: 10048 | J86: 02.03.01.01
B87: =J87 & " " & K87 -> 02.03.02 VIGAS DE CIMENTACION | G87: =SUM(G88:G90) -> 2562.33 | I87: ST2 | J87: 02.03.02 | K87: VIGAS DE CIMENTACION
B88: =J88 & " " & VLOOKUP(I88,BDcuA,2,FALSE) -> 02.03.02.01 CONCRETO F'C=210 KG/CM2 PARA VIGAS DE CIMENTACION | D88: =VLOOKUP(I88,BDcuA,4,FALSE) -> M3 | E88: 1.83 | F88: =VLOOKUP(I88,BDcuA,5,FALSE) -> 401.87 | G88: =ROUND(F88*E88,DpP) -> 735.42 | I88: 10049 | J88: 02.03.02.01
B89: =J89 & " " & VLOOKUP(I89,BDcuA,2,FALSE) -> 02.03.02.02 ENCOFRADO Y DESENCOFRADO NORMAL PARA VIGAS DE CIMENTACION | D89: =VLOOKUP(I89,BDcuA,4,FALSE) -> M2 | E89: 12.81 | F89: =VLOOKUP(I89,BDcuA,5,FALSE) -> 28.61 | G89: =ROUND(F89*E89,DpP) -> 366.49 | I89: 10050 | J89: 02.03.02.02
B90: =J90 & " " & VLOOKUP(I90,BDcuA,2,FALSE) -> 02.03.02.03 ACERO ESTRUCTURAL TRABAJADO PARA VIGAS DE CIMENTACION | D90: =VLOOKUP(I90,BDcuA,4,FALSE) -> KG | E90: 277.12 | F90: =VLOOKUP(I90,BDcuA,5,FALSE) -> 5.27 | G90: =ROUND(F90*E90,DpP) -> 1460.42 | I90: 10051 | J90: 02.03.02.03
B91: =J91 & " " & K91 -> 02.03.03 ZAPATAS | G91: =SUM(G92:G94) -> 24235.59 | I91: ST2 | J91: 02.03.03 | K91: ZAPATAS
B92: =J92 & " " & VLOOKUP(I92,BDcuA,2,FALSE) -> 02.03.03.01 CONCRETO F'C= 210 KG/CM2 PARA ZAPATAS | D92: =VLOOKUP(I92,BDcuA,4,FALSE) -> M3 | E92: 39.23 | F92: =VLOOKUP(I92,BDcuA,5,FALSE) -> 345.78 | G92: =ROUND(F92*E92,DpP) -> 13564.95 | I92: 10052 | J92: 02.03.03.01
B93: =J93 & " " & VLOOKUP(I93,BDcuA,2,FALSE) -> 02.03.03.02 ENCOFRADO Y DESENCOFRADO NORMAL PARA ZAPATAS | D93: =VLOOKUP(I93,BDcuA,4,FALSE) -> M2 | E93: 5 | F93: =VLOOKUP(I93,BDcuA,5,FALSE) -> 39.67 | G93: =ROUND(F93*E93,DpP) -> 198.35 | I93: 10053 | J93: 02.03.03.02
B94: =J94 & " " & VLOOKUP(I94,BDcuA,2,FALSE) -> 02.03.03.03 ACERO ESTRUCTURAL TRABAJADO PARA ZAPATAS | D94: =VLOOKUP(I94,BDcuA,4,FALSE) -> KG | E94: 1121.23 | F94: =VLOOKUP(I94,BDcuA,5,FALSE) -> 9.34 | G94: =ROUND(F94*E94,DpP) -> 10472.29 | I94: 10054 | J94: 02.03.03.03
B95: =J95 & " " & K95 -> 02.03.04 COLUMNAS AISLADAS | G95: =SUM(G96:G98) -> 72828.52 | I95: ST2 | J95: 02.03.04 | K95: COLUMNAS AISLADAS
B96: =J96 & " " & VLOOKUP(I96,BDcuA,2,FALSE) -> 02.03.04.01 CONCRETO F'C=210 KG/CM2 PARA COLUMNAS | D96: =VLOOKUP(I96,BDcuA,4,FALSE) -> M3 | E96: 23.7 | F96: =VLOOKUP(I96,BDcuA,5,FALSE) -> 485.84 | G96: =ROUND(F96*E96,DpP) -> 11514.41 | I96: 10055 | J96: 02.03.04.01
B97: =J97 & " " & VLOOKUP(I97,BDcuA,2,FALSE) -> 02.03.04.02 ENCOFRADO Y DESENCOFRADO NORMAL DE COLUMNAS AISLADAS | D97: =VLOOKUP(I97,BDcuA,4,FALSE) -> M2 | E97: 325.22 | F97: =VLOOKUP(I97,BDcuA,5,FALSE) -> 39.68 | G97: =ROUND(F97*E97,DpP) -> 12904.73 | I97: 10056 | J97: 02.03.04.02
B98: =J98 & " " & VLOOKUP(I98,BDcuA,2,FALSE) -> 02.03.04.03 ACERO ESTRUCTURAL TRABAJADO PARA COLUMNAS AISLADAS | D98: =VLOOKUP(I98,BDcuA,4,FALSE) -> KG | E98: 5139 | F98: =VLOOKUP(I98,BDcuA,5,FALSE) -> 9.42 | G98: =ROUND(F98*E98,DpP) -> 48409.38 | I98: 10057 | J98: 02.03.04.03
B99: =J99 & " " & K99 -> 02.03.05 PLACAS | G99: =SUM(G100:G103) -> 323572.36 | I99: ST2 | J99: 02.03.05 | K99: PLACAS
B100: =J100 & " " & VLOOKUP(I100,BDcuA,2,FALSE) -> 02.03.05.01 CONCRETO F'C=210 KG/CM2 PARA MUROS Y PLACAS | D100: =VLOOKUP(I100,BDcuA,4,FALSE) -> M3 | E100: 171.31 | F100: =VLOOKUP(I100,BDcuA,5,FALSE) -> 485.84 | G100: =ROUND(F100*E100,DpP) -> 83229.25 | I100: 10058 | J100: 02.03.05.01
B101: =J101 & " " & VLOOKUP(I101,BDcuA,2,FALSE) -> 02.03.05.02 ENCOFRADO Y DESENCOFRADO MUROS, 1 CARA, SISTEMA EFCO | D101: =VLOOKUP(I101,BDcuA,4,FALSE) -> M2 | E101: 118.09 | F101: =VLOOKUP(I101,BDcuA,5,FALSE) -> 38.42 | G101: =ROUND(F101*E101,DpP) -> 4537.02 | I101: 10059 | J101: 02.03.05.02
B102: =J102 & " " & VLOOKUP(I102,BDcuA,2,FALSE) -> 02.03.05.03 ENCOFRADO Y DESENCOFRADO MUROS, 2 CARAS, SISTEMA EFCO | D102: =VLOOKUP(I102,BDcuA,4,FALSE) -> M2 | E102: 1641.72 | F102: =VLOOKUP(I102,BDcuA,5,FALSE) -> 33.41 | G102: =ROUND(F102*E102,DpP) -> 54849.87 | I102: 10060 | J102: 02.03.05.03
B103: =J103 & " " & VLOOKUP(I103,BDcuA,2,FALSE) -> 02.03.05.04 ACERO ESTRUCTURAL TRABAJADO PARA MUROS | D103: =VLOOKUP(I103,BDcuA,4,FALSE) -> KG | E103: 19209.79 | F103: =VLOOKUP(I103,BDcuA,5,FALSE) -> 9.42 | G103: =ROUND(F103*E103,DpP) -> 180956.22 | I103: 10061 | J103: 02.03.05.04
...
